Workbook

Sheet Progress
B3: Outreach Progress
C4: Total | D4: Percent | E4: Calls Per
B5: Total Prospects Called | C5: =COUNTA(Nonprofits!C:C) -> 79 | D5: =C5/300 -> 0.26333333 | E5: 1
B6: VM's | C6: =SUM(Nonprofits!AB:AB) -> 60 | D6: =C6/C5 -> 0.75949367 | E6: =$C$5/C6 -> 1.3166667
B7: Talked to Someone | C7: =SUM(Nonprofits!AC:AC) -> 20 | D7: =C7/$C$5 -> 0.25316456 | E7: =$C$5/C7 -> 3.95
B8: Sent Info Email | C8: =SUM(Nonprofits!AD:AD) -> 11 | D8: =C8/$C$5 -> 0.13924051 | E8: =$C$5/C8 -> 7.1818182
B9: Talked to Decision Maker | C9: =SUM(Nonprofits!AE:AE) -> 8 | D9: =C9/$C$5 -> 0.10126582 | E9: =$C$5/C9 -> 9.875
B10: Verbal Yes | C10: =COUNTIF('Beta Group'!B:L,"2. Yes") -> 0 | D10: =C10/$C$5 -> 0 | E10: =$C$5/C10 -> #DIV/0!
B11: Forms Filled Out | C11: =COUNTIF('Beta Group'!B:L,"3. Filled out questionnaire ") -> 3 | D11: =C11/$C$5 -> 0.037974684 | E11: =$C$5/C11 -> 26.333333

Sheet Beta Group
B2: Beta Group | N2: Outreach Progress
B3: Status | C3: Company | D3: Contact Name | E3: State | F3: Contact Date | G3: Phone Number | H3: Email | I3: Website | J3: Contact Method | K3: Notes | L3: Follow Up Date | O3: Nonprofits | Q3: Restaurants | S3: Gov Contractors | U3: Total
B4: 1. Gave feedback | C4: Senior Network Services | D4: Mariam | E4: CA | F4: 45610 | G4: 831-216-6132 | H4: mariama@seniornetworkservices.org | I4: https://seniornetworkservices.org/ | J4: Cold Call | K4: 11-14-2025 - Called, left VM. She called back and said she consults other nonprofits on doing this, asked how we're different than grant watch, and said she wants to be able to opt out in case she gets too many emails(concerned about getting too many emails) | N4: Total Called | O4: =Progress!C5 -> 79 | P4: =Progress!D5 -> 0.26333333 | Q4: =Restaurants!J3 -> 6 | R4: =Restaurants!K3 -> 0.02 | S4: ='Gov Contractors'!D3 -> 5 | T4: ='Gov Contractors'!E3 -> 0.016666667 | U4: =SUM(S4,Q4,O4) -> 90 | V4: =U4/900 -> 0.1
B5: 1. Gave feedback | C5: Anaheim Memorial Manor Inc | D5: Andy | E5: CA | F5: 45975 | G5: 5622575100 | H5: andy.do@rhf.org | J5: Cold Call | K5: 11/14/2025 - Asked to talk to the person that does grant acquisition. Got transferred to Andy. He said sure might as well. Sent him the email with the survey while on the call. He said he'd fill it out after passing it through IT to make sure the link is safe. | N5: VM's | O5: =Progress!C6 -> 60 | P5: =Progress!D6 -> 0.75949367 | Q5: =Restaurants!J4 -> 3 | R5: =Restaurants!K4 -> 0.5 | S5: ='Gov Contractors'!D4 -> 5 | T5: ='Gov Contractors'!E4 -> 1 | U5: =SUM(S5,Q5,O5) -> 68 | V5: =U5/U4 -> 0.75555556
B6: 1. Gave feedback | C6: Patient Safety Movement Foundation | D6: Consuelo | E6: CA | F6: 45966 | G6: 9492307588 | H6: info@psmf.org | I6: https://PSMF.ORG | J6: Cold Call | K6: 11/5/2025 - info@psmf.org - consuelo answered and said that michael wasn't available but that it sound interesting. 11/12/2025 - my email was flagged as spam so she didn't see it. She see's it now and is going to talk to her manager Michael tomorrow during their meeting. She's hoping I can send more info to help me seem like a legitimate thing (website? linkedin? CV?). Also said this sounds interesting because they have such a broad focus that it takes a lot to parse through all the potential grants and find one that's a good match. She also mentioned that they don't have a grant manager and that it would be helpful to mark in the questionnair what kind of time frame of grants they're looking for. | N6: Talked to Someone | O6: =Progress!C7 -> 20 | P6: =Progress!D7 -> 0.25316456 | Q6: =Restaurants!J5 -> 3 | R6: =Restaurants!K5 -> 0.5 | S6: ='Gov Contractors'!D5 -> 1 | T6: ='Gov Contractors'!E5 -> 0.2 | U6: =SUM(S6,Q6,O6) -> 24 | V6: =U6/U4 -> 0.26666667
B7: 2. Recieved Report | C7: Ka Ulukoa | D7: Lee Lamb | E7: HI | F7: 45973 | G7: (808) 741-1276 | H7: lamb@kaulukoa.org | I7: https://www.kaulukoa.org/ | J7: Cold Email | K7: 11/12/2025 - He responded: "This email address is fine, admin@kaulukoa.org. Thanks." | N7: Sent Info Email | O7: =Progress!C11 -> 3 | P7: =Progress!D11 -> 0.037974684 | Q7: =Restaurants!J6 -> 1 | R7: =Restaurants!K6 -> 0.16666667 | S7: ='Gov Contractors'!D6 -> 0 | T7: ='Gov Contractors'!E6 -> 0 | U7: =SUM(S7,Q7,O7) -> 4 | V7: =U7/U4 -> 0.044444444
B8: 2. Recieved Report | C8: Arborbrook Christian Academy | D8: Derek Durst | E8: NC | F8: 45973 | G8: (704) 821-9952 | H8: derek.durst@arborbrook.org | I8: https://www.arborbrook.org/ | J8: Cold Email | K8: 11/12/2025 - "Yes, I would be interested. This is the best email ". As in use this email to send the alerts | N8: Talked to Decision Maker | O8: =Progress!#REF! -> #REF! | P8: =Progress!#REF! -> #REF! | Q8: =Restaurants!J7 -> 4 | R8: =Restaurants!K7 -> 0.66666667 | S8: ='Gov Contractors'!D7 -> 0 | T8: ='Gov Contractors'!E7 -> 0 | U8: =SUM(S8,Q8,O8) -> #REF! | V8: =U8/U4 -> #REF!
B9: 3. Filled out questionnaire | C9: Horizons National Student Enrichment Program Inc. | D9: Alex Hoffmaster | E9: MA | H9: ahoffmaster@horizonsnational.org
B10: 3. Filled out questionnaire | C10: Highland Lakes Family Crisis Center | D10: Hardaway | E10: TX | F10: 46006 | H10: jhardaway@gmail.com
B11: 3. Filled out questionnaire | C11: Friendship Circle SD INC. | D11: Yossi Rodal | E11: CA | H11: rabbiyossi@friendshipsd.org
B13: 4. Interested | C13: Catalina Island Conservancy | D13: Kristine Partridge | E13: CA | F13: 45968 | G13: 562-437-8555 | H13: kristinepartridge@me.com | I13: https://catalinaconservancy.org/ | J13: Linkedin | K13: 11/10/2025 - Said she wouldn't mind getting the emails.
B14: 4. Interested | C14: Sonoma County Farm Bureau | D14: Brooke | E14: CA | F14: 45967 | G14: 7075445575 | H14: Brooke@sonomafb.org | I14: https://WWW.SONOMAFB.ORG | J14: Cold Call | K14: 11/6/2025 - Talked to Brooke, she gave me her email and said to send an email to her and then she'll forward it to Dayna who'll be the one that decides. Brooke@sonomafb.org 11/12/2025 - Also got put in spam - she said to send over my linkedin and she'd forward all three emails/info for Dayna to look at and decide if they want to join. She asked if I was with a company and I explained a bit about my background and how I'm testing out something I've built on the side.
B15: 4. Interested | C15: Children Today Inc | D15: Fernanda | E15: CA | F15: 45967 | G15: 5629978800 | H15: Alexis@childrentoday.org | I15: https://WWW.CHILDRENTODAY.ORG | J15: Cold Call | K15: 11/6/2025 - Fernanda said she'd let Alexis know I called. Alexis@childrentoday.org. 11/12/2025 - Alexis answered and said that Elia is the right person to talk to and gave me her email: elia@childrentoday.org.
B16: 5. Check Back Later | C16: Bikur Cholim | D16: Lucky | E16: CA | F16: 45966 | G16: 3238521900 | H16: info@bikurcholim.net | I16: https://WWW.BIKURCHOLIM.NET | J16: Cold Call | K16: 11/5/2025 - Lucky - Director. Needs Review, how do they connect to it etc(said make the email as detailed as possible so they can look into it. - info@bikurcholim.net. 11/12/2025 - Working through a lot right now (technical challenges etc with other things(I guess they just migrated all of their systems to mac book) - Let them know when we launch, and then reach out again in six months when they're probably more settled and they'll be able to focus on it. REACH OUT WHEN LAUNCHING AND IN SIX MONTHS(5/12/2025) | L16: 45789
B17: 5. Send info | C17: AFRICAN AMERICAN CULTURAL CENTER | D17: JOANNA FARRIS | E17: CA | F17: 46003 | G17: 4089106958 | H17: Jmfarris@netzero.net | J17: Cold Call | K17: 12/12 - Send email with info and she’ll take it to the business development (sales & marketing?) Meeting next week. “Probably nothing will happen until next year”

Sheet Summary
B2: Outreach Progress
C3: Nonprofits | E3: Restaurants | G3: Gov Contractors | I3: Total
B4: Total Called | C4: =Nonprofits!#REF! -> #REF! | D4: =Nonprofits!#REF! -> #REF! | E4: =Restaurants!#REF! -> #REF! | F4: =Restaurants!#REF! -> #REF! | G4: ='Gov Contractors'!#REF! -> #REF! | H4: ='Gov Contractors'!#REF! -> #REF! | I4: =SUM(G4,E4,C4) -> #REF! | J4: =I4/900 -> #REF!
B5: VM's | C5: =Nonprofits!#REF! -> #REF! | D5: =Nonprofits!#REF! -> #REF! | E5: =Restaurants!#REF! -> #REF! | F5: =Restaurants!#REF! -> #REF! | G5: ='Gov Contractors'!#REF! -> #REF! | H5: ='Gov Contractors'!#REF! -> #REF! | I5: =SUM(G5,E5,C5) -> #REF! | J5: =I5/I4 -> #REF!
B6: Talked to Someone | C6: =Nonprofits!#REF! -> #REF! | D6: =Nonprofits!#REF! -> #REF! | E6: =Restaurants!#REF! -> #REF! | F6: =Restaurants!#REF! -> #REF! | G6: ='Gov Contractors'!#REF! -> #REF! | H6: ='Gov Contractors'!#REF! -> #REF! | I6: =SUM(G6,E6,C6) -> #REF! | J6: =I6/I4 -> #REF!
B7: Sent Info Email | C7: =Nonprofits!#REF! -> #REF! | D7: =Nonprofits!#REF! -> #REF! | E7: =Restaurants!#REF! -> #REF! | F7: =Restaurants!#REF! -> #REF! | G7: ='Gov Contractors'!#REF! -> #REF! | H7: ='Gov Contractors'!#REF! -> #REF! | I7: =SUM(G7,E7,C7) -> #REF! | J7: =I7/I4 -> #REF!
B8: Talked to Decision Maker | C8: =Nonprofits!#REF! -> #REF! | D8: =Nonprofits!#REF! -> #REF! | E8: =Restaurants!#REF! -> #REF! | F8: =Restaurants!#REF! -> #REF! | G8: ='Gov Contractors'!#REF! -> #REF! | H8: ='Gov Contractors'!#REF! -> #REF! | I8: =SUM(G8,E8,C8) -> #REF! | J8: =I8/I4 -> #REF!

Sheet Sheet3
B2: Status
B3: 1. Gave feedback | C3: 1 | D3: Yes
B4: 2. Recieved Report | C4: 0 | D4: No
B5: 3. Filled out questionnaire | D5: Maybe
B6: 4. Interested | D6: No Answer Try Again
B7: 5. Send info | D7: Gatekeeper Will Give Message
B8: 6. Check Back Later
B9: 7. Not Interested

Sheet Pipeline Lists
B2: Verticals | C2: Yes/No/Maybe
B3: Nonprofits | C3: Yes | D3: 1
B4: Restaurants | C4: No | D4: 0
B5: Gov. Contractors | C5: Maybe
C6: Uncertain

Sheet Nonprofits
B2: Organization_Name | C2: Contact Date | D2: Phone | E2: Officer_Name | F2: Officer_Title | G2: Mission Statement | H2: Website | I2: Address | J2: City | K2: State | L2: employee_count | M2: volunteer_count | N2: ZIP | O2: Website2 | P2: Total_Revenue | Q2: Grants_Revenue | R2: Grant_Dependency_Pct | S2: Total_Expenses | T2: Mission | U2: Max Weekly Hours | V2: NTEE_Codes | W2: Tax_Year | X2: EIN | Y2: Prospect_Score | Z2: Decision Maker | AA2: Decision Maker Title | AB2: VM/Message | AC2: Talked to Someone | AD2: Send us an Email | AE2: Reached Decision Maker | AF2: Yes/No/Maybe/Uncertain | AG2: Notes
B3: COACHELLA VALLEY REPERTORY | C3: 45966 | D3: 7602962966 | E3: NICOLE TAYLOR CPA | F3: TREASURER | I3: 68510 E PALM CANYON DR | J3: CATHEDRAL CITY | K3: CA | N3: 922341300 | O3: https://CVREP.ORG | P3: 2012562 | Q3: 894440 | R3: 44.4 | S3: 2279846 | T3: COACHELLA VALLEY REPERTORY IS AN EDUCATIONAL, DRAMATIC AND MUSICAL THEATRE ORGANIZATION THAT OFFERS THOUGHT-PROVOKING, INNOVATIVE THEATER OF SUBSTANCE, AND A VOICE TO A WIDE RANGE OF ARTISTS AND VISIONS. CVREP PROVIDES PRODUCTIONS AND OUTREACH PROGRAMS THAT POSITIVELY ENRICH, ENHANCE AND IMPACT THE | U3: {=MAX(_xlfn._xlws.FILTER('Email Outreach Prospects'!F:F, 'Email Outreach Prospects'!B:B=B3))} -> 40 | V3: A, B | W3: 2023 | X3: 954304295 | Y3: 10 | Z3: Joe | AA3: CFO | AB3: 1 | AC3: 0 | AD3: 0 | AE3: 0 | AF3: Uncertain | AG3: No Answer - VM for Joe, CFO
B4: UJIMA ADULT AND FAMILY SERVICES INC | C4: 45966 | D4: 4089281700 | E4: YVONNE MAXWELL | F4: EXECUTIVE DIRECTOR | I4: 1898 THE ALAMEDA | J4: SAN JOSE | K4: CA | N4: 95126 | O4: http://www.ujimaagency.org | P4: 1860541 | Q4: 1779408 | R4: 95.6 | S4: 1697991 | T4: TO PROVIDE AFRICENTRIC MENTAL HEALTH, COUNSELING, AND SUPPORT SERVICES TO THE AFRICAN AMERICAN COMMUNITY THROUGH FOCUSING ON AFRICAN HISTORY, CULTURAL NORMS, AND VALUES | U4: {=MAX(_xlfn._xlws.FILTER('Email Outreach Prospects'!F:F, 'Email Outreach Prospects'!B:B=B4))} -> 40 | V4: A, E, P | W4: 2023 | X4: 770376995 | Y4: 10 | AB4: 1 | AC4: 1 | AD4: 0 | AE4: 0 | AF4: Uncertain | AG4: Gave Operator 12 a message
B5: BURLINGTON COMM SRVS & HOUSING DEV | C5: 45966 | D5: 2134830928 | E5: CECILIA C RAMOS | F5: ADMINISTRATOR | I5: 242 N BURLINGTON AVE | J5: LOS ANGELES | K5: CA | N5: 90026 | O5: https://X | P5: 1286407 | Q5: 1286407 | R5: 100 | S5: 1286407 | T5: TO PROVIDE DAYCARE SERVICES TO LOW AND MODERATE INCOME FAMILIES AND WELFARE RECIPIENTS. | U5: {=MAX(_xlfn._xlws.FILTER('Email Outreach Prospects'!F:F, 'Email Outreach Prospects'!B:B=B5))} -> 1 | V5: P, S | W5: 2023 | X5: 510181441 | Y5: 10 | AB5: 1 | AC5: 1 | AD5: 0 | AE5: 0 | AF5: Uncertain | AG5: burlingtonschoolinc@gmail.com, Maree -- Said to send email, kind of hard to understand with accent(and may not of understood me very well)
B6: Career Technical Education Foundation Sonoma County | C6: 45966 | D6: 7077087080 | E6: Kathy Goodacre | F6: CEO | I6: 1030 Apollo Way 200 | J6: Santa Rosa | K6: CA | N6: 95407 | O6: https://www.ctesonomacounty.org | P6: 2798209 | Q6: 2780988 | R6: 99.4 | S6: 2355047 | T6: INNOVATING THE EDUCATION-TO-CAREER EXPERIENCE TO STRENGTHEN ECONOMIC DEVELOPMENT AND STUDENT SUCCESS. | U6: {=MAX(_xlfn._xlws.FILTER('Email Outreach Prospects'!F:F, 'Email Outreach Prospects'!B:B=B6))} -> 40 | V6: B, S | W6: 2023 | X6: 465607272 | Y6: 10 | AB6: 1 | AC6: 0 | AD6: 0 | AE6: 0 | AF6: Uncertain | AG6: Left VM
B7: COUNCIL OF CHIEF LIBRARIANS | C7: 45966 | D7: 5309088810 | E7: GREGG ATKINS | F7: Director | I7: 1809 S ST STE 101-172 | J7: SACRAMENTO | K7: CA | N7: 95811 | O7: https://CCLIBRARIANS.ORG | P7: 1715620 | Q7: 1702345 | R7: 99.2 | S7: 1452686 | T7: TO REPRESENT, PROMOTE AND ADVANCE LIBRARIES IN PUBLIC CALIFORNIA COMMUNITY COLLEGE EDUCATION. TO PROVIDE A VEHICLE FOR COMMUNICATION, DISCUSSION, AND COLLABORATION AMONG CHIEF LIBRARIANS. TO PROVIDE OPPORTUNITIES FOR PROFESSIONAL DEVELOPMENT, TRAINING, AND LEADERSHIP OF CHIEF AND OTHER ACADEMIC LIBR | U7: {=MAX(_xlfn._xlws.FILTER('Email Outreach Prospects'!F:F, 'Email Outreach Prospects'!B:B=B7))} -> 5 | V7: A, B | W7: 2023 | X7: 954214083 | Y7: 10 | Z7: GREGG ATKINS | AA7: Director | AB7: 1 | AC7: 0 | AD7: 0 | AE7: 0 | AF7: Uncertain | AG7: Left VM - voiemailbox for Gregg
B8: Fair Housing Advocates of Northern California | C8: 45966 | D8: 4154575025 | E8: Caroline Peattie | F8: Executive Director | I8: 851 Irwin Street Suite 218 | J8: San Rafael | K8: CA | N8: 94901 | O8: https://www.fairhousingnorcal.org | P8: 1839889 | Q8: 1224928 | R8: 66.6 | S8: 1961348 | T8: We provide fair housing, pre-purchase, and mortgage foreclosure prevention services in Marin, Sonoma, and Solano counties, with advisory training in other counties. Our services to tenants and homeowners are available at no charge in English and Spanish. | U8: {=MAX(_xlfn._xlws.FILTER('Email Outreach Prospects'!F:F, 'Email Outreach Prospects'!B:B=B8))} -> 37.5 | V8: B, S | W8: 2023 | X8: 680087976 | Y8: 10 | AB8: 1 | AC8: 0 | AD8: 0 | AE8: 0 | AF8: Uncertain | AG8: Left VM
B9: Legal Aid Association of California | C9: 45966 | D9: 5108933000 | E9: Salena Copeland | F9: Executive Dir. | I9: 1832 Second Street Suite 105 | J9: Berkeley | K9: CA | N9: 94710 | O9: https://www.laaconline.org | P9: 1644600 | Q9: 1532722 | R9: 93.2 | S9: 1566417 | T9: The Legal Aid Association of California, the statewide membership of legal services nonprofits, serves its members through advocacy and other support in efforts to provide legal assistance to low-income Californians and ensure access to justice. | U9: {=MAX(_xlfn._xlws.FILTER('Email Outreach Prospects'!F:F, 'Email Outreach Prospects'!B:B=B9))} -> 40 | V9: B | W9: 2023 | X9: 330042690 | Y9: 10 | AB9: 1 | AC9: 0 | AD9: 0 | AE9: 0 | AF9: Uncertain | AG9: Left VM
B10: Scientific Adventures dba Scientific | C10: 45966 | D10: 4155315288 | E10: Courtenay Carr Heuer | F10: Executive Dir. | I10: PO Box 11123 | J10: Oakland | K10: CA | N10: 94611 | O10: https://www.scientificadventures.org | P10: 1142976 | Q10: 855271 | R10: 74.8 | S10: 907002 | T10: To remove systemic barriers to all girls participation in STEM starting in transitional kindergarten, engage them through hands-on learning, increase their positive attitudes toward STEM, and equip them with 21st century skills. | U10: {=MAX(_xlfn._xlws.FILTER('Email Outreach Prospects'!F:F, 'Email Outreach Prospects'!B:B=B10))} -> 40 | V10: A, B | W10: 2023 | X10: 472414936 | Y10: 10 | Z10: Courtenay Carr Heuer | AA10: Executive Dir. | AB10: 1 | AC10: 0 | AD10: 0 | AE10: 0 | AF10: Uncertain | AG10: Left VM - voiemailbox for courtenay
B11: Santa Ynez Valley Charter School Inc | C11: 45966 | D11: 8056867363 | E11: Matt Stockton | F11: Board President | I11: 1224 Tyndall Street | J11: Santa Ynez | K11: CA | N11: 93460 | O11: https://www.syvcs.org | P11: 2102762 | Q11: 1939880 | R11: 92.3 | S11: 2102803 | T11: To work collaboratively to create a supportive innovative and academically challenging educational environment that nurtures its students and prepares them for high school and beyond through close curricular articulation. | U11: {=MAX(_xlfn._xlws.FILTER('Email Outreach Prospects'!F:F, 'Email Outreach Prospects'!B:B=B11))} -> 40 | V11: B, C | W11: 2022 | X11: 770552159 | Y11: 10 | AB11: 1 | AC11: 0 | AD11: 0 | AE11: 0 | AF11: Uncertain | AG11: Left VM
B12: Project Hope Alliance | C12: 45966 | D12: 9497227824 | E12: JENNIFER FRIEND | F12: CEO | I12: 1954 Placentia Avenue Suite 202 | J12: Costa Mesa | K12: CA | N12: 92627 | O12: https://www.projecthopealliance.org | P12: 3045129 | Q12: 2387123 | R12: 78.4 | S12: 2991624 | T12: THE MISSION OF PROJECT HOPE ALLIANCE IS TO END THE CYCLE OF HOMELESSNESS, ONE CHILD AT A TIME. OUR VISION IS EQUIPPING HOMELESS CHILDREN WITH THE TOOLS AND OPPORTUNITIES TO LEARN THEIR WAY TO A BETTER TOMORROW. | U12: {=MAX(_xlfn._xlws.FILTER('Email Outreach Prospects'!F:F, 'Email Outreach Prospects'!B:B=B12))} -> 40 | V12: P | W12: 2023 | X12: 753099628 | Y12: 10 | Z12: JENNIFER FRIEND | AA12: CEO | AB12: 1 | AC12: 0 | AD12: 0 | AE12: 0 | AF12: Uncertain | AG12: Left VM - voiemailbox for Jennifer
B13: STARTX | C13: 45966 | D13: 6502839206 | E13: SHANNON MCCLENAGHAN | F13: DIRECTOR | I13: 2627 HANOVER ST | J13: PALO ALTO | K13: CA | N13: 94304 | O13: https://STARTX.COM | P13: 1809968 | Q13: 1534495 | R13: 84.8 | S13: 2321609 | T13: STARTX IS A NONPROFIT EDUCATIONAL PROGRAM RUN PRIMARILY BY ALUMNI AND STUDENTS OF STANFORD UNIVERSITY. THE MISSION OF STARTX IS TO ACCELERATE THE DEVELOPMENT OF HIGH-POTENTIAL, STANFORD ENTREPRENEURS THROUGH EXPERIENTIAL EDUCATION. | U13: {=MAX(_xlfn._xlws.FILTER('Email Outreach Prospects'!F:F, 'Email Outreach Prospects'!B:B=B13))} -> 60 | V13: B | W13: 2023 | X13: 454308444 | Y13: 10 | AB13: 1 | AC13: 0 | AD13: 0 | AE13: 0
B14: PATIENT SAFETY MOVEMENT FOUNDATION | C14: 45966 | D14: 9492307588 | E14: MICHAEL AE RAMSAY | F14: MD CEO | I14: 15642 SAND CANYON AVE STE 51268 | J14: IRVINE | K14: CA | N14: 92619 | O14: https://PSMF.ORG | P14: 2096479 | Q14: 2063971 | R14: 98.4 | S14: 2189165 | T14: OUR MISSION IS TO DISSEMINATE ACTIONABLE EVIDENCE-BASED PRACTICES, ADVANCE THEIR INTEGRATION BY HEALTHCARE ORGANIZATIONS, AND CULTIVATE DATA TRANSPARENCY BY 2030. | U14: {=MAX(_xlfn._xlws.FILTER('Email Outreach Prospects'!F:F, 'Email Outreach Prospects'!B:B=B14))} -> 0 | V14: E | W14: 2023 | X14: 462730379 | Y14: 10 | Z14: Consuelo | AB14: 1 | AC14: 1 | AD14: 1 | AE14: 1 | AF14: Maybe | AG14: info@psmf.org - consuelo answered and said that michael wasn't available but that it sound interesting.
B15: NEXT DOOR SOLUTIONS TO DOMESTIC VIOLENCE | C15: 45966 | D15: 4085017550 | E15: COLSARIA HENDERSON | F15: EXECUTIVE DIRECTOR | I15: 234 EAST GISH ROAD SUITE 200 | J15: SAN JOSE | K15: CA | N15: 95112 | O15: https://WWW.NEXTDOORSOLUTIONS.ORG | P15: 4451135 | Q15: 4467191 | R15: 100.4 | S15: 4809493 | T15: TO END DOMESTIC VIOLENCE IN THE MOMENT AND FOR ALL TIME. | U15: {=MAX(_xlfn._xlws.FILTER('Email Outreach Prospects'!F:F, 'Email Outreach Prospects'!B:B=B15))} -> 40 | V15: B, P | W15: 2023 | X15: 942420708 | Y15: 10 | AB15: 1 | AC15: 0 | AD15: 0 | AE15: 0
B16: Catholic Charities of Yolo-Solano | C16: 45966 | D16: 7076448909 | E16: John Watkins | F16: Executive Director | I16: 125 Corporate Place | J16: Vallejo | K16: CA | N16: 94590 | O16: https://www.csssolano.org | P16: 1512402 | Q16: 1047412 | R16: 69.3 | S16: 1635446 | T16: OUR MISSION IS TO REACH OUT AND PROVIDE ASSISTANCE TO ANYONE IN NEED IN OUR COMMUNITY, ESPECIALLY THE POOR AND DISADVANTAGED. WE OFFER HEALTH AND SOCIAL SERVICE PROGRAMS THAT CONTRIBUTE TO THE INDIVIDUAL'S FREEDOM AND INDEPENDENCE, WHILE ALWAYS VALUING THE DIGNITY OF HUMAN LIFE AND IMPORTANCE OF FAM | U16: {=MAX(_xlfn._xlws.FILTER('Email Outreach Prospects'!F:F, 'Email Outreach Prospects'!B:B=B16))} -> 40 | V16: E, P | W16: 2022 | X16: 465010936 | Y16: 10 | AB16: 1 | AC16: 0 | AD16: 0 | AE16: 0
B17: HUNGER AT HOME | C17: 45966 | D17: 4083180038 | E17: WILLIAM STERNER | F17: PRESIDENT | I17: 1560 BERGER DRIVE | J17: SAN JOSE | K17: CA | N17: 95112 | O17: https://HUNGERATHOME.ORG | P17: 4769513 | Q17: 4767688 | R17: 100 | S17: 4888587 | T17: HUNGER AT HOME SERVES AS A CONDUIT BETWEEN THE BUSINESS COMMUNITY AND NONPROFIT PARTNERS BY WHICH EXCESS FOOD AND OTHER SURPLUS IS CHANNELED TO THE HOMELESS AND THE HUNGRY. | U17: {=MAX(_xlfn._xlws.FILTER('Email Outreach Prospects'!F:F, 'Email Outreach Prospects'!B:B=B17))} -> 40 | V17: P | W17: 2022 | X17: 475462753 | Y17: 10 | AB17: 1 | AC17: 0 | AD17: 0 | AE17: 0
B18: BIKUR CHOLIM | C18: 45966 | D18: 3238521900 | E18: HAROLD TEN | F18: PRESIDENT/CEO (Rabi Ten) | I18: 8489 WEST THIRD STREET | J18: LOS ANGELES | K18: CA | N18: 90048 | O18: https://WWW.BIKURCHOLIM.NET | P18: 1458541 | Q18: 1421416 | R18: 97.5 | S18: 874068 | T18: BIKUR CHOLIM ORGANIZES AND SUBSIDIZES MEDICAL TREATMENT, SPEECH AND PHYSICAL THERAPY, MEDICATION, DURABLE MEDICAL EQUIPMENT, BLOOD PRODUCTS, HOMECARE, TRANSPORTATION, HOUSING FOR PATIENTS AND FAMILY-MEMBERS, MEALS, AND DIAGNOSTICS WHILE PROVIDING SOCIAL SUPPORT AND ADVOCACY. | U18: {=MAX(_xlfn._xlws.FILTER('Email Outreach Prospects'!F:F, 'Email Outreach Prospects'!B:B=B18))} -> 90 | V18: E, S | W18: 2022 | X18: 954521980 | Y18: 10 | Z18: Lucky | AA18: Director | AB18: 1 | AC18: 1 | AD18: 1 | AE18: 1 | AF18: Maybe | AG18: Lucky - Director. Needs Review, how do they connect to it etc(said make the email as detailed as possible so they can look into it. - info@bikurcholim.net
B19: BUDDHIST GLOBAL RELIEF | C19: 45966 | D19: 6098644054 | E19: HILLARY CHEN | F19: Treasurer | I19: 506 BROUGHTON LANE | J19: FOSTER CITY | K19: CA | N19: 94404 | O19: https://WWW.BUDDHISTGLOBALRELIEF.ORG | P19: 1806042 | Q19: 1654299 | R19: 91.6 | S19: 1927648 | T19: TO ALLEVIATE SUFFERING, POVERTY AND OPPRESSION THROUGH DIRECT AID, ECONOMIC AND TECHINICAL ASSISTANCE, EDUCATION AND OTHER FORMS OF CHARITABLE ASSISTANCE TO PEOPLE IN NEED THROUGHTOUT THE WORLD | U19: {=MAX(_xlfn._xlws.FILTER('Email Outreach Prospects'!F:F, 'Email Outreach Prospects'!B:B=B19))} -> 30 | V19: B | W19: 2023 | X19: 262852923 | Y19: 10 | AB19: 1 | AC19: 0 | AD19: 0 | AE19: 0 | AG19: Hillary Chen's Email
B20: VILLA GREENTREE INC | C20: 45967 | D20: 5622575100 | E20: FRANK ROSSELLO | F20: CFO/V.P., FINANCE | I20: 911 NORTH STUDEBAKER ROAD | J20: LONG BEACH | K20: CA | N20: 90815 | O20: https://WWW.RHF.ORG | P20: 2347222 | Q20: 1306342 | R20: 55.7 | S20: 1950843 | T20: VILLA GREENTREE, INC. IS A NOT-FOR-PROFIT CORPORATION FORMED IN ACCORDANCE WITH THE NOT-FOR-PROFIT STATUTES OF THE STATE OF INDIANA. THE CORPORATION WAS FORMED FOR THE PURPOSE OF OPERATING A 202 UNIT COMMUNITY KNOWN AS YELLOWWOOD TERRACE LOCATED IN CLARKSVILLE, INDIANA, WHICH PROVIDES HOUSING FOR LO | U20: {=MAX(_xlfn._xlws.FILTER('Email Outreach Prospects'!F:F, 'Email Outreach Prospects'!B:B=B20))} -> 0.2 | V20: P, S | W20: 2023 | X20: 311042917 | Y20: 10 | AB20: 1 | AC20: 0 | AD20: 0 | AE20: 0 | AF20: Uncertain | AG20: Operator connected me to Frank
B21: The Clearity Foundation | C21: 45967 | D21: 8586570282 | E21: Hillary C Theakston | F21: Executive Director | I21: 8880 Rio San Diego Drive STE 800 | J21: San Diego | K21: CA | N21: 92108 | O21: https://www.clearityfoundation.org | P21: 1787046 | Q21: 1852123 | R21: 103.6 | S21: 1932061 | T21: The mission is to seek better treatment options for women with ovarian cancer by providing diagnostic services that determine the molecular profile of the individual patient and providing doctors access to molecular profiling for their ovarian cancer patients. | U21: {=MAX(_xlfn._xlws.FILTER('Email Outreach Prospects'!F:F, 'Email Outreach Prospects'!B:B=B21))} -> 0 | V21: E | W21: 2023 | X21: 261095856 | Y21: 10 | AB21: 1 | AC21: 0 | AD21: 0 | AE21: 0 | AF21: Uncertain
B22: CALIFORNIA SCHOOL BOARDS FOUNDATION | C22: 45967 | D22: 9163714691 | E22: LARE BLOODWORTH | F22: CHIEF FINANCIAL OFFICER | I22: 3251 BEACON BOULEVARD | J22: WEST SACRAMENTO | K22: CA | N22: 956913531 | O22: https://WWW.CSBA.ORG | P22: 2152782 | Q22: 2098228 | R22: 97.5 | S22: 1025597 | T22: THE MISSION OF THE CALIFORNIA SCHOOL BOARDS FOUNDATION IS TO PROVIDE EDUCATION, SUPPORT, AND TRAINING TO SCHOOL BOARD MEMBERS, CONDUCT POLICY RESEARCH AND ANALYSIS ON EDUCATION-RELATED ISSUES, TO RECOGNIZE EDUCATIONAL LEADERSHIP AND ACHIEVEMENTS IN CALIFORNIA, TO ENCOURAGE AND FACILITATE THE PROCESS | U22: {=MAX(_xlfn._xlws.FILTER('Email Outreach Prospects'!F:F, 'Email Outreach Prospects'!B:B=B22))} -> 8 | V22: B | W22: 2023 | X22: 941623582 | Y22: 10 | AB22: 1 | AC22: 0 | AD22: 0 | AE22: 0 | AF22: Uncertain
B23: SONOMA COUNTY FARM BUREAU | C23: 45967 | D23: 7075445575 | E23: JOHN BIDIA | F23: TREASURER | I23: 3589 WESTWIND BLVD | J23: SANTA ROSA | K23: CA | N23: 95403 | O23: https://WWW.SONOMAFB.ORG | P23: 1217815 | Q23: 656471 | R23: 53.9 | S23: 1098740 | T23: SEE SCHEDULE O | U23: {=MAX(_xlfn._xlws.FILTER('Email Outreach Prospects'!F:F, 'Email Outreach Prospects'!B:B=B23))} -> 0 | V23: B | W23: 2023 | X23: 941210577 | Y23: 10 | Z23: Dayna Ghirardelli | AA23: Executive Director | AB23: 1 | AC23: 1 | AD23: 1 | AE23: 0 | AF23: Uncertain | AG23: Talked to Brooke, she gave me her email and said to send an email to her and then she'll forward it to Dayna who'll be the one that decides. Brooke@sonomafb.org
B24: Satellite Senior Homes III Inc | C24: 45967 | D24: 5106470700 | E24: SUSAN FRIEDLAND | F24: CEO | I24: 1835 Alcatraz Avenue | J24: Berkeley | K24: CA | N24: 94703 | O24: https://www.sahahomes.org | P24: 2881971 | Q24: 2145260 | R24: 74.4 | S24: 2290752 | T24: TO PROVIDE LOW-INCOME ELDERLY & HANDICAPPED PERSONS WITH AFFORDABLE HOUSING FACILITIES & SERVICES SPECIALLY DESIGNED TO MEET THEIR PHYSICAL, SOCIAL & PSYCHOLOGICAL NEEDS, AND TO PROMOTE THEIR HEALTH, SECURITY, HAPPINESS & USEFULNESS IN LONGER LIVING ON A NONPROFIT BASIS. | U24: {=MAX(_xlfn._xlws.FILTER('Email Outreach Prospects'!F:F, 'Email Outreach Prospects'!B:B=B24))} -> 0.1 | V24: E, P, S | W24: 2023 | X24: 942835291 | Y24: 10 | AB24: 1 | AC24: 0 | AD24: 0 | AE24: 0 | AF24: Uncertain
B25: CHILDREN TODAY INC | C25: 45967 | D25: 5629978800 | E25: ELIA ROCHA | F25: EXECUTIVE DIRECTOR | I25: 2951 LONG BEACH BLVD | J25: LONG BEACH | K25: CA | N25: 90806 | O25: https://WWW.CHILDRENTODAY.ORG | P25: 1903027 | Q25: 1869459 | R25: 98.2 | S25: 1817646 | T25: TO PROVIDE TRAUMA-INFORMED CHILD DEVELOPMENT, PRESCHOOL, AND FAMILY SUPPORT SERVICES TO FAMILIES EXPERIENCING HOMELESSNESS, AND/OR MALTREATMENT, FOSTERING LONG-TERM STABILITY AND SUCCESS. | U25: {=MAX(_xlfn._xlws.FILTER('Email Outreach Prospects'!F:F, 'Email Outreach Prospects'!B:B=B25))} -> 40 | V25: B, P | W25: 2023 | X25: 954635295 | Y25: 10 | Z25: Alexis | AB25: 1 | AC25: 1 | AD25: 1 | AE25: 0 | AF25: Uncertain | AG25: Fernanda said she'd let Alexis know I called. Alexis@childrentoday.org
B26: Court Appointed Special Advocates | C26: 45967 | D26: 8317612956 | E26: Josue Barajas | F26: President | I26: 813 Freedom Blvd | J26: Watsonville | K26: CA | N26: 95076 | O26: https://WWW.CASAOFSANTACRUZ.ORG | P26: 1832706 | Q26: 1786616 | R26: 97.5 | S26: 2153201 | T26: CASA of Santa Cruz advocates for children and youth, providing court appointed volunteers so each child in the dependency and juvenile court system feels cared for and connected with the people, families and resources they need to heal and flourish into adulthood. | U26: {=MAX(_xlfn._xlws.FILTER('Email Outreach Prospects'!F:F, 'Email Outreach Prospects'!B:B=B26))} -> 40 | V26: P | W26: 2023 | X26: 770305354 | Y26: 10 | AB26: 1 | AC26: 0 | AD26: 0 | AE26: 0 | AF26: Uncertain
B27: FAMILY SUPPORT NETWORK | C27: 45967 | D27: 7144473301 | E27: MAURA BYRON | F27: EXECUTIVE DIRECTOR | I27: 1894 N MAIN STREET | J27: ORANGE | K27: CA | N27: 92865 | O27: https://WWW.FSN-OC.ORG | P27: 1155471 | Q27: 1143003 | R27: 98.9 | S27: 1165113 | T27: PROVIDES SERVICES OFFERING RESOURCES AND ADVOCACY FOR FAMILIES/CHILDREN WITH SOCIAL, EMOTIONAL, INTELLECTUAL AND PHYSICAL NEEDS SO THEY MAY REACH THEIR FULL POTENTIAL. | U27: {=MAX(_xlfn._xlws.FILTER('Email Outreach Prospects'!F:F, 'Email Outreach Prospects'!B:B=B27))} -> 50 | V27: P | W27: 2023 | X27: 330248195 | Y27: 10 | Z27: Moe | AA27: Byron | AB27: 1 | AC27: 1 | AD27: 0 | AE27: 0 | AF27: Uncertain | AG27: Kathia sent me to Moe's VMbox (maura byron)
B28: STUDENTS RUN AMERICA | C28: 45967 | D28: 8186543360 | E28: GABRIELA ARVIZU | F28: PRESIDENT/CEO | I28: 5252 CREBS AVENUE | J28: TARZANA | K28: CA | N28: 91356 | O28: https://WWW.SRLA.ORG | P28: 3711013 | Q28: 3515368 | R28: 94.7 | S28: 3601363 | T28: CHALLENGE UNDERSERVED SECONDARY STUDENTS TO STAY IN SCHOOL AND EXPERIENCE THE BENEFITS OF GOAL-SETTING, CHARACTER DEVELOPMENT, ADULT MENTORING AND IMPROVED HEALTH BY PROVIDING THEM WITH A LIFE-CHANGING EXPERIENCE: COMPLETING THE LA MARATHON. | U28: {=MAX(_xlfn._xlws.FILTER('Email Outreach Prospects'!F:F, 'Email Outreach Prospects'!B:B=B28))} -> 40 | V28: B, E | W28: 2023 | X28: 954430502 | Y28: 10 | AB28: 1 | AC28: 0 | AD28: 0 | AE28: 0 | AF28: Uncertain
B29: YOUNG WOMENS CHRISTIAN ASSOCIATION OF THE HARBOR AREA | C29: 45967 | D29: 3105470831 | E29: JULIE WICHMANN HUERTA | F29: PRESIDENT | I29: 437 W 9TH STREET | J29: SAN PEDRO | K29: CA | N29: 90731 | O29: https://ywcaharbor.org | P29: 1457085 | Q29: 687388 | R29: 47.2 | S29: 1356180 | T29: THE MISSION OF THE YWCA IS TO FOSTER THE ECONOMIC SELF-SUFFICIENCY, EMOTIONAL AND PHYSICAL HEALTH OF WOMEN AND GIRLS IN A WORLD OF PEACE, RACIAL JUSTICE, DIGNITY, FREEDOM AND EQUALITY FOR ALL. | U29: {=MAX(_xlfn._xlws.FILTER('Email Outreach Prospects'!F:F, 'Email Outreach Prospects'!B:B=B29))} -> 40 | V29: E | W29: 2022 | X29: 951691337 | Y29: 10 | AB29: 0 | AC29: 0 | AD29: 0 | AE29: 0 | AF29: Uncertain
B30: SENIOR NETWORK SERVICES INC | C30: 45967 | D30: 8314621433 | E30: COREY F AZEVEDO | F30: Executive Dir. | I30: 1777-A CAPITOLA ROAD | J30: SANTA CRUZ | K30: CA | N30: 95062 | O30: https://seniornetworkservices.org | P30: 1956265 | Q30: 1856854 | R30: 94.9 | S30: 2036635 | T30: Senior Network Services is a nonprofit agency providing senior citizens and persons with disabilities with information, guidance and assistance in coordinating existing resources to promote independence and the highest quality of life. | U30: {=MAX(_xlfn._xlws.FILTER('Email Outreach Prospects'!F:F, 'Email Outreach Prospects'!B:B=B30))} -> 40 | V30: P | W30: 2023 | X30: 942259716 | Y30: 10 | AB30: 1 | AC30: 0 | AD30: 0 | AE30: 0 | AF30: Uncertain | AG30: She helps people find the right fonuidatins and says it's technical. Knows the ins and outs etc. Tech for good. Social positive changes using tech. Is building an app -- targinily -signal also is anlother example of tech for good. Targinily is a tansition service for refugees- people volunteer and they translate for people around the world. Similar not translation but also tech for good.
B31: HILLSDALE HIGH SCHOOL FOUNDATION | C31: 45967 | D31: 6505582618 | E31: MARCINE JANSEN | F31: EXECUTIVE DIRECTOR | I31: 63 BOVET ROAD 218 | J31: SAN MATEO | K31: CA | N31: 94402 | O31: https://WWW.HILLSDALEHSFOUNDATION.ORG | P31: 1995846 | Q31: 1934778 | R31: 96.9 | S31: 765746 | T31: HHSF RAISES FUNDS TO SUSTAIN HILLSDALE HIGH SCHOOL'S (HHS) UNIQUE ACADEMIC ENVIRONMENT OF SMALL LEARNING COMMUNITIES (SLCS). THE SLC MODEL PROVIDES A PERSONALIZED, RIGOROUS, AND ENGAGING EDUCATION. | U31: {=MAX(_xlfn._xlws.FILTER('Email Outreach Prospects'!F:F, 'Email Outreach Prospects'!B:B=B31))} -> 25 | V31: B, C | W31: 2023 | X31: 870800728 | Y31: 10 | AB31: 1 | AC31: 0 | AD31: 0 | AE31: 0 | AF31: Uncertain
B32: SHELTER SOLANO INC | C32: 45967 | D32: 9259577595 | E32: JOHN ECKSTROM | F32: CEO | I32: PO BOX 5368 | J32: CONCORD | K32: CA | N32: 94524 | O32: https://WWW.SHELTERINC.ORG | P32: 2588611 | Q32: 2402626 | R32: 92.8 | S32: 3026486 | T32: SHELTER SOLANO IS A YEAR-ROUND EMERGENCY SHELTER LOCATED ON 3.5 ACRES IN FAIRFIELD, CA. SHELTER SOLANO CAN MEET THE EMERGENCY HOUSING NEEDS OF INDIVIDUALS AND FAMILIES WITH ACCOMMODATIONS INCLUDING DORMITORY STYLE ROOMS, FAMILY-SIZED ROOMS, AND SEPARATE APARTMENT-STYLE UNITS. THE CAMPUS IS SECURED A | U32: {=MAX(_xlfn._xlws.FILTER('Email Outreach Prospects'!F:F, 'Email Outreach Prospects'!B:B=B32))} -> 1 | V32: P, S | W32: 2023 | X32: 832704105 | Y32: 10 | AB32: 1 | AC32: 0 | AD32: 0 | AE32: 0 | AF32: Uncertain | AG32: Number goes to John's phone
B33: DIAKONIA HOUSING INC | C33: 45967 | D33: 5622575100 | E33: FRANK ROSSELLO | F33: CFO/V.P., FINANCE | I33: 911 N STUDEBAKER ROAD | J33: LONG BEACH | K33: CA | N33: 90815 | O33: https://WWW.RHF.ORG | P33: 1103085 | Q33: 655705 | R33: 59.4 | S33: 1138362 | T33: DIAKONIA HOUSING, INC. IS A NOT-FOR-PROFIT CORPORATION FORMED IN ACCORDANCE WITH THE NOT-FOR-PROFIT STATUTES OF THE STATE OF INDIANA. THE CORPORATION WAS FORMED FOR THE PURPOSE OF OPERATING A 100 UNIT COMMUNITY KNOWN AS LONGFELLOW PLAZA LOCATED IN ANDERSON, INDIANA, WHICH PROVIDES HOUSING FOR LOW IN | U33: {=MAX(_xlfn._xlws.FILTER('Email Outreach Prospects'!F:F, 'Email Outreach Prospects'!B:B=B33))} -> 0.2 | V33: P, S | W33: 2023 | X33: 953815145 | Y33: 10 | AB33: 1 | AC33: 0 | AD33: 0 | AE33: 0 | AF33: Uncertain | AG33: Operator connected me to Frank's number
B34: FRIENDSHIP HOUSE III INC | C34: 45973 | D34: 5622575100 | E34: FRANK ROSSELLO | F34: CFO/V.P., FINANCE | I34: 911 N STUDEBAKER ROAD | J34: LONG BEACH | K34: CA | N34: 90815 | O34: https://WWW.RHF.ORG | P34: 3340837 | Q34: 2000869 | R34: 59.9 | S34: 2740454 | T34: FRIENDSHIP HOUSE III, INC. IS A NOT-FOR-PROFIT CORPORATION FORMED IN ACCORDANCE WITH THE NOT-FOR-PROFIT STATUTES OF THE STATE OF INDIANA. THE CORPORATION WAS FORMED FOR THE PURPOSE OF OPERATING A 167 UNIT COMMUNITY KNOWN AS CROOKED CREEK TOWER, LOCATED IN INDIANAPOLIS, INDIANA, AND A 140 UNIT COMMUN | U34: {=MAX(_xlfn._xlws.FILTER('Email Outreach Prospects'!F:F, 'Email Outreach Prospects'!B:B=B34))} -> 0.2 | V34: P, S | W34: 2023 | X34: 310956562 | Y34: 10 | AB34: 1 | AC34: 0 | AD34: 0 | AE34: 0 | AF34: Uncertain
B35: MARIN AUDUBON SOCIETY | C35: 45973 | D35: 4159246057 | E35: BARBARA SALZMAN | F35: President | I35: PO BOX 599 | J35: MILL VALLEY | K35: CA | N35: 94942 | O35: https://WWW.MARINAUDUBON.ORG | P35: 1005699 | Q35: 926238 | R35: 92.1 | S35: 563461 | T35: THE MARIN AUDUBON SOCIETY IS DEDICATED TO ACTIVE PARTICIPATION IN CONSERVATION, ENVIRONMENTAL EDUCATION, AND ENJOYMENT OF OUR NATURAL HERITAGE. WE ADVOCATE SOUND LAND AND WATER RESOURCE PLANNING, AND ACT TO RESTORE, ENHANCE, AND SAFEGUARD OUR WETLANDS AND OTHER NATURAL HABITATS. BIRDS AND OTHER WILD | U35: {=MAX(_xlfn._xlws.FILTER('Email Outreach Prospects'!F:F, 'Email Outreach Prospects'!B:B=B35))} -> 40 | V35: A, B, C, E | W35: 2023 | X35: 946076664 | Y35: 10 | AB35: 1 | AC35: 0 | AD35: 0 | AE35: 0 | AF35: Uncertain
B36: Nihonmachi Little Friends | C36: 45973 | D36: 4159228898 | E36: Mokuau Dawn | F36: Chairperson | I36: 1830 Sutter Street | J36: San Francisco | K36: CA | N36: 94115 | O36: https://nlfchildcare.org | P36: 2842354 | Q36: 1667238 | R36: 58.7 | S36: 2537391 | T36: Nihonmachi Little Friends (NLF) is a Japanese bilingual multicultural & educational childcare organization. | U36: {=MAX(_xlfn._xlws.FILTER('Email Outreach Prospects'!F:F, 'Email Outreach Prospects'!B:B=B36))} -> 40 | V36: B | W36: 2023 | X36: 942325686 | Y36: 10 | Z36: Dawn | AB36: 0 | AC36: 1 | AD36: 1 | AE36: 0 | AF36: Uncertain | AG36: Nlfchildcare@gmail.com
B37: CODEPINK WOMEN FOR PEACE | C37: 45973 | D37: 3108273046 | E37: JODIE EVANS | F37: President | I37: 578 WASHINGTON BLVD 395 | J37: MARINA DEL REY | K37: CA | N37: 90292 | O37: https://www.codepink.org | P37: 1328143 | Q37: 1273425 | R37: 95.9 | S37: 1303424 | T37: TO END U.S. WARS AND MILITARISM, SUPPORT PEACE AND HUMAN RIGHTS INITIATIVES. | U37: {=MAX(_xlfn._xlws.FILTER('Email Outreach Prospects'!F:F, 'Email Outreach Prospects'!B:B=B37))} -> 40 | V37: B, E | W37: 2023 | X37: 262823386 | Y37: 10 | AB37: 1 | AC37: 0 | AD37: 0 | AE37: 0 | AF37: Uncertain
B38: CHRYSALIS CHARTER SCHOOL | C38: 45973 | D38: 5305479726 | E38: CATHERINE THOMPSON | F38: ADMINISTRATOR/ SUPERINTENDENT | I38: PO BOX 709 | J38: PALO CEDRO | K38: CA | N38: 96073 | O38: https://WWW.CHRYSALISCHARTERSCHOOL.COM | P38: 3363431 | Q38: 3294448 | R38: 97.9 | S38: 2991894 | T38: TO PROVIDE A PUBLIC EDUCATION WITH A SCIENCE AND NATURE EMPHASIS TO CHILDREN FROM TRANSITIONAL KINDERGARTEN THROUGH EIGHTH GRADE | U38: {=MAX(_xlfn._xlws.FILTER('Email Outreach Prospects'!F:F, 'Email Outreach Prospects'!B:B=B38))} -> 40 | V38: B, C, P | W38: 2023 | X38: 810569209 | Y38: 10 | Z38: Tim Drury | AB38: 0 | AC38: 1 | AD38: 1 | AE38: 0 | AF38: Uncertain | AG38: Talked to Catherine - she said I should email Tim Drury who's their administrative something or other. - timdrury@chrysalischarter.org. Also answered some questions about how they work: Teacher ran school- they have a teacher cooperative that decisions. development committee and another committee - someone onsite who does grants (parent volunteers who do the grant finding)
B39: FRIENDSHIP CIRCLE SD INC | C39: 45973 | D39: 4087555770 | E39: YOSEF RODAL | F39: Executive Dir. | I39: 441 SAXONY ROAD | J39: ENCINITAS | K39: CA | N39: 92024 | O39: https://www.friendshipsd.org | P39: 2690324 | Q39: 2531992 | R39: 94.1 | S39: 771056 | T39: to enrich the lives of children, teens and adults with special needs through social and recreational experiences and to inspire volunteers to participate in building a stronger and more inclusive community. | U39: {=MAX(_xlfn._xlws.FILTER('Email Outreach Prospects'!F:F, 'Email Outreach Prospects'!B:B=B39))} -> 25 | V39: P | W39: 2023 | X39: 203472700 | Y39: 10 | AB39: 1 | AC39: 0 | AD39: 0 | AE39: 0 | AF39: Uncertain
B40: BREAKTHROUGH SILICON VALLEY | C40: 45973 | D40: 4082876357 | E40: RAMON GARCIA-GOMEZ | F40: TREASURER | I40: 1635 PARK AVENUE | J40: SAN JOSE | K40: CA | N40: 951262123 | O40: https://WWW.BREAKTHROUGHSV.ORG | P40: 2246362 | Q40: 2189567 | R40: 97.5 | S40: 2924323 | T40: BREAKTHROUGH SILICON VALLEY PREPARES HIGHLY-MOTIVATED STUDENTS TO BECOME FIRST-GENERATION COLLEGE GRADUATES AND INSPIRES EMERGING LEADERS TO BE THE NEXT GENERATION OF EDUCATORS AND ADVOCATES FOR EQUITY. | U40: {=MAX(_xlfn._xlws.FILTER('Email Outreach Prospects'!F:F, 'Email Outreach Prospects'!B:B=B40))} -> 40 | V40: B | W40: 2023 | X40: 262168102 | Y40: 10 | Z40: Rebeca Duran | AB40: 1 | AC40: 1 | AD40: 0 | AE40: 0 | AF40: Uncertain | AG40: Talked to Vanessa - she said it would be best to talk to marisol or new executive director rebeca duran. She took my name, number, and email and a message so they can reach out
B41: THOMAS HOUSE TEMPORARY SHELTER | C41: 45973 | D41: 7145540357 | E41: SHAKOYA GREEN LONG | F41: CEO | I41: PO BOX 2737 | J41: GARDEN GROVE | K41: CA | N41: 928422737 | O41: https://WWW.THOMASHOUSESHELTER.ORG | P41: 1900870 | Q41: 1811413 | R41: 95.3 | S41: 1772001 | T41: TO PROVIDE A SAFE, SUPPORTIVE ENVIRONMENT AND RESOURCES NECESSARY FOR HOMELESS FAMILIES WITH CHILDREN TO REMAIN TOGETHER WHILE EMPOWERING THEM TO BECOME INDEPENDENT AND SELF-SUFFICIENT. TO KEEP AT RISK FAMILIES FROM BECOMING HOMELESS BY PROVIDING PREVENTION SERVICES INCLUDING RENTAL ASSISTANCE. | U41: {=MAX(_xlfn._xlws.FILTER('Email Outreach Prospects'!F:F, 'Email Outreach Prospects'!B:B=B41))} -> 40 | V41: C, P | W41: 2023 | X41: 330204757 | Y41: 10 | Z41: Shakoya | AB41: 1 | AC41: 1 | AD41: 1 | AE41: 0 | AF41: Uncertain | AG41: Talked to Angie - she said talk to the CEO, Shakoya. shakoya@thomashouseshelter.org - shoot her an email - set up a time to chat about it. Angie said she'd send her a message about it right now.
B42: COLLEGE OF ADAPTIVE ARTS | C42: 45973 | D42: 4085383809 | E42: NICOLE KIM | F42: EXECUTIVE DIRECTOR | I42: 14000 FRUITVALE AVE | J42: SARATOGA | K42: CA | N42: 95070 | O42: https://www.collegeofadaptivearts.org | P42: 1895170 | Q42: 918122 | R42: 48.4 | S42: 1753211 | T42: COLLEGE OF ADAPTIVE ARTS PROVIDES AN EQUITABLE COLLEGIATE EXPERIENCE TO ADULTS WITH SPECIAL NEEDS WHO HISTORICALLY HAVE NOT HAD ACCESS TO COLLEGE EDUCATION. | U42: {=MAX(_xlfn._xlws.FILTER('Email Outreach Prospects'!F:F, 'Email Outreach Prospects'!B:B=B42))} -> 50 | V42: A, B | W42: 2023 | X42: 270342896 | Y42: 10 | Z42: Deanna | AB42: 1 | AC42: 1 | AD42: 1 | AE42: 0 | AF42: Uncertain | AG42: Has developement director who manages this and works with someone already. Deanna. deanna@collegeofadaptivearts.org
B43: HEALTH EDUCATION COUNCIL | C43: 45973 | D43: 9165563344 | E43: DEBRA OTO-KENT | F43: Executive Dir. | I43: 7617 ALMA VISTA WAY C | J43: SACRAMENTO | K43: CA | N43: 95831 | O43: https://www.healthedcouncil.org | P43: 4863625 | Q43: 4101646 | R43: 84.3 | S43: 4028812 | T43: The Health Education Council, Inc. (HEC) is a California nonprofit corporation serving to implement programs that impact the underlying drivers of health education, neighborhood safety, social connection, economic well-being, access to healthy resources that affect a persons ability to achieve healt | U43: {=MAX(_xlfn._xlws.FILTER('Email Outreach Prospects'!F:F, 'Email Outreach Prospects'!B:B=B43))} -> 40 | V43: B, E, S | W43: 2023 | X43: 680249296 | Y43: 10 | Z43: Could be Roxxana, could be Karrie | AB43: 1 | AC43: 1 | AD43: 0 | AE43: 1 | AF43: Uncertain | AG43: Shannon- Took my number and email address and a message - said she'd talk to a couple people about it and that if they're interested then they'll shoot me a call (also that they are good at calling people back and I have nothing to worry about)
B44: Challenge Success | C44: 45973 | D44: 6507239250 | E44: Gary Alpert | F44: Treasurer | I44: PO Box 20053 | J44: Stanford | K44: CA | N44: 94309 | O44: https://www.challengesuccess.org | P44: 3847543 | Q44: 2319479 | R44: 60.3 | S44: 2076414 | T44: Challenge Success partners with schools, families, and communities to embrace a broad definition of success and implement research-based strategies that promote student well-being and engagement with learning. | U44: {=MAX(_xlfn._xlws.FILTER('Email Outreach Prospects'!F:F, 'Email Outreach Prospects'!B:B=B44))} -> 40 | V44: B | W44: 2023 | X44: 453767621 | Y44: 10 | AB44: 0 | AC44: 0 | AD44: 0 | AE44: 0 | AF44: Uncertain
B45: Reignite Hope | C45: 45975 | D45: 3108470156 | E45: Steve D Bunyard | F45: President | I45: 2074 Stonewood Court | J45: San Pedro | K45: CA | N45: 90732 | O45: https://www.reignitehope.com | P45: 1550448 | Q45: 1517133 | R45: 97.9 | S45: 1262827 | T45: Restoring hope and dignity to former gang members, ex-offenders and the homeless by teaching them job skills for a career in welding. | U45: {=MAX(_xlfn._xlws.FILTER('Email Outreach Prospects'!F:F, 'Email Outreach Prospects'!B:B=B45))} -> 40 | V45: B, P | W45: 2023 | X45: 813244816 | Y45: 10 | AB45: 1 | AC45: 0 | AD45: 0 | AE45: 0 | AF45: Uncertain
B46: Satellite Senior Homes II Inc | C46: 45975 | D46: 5106470700 | E46: SUSAN FRIEDLAND | F46: CEO | I46: 1835 Alcatraz Avenue | J46: Berkeley | K46: CA | N46: 94703 | O46: https://www.sahahomes.org | P46: 3207683 | Q46: 2479178 | R46: 77.3 | S46: 3166727 | T46: TO PROVIDE AFFORDABLE RENTAL HOUSING FOR LOW AND MODERATE-INCOME ELDERLY PERSONS. | U46: {=MAX(_xlfn._xlws.FILTER('Email Outreach Prospects'!F:F, 'Email Outreach Prospects'!B:B=B46))} -> 0.1 | V46: P, S | W46: 2023 | X46: 942598866 | Y46: 10 | AB46: 1 | AC46: 0 | AD46: 0 | AE46: 0 | AF46: Uncertain
B47: COURT APPOINTED SPECIAL ADVOCATES | C47: 45975 | D47: 6616312272 | E47: ASHLEY VORHEES | F47: EXECUTIVE DIRECTOR | I47: 1717 COLUMBUS | J47: BAKERSFIELD | K47: CA | N47: 93305 | O47: https://KERNCASA.ORG | P47: 1429954 | Q47: 1390820 | R47: 97.3 | S47: 1475731 | T47: TO PROVIDE SPECIALLY TRAINED VOLUNTEERS TO REPRESENT THE BEST INTERESTS OF CHILDREN UNDER PROTECTION OF THE JUVENILE COURT BECAUSE OF ABUSE OR NEGLECT. | U47: {=MAX(_xlfn._xlws.FILTER('Email Outreach Prospects'!F:F, 'Email Outreach Prospects'!B:B=B47))} -> 40 | V47: P | W47: 2023 | X47: 770344298 | Y47: 10 | AB47: 0 | AC47: 1 | AD47: 1 | AE47: 0 | AF47: Uncertain
B48: CENTRAL CALIFORNIA APPELLATE PROGRAM | C48: 45975 | D48: 9164413792 | E48: GEORGE BOND | F48: TREASURER | I48: 2150 RIVER PLAZA DRIVE 300 | J48: SACRAMENTO | K48: CA | N48: 95833 | O48: https://WWW.CAPCENTRAL.ORG | P48: 4975016 | Q48: 4960635 | R48: 99.7 | S48: 4981117 | T48: THE PRIMARY PURPOSES OF THIS CORPORATION ARE TO ASSIST INDIGENT CRIMINAL APPELLANTS, PRINCIPALLY IN THE APPELLATE COURTS OF THE STATE OF CALIFORNIA BUT ALSO IN FEDERAL APPELLATE COURTS, AND TO PROVIDE EDUCATIONAL PROGRAMS FOR LAW STUDENTS AND ATTORNEYS IN ORDER TO ADVANCE THE ADMINISTRATION OF CRIMI | U48: {=MAX(_xlfn._xlws.FILTER('Email Outreach Prospects'!F:F, 'Email Outreach Prospects'!B:B=B48))} -> 40 | V48: B | W48: 2023 | X48: 680117367 | Y48: 10 | AB48: 1 | AC48: 0 | AD48: 0 | AE48: 0 | AF48: Uncertain
B49: FRIENDS OF THE MANDARIN SCHOLARS | C49: 45975 | D49: 6502003350 | E49: JENNY YANG | F49: Chairman | I49: PO BOX 123 | J49: SAN MATEO | K49: CA | N49: 94401 | O49: https://MANDARINSCHOLARS.ORG | P49: 2284992 | Q49: 2122690 | R49: 92.9 | S49: 182427 | T49: Our mission is to support K-8 Mandarin instruction within the San Mateo-Foster City School District in order to enable students from all backgrounds the opportunity to develop a mastery of Mandarin Chinese language and appreciation of Chinese culture. | U49: {=MAX(_xlfn._xlws.FILTER('Email Outreach Prospects'!F:F, 'Email Outreach Prospects'!B:B=B49))} -> 20 | V49: B | W49: 2023 | X49: 452465260 | Y49: 10 | AB49: 1 | AC49: 0 | AD49: 0 | AE49: 0 | AF49: Uncertain | AG49: closed Mondays
B50: Fathers and Mothers Who Care | C50: 45975 | D50: 3232477667 | E50: Linda Kelly | F50: Executive Director | I50: 10975 S Vermont Ave | J50: Los Angeles | K50: CA | N50: 90044 | O50: https://www.fmwc.org | P50: 1018765 | Q50: 468883 | R50: 46 | S50: 1051336 | T50: Fathers and Mothers Who Care is a social service charity and grassroots non-profit organization dedicated to creating a better America for all people by addressing underserved communities social educational and health needs. Their mission is to spark community development by restoring underserved co | U50: {=MAX(_xlfn._xlws.FILTER('Email Outreach Prospects'!F:F, 'Email Outreach Prospects'!B:B=B50))} -> 40 | V50: B, E, P, S | W50: 2022 | X50: 954648247 | Y50: 10 | AB50: 1 | AC50: 0 | AD50: 0 | AE50: 0 | AF50: Uncertain
B51: ANAHEIM MEMORIAL MANOR INC | C51: 45975 | D51: 5622575100 | E51: FRANK ROSSELLO | F51: CFO/V.P., FINANCE | I51: 911 N STUDEBAKER ROAD | J51: LONG BEACH | K51: CA | N51: 90815 | O51: https://WWW.RHF.ORG | P51: 1389276 | Q51: 1003647 | R51: 72.2 | S51: 1236992 | T51: ANAHEIM MEMORIAL MANOR, INC. IS A NOT-FOR-PROFIT CORPORATION FORMED IN ACCORDANCE WITH THE NOT-FOR-PROFIT STATUTES OF THE STATE OF CALIFORNIA. THE CORPORATION WAS FORMED FOR THE PURPOSE OF OPERATING A 75 UNIT COMMUNITY KNOWN AS ANAHEIM MEMORIAL MANOR LOCATED IN ANAHEIM, CALIFORNIA, WHICH PROVIDES HO | U51: {=MAX(_xlfn._xlws.FILTER('Email Outreach Prospects'!F:F, 'Email Outreach Prospects'!B:B=B51))} -> 0.2 | V51: P, S | W51: 2023 | X51: 953618525 | Y51: 10 | Z51: Andy | AB51: 0 | AC51: 0 | AD51: 1 | AE51: 1 | AF51: Yes | AG51: Sometimes they apply for public funding (either grants or public funding home or cdg favorable financing low interest loans partering with the city) Gap funding
B52: 4 CHRIST MISSION | C52: 46003 | D52: 8587487001 | E52: PAUL SUH | F52: PRESIDENT | H52: WWW.4CHRISTMISSION.ORG | K52: CA | AB52: 0
B53: BIRMINGHAM HOST COMMITTEE 2025 WORLD POL | C53: 46003 | D53: 2052972230 | E53: DJ MACKOVETS | F53: CEO | H53: BHM2025.COM | K53: AL | AB53: 1 | AC53: 0 | AD53: 0 | AE53: 0 | AF53: Uncertain
B54: CLERESTORY INC | C54: 46003 | D54: 2052596636 | E54: GREG MIXON | F54: CHAIRMAN/PRESIDENT | H54: WWW.CLERESTORYINC.ORG | K54: AL | AB54: 1 | AC54: 0 | AD54: 0 | AE54: 1 | AF54: Uncertain
B55: EMPOWERMENT INCORPORATED | C55: 46003 | D55: 2059016263 | E55: CEDRIC ALLEN | F55: PRESIDENT | K55: AL | AB55: 0 | AC55: 0 | AD55: 0 | AE55: 0 | AF55: Uncertain
B56: FREE WILL BAPTIST CHILDRENS HO | C56: 46003 | D56: 2059249751 | K56: AL | AB56: 1 | AC56: 0 | AD56: 0 | AE56: 0 | AF56: Uncertain
B57: MOWA BAND OF CHOCTAW INDIAN COMMISSION | C57: 46003 | D57: 2518295500 | E57: LEBARON BYRD | F57: CEO | H57: N/A | K57: AL | AB57: 1
B58: THOMAS HOSPITAL FOUNDATION INC | C58: 46003 | D58: 2514353030 | E58: DEANNA AUNER | F58: DIRECTOR | H58: INFIRMARYHEALTH.ORG/THOMASHOSPITAL/FND | K58: AL | AB58: 1
B59: 4 KIDS 2 KIDS | C59: 46003 | D59: 8055730752 | E59: LORIE VOS | F59: BOARD MEMBER/CEO | H59: 4K2KONLINE.ORG | K59: CA | AC59: 1 | AG59: Not a business thanks goodbye
B60: A2SV FOUNDATION | C60: 46003 | D60: 4708469962 | E60: BRIAN BELL | F60: CEO/DIRECTOR | H60: HTTPS://A2SV.ORG/ | K60: CA | AB60: 1
B61: AFRICAN AMERICAN CULTURAL CENTER | C61: 46003 | D61: 4089106958 | E61: JOANNA FARRIS | F61: PRESIDENT | H61: SVAFRICANAMERICANCULTURALCENTER.ORG | K61: CA | AB61: 0 | AC61: 1 | AD61: 1 | AE61: 1 | AF61: Uncertain | AG61: Send email with info and she’ll take it to the business development (sales & marketing?) Meeting next week. “Probably nothing will happen until next year”
B62: ANTARA INTERNATIONAL INC | C62: 46003 | D62: 4152542927 | E62: MADHURA V NIRKHE | F62: Former CEO | H62: www.antarainternational.org | K62: CA | AB62: 1
B63: ARROYO GRANDE COMMUNITY HOSPITAL | C63: 46003 | D63: 8057393686 | E63: CHARLES COVA | F63: FORMER OFFICER (DIV SVP OPERATIONS & CEO) | H63: WWW.DIGNITYHEALTH.ORG | K63: CA | AC63: 1 | AD63: 0 | AE63: 0 | AF63: Uncertain | AG63: Amber took my info and said she'd look into who would be best to connect me with with the foundation team
B64: 3D Nonprofit Corporation | C64: 46003 | D64: 4358799383 | E64: Caralyn Brook | F64: Founder/Director | H64: N/A | K64: UT | U64: {=MAX(_xlfn._xlws.FILTER('Email Outreach Prospects'!F:F, 'Email Outreach Prospects'!B:B=B64))} -> #VALUE! | AB64: 1
B65: ASSISTANCE LEAGUE OF SALT LAKE CITY | C65: 46003 | D65: 8014843401 | E65: ANA FACELLI | F65: 3RD VICE PRESIDENT - MEMBE | H65: WWW.ALSLC.ORG | K65: UT | U65: {=MAX(_xlfn._xlws.FILTER('Email Outreach Prospects'!F:F, 'Email Outreach Prospects'!B:B=B65))} -> #VALUE! | AB65: 1
B66: BIG STUFF HEALTH SHARE | C66: 46003 | D66: 8664669696 | E66: JAMES R MARTIN | F66: PRESIDENT | H66: BIGSTUFFHEALTHSHARE.COM | K66: UT | U66: {=MAX(_xlfn._xlws.FILTER('Email Outreach Prospects'!F:F, 'Email Outreach Prospects'!B:B=B66))} -> #VALUE! | AB66: 0 | AG66: Bad number
B67: HEARSEE | C67: 46003 | D67: 4358628296 | E67: JAMES BLOOMFIELD | F67: PRESIDENT | H67: HEARSEEMOBILITY.ORG | K67: UT | U67: {=MAX(_xlfn._xlws.FILTER('Email Outreach Prospects'!F:F, 'Email Outreach Prospects'!B:B=B67))} -> #VALUE! | AB67: 1
B68: LIFE LIFTED CHARITIES | C68: 46003 | D68: 8012573400 | E68: MATTHEW B GARFF | F68: President & CEO | K68: UT | U68: {=MAX(_xlfn._xlws.FILTER('Email Outreach Prospects'!F:F, 'Email Outreach Prospects'!B:B=B68))} -> #VALUE! | AB68: 1
B69: RED CEDAR CORPORATION | C69: 46003 | D69: 8016737178 | E69: GLEN A ALLRED | F69: PRESIDENTTREASURER | K69: UT | U69: {=MAX(_xlfn._xlws.FILTER('Email Outreach Prospects'!F:F, 'Email Outreach Prospects'!B:B=B69))} -> #VALUE! | AB69: 0 | AG69: Mailbox full
B70: THE VICTORIA PROJECT INC | C70: 46003 | D70: 8054550507 | E70: Janelle Green | F70: President | G70: THE VICTORIA PROJECT IS A COMMUNITY HEALING FUND COMMITTED TO SUPPORTING ACCESS TO HOLISTIC MATERNITY CARE. | H70: WWW.THE-VICTORIA-PROJECT.COM | I70: CA | K70: CA | L70: 5 | M70: 3 | AB70: 0 | AE70: 1
B71: PUKUU CULTURAL COMMUNITY SERVICES | C71: 46003 | D71: 8183366105 | E71: CARMEN MENDIVIL | F71: DIRECTOR | G71: TO OFFER TEMPORARY AID TO LOW INCOME AMERICAN INDIANS | H71: N/A | I71: CA | K71: CA | L71: 10 | M71: 2 | AB71: 0
B72: PWT United Inc | C72: 46003 | D72: 9169609800 | E72: Kevin Brown | F72: CEO | G72: To strategically partner with like-minded people and organizations to provide career opportunities, to ensure job career readiness, and to meet the holistic needs for those who we serve, on this journey called life. | H72: www.peopleworkingtogether.org | I72: CA | K72: CA | L72: 8 | AB72: 1
B73: AUTISTRY STUDIOS INCORPORATED | C73: 46003 | D73: 4154541037 | E73: JANET K LAWSON MFT | F73: EXEC DIR, CE | G73: WE HELP TEENS AND ADULTS WITH AUTISM, AND OTHER LEARNING DIFFERENCES BECOME SUCCESSFULLY INDEPENDENT BY LEVERAGING THEIR INTERESTS AND TALENTS. WE DELIVER SERVICE THROUGH WORKSHOPS, INDIVIDUAL THERAPY AND PRODUCTS AS NEEDED. | H73: WWW.AUTISTRYSTUDIOS.COM | I73: CA | K73: CA | L73: 9 | AB73: 1
B74: HOPE CENTER OF ORANGE COUNTY | C74: 46003 | D74: 6572537053 | E74: BRIAN DONAHUE | F74: CHAIR | G74: TO BRING RELIABLE RELIEF AND CONSISTENT SUPPORT TO INDIVIDUALS EXPERIENCING HOMELESSNESS IN THE NORTH ORANGE COUNTY SERVICE PLANNING AREA (SPA). | H74: HTTPS://OCHOPECENTER.ORG/ | I74: CA | K74: CA | L74: 2 | M74: 0 | AB74: 1
B75: KOREAN AMERICAN FEDERATION OF LA | C75: 46003 | D75: 3237320700 | E75: DAVID CHOI | F75: EXECUTIVE VICE PRESIDENT | G75: TO SUPPORT AND SERVE BETTER FOR THE FURTHERANCE OF THE RIGHTS AND INTERESTS OF THE KOREAN COMMUNITY AT LOS ANGELES | H75: WWW.KAFLA.ORG | I75: CA | K75: CA | L75: 8 | AC75: 1 | AF75: No | AG75: trying not to spend money right now. I talked to Ed and he looked at the website
B76: LADMC FOUNDATION | C76: 46003 | D76: 6263310781 | E76: William Nelson | F76: Board Member President | G76: LADMC FOUNDATIONS GOAL IS TO TRAIN LOS ANGELES COUNTY NURSES IN LEADERSHIP AND HEALTH CARE, AND TO PROMOTE HEALTH AND WELLNESS EDUCATION TO COMMUNITIES AND NEIGHBORHOODS THROUGHOUT THE LOS ANGELES REGION. | H76: N/A | I76: CA | K76: CA | L76: 3 | M76: 1 | AG76: Bad number
B77: PRIME WELLNESS COMMUNITY | C77: 46003 | D77: 3235528899 | E77: DENYS SLESARENKO | F77: CEO | G77: COMMUNITY WELLNESS | I77: CA | K77: CA | L77: 10 | AC77: 1 | AD77: 0 | AE77: 1 | AF77: No | AG77: They use grant station and pay $150 monthly subscription. Grant station then recommends grants to apply to, the nonprofit approves, and it’s $250-$300 per application. They win about 35% percent of the time. Denys said they need the full package because they’re too small to have someone writing the applications in house.
B78: LOS ANGELES COMMUNITY GARDEN COUNCIL | C78: 46003 | D78: 3239027167 | E78: DIANA CAMPOS JIMENEZ | F78: EXECUTIVE DIRECTOR | G78: TO STRENGTHEN COMMUNITIES BY BUILDING AND SUPPORTING COMMUNITY GARDENS WHERE PEOPLE CAN GROW HEALTHY FOOD IN THEIR NEIGHBORHOOD. | H78: WWW.LAGARDENCOUNCIL.ORG | I78: CA | K78: CA | L78: 1 | M78: 0 | AB78: 0 | AG78: Bad Number
B79: F C Cancer Foundation A California | C79: 46003 | D79: 8555283336 | E79: Brandon Ward | F79: President | G79: Education and awareness of cancer patients' challenges | H79: www.fccancerfoundation.org | I79: CA | K79: CA | L79: 3 | AB79: 1
B80: Indian Child and Family Preservation Program | C80: 46003 | D80: 7075448509 | E80: MARGIE MEJIA | F80: VICE PRESIDENT | G80: To provide advocacy and cultural awareness to Native American children and families. | H80: WWW.ICIPP.net | I80: CA | K80: CA | L80: 7 | M80: 0 | AB80: 1 | AC80: 1
B81: Coalition On Homelessness | D81: 4153463740 | E81: Jennifer Freidenbach | F81: Executive Director | G81: We work to organize homeless people and front-line service providers to create permanent solutions to homelessness while protecting the civil and human rights of those forced to remain on the streets. | H81: www.cohsf.org | I81: CA | K81: CA | L81: 10 | M81: 5
B82: FRIENDS OF GRACE | D82: 9493317277 | E82: STEPHEN TANG | F82: Board member CEO | G82: To reach people with the gospel of Jesus Christ through medical and dental treatments, English Bible training classes, theological training and to support seminary study at different parts of the world | H82: friendsofgrace.org | I82: CA | K82: CA | L82: 1
B83: TIP Global Health | D83: 8312346053 | E83: Wendy Leonard MD | F83: Executive Director | G83: The Ihangane Project achieves lasting improvements in health outcomes, beginning in Rwanda, by promoting community-driven solutions that strengthen national health systems. The successful solutions we co-create with local communities are shared with the national government. | H83: tipglobalhealth.org | I83: CA | K83: CA | L83: 2
B84: CBCC FOUNDATION FOR COMMUNITY WELLNESS | D84: 6613222206 | E84: KAREN LEVINE | F84: PRESIDENT | G84: SERVING THE EDUCATIONAL, FINANCIAL, AND EMOTIONAL NEEDS OF KERN COUNTY CANCER PATIENTS AND THEIR FAMILIES. | H84: N/A | I84: CA | K84: CA | L84: 2 | M84: 1
B85: THE TRIBAL CHILD CARE ASSOCIATION | D85: 5306745374 | E85: KIMBERLY NALL | F85: Executive Dir. | G85: TO SUSTAIN AND MAINTAIN HIGH QUALITY, CULTURALLY RELEVANT CHILD CARE PROGRAMS THROUGH THE UNIFICATION OF TRIBAL VOICES AND BY PROVIDING SUPPORT, SHARING KNOWLEDGE, EDUCATING TRIBES, FEDERAL, STATE, AND LOCAL GOVERNMENTS AND AGENCIES. | H85: WWW.TRIBALCHILDCARECA.ORG | I85: CA | K85: CA | L85: 4 | M85: 0
B86: GRACE SOCIAL AND MEDICAL SERVICES INC | D86: 7145047332 | E86: REDA BESHAI | F86: PRESIDENT | G86: To help new immigrants by providing for basic needs, enhancing education and employment opportunities, and providing legal support to cement their place in America as happy and productive citizens. | H86: WWW.ELEVATEDBYGRACE.ORG | I86: CA | K86: CA | L86: 8
B87: FOUNDATION FOR CHIROPRACTIC PROGRES | D87: 8669013427 | E87: SHERRY MCALLISTER | F87: PRESIDENT | G87: GENERATE POSITIVE PRESS FOR THE CHRIOPRACTIC PROFESSION AND INCREASE PUBLIC AWARENESS OF BENEFITS OF CHIROPRACTIC CARE. | H87: WWW.F4CP.ORG | I87: CA | K87: CA | L87: 4
B88: HEALTH CARE FOUNDATION FOR VENTURA | D88: 8056523361 | E88: Amy Towner | F88: CEO | G88: Health Care Foundation for Ventura County, Inc. is dedicated to strengthening, enhancing and augmenting the capacity of Ventura County Health Care Agency, especially their hospitals, Ventura County Medical Center and Santa Paula Hospital, to provide high quality care for all. | H88: hcfvc.org | I88: CA | K88: CA | L88: 6
B89: LONG BEACH CENTER FOR ECONOMIC INCLUSION | D89: 3105626665 | E89: EMILY KAZIM | F89: Executive Dir. | G89: LBCEI is a community development corporation that expands inclusive economic opportunities to build and sustain wealth for all communities in Long Beach. | H89: LBCEI.ORG | I89: CA | K89: CA | L89: 2
B90: INSIDE-OUTSIDE CIRCLE FOUNDATION | D90: 4153369585 | E90: ARI ROSEN | F90: BOARD MEMBER | G90: INSIDE OUTSIDE CIRCLE EMPOWERS SYSTEM-IMPACTED PEOPLE TO LEAD CHANGE FROM WITHIN BY PROVIDING OPPORTUNITIES FOR INCARCERATED AND FORMERLY INCARCERATED PEOPLE TO HEAL AND SERVE BOTH THEMSELVES AND OTHERS. WE EXIST TO REDUCE RECIDIVISM AND ALL FORMS OF VIOLENCE - PHYSICAL, EMOTIONAL, AND PSYCHOLOGICAL - IN OUR PRISONS AND COMMUNITIES. | H90: WWW.INSIDECIRCLE.ORG | I90: CA | K90: CA | L90: 4 | M90: 1
B91: HORN OF AFRICA COMMUNITY OF NORTH AMERICA | D91: 6195592970 | E91: ABDI MOHAMOUD | F91: DIRECTOR | G91: To provide services and facilitate the assimilation and merge of the Somalian community into the larger stream of the United States of America. Services include cultural education, social classes, sheltering information, skill instructions and translation assitance and services | H91: hornafrica.org | I91: CA | K91: CA | L91: 6
B92: 4 CHRIST MISSION | D92: 8587487001 | E92: PAUL SUH | F92: PRESIDENT | G92: TO ENGAGE IN RELIGIOUS ACTIVITIES AND ADMINISTER AND EVANGELISM | H92: WWW.4CHRISTMISSION.ORG | I92: CA | K92: CA | L92: 3
B93: ST LUKES FAMILY MEDICAL GROUP | D93: 2095491057 | E93: DR RICHARD J HECK MD | F93: CEO | G93: A GENERAL PRACTICE MEDICAL CLINICAL PROVIDING MEDICAL SERVICES TO INDIVIDUALS AND FAMILIES IN MODESTO WHO DO NOT QUALIFY FOR ANY OTHER FREE GOVERNMENT HEALTH CARE PROGRAMS AND HAVE NO HEALTH INSURANCE AND CANNOT AFFORD TO PAY FOR THEIR HEALTH CARE. | H93: WWW.STLUKESFP.ORG | I93: CA | K93: CA | L93: 6
B94: CHANGING PEOPLES LIVES INC | D94: 9097969440 | E94: ELISEO LOZANO | F94: PRESIDENT | G94: SUPPORTS NBSP;THE NBSP;MISSIONS NBSP;OF NBSP;THE NBSP;SEVENTH NBSP;DAY NBSP;ADVENTIST NBSP;MESSAGE NBSP;BOTH NBSP;THROUGH NBSP;HUMANITARIAN NBSP;AND NBSP;SPECIAL NBSP;OUTREACH NBSP;INITIATIVES NBSP;IN NBSP;THOSE NBSP;COUNTRIES NBSP;OF NBSP;THE NBSP;WORLD NBSP;WHERE NBSP;RELIGIOUS NBSP;FREEDOM NBSP;IS NBSP;HIGHLY NBSP;RESTRICTED | H94: www.cplives.org | I94: CA | K94: CA | L94: 10
B95: Seed House Project | D95: 8133519718 | E95: Garrett Underwood | F95: Executive Director | G95: See Schedule O | H95: www.seedhouseproject.org | I95: CA | K95: CA | L95: 7 | M95: 3
B96: AGAPE CHILDREN'S MINISTRY INC | D96: 2095439255 | E96: DAN BLACKMAN | F96: Vice President | G96: AGAPE CHILDREN'S MINISTRY, INC. (THE MINISTRY) IS A NOT-FOR-PROFIT CORPORATION ESTABLISHED UNDER THE LAWS OF THE STATE OF CALIFORNIA. THE MINISTRY IS A RELIGIOUS ORGANIZATION DEDICATED TO THE FOLLOWING OBJECTIVES: 1. RESCUING STREET CHILDREN AND AT-RISK CHILDREN IN DEVELOPING COUNTRIES; 2. TO SHARE THE LIFE CHANGING MESSAGE OF THE GOSPEL OF JESUS CHRIST WITH THOSE WE ENCOUNTER PARTICULARLY THE CHILDREN, THEIR FAMILIES, AND THEIR EXTENDED FAMILIES; 3. IN A LOVING, SUPPORTIVE CHRISTIAN ENVIRONMENT, TO REHABILITATE THE CHILDREN WE RESCUE BY PROVIDING APPROPRIATE EDUCATION, TRAINING, COUNSELING, SPIRITUAL MENTORING AND DISCIPLESHIP, AND PREPARATION FOR REINTEGRATION; 4. WHENEVER POSSIBLE, TO REINTEGRATE THE CHILDREN BACK INTO THEIR FAMILIES OR EXTENDED FAMILIES AND BACK INTO THEIR CULTURE AND COMMUNITIES. THE GOALS ARE ACCOMPLISHED THROUGH, BUT NOT LIMITED TO, THE ESTABLISHMENT AND OPERATION OF COMMUNITY REHABILITATION CENTERS, ACADEMIC AND TRAINING PROGRAMS, COUNSELING PROGRAMS, AND DISCI | H96: WWW.AGAPECHILDREN.ORG | I96: CA | K96: CA | L96: 5
B97: ANGELS OF GRACE INC | D97: 5592867546 | E97: ELIZABETH CASAREZ | F97: Executive Dir. | G97: THE SPECIFIC PURPOSE OF THIS ORGANIZATION IS TO PROVIDE FOSTER CARE SERVICES WITH THE ULTIMATE GOAL OF REUNIFICATION OF THE CHILD WIHT THEIR BIOLOGICAL FAMILY IF DOING SO WOULD BE IN THE BEST INTEREST OF THE CHILD. | H97: WWW.ANGELSOFGRACE.COM | I97: CA | K97: CA | L97: 8
B98: 4EVERGREEN FOSTER FAMILY AGENCY INC | D98: 5595156412 | E98: DEBORAH WENGER | F98: PRESIDENT | G98: AT 4EVERGREEN FOSTER FAMILY AGENCY, INC, WELLBEING IS AT THE FOREFRONT OF WHAT WERE WORKING TOWARDS TO HELP EVERY CHILD GROW TO REACH THEIR GOALS AND FULFILL THEIR POTENTIAL. OUR PROGRAMS AND ACTIVITIES ARE DESIGNED TO BE A CATALYST THAT HELPS SERVE THE NEEDS OF CHILDREN WHO HAVE BEEN REMOVED FROM THEIR HOMES DUE TO ABUSE AND NEGLECT. | H98: WWW.4EVERGREENFFAINC.ORG | I98: CA | K98: CA | L98: 6
B99: Mary Elizabeth Inn The | D99: 4156736768 | E99: Dion Roberts | F99: Executive Director | G99: To end the cycle of violence and homelessness for women in San Francisco by providing permanent housing and supportive services. | H99: meinn.org | I99: CA | K99: CA | L99: 10 | M99: 8
B100: ROUNDHOUSE COUNCIL INC | D100: 5302846866 | E100: CHARLENE MULLEN | F100: SECRETARY | G100: TO PROVIDE EDUCATIONAL OPPORTUNITIES AND OTHER RESOURCES TO CREATE AND PROMOTE COMMUNITY WELL-BEING AND POSITIVE ATTITUDES, WHICH ENHANCE THE QUALITY OF LIFE FOR MAIDU AND OTHER NATIVE AMERICAN CULTURES. | I100: CA | K100: CA | L100: 7
B101: AFRICAN ADVOCACY NETWORK | D101: 4155031032 | E101: Adoubou Traore | F101: Executive Dir. | G101: AFRICAN ADVOCACY NETWORK (AAN)FOUNDED TO SERVE THE GROWING DIASPORA OF AFRICAN AND AFRO-CARIBBEAN IMMIGRANTS. AAN PROVIDES IMMIGRATION LEGAL SERVICES, CASE MANAGEMENT, AND SOCIAL INTEGRATION SERVICES BASED ON A UNIQUE CULTURAL BROKERING MODEL. | H101: WWW.AANSF.ORG | I101: CA | K101: CA | L101: 10
...

Sheet Foundations
B2: business name | C2: Contact Date | D2: phone | E2: Email | F2: website | G2: state | H2: EIN | I2: total assets | J2: grantee count | K2: cb grant count | L2: intermediary grant count | M2: paid officer count | N2: top officer name | O2: top officer title | P2: Column1 | Q2: Linkedin URL | R2: segment | S2: Sent VM | T2: Talked to Someone | U2: Send us an Email | V2: Reached Decision Maker | W2: Yes/No/Maybe/Uncertain | X2: Notes
B3: THE WILLIAM & FLORA HEWLETT FOUNDATION | C3: 46007 | D3: 6502344500 | F3: WWW.HEWLETT.ORG | G3: CA | I3: 13332174215 | J3: 1072 | K3: 1160 | L3: 71 | M3: 0 | N3: MARIANO-FLORENTINO CUELLAR | O3: CHAIR | P3: Foundation | R3: Intermediary Funders | W3: No Answer Try Again
B4: CONRAD N HILTON FOUNDATION | C4: 46007 | D4: 8188513724 | F4: WWW.HILTONFOUNDATION.ORG | G4: CA | I4: 7099706570 | J4: 976 | K4: 1057 | L4: 148 | M4: 1 | N4: PETER A LAUGHARN | O4: PRESIDENT AND CEO | P4: Foundation | R4: Intermediary Funders | W4: No Answer Try Again | X4: Michael@hilton
B5: THE CALIFORNIA WELLNESS FOUNDATION | C5: 46007 | D5: 8187021900 | F5: WWW.CALWELLNESS.ORG | G5: CA | I5: 1042135742 | J5: 738 | K5: 689 | L5: 49 | M5: 1 | N5: JUDY BELK | O5: PRESIDENT & CEO | P5: Foundation | R5: Intermediary Funders | W5: No Answer Try Again
B6: The James Irvine Foundation | C6: 46007 | D6: 4157772244 | F6: www.Irvine.org | G6: CA | I6: 3245582018 | J6: 628 | K6: 56 | L6: 36 | M6: 1 | N6: MELISSA LOPEZ | O6: PRESIDENT& CEO/DIR | P6: Foundation | R6: Intermediary Funders | W6: No Answer Try Again
B7: AARON'S FOUNDATION INC | D7: 678-402-3000 | E7: investorrelations@aarons.com | F7: https://www.aarons.com/aarons-gives | G7: =_xlfn.XLOOKUP(H7,Sheet2!B:B,Sheet2!D:D) -> GA | H7: 453611066 | I7: =_xlfn.XLOOKUP(H7,Sheet2!B:B,Sheet2!E:E) -> 201086 | J7: =_xlfn.XLOOKUP($H7,Sheet2!$B:$B,Sheet2!F:F) -> 128 | K7: =_xlfn.XLOOKUP($H7,Sheet2!$B:$B,Sheet2!G:G) -> 1 | L7: =_xlfn.XLOOKUP($H7,Sheet2!$B:$B,Sheet2!H:H) -> 10 | M7: =_xlfn.XLOOKUP($H7,Sheet2!$B:$B,Sheet2!I:I) -> 0 | N7: Rachel George | O7: Board Member / Senior Executive | P7: Foundation | Q7: https://www.linkedin.com/in/rachel-george-4b0a227/ | R7: =_xlfn.XLOOKUP(H7,Sheet2!B:B,Sheet2!N:N) -> Intermediary Funders
B8: Alaska Airlines Foundation | C8: 46008 | D8: 206-392-5719 | E8: Not publicly available | F8: https://www.alaskaair.com/content/about-us/social-responsibility/alaska-airlines-foundation | G8: =_xlfn.XLOOKUP(H8,Sheet2!B:B,Sheet2!D:D) -> AK | H8: 920166198 | I8: =_xlfn.XLOOKUP(H8,Sheet2!B:B,Sheet2!E:E) -> 10478825 | J8: =_xlfn.XLOOKUP($H8,Sheet2!$B:$B,Sheet2!F:F) -> 80 | K8: =_xlfn.XLOOKUP($H8,Sheet2!$B:$B,Sheet2!G:G) -> 1 | L8: =_xlfn.XLOOKUP($H8,Sheet2!$B:$B,Sheet2!H:H) -> 31 | M8: =_xlfn.XLOOKUP($H8,Sheet2!$B:$B,Sheet2!I:I) -> 0 | N8: Diana Birkett Rakow | O8: Chair of Board / SVP Public Affairs & Sustainability | P8: Foundation | Q8: https://www.linkedin.com/in/dianabirkettrakow/ | R8: =_xlfn.XLOOKUP(H8,Sheet2!B:B,Sheet2!N:N) -> Intermediary Funders | S8: 1 | X8: Bad number
B9: ALBERT AND ELAINE BORCHARD | C9: 46008 | D9: 8185651020 | E9: michael.spurgeon@borchardfoundation.org | F9: https://borchardfoundation.org | G9: =_xlfn.XLOOKUP(H9,Sheet2!B:B,Sheet2!D:D) -> CA | H9: 953294377 | I9: =_xlfn.XLOOKUP(H9,Sheet2!B:B,Sheet2!E:E) -> 18275989 | J9: =_xlfn.XLOOKUP($H9,Sheet2!$B:$B,Sheet2!F:F) -> 38 | K9: =_xlfn.XLOOKUP($H9,Sheet2!$B:$B,Sheet2!G:G) -> 36 | L9: =_xlfn.XLOOKUP($H9,Sheet2!$B:$B,Sheet2!H:H) -> 0 | M9: =_xlfn.XLOOKUP($H9,Sheet2!$B:$B,Sheet2!I:I) -> 2 | N9: Michael Spurgeon | O9: Executive Vice President / Director Center on Literary Arts | P9: Foundation | Q9: Not found | R9: =_xlfn.XLOOKUP(H9,Sheet2!B:B,Sheet2!N:N) -> California CB
B10: ALFRED P SLOAN FOUNDATION | C10: 46008 | D10: 212-649-1649 - ext 1676 | E10: Not publicly available | F10: https://sloan.org | G10: =_xlfn.XLOOKUP(H10,Sheet2!B:B,Sheet2!D:D) -> NY | H10: 131623877 | I10: =_xlfn.XLOOKUP(H10,Sheet2!B:B,Sheet2!E:E) -> 2116962267 | J10: =_xlfn.XLOOKUP($H10,Sheet2!$B:$B,Sheet2!F:F) -> 182 | K10: =_xlfn.XLOOKUP($H10,Sheet2!$B:$B,Sheet2!G:G) -> 0 | L10: =_xlfn.XLOOKUP($H10,Sheet2!$B:$B,Sheet2!H:H) -> 20 | M10: =_xlfn.XLOOKUP($H10,Sheet2!$B:$B,Sheet2!I:I) -> 2 | N10: Daniel L. Goroff | O10: Vice President & Program Director | P10: Foundation | Q10: Not found | R10: =_xlfn.XLOOKUP(H10,Sheet2!B:B,Sheet2!N:N) -> Intermediary Funders | S10: 1
B11: ALLETTA MORRIS MCBEAN CHARITABLE TRUST | C11: 46008 | D11: 760-564-3000 | E11: mcbeanproperties@att.net | F11: http://www.allettamcbeancharitabletrust.org | G11: =_xlfn.XLOOKUP(H11,Sheet2!B:B,Sheet2!D:D) -> CA | H11: 943019660 | I11: =_xlfn.XLOOKUP(H11,Sheet2!B:B,Sheet2!E:E) -> 20496407 | J11: =_xlfn.XLOOKUP($H11,Sheet2!$B:$B,Sheet2!F:F) -> 39 | K11: =_xlfn.XLOOKUP($H11,Sheet2!$B:$B,Sheet2!G:G) -> 4 | L11: =_xlfn.XLOOKUP($H11,Sheet2!$B:$B,Sheet2!H:H) -> 1 | M11: =_xlfn.XLOOKUP($H11,Sheet2!$B:$B,Sheet2!I:I) -> 0 | N11: Charlene C. Kleiner | O11: Administrator | P11: Foundation | Q11: Not found | R11: =_xlfn.XLOOKUP(H11,Sheet2!B:B,Sheet2!N:N) -> California CB | S11: 1
B12: ALLIANCE HEALTHCARE FOUNDATION | C12: 46008 | D12: 858-875-3305 | E12: barbara.valdivia@alliancehf.org | F12: https://alliancehf.org | G12: =_xlfn.XLOOKUP(H12,Sheet2!B:B,Sheet2!D:D) -> CA | H12: 330340635 | I12: =_xlfn.XLOOKUP(H12,Sheet2!B:B,Sheet2!E:E) -> 85505150 | J12: =_xlfn.XLOOKUP($H12,Sheet2!$B:$B,Sheet2!F:F) -> 68 | K12: =_xlfn.XLOOKUP($H12,Sheet2!$B:$B,Sheet2!G:G) -> 8 | L12: =_xlfn.XLOOKUP($H12,Sheet2!$B:$B,Sheet2!H:H) -> 0 | M12: =_xlfn.XLOOKUP($H12,Sheet2!$B:$B,Sheet2!I:I) -> 2 | N12: Barbara Orozco-Valdivia MPH | O12: Vice President of Programs & Community Partnerships | P12: Foundation | Q12: https://www.linkedin.com/in/barbaraorozcovaldivia/ | R12: =_xlfn.XLOOKUP(H12,Sheet2!B:B,Sheet2!N:N) -> California CB | S12: 1
B13: ALLY CHARITABLE FOUNDATION | D13: 980-312-8320 | E13: grants@ally.com | F13: https://ally.com/about/social-impact/grants/ | G13: =_xlfn.XLOOKUP(H13,Sheet2!B:B,Sheet2!D:D) -> NC | H13: 844571035 | I13: =_xlfn.XLOOKUP(H13,Sheet2!B:B,Sheet2!E:E) -> 81746335 | J13: =_xlfn.XLOOKUP($H13,Sheet2!$B:$B,Sheet2!F:F) -> 156 | K13: =_xlfn.XLOOKUP($H13,Sheet2!$B:$B,Sheet2!G:G) -> 6 | L13: =_xlfn.XLOOKUP($H13,Sheet2!$B:$B,Sheet2!H:H) -> 14 | M13: =_xlfn.XLOOKUP($H13,Sheet2!$B:$B,Sheet2!I:I) -> 0 | N13: Kathie Patterson | O13: Chair / Chief HR & Corporate Citizenship Officer | P13: Foundation | Q13: https://www.linkedin.com/in/kathie-patterson-9aaa058/ | R13: =_xlfn.XLOOKUP(H13,Sheet2!B:B,Sheet2!N:N) -> Intermediary Funders
B14: ALTMAN FOUNDATION | D14: 212-682-0970 | E14: info@altman.org | F14: https://www.altmanfoundation.org | G14: =_xlfn.XLOOKUP(H14,Sheet2!B:B,Sheet2!D:D) -> NY | H14: 131623879 | I14: =_xlfn.XLOOKUP(H14,Sheet2!B:B,Sheet2!E:E) -> 283326707 | J14: =_xlfn.XLOOKUP($H14,Sheet2!$B:$B,Sheet2!F:F) -> 150 | K14: =_xlfn.XLOOKUP($H14,Sheet2!$B:$B,Sheet2!G:G) -> 57 | L14: =_xlfn.XLOOKUP($H14,Sheet2!$B:$B,Sheet2!H:H) -> 22 | M14: =_xlfn.XLOOKUP($H14,Sheet2!$B:$B,Sheet2!I:I) -> 0 | N14: Deborah T. Velazquez | O14: President | P14: Foundation | Q14: Not found | R14: =_xlfn.XLOOKUP(H14,Sheet2!B:B,Sheet2!N:N) -> Intermediary Funders
B15: AMERICAN WOODMARK FOUNDATION INC | D15: 540-665-9100 | E15: Not publicly available | F15: https://americanwoodmark.com | G15: =_xlfn.XLOOKUP(H15,Sheet2!B:B,Sheet2!D:D) -> VA | H15: 541759773 | I15: =_xlfn.XLOOKUP(H15,Sheet2!B:B,Sheet2!E:E) -> 1278837 | J15: =_xlfn.XLOOKUP($H15,Sheet2!$B:$B,Sheet2!F:F) -> 260 | K15: =_xlfn.XLOOKUP($H15,Sheet2!$B:$B,Sheet2!G:G) -> 7 | L15: =_xlfn.XLOOKUP($H15,Sheet2!$B:$B,Sheet2!H:H) -> 20 | M15: =_xlfn.XLOOKUP($H15,Sheet2!$B:$B,Sheet2!I:I) -> 0 | N15: Brenda Dupont | O15: Chair / Executive Assistant to CEO | P15: Foundation | Q15: https://www.linkedin.com/in/brenda-dupont-38a45533 | R15: =_xlfn.XLOOKUP(H15,Sheet2!B:B,Sheet2!N:N) -> Intermediary Funders
B16: ANN JACKSON FAMILY FOUNDATION | C16: 46008 | D16: 805-969-2258 | E16: palmer.jackson@gmail.com | F16: https://www.annjacksonfamilyfoundation.org | G16: =_xlfn.XLOOKUP(H16,Sheet2!B:B,Sheet2!D:D) -> CA | H16: 953367511 | I16: =_xlfn.XLOOKUP(H16,Sheet2!B:B,Sheet2!E:E) -> 88737372 | J16: =_xlfn.XLOOKUP($H16,Sheet2!$B:$B,Sheet2!F:F) -> 98 | K16: =_xlfn.XLOOKUP($H16,Sheet2!$B:$B,Sheet2!G:G) -> 372 | L16: =_xlfn.XLOOKUP($H16,Sheet2!$B:$B,Sheet2!H:H) -> 0 | M16: =_xlfn.XLOOKUP($H16,Sheet2!$B:$B,Sheet2!I:I) -> 0 | N16: Palmer G. Jackson Jr. | O16: President / Managing Trustee | P16: Foundation | Q16: https://www.linkedin.com/in/palmerjackson/ | R16: =_xlfn.XLOOKUP(H16,Sheet2!B:B,Sheet2!N:N) -> California CB | S16: 1
B17: Whitier Trust | C17: 46008 | D17: 626-441-5188 | E17: Not publicly available | F17: None | G17: =_xlfn.XLOOKUP(H17,Sheet2!B:B,Sheet2!D:D) -> CA | H17: 952114455 | I17: =_xlfn.XLOOKUP(H17,Sheet2!B:B,Sheet2!E:E) -> 42771908 | J17: =_xlfn.XLOOKUP($H17,Sheet2!$B:$B,Sheet2!F:F) -> 30 | K17: =_xlfn.XLOOKUP($H17,Sheet2!$B:$B,Sheet2!G:G) -> 44 | L17: =_xlfn.XLOOKUP($H17,Sheet2!$B:$B,Sheet2!H:H) -> 0 | M17: =_xlfn.XLOOKUP($H17,Sheet2!$B:$B,Sheet2!I:I) -> 1 | N17: Pegine E. Grayson | O17: Executive Director / Secretary | P17: Foundation Management | Q17: Not found | R17: =_xlfn.XLOOKUP(H17,Sheet2!B:B,Sheet2!N:N) -> California CB | X17: Pegine said this sounds great and that I should send a write up of what we're doing (2-3) pages to Jesse ostroff. - notes from calls: 12 people on team. Send it to her and she can share it and they can say this is a great resource. And send it to all the foundations they’re over. The foundations can determine which clients need to diversify and give them capacity building grants so they can use our service. Send email to Jesse ostraf Jostroff@whitiertrust.com We had a brief conversation and that she suggested I reach ut to him because its possible for clients who want capacity building their grantees
B18: Anschutz Family Foundation | D18: 303-293-2338 | E18: abel@anschutzfamily.org | F18: https://anschutzfamilyfoundation.org | G18: =_xlfn.XLOOKUP(H18,Sheet2!B:B,Sheet2!D:D) -> CO | H18: 742132676 | I18: =_xlfn.XLOOKUP(H18,Sheet2!B:B,Sheet2!E:E) -> 45765575 | J18: =_xlfn.XLOOKUP($H18,Sheet2!$B:$B,Sheet2!F:F) -> 160 | K18: =_xlfn.XLOOKUP($H18,Sheet2!$B:$B,Sheet2!G:G) -> 236 | L18: =_xlfn.XLOOKUP($H18,Sheet2!$B:$B,Sheet2!H:H) -> 13 | M18: =_xlfn.XLOOKUP($H18,Sheet2!$B:$B,Sheet2!I:I) -> 0 | N18: Abel Wurmnest | O18: Executive Director | P18: Foundation | Q18: https://www.linkedin.com/in/abel-wurmnest-06359916 | R18: =_xlfn.XLOOKUP(H18,Sheet2!B:B,Sheet2!N:N) -> Intermediary Funders
B19: ARCONIC CHARITABLE FOUNDATION II | D19: 412-315-2984 | E19: ryan.kish@arconic.com | F19: https://www.arconic.com/foundation | G19: =_xlfn.XLOOKUP(H19,Sheet2!B:B,Sheet2!D:D) -> PA | H19: 843049720 | I19: =_xlfn.XLOOKUP(H19,Sheet2!B:B,Sheet2!E:E) -> 0 | J19: =_xlfn.XLOOKUP($H19,Sheet2!$B:$B,Sheet2!F:F) -> 82 | K19: =_xlfn.XLOOKUP($H19,Sheet2!$B:$B,Sheet2!G:G) -> 4 | L19: =_xlfn.XLOOKUP($H19,Sheet2!$B:$B,Sheet2!H:H) -> 11 | M19: =_xlfn.XLOOKUP($H19,Sheet2!$B:$B,Sheet2!I:I) -> 0 | N19: Ryan Kish | O19: President and Treasurer | P19: Foundation | Q19: https://www.linkedin.com/in/ryankish/ | R19: =_xlfn.XLOOKUP(H19,Sheet2!B:B,Sheet2!N:N) -> Intermediary Funders
B20: ARCUS FOUNDATION | D20: 212-488-3000 | E20: hantonissen@arcusfoundation.org | F20: https://www.arcusfoundation.org | G20: =_xlfn.XLOOKUP(H20,Sheet2!B:B,Sheet2!D:D) -> NY | H20: 383332791 | I20: =_xlfn.XLOOKUP(H20,Sheet2!B:B,Sheet2!E:E) -> 275369766 | J20: =_xlfn.XLOOKUP($H20,Sheet2!$B:$B,Sheet2!F:F) -> 168 | K20: =_xlfn.XLOOKUP($H20,Sheet2!$B:$B,Sheet2!G:G) -> 437 | L20: =_xlfn.XLOOKUP($H20,Sheet2!$B:$B,Sheet2!H:H) -> 30 | M20: =_xlfn.XLOOKUP($H20,Sheet2!$B:$B,Sheet2!I:I) -> 0 | N20: Annette Lanjouw | O20: Chief Executive Officer | P20: Foundation | Q20: https://www.linkedin.com/in/annette-lanjouw-1a959ab/ | R20: =_xlfn.XLOOKUP(H20,Sheet2!B:B,Sheet2!N:N) -> Intermediary Funders
B21: AVANGRID FOUNDATION INC | D21: 203-836-6457 | E21: avangridfoundation@avangrid.com | F21: https://www.avangrid.com/avangrid-foundation | G21: =_xlfn.XLOOKUP(H21,Sheet2!B:B,Sheet2!D:D) -> CT | H21: 134200689 | I21: =_xlfn.XLOOKUP(H21,Sheet2!B:B,Sheet2!E:E) -> 5760467 | J21: =_xlfn.XLOOKUP($H21,Sheet2!$B:$B,Sheet2!F:F) -> 64 | K21: =_xlfn.XLOOKUP($H21,Sheet2!$B:$B,Sheet2!G:G) -> 0 | L21: =_xlfn.XLOOKUP($H21,Sheet2!$B:$B,Sheet2!H:H) -> 32 | M21: =_xlfn.XLOOKUP($H21,Sheet2!$B:$B,Sheet2!I:I) -> 0 | N21: Pablo Colon | O21: Director Corporate Citizenship / Executive Director | P21: Foundation | Q21: Not found | R21: =_xlfn.XLOOKUP(H21,Sheet2!B:B,Sheet2!N:N) -> Intermediary Funders
B22: BALL BROTHERS FOUNDATION | D22: 765-741-5500 | E22: info@ballfdn.org | F22: https://www.ballfdn.org | G22: =_xlfn.XLOOKUP(H22,Sheet2!B:B,Sheet2!D:D) -> IN | H22: 350882856 | I22: =_xlfn.XLOOKUP(H22,Sheet2!B:B,Sheet2!E:E) -> 170691544 | J22: =_xlfn.XLOOKUP($H22,Sheet2!$B:$B,Sheet2!F:F) -> 59 | K22: =_xlfn.XLOOKUP($H22,Sheet2!$B:$B,Sheet2!G:G) -> 18 | L22: =_xlfn.XLOOKUP($H22,Sheet2!$B:$B,Sheet2!H:H) -> 17 | M22: =_xlfn.XLOOKUP($H22,Sheet2!$B:$B,Sheet2!I:I) -> 0 | N22: Jud Fisher | O22: President and CEO | P22: Foundation | Q22: Not found | R22: =_xlfn.XLOOKUP(H22,Sheet2!B:B,Sheet2!N:N) -> Intermediary Funders
B23: BANK OF GREENE COUNTY | D23: 518-943-1424 | E23: amandakg@tbogc.com | F23: https://www.thebankofgreenecounty.com | G23: =_xlfn.XLOOKUP(H23,Sheet2!B:B,Sheet2!D:D) -> NY | H23: 141810419 | I23: =_xlfn.XLOOKUP(H23,Sheet2!B:B,Sheet2!E:E) -> 11848394 | J23: =_xlfn.XLOOKUP($H23,Sheet2!$B:$B,Sheet2!F:F) -> 190 | K23: =_xlfn.XLOOKUP($H23,Sheet2!$B:$B,Sheet2!G:G) -> 6 | L23: =_xlfn.XLOOKUP($H23,Sheet2!$B:$B,Sheet2!H:H) -> 10 | M23: =_xlfn.XLOOKUP($H23,Sheet2!$B:$B,Sheet2!I:I) -> 0 | N23: Amanda Grant | O23: Charitable Foundation Contact | P23: Foundation | Q23: Not found | R23: =_xlfn.XLOOKUP(H23,Sheet2!B:B,Sheet2!N:N) -> Intermediary Funders
B24: BARSTOW FOUNDATION | D24: 989-839-5305 | E24: Not found | F24: None | G24: =_xlfn.XLOOKUP(H24,Sheet2!B:B,Sheet2!D:D) -> CA | H24: 386151026 | I24: =_xlfn.XLOOKUP(H24,Sheet2!B:B,Sheet2!E:E) -> 5545120 | J24: =_xlfn.XLOOKUP($H24,Sheet2!$B:$B,Sheet2!F:F) -> 40 | K24: =_xlfn.XLOOKUP($H24,Sheet2!$B:$B,Sheet2!G:G) -> 84 | L24: =_xlfn.XLOOKUP($H24,Sheet2!$B:$B,Sheet2!H:H) -> 0 | M24: =_xlfn.XLOOKUP($H24,Sheet2!$B:$B,Sheet2!I:I) -> 1 | N24: John E. Kessler | O24: EVP/Senior Trust Officer (Former) | P24: Foundation | Q24: Not found | R24: =_xlfn.XLOOKUP(H24,Sheet2!B:B,Sheet2!N:N) -> California CB
B25: BCM Foundation | D25: 562-696-0338 | E25: Use contact form | F25: https://bcm-foundation.org | G25: =_xlfn.XLOOKUP(H25,Sheet2!B:B,Sheet2!D:D) -> CA | H25: 262667384 | I25: =_xlfn.XLOOKUP(H25,Sheet2!B:B,Sheet2!E:E) -> 53348657 | J25: =_xlfn.XLOOKUP($H25,Sheet2!$B:$B,Sheet2!F:F) -> 24 | K25: =_xlfn.XLOOKUP($H25,Sheet2!$B:$B,Sheet2!G:G) -> 12 | L25: =_xlfn.XLOOKUP($H25,Sheet2!$B:$B,Sheet2!H:H) -> 0 | M25: =_xlfn.XLOOKUP($H25,Sheet2!$B:$B,Sheet2!I:I) -> 1 | N25: James D. Shepard | O25: Trustee / Managing Director | P25: Foundation | Q25: Not found | R25: =_xlfn.XLOOKUP(H25,Sheet2!B:B,Sheet2!N:N) -> California CB
B26: BELLA VISTA FOUNDATION | D26: 415-561-6540 | E26: ejohansson@pfs-llc.net | F26: https://www.bellavistafoundation.org | G26: =_xlfn.XLOOKUP(H26,Sheet2!B:B,Sheet2!D:D) -> CA | H26: 943345967 | I26: =_xlfn.XLOOKUP(H26,Sheet2!B:B,Sheet2!E:E) -> 68423844 | J26: =_xlfn.XLOOKUP($H26,Sheet2!$B:$B,Sheet2!F:F) -> 88 | K26: =_xlfn.XLOOKUP($H26,Sheet2!$B:$B,Sheet2!G:G) -> 17 | L26: =_xlfn.XLOOKUP($H26,Sheet2!$B:$B,Sheet2!H:H) -> 6 | M26: =_xlfn.XLOOKUP($H26,Sheet2!$B:$B,Sheet2!I:I) -> 0 | N26: Emily Johansson | O26: Program Director / Co-Executive Director | P26: Foundation | Q26: https://www.linkedin.com/in/emily-johansson-8043251 | R26: =_xlfn.XLOOKUP(H26,Sheet2!B:B,Sheet2!N:N) -> California CB
B27: BERKSHIRE BANK FOUNDATION INC | D27: 413-447-1722 | E27: foundation@berkshirebank.com | F27: https://www.berkshirebank.com/about-us/our-impact/community-support/berkshire-bank-foundation | G27: =_xlfn.XLOOKUP(H27,Sheet2!B:B,Sheet2!D:D) -> MA | H27: 43365869 | I27: =_xlfn.XLOOKUP(H27,Sheet2!B:B,Sheet2!E:E) -> 18644149 | J27: =_xlfn.XLOOKUP($H27,Sheet2!$B:$B,Sheet2!F:F) -> 203 | K27: =_xlfn.XLOOKUP($H27,Sheet2!$B:$B,Sheet2!G:G) -> 16 | L27: =_xlfn.XLOOKUP($H27,Sheet2!$B:$B,Sheet2!H:H) -> 19 | M27: =_xlfn.XLOOKUP($H27,Sheet2!$B:$B,Sheet2!I:I) -> 0 | N27: Lori Gazzillo Kiely | O27: Managing Director / Foundation Director | P27: Foundation | Q27: https://www.linkedin.com/in/lori-gazzillo-kiely-8291174 | R27: =_xlfn.XLOOKUP(H27,Sheet2!B:B,Sheet2!N:N) -> Intermediary Funders
B28: BESS J HODGES FOUNDATION | D28: 562-961-4115 | E28: Not found | F28: None | G28: =_xlfn.XLOOKUP(H28,Sheet2!B:B,Sheet2!D:D) -> CA | H28: 330046140 | I28: =_xlfn.XLOOKUP(H28,Sheet2!B:B,Sheet2!E:E) -> 6370611 | J28: =_xlfn.XLOOKUP($H28,Sheet2!$B:$B,Sheet2!F:F) -> 35 | K28: =_xlfn.XLOOKUP($H28,Sheet2!$B:$B,Sheet2!G:G) -> 215 | L28: =_xlfn.XLOOKUP($H28,Sheet2!$B:$B,Sheet2!H:H) -> 0 | M28: =_xlfn.XLOOKUP($H28,Sheet2!$B:$B,Sheet2!I:I) -> 2 | N28: George Murchison | O28: Executive Director | P28: Foundation | Q28: Not found | R28: =_xlfn.XLOOKUP(H28,Sheet2!B:B,Sheet2!N:N) -> California CB
B29: BISSELL Pet Foundation | D29: 616-735-6666 | E29: info@bissellpetfoundation.org | F29: https://www.bissellpetfoundation.org | G29: =_xlfn.XLOOKUP(H29,Sheet2!B:B,Sheet2!D:D) -> MI | H29: 383853264 | I29: =_xlfn.XLOOKUP(H29,Sheet2!B:B,Sheet2!E:E) -> 4578467 | J29: =_xlfn.XLOOKUP($H29,Sheet2!$B:$B,Sheet2!F:F) -> 229 | K29: =_xlfn.XLOOKUP($H29,Sheet2!$B:$B,Sheet2!G:G) -> 0 | L29: =_xlfn.XLOOKUP($H29,Sheet2!$B:$B,Sheet2!H:H) -> 12 | M29: =_xlfn.XLOOKUP($H29,Sheet2!$B:$B,Sheet2!I:I) -> 0 | N29: Emma Allen (Geers) | O29: Associate Grants and Programs Manager | P29: Foundation | Q29: https://www.linkedin.com/in/emma-allen-geers-a588abb6 | R29: =_xlfn.XLOOKUP(H29,Sheet2!B:B,Sheet2!N:N) -> Intermediary Funders
... B106: Public Welfare Foundation Inc | D106: (202) 965-1800 | E106: info@publicwelfare.org | F106: https://www.publicwelfare.org | G106: =_xlfn.XLOOKUP(H106,Sheet2!B:B,Sheet2!D:D) -> DC | H106: 540597601 | I106: =_xlfn.XLOOKUP(H106,Sheet2!B:B,Sheet2!E:E) -> 601086862 | J106: =_xlfn.XLOOKUP($H106,Sheet2!$B:$B,Sheet2!F:F) -> 166 | K106: =_xlfn.XLOOKUP($H106,Sheet2!$B:$B,Sheet2!G:G) -> 11 | L106: =_xlfn.XLOOKUP($H106,Sheet2!$B:$B,Sheet2!H:H) -> 11 | M106: =_xlfn.XLOOKUP($H106,Sheet2!$B:$B,Sheet2!I:I) -> 5 | N106: Thena Robinson Mock | O106: Vice President of Programs | P106: Foundation | Q106: https://www.linkedin.com/in/thena-robinsonmock | R106: =_xlfn.XLOOKUP(H106,Sheet2!B:B,Sheet2!N:N) -> Intermediary Funders
B107: BlueStone Services | D107: 888-797-2583 | F107: bluestonesvc.com | N107: Trey Gailey CPA | O107: Managing Director | P107: Foundation Management
B108: Crewe Foundation Services | D108: (385) 322-3400 | F108: crewefoundationservices.com | N108: Don Evans | O108: President and CEO | P108: Foundation Management
B109: Foundation Group | F109: 501c3.org | N109: Greg McRay EA | O109: President and CEO | P109: Foundation Management
B110: Foundation Source | F110: foundationsource.com | N110: Elizabeth Wong | O110: Head of Philanthropic Advisory Services | P110: Foundation Management
B111: Pacific Foundation Services | F111: pfs-llc.net | N111: Juliana Grenzeback | O111: President | P111: Foundation Management
B112: Sterling Foundation Management | D112: 703-437-9720 | F112: sterlingfoundations.com | N112: Roger D. Silk PhD | O112: Founder and CEO | P112: Foundation Management
B113: Arden Trust Company | F113: ardentrust.com | N113: Michael Roberts | O113: President | P113: Foundation Management
B114: Bessemer Trust | F114: bessemertrust.com | N114: Caroline Woodruff Hodkinson | O114: Managing Director Head of Philanthropy | P114: Foundation Management
B115: Fiduciary Trust Company | F115: fiduciary-trust.com | N115: Suma V. Nair JD | O115: Chief Fiduciary Officer | P115: Foundation Management
B116: Glenmede Trust | F116: glenmede.com | N116: Nina L. Cohen JD CAP | O116: Director Endowment & Foundation Advisory | P116: Foundation Management
B117: Aly Sterling Philanthropy | F117: alysterling.com | N117: Aly Sterling | O117: Founder and President | P117: Foundation Management
B118: Bridgespan Group | D118: (617) 572-2833 | F118: bridgespan.org | N118: William Foster | O118: Managing Partner | P118: Foundation Management
B119: CCS Fundraising | F119: ccsfundraising.com | N119: Jon Kane | O119: President and CEO | P119: Foundation Management
B120: Cascade Philanthropy Advisors | F120: cascadephilanthropy.org | N120: Lowell Weiss | O120: President/Founder | P120: Foundation Management
B121: Convergent Nonprofit Solutions | F121: convergentnonprofit.com | N121: Tom Ralser | O121: Principal | P121: Foundation Management
B122: Daylight Advisors | F122: daylightadvisors.com | N122: Dien Yuen | O122: Founder and CEO | P122: Foundation Management
B123: Family Philanthropy Advisors | F123: fpadvisors.com | N123: Ellen George | O123: Founder/Principal | P123: Foundation Management
B124: Rockefeller Philanthropy Advisors | D124: (212) 812-4330 | F124: rockpa.org | N124: Walter Sweet | O124: Interim Co-CEO and Co-President | P124: Foundation Management
B125: The Philanthropic Initiative | F125: tpi.org | N125: Leslie Pine | O125: Managing Partner | P125: Foundation Management
B126: Third Plateau | F126: thirdplateau.com | N126: Susan Hirsch | O126: Co-founder | P126: Foundation Management
B127: Armanino | F127: armanino.com | N127: Brenda Kahler | O127: Director Nonprofit Industry Leader | P127: Foundation Management
B128: GHJ Advisors | F128: ghjadvisors.com | N128: Donella Wilson CPA | O128: Nonprofit Practice Leader | P128: Foundation Management
B129: Plante Moran | F129: plantemoran.com | N129: Sara Montgomery | O129: Leader Family Education and Philanthropic Advisory | P129: Foundation Management
B130: Fidelity Charitable | D130: (800) 952-4438 | F130: fidelitycharitable.org | N130: Jacob V. Pruitt | O130: President | P130: Foundation Management
B131: Goldman Sachs Ayco | F131: goldmansachs.com/ayco | N131: Esta Stecher | O131: Chair GS Philanthropy Fund and Ayco Charitable Foundation | P131: Foundation Management
B132: JP Morgan Private Bank | F132: privatebank.jpmorgan.com | N132: Casey Castaneda | O132: National Head of Private Foundation Services | P132: Foundation Management
B133: Schwab Charitable | D133: (800) 746-6216 | F133: dafgiving360.org | N133: Sam Kang | O133: President | P133: Foundation Management
B134: Vanguard Charitable | D134: (888) 383-4483 | F134: vanguardcharitable.org | N134: Rebecca Moffett | O134: President | P134: Foundation Management
B135: California Community Foundation | D135: (213) 413-4130 | F135: calfund.org | N135: Miguel A. Santana | O135: President and CEO | P135: Foundation Management
B136: Chicago Community Trust | C136: 46014 | D136: (312) 616-8000 | F136: cct.org | N136: Sheila M. Cawley | O136: Chief Philanthropy Officer | P136: Foundation Management | X136: no answer
B137: Cleveland Foundation | D137: (216) 861-3810 | F137: clevelandfoundation.org | N137: Ginger F. Mlakar | O137: SVP Philanthropic Strategy General Counsel | P137: Foundation Management
B138: Foundation for the Carolinas | D138: (704) 973-4500 | F138: fftc.org | N138: Cathy Bessant | O138: President and CEO | P138: Foundation Management
B139: Marin Community Foundation | D139: (415) 464-2500 | F139: marincf.org | N139: Janelle Cavanagh | O139: Chief Philanthropy Officer | P139: Foundation Management
B140: Silicon Valley Community Foundation | D140: (650) 450-5400 | F140: siliconvalleycf.org | N140: Marie D'Costa | O140: EVP of Philanthropic Partnerships | P140: Foundation Management
B141: Fractured Atlas | D141: (212) 277-8020 | F141: fracturedatlas.org | N141: Theresa Hubbard | O141: Chief Executive Officer | P141: Foundation Management
B142: National Philanthropic Trust | D142: (215) 277-3010 | F142: nptrust.org | N142: Holly Welch Stubbing | O142: President and CEO | P142: Foundation Management
B143: New Venture Fund | D143: (202) 595-1061 | F143: newventurefund.org | N143: Lee Bodner | O143: President | P143: Foundation Management
B144: Tides Foundation | D144: (415) 561-6400 | F144: tides.org | N144: Janiece Evans-Page | O144: Chief Executive Officer | P144: Foundation Management
B145: Arden Trust Company | N145: Theresa de Leon | O145: National Director of Sales | P145: Foundation Management
B146: Fiduciary Trust Company | D146: (617) 574-3460 | N146: Aimee Fukuchi Bryant JD | O146: Vice President and Trust Counsel | P146: Foundation Management
B147: Foundation Source | D147: 800-839-0054 | N147: Joseph Mrak | O147: Chief Executive Officer | P147: Foundation Management
B148: Glenmede Trust | N148: Kenneth E. Spruill | O148: Managing Director Center for Family Philanthropy and Wealth Education | P148: Foundation Management

Sheet Sheet2
B2: ein | C2: business name | D2: state | E2: total assets | F2: grantee count | G2: cb grant count | H2: intermediary grant count | I2: paid officer count | J2: phone | K2: website | L2: top officer name | M2: top officer title | N2: segment | O2: segment priority
B3: 453611066 | C3: AARON'S FOUNDATION INC | D3: GA | E3: 201086 | F3: 128 | G3: 1 | H3: 10 | I3: 0 | J3: 6784023332 | K3: https://www.mlb.com/braves/community/atlanta-braves-foundation/henry-louis-aaron-fund | L3: DOUGLAS A LINDSAY | M3: DIRECTOR | N3: Intermediary Funders | O3: 1
B4: 920166198 | C4: Alaska Airlines Foundation | D4: AK | E4: 10478825 | F4: 80 | G4: 1 | H4: 31 | I4: 0 | J4: 2063925719 | K4: N/A | L4: Diana Birkett Rakow | M4: Chairman and President | N4: Intermediary Funders | O4: 1
B5: 953294377 | C5: ALBERT AND ELAINE BORCHARD | D5: CA | E5: 18275989 | F5: 38 | G5: 36 | H5: 0 | I5: 2 | J5: 8185651020 | K5: WWW.BORCHARDFOUNDATION.ORG | L5: EDWARD D SPURGEON | M5: DIRECTOR/PRESIDENT | N5: California CB | O5: 4
B6: 131623877 | C6: ALFRED P SLOAN FOUNDATION | D6: NY | E6: 2116962267 | F6: 182 | G6: 0 | H6: 20 | I6: 2 | J6: 2126491649 | K6: WWW.SLOAN.ORG | L6: Adam Falk | M6: Trustee/President | N6: Intermediary Funders | O6: 1
B7: 943019660 | C7: ALLETTA MORRIS MCBEAN CHARITABLE TRUST | D7: CA | E7: 20496407 | F7: 39 | G7: 4 | H7: 1 | I7: 0 | J7: 7605643000 | K7: WWW.ALLETTAMCBEANCHARITABLETRUST.ORG | L7: DONALD CHRIST | M7: TRUSTEE/PRES. | N7: California CB | O7: 4
B8: 330340635 | C8: ALLIANCE HEALTHCARE FOUNDATION | D8: CA | E8: 85505150 | F8: 68 | G8: 8 | H8: 0 | I8: 2 | J8: 8586780974 | K8: WWW.ALLIANCEHF.ORG | L8: Nancy Sasaki Thru Mar 2018 | M8: Executive Director | N8: California CB | O8: 4
B9: 844571035 | C9: ALLY CHARITABLE FOUNDATION | D9: NC | E9: 81746335 | F9: 156 | G9: 6 | H9: 14 | I9: 0 | J9: 9803128320 | K9: WWW.ALLY.COM/ABOUT/SOCIAL-IMPACT/GRANTS/ | L9: MICHAEL RIZER | M9: PRESIDENT | N9: Intermediary Funders | O9: 1
B10: 131623879 | C10: ALTMAN FOUNDATION | D10: NY | E10: 283326707 | F10: 150 | G10: 57 | H10: 22 | I10: 0 | J10: 2126820970 | K10: WWW.ALTMANFOUNDATION.ORG | L10: JANE B O'CONNELL | M10: CHAIR, TRUSTEE | N10: Intermediary Funders | O10: 1
B11: 541759773 | C11: AMERICAN WOODMARK FOUNDATION INC | D11: VA | E11: 1278837 | F11: 260 | G11: 7 | H11: 20 | I11: 0 | J11: 5406659100 | K11: AMERICANWOODMARK.COM | L11: RICHARD HARTMAN | M11: SECRETARY | N11: Intermediary Funders | O11: 1
B12: 953367511 | C12: ANN JACKSON FAMILY FOUNDATION | D12: CA | E12: 88737372 | F12: 98 | G12: 372 | H12: 0 | I12: 0 | J12: 8059692258 | K12: WWW.ANNJACKSONFAMILYFOUNDATION.ORG | L12: PALMER G JACKSON | M12: PRESIDENT | N12: California CB | O12: 4
B13: 952114455 | C13: ANN PEPPERS FOUNDATION | D13: CA | E13: 42771908 | F13: 30 | G13: 44 | H13: 0 | I13: 1 | J13: 6264415188 | K13: N/A | L13: PHILIP A SWAN | M13: PRESIDENT/DIRECTOR | N13: California CB | O13: 4
B14: 742132676 | C14: Anschutz Family Foundation | D14: CO | E14: 45765575 | F14: 160 | G14: 236 | H14: 13 | I14: 0 | J14: 3032932338 | K14: www.anschutzfamilyfoundation.org | L14: Sue Anschutz-Rodgers | M14: Chair, President | N14: Intermediary Funders | O14: 1
... B24: 330046140 | C24: BESS J HODGES FOUNDATION | D24: CA | E24: 6370611 | F24: 35 | G24: 215 | H24: 0 | I24: 2 | J24: 5629614115 | K24: https://et.cybo.com/US-biz/bess-j-hodges-foundation | L24: JOYCE MURCHISON | M24: TRUSTEE | N24: California CB | O24: 4
B25: 383853264 | C25: BISSELL Pet Foundation | D25: MI | E25: 4578467 | F25: 229 | G25: 0 | H25: 12 | I25: 0 | K25: http://www.bissellpetfoundation.org | L25: Mark J Bissell | M25: Director/President | N25: Intermediary Funders | O25: 1
B26: 941196182 | C26: BOTHIN FOUNDATION | D26: CA | E26: 42569751 | F26: 93 | G26: 20 | H26: 0 | I26: 0 | J26: 4155616540 | K26: WWW.BOTHINFOUNDATION.ORG | L26: DEVON LAYCOX | M26: PRESIDENT | N26: California CB | O26: 4
B27: 262992045 | C27: BRITTINGHAM FAMILY FOUNDATION | D27: CA | E27: 49647859 | F27: 43 | G27: 55 | H27: 0 | I27: 1 | J27: 8054511200 | K27: WWW.BRITTINGHAMFAMILYFOUNDATION.ORG | L27: SCOTT BRITTINGHAM | M27: PRESIDENT | N27: California CB | O27: 4
B28: 821511283 | C28: CARESTAR FOUNDATION | D28: CA | E28: 62671015 | F28: 29 | G28: 15 | H28: 0 | I28: 4 | J28: 5107106799 | K28: WWW.CARESTARFOUNDATION.ORG | L28: TANIR AMI | M28: CEO | N28: California CB | O28: 4
B29: 746078530 | C29: Carl C Anderson Sr and Marie Jo Anderson | D29: TX | E29: 64104719 | F29: 217 | G29: 14 | H29: 11 | I29: 2 | J29: 8888663275 | K29: www.theandersonfoundation.org | L29: Carl Anderson III | M29: Chairman | N29: Intermediary Funders | O29: 1
B30: 131628151 | C30: CARNEGIE CORPORATION OF NEW YORK | D30: NY | E30: 4536407530 | F30: 315 | G30: 8 | H30: 29 | I30: 5 | J30: 2123713200 | K30: https://www.carnegie.org | L30: VARTAN GREGORIAN SEE STMT 18 | M30: PRESIDENT | N30: Intermediary Funders | O30: 1
B31: 381211227 | C31: CHARLES STEWART MOTT FOUNDATION | D31: MI | E31: 3710874863 | F31: 676 | G31: 41 | H31: 49 | I31: 0 | J31: 8102385651 | K31: WWW.MOTT.ORG | L31: KAREN ALDRIDGE-EASON | M31: TRUSTEE | N31: Intermediary Funders | O31: 1
B32: 562582815 | C32: CITIZENS PHILANTHROPIC FOUNDATION INC | D32: NJ | E32: 16928371 | F32: 322 | G32: 28 | H32: 17 | I32: 0 | J32: 4012823638 | K32: HTTPS://WWW.CITIZENSBANK.COM/ABOUT-US/COMMUNITY.A | L32: BARBARA COTTAM END 1022 | M32: PRESIDENT | N32: Intermediary Funders | O32: 1
B33: 251086799 | C33: CLAUDE WORTHINGTON BENEDUM FOUNDATION | D33: PA | E33: 433734264 | F33: 130 | G33: 32 | H33: 17 | I33: 1 | J33: 4122880360 | K33: WWW.BENEDUM.ORG | L33: GREGORY S BABE | M33: TRUSTEE (1)(2) | N33: Intermediary Funders | O33: 1
B34: 61057387 | C34: CONNECTICUT HEALTH FOUNDATION INC | D34: CT | E34: 122596033 | F34: 87 | G34: 9 | H34: 30 | I34: 2 | J34: 8607241580 | K34: WWW.CTHEALTH.ORG | L34: TIFFANY DONELSON | M34: PRESIDENT & CEO | N34: Intermediary Funders | O34: 1
B35: 943100217 | C35: CONRAD N HILTON FOUNDATION | D35: CA | E35: 7099706570 | F35: 976 | G35: 1057 | H35: 148 | I35: 1 | J35: 8188513724 | K35: WWW.HILTONFOUNDATION.ORG | L35: PETER A LAUGHARN | M35: PRESIDENT AND CEO | N35: Intermediary Funders | O35: 1
B36: 680208980 | C36: Dean and Margaret Lesher Foundation | D36: CA | E36: 72758653 | F36: 79 | G36: 16 | H36: 4 | I36: 1 | J36: 9259359988 | K36: N/A | L36: Jill O'Brien | M36: Director | N36: California CB | O36: 4
B37: 416034786 | C37: DELUXE CORPORATION FOUNDATION | D37: CA | E37: 20794039 | F37: 56 | G37: 85 | H37: 0 | I37: 0 | J37: 6514837111 | K37: https://locators.bankofamerica.com/ca/ranchocordova/financial-centers-rancho-cordova-11167.html | L37: BARRY C MCCARTHY | M37: PRESIDENT | N37: California CB | O37: 4
... B64: 237093598 | C64: John D and Catherine T MacArthur Foundation (Consolidated) | D64: IL | E64: 8672283398 | F64: 1132 | G64: 38 | H64: 60 | I64: 3 | J64: 3127268000 | K64: www.macfound.org | L64: BUCK BETTEN | M64: DIRECTOR | N64: Intermediary Funders | O64: 1
B65: 866052431 | C65: JOHN F LONG FOUNDATION INC | D65: AZ | E65: 7835571 | F65: 87 | G65: 0 | H65: 13 | I65: 1 | K65: www.jflongproperties.com foundation | L65: Jacob F Long | M65: President Treasurer | N65: Intermediary Funders | O65: 1
B66: 953759369 | C66: JOHN GOGIAN FAMILY FOUNDATION | D66: CA | E66: 4888501 | F66: 50 | G66: 186 | H66: 1 | I66: 2 | J66: 3103250954 | K66: WWW.GOGIANFOUNDATION.ORG | L66: Kate Crane | M66: Chair | N66: California CB | O66: 4
B67: 650464177 | C67: JOHN S AND JAMES L KNIGHT FOUNDATION | D67: FL | E67: 2533365916 | F67: 314 | G67: 40 | H67: 59 | I67: 1 | J67: 3059082600 | K67: WWW.KF.ORG | L67: FRANK BORGES | M67: CHAIRMAN AND TRUSTEE | N67: Intermediary Funders | O67: 1
B68: 621322826 | C68: JOHN TEMPLETON FOUNDATION | D68: PA | E68: 3398215797 | F68: 215 | G68: 1 | H68: 18 | I68: 4 | J68: 6109412828 | K68: WWW.TEMPLETON.ORG | L68: Jinde Guo | M68: Vice President, INVESTMENTS | N68: Intermediary Funders | O68: 1
B69: 776154307 | C69: June G Outhwaite Charitable Trust | D69: CA | E69: 14924634 | F69: 53 | G69: 15 | H69: 1 | I69: 1 | J69: 8055600841 | K69: www.outhwaitefoundation.org | L69: Kent L Englert | M69: Trustee | N69: California CB | O69: 4
B70: 770559337 | C70: JW & HM GOODMAN FAMILY CHARITABLE | D70: CA | E70: 8187448 | F70: 33 | G70: 28 | H70: 1 | I70: 0 | J70: 5037501814 | K70: www.goodmanfamilyfoundation.org | L70: JOSEPH W GOODMAN | M70: PRESIDENT, BOARD CHAIR | N70: California CB | O70: 4
B71: 591885997 | C71: KOCH FOUNDATION | D71: FL | E71: 71661279 | F71: 111 | G71: 1 | H71: 61 | I71: 0 | J71: 3523737491 | K71: WWW.THEKOCHFOUNDATION.ORG | L71: CAROLYN L BOMBERGER | M71: ASST. TREASURER | N71: Intermediary Funders | O71: 1
B72: 941624987 | C72: KORET FOUNDATION | D72: CA | E72: 315527122 | F72: 245 | G72: 319 | H72: 13 | I72: 2 | J72: 4158827740 | K72: WWW.KORET.ORG | L72: MICHAEL J BOSKIN | M72: DIRECTOR | N72: Intermediary Funders | O72: 1
B73: 680237238 | C73: LEO M SHORTINO FAMILY FOUNDATION | D73: CA | E73: 62845642 | F73: 40 | G73: 20 | H73: 0 | I73: 2 | J73: 4082756306 | K73: WWW.SHORTINO.ORG | L73: DAVID HEIMAN | M73: CHAIRMAN | N73: California CB | O73: 4
B74: 61479957 | C74: LIBERTY BANK FOUNDATION INC | D74: CT | E74: 29902734 | F74: 136 | G74: 5 | H74: 12 | I74: 1 | J74: 8602758239 | K74: https://libertybank.ge/en | L74: DAVID GLIDDEN | M74: PRESIDENT AND CEO | N74: Intermediary Funders | O74: 1
B75: 141893520 | C75: LIBERTY MUTUAL FOUNDATION INC | D75: MA | E75: 46556209 | F75: 500 | G75: 334 | H75: 24 | I75: 0 | J75: 6173579500 | K75: WWW.LIBERTYMUTUALFOUNDATION.ORG | L75: DAVID H LONG | M75: CHAIRMAN/DIRECTOR | N75: Intermediary Funders | O75: 1
B76: 350868122 | C76: LILLY ENDOWMENT INC | D76: IN | E76: 62180012552 | F76: 947 | G76: 154 | H76: 10 | I76: 1 | J76: 3179245471 | K76: WWW.LILLYENDOWMENT.ORG | L76: N CLAY ROBBINS | M76: CHAIRCEO DIR | N76: Intermediary Funders | O76: 1
B77: 366108775 | C77: LLOYD A FRY FOUNDATION | D77: IL | E77: 198005600 | F77: 222 | G77: 88 | H77: 15 | I77: 2 | J77: 3125800310 | K77: FRYFOUNDATION.ORG | L77: Sydney Sidwell | M77: President and Secretary | N77: Intermediary Funders | O77: 1
... B102: 540597601 | C102: Public Welfare Foundation Inc | D102: DC | E102: 601086862 | F102: 166 | G102: 11 | H102: 11 | I102: 5 | J102: 2029651800 | K102: WWW.PUBLICWELFARE.ORG | L102: FREIBERG JINA | M102: DIRECTOR | N102: Intermediary Funders | O102: 1

Sheet Sheet4
B2: tier | C2: company name | D2: company type | E2: company website | F2: contact name | G2: contact title | H2: contact type | I2: linkedin url | J2: email | K2: email source | L2: phone | M2: phone from 990 | N2: office location | O2: ein 990 | P2: assets from 990 | Q2: grants received 2022plus | R2: unique funders | S2: capacity grants received | T2: notes | U2: source file
B3: 1 | C3: BlueStone Services | D3: Outsourced Foundation Services | E3: bluestonesvc.com | F3: Trey Gailey CPA | G3: Managing Director | H3: primary | J3: tgailey@bluestonesvc.com | K3: inferred | L3: 888-797-2583 | N3: Timonium MD | T3: Director of Accounting Solutions | U3: batch2_2025-12-18
B4: 1 | C4: BlueStone Services | D4: Outsourced Foundation Services | E4: bluestonesvc.com | F4: Karl Wappaus | G4: Director of Business Development | H4: secondary | J4: kwappaus@bluestonesvc.com | K4: inferred | N4: Timonium MD | T4: Client Relations | U4: batch2_2025-12-18
B5: 1 | C5: BlueStone Services | D5: Outsourced Foundation Services | E5: bluestonesvc.com | F5: Deborah Nealon | G5: Leadership | H5: secondary | J5: dnealon@bluestonesvc.com | K5: inferred | N5: Timonium MD | T5: 2024 TEDCO Woman of Influence | U5: batch2_2025-12-18
B6: 1 | C6: Crewe Foundation Services | D6: Dedicated Foundation Manager | E6: crewefoundationservices.com | F6: Don Evans | G6: President and CEO | H6: primary | I6: https://www.linkedin.com/in/donevansprofile/ | J6: don.evans@crewefoundationservices.com | K6: inferred | L6: (385) 322-3400 | N6: Salt Lake City UT | T6: 25+ years gift planning; fluent Spanish | U6: batch2_2025-12-18
B7: 1 | C7: Foundation Group | D7: Nonprofit Formation/Compliance | E7: 501c3.org | F7: Greg McRay EA | G7: President and CEO | H7: primary | I7: https://www.linkedin.com/in/gregmcray | J7: gmcray@501c3.org | K7: inferred | N7: Nashville TN | T7: Founder; IRS Enrolled Agent | U7: batch2_2025-12-18
B8: 1 | C8: Foundation Group | D8: Nonprofit Formation/Compliance | E8: 501c3.org | F8: Shannon Evans EA MBA | G8: Director of Compliance Services | H8: secondary | J8: sevans@501c3.org | K8: inferred | N8: Nashville TN | T8: IRS Enrolled Agent | U8: batch2_2025-12-18
B9: 1 | C9: Foundation Source | D9: Dedicated Foundation Manager | E9: foundationsource.com | F9: Elizabeth Wong | G9: Head of Philanthropic Advisory Services | H9: primary | I9: https://www.linkedin.com/in/elizabeth-wong-1aa0691a/ | J9: elizabeth.wong@foundationsource.com | K9: inferred | N9: Fairfield CT | T9: 30+ years experience; former Gates Foundation | U9: batch2_2025-12-18
B10: 1 | C10: Foundation Source | D10: Dedicated Foundation Manager | E10: foundationsource.com | F10: Gillian Howell | G10: Head of Client Advisory Solutions | H10: secondary | I10: https://www.linkedin.com/in/gillian-howell-24b43017/ | J10: gillian.howell@foundationsource.com | K10: inferred | N10: Fairfield CT | T10: 35+ years experience; former Bank of America Managing Director | U10: batch2_2025-12-18
B11: 1 | C11: Foundation Source | D11: Dedicated Foundation Manager | E11: foundationsource.com | F11: Charles R. Casey | G11: President Premier Foundation Services | H11: secondary | I11: https://www.linkedin.com/in/charles-casey-bb7893/ | J11: charles.casey@foundationsource.com | K11: inferred | N11: San Francisco CA | T11: Former Pacific Foundation Services CEO | U11: batch2_2025-12-18
B12: 1 | C12: Foundation Source | D12: Dedicated Foundation Manager | E12: foundationsource.com | F12: Joseph Mrak III | G12: Chief Executive Officer | H12: secondary | J12: joseph.mrak@foundationsource.com | K12: inferred | N12: Fairfield CT | T12: CEO | U12: batch2_2025-12-18
B13: 1 | C13: Pacific Foundation Services | D13: Dedicated Foundation Manager | E13: pfs-llc.net | F13: Juliana Grenzeback | G13: President | H13: primary | I13: https://www.linkedin.com/in/jgrenzeback/ | J13: juliana.grenzeback@pfs-llc.net | K13: inferred | N13: San Francisco CA | T13: With PFS since 2015; acquired by Foundation Source June 2025 | U13: batch2_2025-12-18
B14: 1 | C14: Sterling Foundation Management | D14: Dedicated Foundation Manager | E14: sterlingfoundations.com | F14: Roger D. Silk PhD | G14: Founder and CEO | H14: primary | I14: https://www.linkedin.com/in/roger-silk/ | J14: rsilk@sterlingfoundations.com | K14: inferred | L14: 703-437-9720 | N14: Reston VA | T14: PhD Stanford; CFA; former World Bank; author | U14: batch2_2025-12-18
B15: 1 | C15: Sterling Foundation Management | D15: Dedicated Foundation Manager | E15: sterlingfoundations.com | F15: James W. Lintott Esq | G15: Founder and Chairman | H15: secondary | J15: jlintott@sterlingfoundations.com | K15: inferred | N15: Reston VA | T15: Co-author with Silk | U15: batch2_2025-12-18
B16: 1 | C16: Sterling Foundation Management | D16: Dedicated Foundation Manager | E16: sterlingfoundations.com | F16: Giovanni Kotoriy | G16: Vice President Foundation Consulting | H16: secondary | J16: gkotoriy@sterlingfoundations.com | K16: inferred | N16: Reston VA | U16: batch2_2025-12-18
B17: 1 | C17: Sterling Foundation Management | D17: Dedicated Foundation Manager | E17: sterlingfoundations.com | F17: JC Chang | G17: Client Services Director | H17: secondary | J17: jcchang@sterlingfoundations.com | K17: inferred | N17: Reston VA | U17: batch2_2025-12-18
B18: 2 | C18: Arden Trust Company | D18: Limited Purpose Trust Company | E18: ardentrust.com | F18: Michael Roberts | G18: President | H18: primary | J18: mroberts@ardentrust.com | K18: inferred | N18: Wilmington DE | T18: Directs personal trust operations | U18: batch2_2025-12-18
B19: 2 | C19: Arden Trust Company | D19: Limited Purpose Trust Company | E19: ardentrust.com | F19: Chris Wooten | G19: SVP Sales Manager | H19: secondary | J19: cwooten@ardentrust.com | K19: inferred | N19: Wilmington DE | T19: 19+ years trust/wealth management | U19: batch2_2025-12-18
B20: 2 | C20: Arden Trust Company | D20: Limited Purpose Trust Company | E20: ardentrust.com | F20: Doug Sherry JD | G20: Philanthropy Spokesperson | H20: secondary | J20: dsherry@ardentrust.com | K20: inferred | N20: Wilmington DE | T20: Conference speaker | U20: batch2_2025-12-18
B21: 2 | C21: Bessemer Trust | D21: Multi-Family Office | E21: bessemertrust.com | F21: Caroline Woodruff Hodkinson | G21: Managing Director Head of Philanthropy | H21: primary | I21: https://www.linkedin.com/in/caroline-woodruff-hodkinson-a973b224/ | J21: chodkinson@bessemertrust.com | K21: inferred | N21: New York NY | T21: With Bessemer since 2011; MS Philanthropy NYU | U21: batch2_2025-12-18
B22: 2 | C22: Bessemer Trust | D22: Multi-Family Office | E22: bessemertrust.com | F22: Christopher A. Pastor | G22: SVP Philanthropy and Family Governance Advisor | H22: secondary | J22: cpastor@bessemertrust.com | K22: inferred | N22: New York NY | U22: batch2_2025-12-18
B23: 2 | C23: Fiduciary Trust Company | D23: Trust Company | E23: fiduciary-trust.com | F23: Suma V. Nair JD | G23: Chief Fiduciary Officer | H23: primary | J23: suma.nair@fiduciary-trust.com | K23: inferred | N23: Boston MA | T23: Incoming BBA President 2025-26 | U23: batch2_2025-12-18
B24: 2 | C24: Fiduciary Trust Company | D24: Trust Company | E24: fiduciary-trust.com | F24: Austin V. Shapard | G24: President and CEO | H24: secondary | J24: austin.shapard@fiduciary-trust.com | K24: inferred | N24: Boston MA | T24: Former Rockefeller & Co President | U24: batch2_2025-12-18
B25: 2 | C25: Glenmede Trust | D25: Trust Company | E25: glenmede.com | F25: Nina L. Cohen JD CAP | G25: Director Endowment & Foundation Advisory | H25: primary | J25: nina.cohen@glenmede.com | K25: inferred | N25: Philadelphia PA | T25: 10+ years leading philanthropic advisory | U25: batch2_2025-12-18
B26: 2 | C26: Glenmede Trust | D26: Trust Company | E26: glenmede.com | F26: Kenneth E. Spruill Jr | G26: Managing Director Center for Family Philanthropy | H26: secondary | I26: https://www.linkedin.com/in/ken-spruill/ | J26: kenneth.spruill@glenmede.com | K26: verified | N26: Pittsburgh PA | T26: Former PNC Private Bank Hawthorn | U26: batch2_2025-12-18
B27: 3 | C27: Aly Sterling Philanthropy | D27: Philanthropy Consulting | E27: alysterling.com | F27: Aly Sterling | G27: Founder and President | H27: primary | I27: https://www.linkedin.com/in/aly-sterling-9b942029/ | J27: aly@alysterling.com | K27: inferred | N27: Toledo OH | U27: batch2_2025-12-18
B28: 3 | C28: Aly Sterling Philanthropy | D28: Philanthropy Consulting | E28: alysterling.com | F28: Jenny Goldberg | G28: Vice President | H28: secondary | J28: jenny@alysterling.com | K28: website | N28: Toledo OH | T28: Handles executive search applications | U28: batch2_2025-12-18
B29: 3 | C29: Bridgespan Group | D29: Philanthropy Advisor | E29: bridgespan.org | F29: William Foster | G29: Managing Partner | H29: primary | J29: wfoster@bridgespan.org | K29: inferred | L29: (617) 572-2833 | M29: (617) 572-2833 | N29: Boston MA | O29: 311625487 | P29: $204M | Q29: 32 | R29: 20 | S29: 2 | T29: Since 2002; focus on philanthropic big bets | U29: batch2_2025-12-18
B30: 3 | C30: Bridgespan Group | D30: Philanthropy Advisor | E30: bridgespan.org | F30: Chris Addy | G30: Partner Boston Office | H30: secondary | J30: caddy@bridgespan.org | K30: inferred | L30: (617) 572-2833 | M30: (617) 572-2833 | N30: Boston MA | O30: 311625487 | P30: $204M | Q30: 32 | R30: 20 | S30: 2 | T30: 14+ years; climate health equity focus | U30: batch2_2025-12-18
B31: 3 | C31: CCS Fundraising | D31: Fundraising Consulting | E31: ccsfundraising.com | F31: Jon Kane | G31: President and CEO | H31: primary | J31: jkane@ccsfundraising.com | K31: inferred | N31: New York NY | U31: batch2_2025-12-18
B32: 3 | C32: CCS Fundraising | D32: Fundraising Consulting | E32: ccsfundraising.com | F32: Rick Happy | G32: Chairman | H32: secondary | J32: rhappy@ccsfundraising.com | K32: inferred | N32: New York NY | T32: 30+ years with firm | U32: batch2_2025-12-18
B33: 3 | C33: CCS Fundraising | D33: Fundraising Consulting | E33: ccsfundraising.com | F33: Caroline Chick | G33: Partner and Managing Director | H33: secondary | J33: cchick@ccsfundraising.com | K33: inferred | N33: New York NY | T33: Board of Directors; Women in Philanthropy leader | U33: batch2_2025-12-18
B34: 3 | C34: Cascade Philanthropy Advisors | D34: Philanthropy Advisor | E34: cascadephilanthropy.org | F34: Lowell Weiss | G34: President/Founder | H34: primary | I34: https://www.linkedin.com/in/lowell-weiss-2a860ba/ | J34: lowell@cascadephilanthropy.org | K34: inferred | N34: Seattle WA | T34: Former Gates Foundation; Clinton White House | U34: batch2_2025-12-18
B35: 3 | C35: Convergent Nonprofit Solutions | D35: Fundraising Consulting | E35: convergentnonprofit.com | F35: Tom Ralser | G35: Principal | H35: primary | J35: tralser@convergentnonprofit.com | K35: inferred | N35: Atlanta GA | T35: Investment-Driven Model creator | U35: batch2_2025-12-18
B36: 3 | C36: Convergent Nonprofit Solutions | D36: Fundraising Consulting | E36: convergentnonprofit.com | F36: Brian H. Abernathy | G36: General Manager | H36: secondary | J36: babernathy@convergentnonprofit.com | K36: inferred | N36: Atlanta GA | T36: Leadership Georgia 2019 | U36: batch2_2025-12-18
B37: 3 | C37: Daylight Advisors | D37: Advisor Training | E37: daylightadvisors.com | F37: Dien Yuen | G37: Founder and CEO | H37: primary | J37: dyuen@daylightadvisors.com | K37: inferred | N37: Remote | T37: 25 years philanthropy; IPA program creator | U37: batch2_2025-12-18
B38: 3 | C38: Family Philanthropy Advisors | D38: Foundation Management | E38: fpadvisors.com | F38: Ellen George | G38: Founder/Principal | H38: primary | J38: egeorge@fpadvisors.com | K38: inferred | N38: Minneapolis MN | T38: 20+ years; with FPA since launch 1999 | U38: batch2_2025-12-18
B39: 3 | C39: Family Philanthropy Advisors | D39: Foundation Management | E39: fpadvisors.com | F39: Suzanne Paki | G39: Team Member | H39: secondary | J39: spaki@fpadvisors.com | K39: inferred | N39: Minneapolis MN | T39: Since 2003; former NZ Embassy | U39: batch2_2025-12-18
B40: 3 | C40: Rockefeller Philanthropy Advisors | D40: Philanthropy Advisor | E40: rockpa.org | F40: Walter Sweet | G40: Interim Co-CEO and Co-President | H40: primary | J40: wsweet@rockpa.org | K40: inferred | L40: (212) 812-4330 | M40: (212) 812-4330 | N40: New York NY | O40: 133615533 | P40: $912M | Q40: 614 | R40: 186 | S40: 42 | T40: Former exec in charge of advisory practice | U40: batch2_2025-12-18
B41: 3 | C41: Rockefeller Philanthropy Advisors | D41: Philanthropy Advisor | E41: rockpa.org | F41: A. Nicole Campbell | G41: Interim Co-CEO and Co-President | H41: secondary | J41: ncampbell@rockpa.org | K41: inferred | L41: (212) 812-4330 | M41: (212) 812-4330 | N41: New York NY | O41: 133615533 | P41: $912M | Q41: 614 | R41: 186 | S41: 42 | U41: batch2_2025-12-18
B42: 3 | C42: Rockefeller Philanthropy Advisors | D42: Philanthropy Advisor | E42: rockpa.org | F42: Olga Tarasov | G42: VP of Inquiry & Insights | H42: secondary | J42: otarasov@rockpa.org | K42: inferred | L42: (212) 812-4330 | M42: (212) 812-4330 | N42: New York NY | O42: 133615533 | P42: $912M | Q42: 614 | R42: 186 | S42: 42 | T42: Leads research and publications | U42: batch2_2025-12-18
B43: 3 | C43: The Philanthropic Initiative | D43: Philanthropy Advisor | E43: tpi.org | F43: Leslie Pine | G43: Managing Partner | H43: primary | J43: lpine@tpi.org | K43: inferred | N43: Boston MA | T43: Principal architect of TPI approach | U43: batch2_2025-12-18
B44: 3 | C44: The Philanthropic Initiative | D44: Philanthropy Advisor | E44: tpi.org | F44: Maggi Alexander | G44: Senior Partner Director Global Philanthropy | H44: secondary | J44: malexander@tpi.org | K44: inferred | N44: Boston MA | U44: batch2_2025-12-18
B45: 3 | C45: The Philanthropic Initiative | D45: Philanthropy Advisor | E45: tpi.org | F45: Ellen Remmer | G45: Senior Partner | H45: secondary | J45: eremmer@tpi.org | K45: inferred | N45: Boston MA | T45: Recognized leader in strategic philanthropy | U45: batch2_2025-12-18
B46: 3 | C46: Third Plateau | D46: Philanthropy Advisor | E46: thirdplateau.com | F46: Susan Hirsch | G46: Co-founder | H46: primary | J46: shirsch@thirdplateau.com | K46: inferred | N46: San Francisco CA | T46: Founded Hirsch 1999; SF Biz Times Power 100 | U46: batch2_2025-12-18
B47: 3 | C47: Third Plateau | D47: Philanthropy Advisor | E47: thirdplateau.com | F47: Mike Berkowitz | G47: Co-founder | H47: secondary | J47: mberkowitz@thirdplateau.com | K47: inferred | N47: San Francisco CA | U47: batch2_2025-12-18
B48: 3 | C48: Third Plateau | D48: Philanthropy Advisor | E48: thirdplateau.com | F48: Erica Kashiri | G48: Chief Operating Officer | H48: secondary | J48: ekashiri@thirdplateau.com | K48: inferred | N48: San Francisco CA | T48: Former Sacramento workforce director | U48: batch2_2025-12-18
B49: 4 | C49: Armanino | D49: CPA/Consulting | E49: armanino.com | F49: Brenda Kahler | G49: Director Nonprofit Industry Leader | H49: primary | J49: brenda.kahler@armanino.com | K49: inferred | N49: San Ramon CA | T49: Leads nonprofit client engagement | U49: batch2_2025-12-18
B50: 4 | C50: Armanino | D50: CPA/Consulting | E50: armanino.com | F50: Matt Armanino | G50: CEO | H50: secondary | J50: matt.armanino@armanino.com | K50: inferred | N50: San Ramon CA | U50: batch2_2025-12-18
B51: 4 | C51: GHJ Advisors | D51: CPA/Consulting | E51: ghjadvisors.com | F51: Donella Wilson CPA | G51: Nonprofit Practice Leader | H51: primary | J51: dwilson@ghjadvisors.com | K51: inferred | N51: Los Angeles CA | T51: GHJ Foundation President; Most Influential Women in Accounting | U51: batch2_2025-12-18
B52: 4 | C52: GHJ Advisors | D52: CPA/Consulting | E52: ghjadvisors.com | F52: Lizbeth Nevarez CPA | G52: Nonprofit Tax Practice Leader | H52: secondary | J52: lnevarez@ghjadvisors.com | K52: inferred | N52: Los Angeles CA | T52: 15+ years public accounting | U52: batch2_2025-12-18
B53: 4 | C53: Plante Moran | D53: CPA/Consulting | E53: plantemoran.com | F53: Sara Montgomery | G53: Leader Family Education and Philanthropic Advisory | H53: primary | J53: sara.montgomery@plantemoran.com | K53: inferred | N53: Southfield MI | T53: 15+ years UHNW families; WSJ NYT Kiplinger | U53: batch2_2025-12-18
B54: 5 | C54: Fidelity Charitable | D54: DAF Sponsor | E54: fidelitycharitable.org | F54: Jacob V. Pruitt | G54: President | H54: primary | I54: https://www.linkedin.com/in/jacobvpruitt/ | J54: jacob.pruitt@fmr.com | K54: inferred | L54: (800) 952-4438 | M54: (800) 952-4438 | N54: Boston MA | O54: 110303001 | P54: $56.7B | Q54: 176 | R54: 102 | S54: 45 | T54: Former T. Rowe Price | U54: batch2_2025-12-18
B55: 5 | C55: Fidelity Charitable | D55: DAF Sponsor | E55: fidelitycharitable.org | F55: Karen Heald | G55: VP of Philanthropic Strategies | H55: secondary | J55: karen.heald@fmr.com | K55: inferred | L55: (800) 952-4438 | M55: (800) 952-4438 | N55: Boston MA | O55: 110303001 | P55: $56.7B | Q55: 176 | R55: 102 | S55: 45 | T55: Long-term charitable planning expert | U55: batch2_2025-12-18
B56: 5 | C56: Goldman Sachs Ayco | D56: Financial Planning | E56: goldmansachs.com/ayco | F56: Esta Stecher | G56: Chair GS Philanthropy Fund and Ayco Charitable Foundation | H56: primary | K56: (contact via Goldman) | T56: Partner 25+ years; former GS Management Committee | U56: batch2_2025-12-18
B57: 5 | C57: JP Morgan Private Bank | D57: Private Bank | E57: privatebank.jpmorgan.com | F57: Casey Castaneda | G57: National Head of Private Foundation Services | H57: primary | J57: casey.castaneda@jpmorgan.com | K57: inferred | N57: New York NY | T57: 15 years family philanthropy; entire career at JPM | U57: batch2_2025-12-18
B58: 5 | C58: Schwab Charitable | D58: DAF Sponsor | E58: dafgiving360.org | F58: Sam Kang | G58: President | H58: primary | J58: sam.kang@schwab.com | K58: inferred | L58: (800) 746-6216 | M58: (800) 746-6216 | N58: San Francisco CA | O58: 311640316 | P58: $41.1B | Q58: 3 | R58: 2 | S58: 0 | T58: Since July 2021; former TD Ameritrade; CAP | U58: batch2_2025-12-18
B59: 5 | C59: Schwab Charitable | D59: DAF Sponsor | E59: dafgiving360.org | F59: Doug Campbell | G59: Managing Director Strategy Product Marketing | H59: secondary | J59: douglas.campbell@schwab.com | K59: verified | L59: (800) 746-6216 | M59: (800) 746-6216 | N59: San Francisco CA | O59: 311640316 | P59: $41.1B | Q59: 3 | R59: 2 | S59: 0 | T59: MBA Colorado State; Lilly School certificate | U59: batch2_2025-12-18
B60: 5 | C60: Vanguard Charitable | D60: DAF Sponsor | E60: vanguardcharitable.org | F60: Rebecca Moffett | G60: President | H60: primary | J60: rmoffett@vanguardcharitable.org | K60: inferred | L60: (888) 383-4483 | M60: (888) 383-4483 | N60: Malvern PA | O60: 232888152 | P60: $17.0B | Q60: 28 | R60: 18 | S60: 7 | U60: batch2_2025-12-18
B61: 5 | C61: Vanguard Charitable | D61: DAF Sponsor | E61: vanguardcharitable.org | F61: Bryan Kelley | G61: Head of Client Services and Operations | H61: secondary | J61: bkelley@vanguardcharitable.org | K61: inferred | L61: (888) 383-4483 | M61: (888) 383-4483 | N61: Malvern PA | O61: 232888152 | P61: $17.0B | Q61: 28 | R61: 18 | S61: 7 | T61: 30 years leadership | U61: batch2_2025-12-18
B62: 6 | C62: California Community Foundation | D62: Community Foundation | E62: calfund.org | F62: Miguel A. Santana | G62: President and CEO | H62: primary | I62: https://www.linkedin.com/in/miguel-a-santana-54860824/ | J62: msantana@calfund.org | K62: inferred | L62: (213) 413-4130 | M62: (213) 413-4130 | N62: Los Angeles CA | O62: 953510055 | P62: $2.1B | Q62: 249 | R62: 136 | S62: 39 | T62: Since Aug 2023; former Weingart CEO | U62: batch2_2025-12-18
B63: 6 | C63: California Community Foundation | D63: Community Foundation | E63: calfund.org | F63: Amani Jadallah | G63: Director Philanthropic Support | H63: secondary | I63: https://www.linkedin.com/in/amani-jadallah-6b304658/ | J63: ajadallah@calfund.org | K63: inferred | L63: (213) 413-4130 | M63: (213) 413-4130 | N63: Los Angeles CA | O63: 953510055 | P63: $2.1B | Q63: 249 | R63: 136 | S63: 39 | U63: batch2_2025-12-18
B64: 6 | C64: Chicago Community Trust | D64: Community Foundation | E64: cct.org | F64: Sheila M. Cawley | G64: Chief Philanthropy Officer | H64: primary | J64: scawley@cct.org | K64: inferred | L64: (312) 616-8000 | M64: (312) 616-8000 | N64: Chicago IL | O64: 362167000 | P64: $6.0B | Q64: 67 | R64: 38 | S64: 24 | T64: Leads philanthropic experts team | U64: batch2_2025-12-18
B65: 6 | C65: Chicago Community Trust | D65: Community Foundation | E65: cct.org | F65: Molly Rand | G65: Senior Director of Philanthropy | H65: secondary | J65: mrand@cct.org | K65: inferred | L65: (312) 616-8000 | M65: (312) 616-8000 | N65: Chicago IL | O65: 362167000 | P65: $6.0B | Q65: 67 | R65: 38 | S65: 24 | U65: batch2_2025-12-18
B66: 6 | C66: Chicago Community Trust | D66: Community Foundation | E66: cct.org | F66: Kristin Carlson Vogen | G66: Associate VP Philanthropic Strategies | H66: secondary | J66: kvogen@cct.org | K66: inferred | L66: (312) 616-8000 | M66: (312) 616-8000 | N66: Chicago IL | O66: 362167000 | P66: $6.0B | Q66: 67 | R66: 38 | S66: 24 | U66: batch2_2025-12-18
B67: 6 | C67: Cleveland Foundation | D67: Community Foundation | E67: clevelandfoundation.org | F67: Ginger F. Mlakar | G67: SVP Philanthropic Strategy General Counsel | H67: primary | J67: gmlakar@clevelandfoundation.org | K67: inferred | L67: (216) 861-3810 | M67: (216) 861-3810 | N67: Cleveland OH | O67: 340714588 | P67: $2.9B | Q67: 61 | R67: 34 | S67: 16 | U67: batch2_2025-12-18
B68: 6 | C68: Cleveland Foundation | D68: Community Foundation | E68: clevelandfoundation.org | F68: Terri Bradford Eason | G68: Senior Director Philanthropy Initiatives | H68: secondary | J68: teason@clevelandfoundation.org | K68: inferred | L68: (216) 861-3810 | M68: (216) 861-3810 | N68: Cleveland OH | O68: 340714588 | P68: $2.9B | Q68: 61 | R68: 34 | S68: 16 | U68: batch2_2025-12-18
B69: 6 | C69: Cleveland Foundation | D69: Community Foundation | E69: clevelandfoundation.org | F69: Lillian Kuri | G69: President and CEO | H69: secondary | I69: https://www.linkedin.com/in/lillian-kuri-a592836/ | J69: lkuri@clevelandfoundation.org | K69: inferred | L69: (216) 861-3810 | M69: (216) 861-3810 | N69: Cleveland OH | O69: 340714588 | P69: $2.9B | Q69: 61 | R69: 34 | S69: 16 | T69: Since 2023 | U69: batch2_2025-12-18
B70: 6 | C70: Foundation for the Carolinas | D70: Community Foundation | E70: fftc.org | F70: Cathy Bessant | G70: President and CEO | H70: primary | J70: cbessant@fftc.org | K70: inferred | L70: (704) 973-4500 | M70: (704) 973-4500 | N70: Charlotte NC | O70: 566047886 | P70: $3.5B | Q70: 192 | R70: 60 | S70: 94 | T70: Started Jan 2024; former BofA 40 years | U70: batch2_2025-12-18
B71: 6 | C71: Marin Community Foundation | D71: Community Foundation | E71: marincf.org | F71: Janelle Cavanagh | G71: Chief Philanthropy Officer | H71: primary | J71: jcavanagh@marincf.org | K71: inferred | L71: (415) 464-2500 | M71: (415) 464-2500 | N71: Novato CA | O71: 943007979 | P71: $1.1B | Q71: 34 | R71: 21 | S71: 5 | T71: Former Global Fund for Women VP | U71: batch2_2025-12-18
B72: 6 | C72: Marin Community Foundation | D72: Community Foundation | E72: marincf.org | F72: Edward Wang | G72: VP The Family Office of Philanthropy | H72: secondary | J72: ewang@marincf.org | K72: inferred | L72: (415) 464-2500 | M72: (415) 464-2500 | N72: Novato CA | O72: 943007979 | P72: $1.1B | Q72: 34 | R72: 21 | S72: 5 | T72: 21/64 Certified; Daylight Advisory Board | U72: batch2_2025-12-18
B73: 6 | C73: Marin Community Foundation | D73: Community Foundation | E73: marincf.org | F73: Odette Nemes | G73: VP Philanthropic Services | H73: secondary | J73: onemes@marincf.org | K73: inferred | L73: (415) 464-2500 | M73: (415) 464-2500 | N73: Novato CA | O73: 943007979 | P73: $1.1B | Q73: 34 | R73: 21 | S73: 5 | U73: batch2_2025-12-18
B74: 6 | C74: Silicon Valley Community Foundation | D74: Community Foundation | E74: siliconvalleycf.org | F74: Marie D'Costa | G74: EVP of Philanthropic Partnerships | H74: primary | J74: mdcosta@siliconvalleycf.org | K74: inferred | L74: (650) 450-5400 | M74: (650) 450-5400 | N74: Mountain View CA | O74: 205205488 | P74: $10.4B | Q74: 139 | R74: 64 | S74: 32 | T74: Hired Aug 2024; former NY Community Trust | U74: batch2_2025-12-18
B75: 6 | C75: Silicon Valley Community Foundation | D75: Community Foundation | E75: siliconvalleycf.org | F75: Ana Akhtar | G75: VP of Philanthropic Services | H75: secondary | J75: aakhtar@siliconvalleycf.org | K75: inferred | L75: (650) 450-5400 | M75: (650) 450-5400 | N75: Mountain View CA | O75: 205205488 | P75: $10.4B | Q75: 139 | R75: 64 | S75: 32 | U75: batch2_2025-12-18
B76: 6 | C76: Silicon Valley Community Foundation | D76: Community Foundation | E76: siliconvalleycf.org | F76: Nicole Taylor | G76: President and CEO | H76: secondary | J76: ntaylor@siliconvalleycf.org | K76: inferred | L76: (650) 450-5400 | M76: (650) 450-5400 | N76: Mountain View CA | O76: 205205488 | P76: $10.4B | Q76: 139 | R76: 64 | S76: 32 | T76: Power 100 2024; Anthem Awards winner | U76: batch2_2025-12-18
B77: 7 | C77: Fractured Atlas | D77: Fiscal Sponsor Arts | E77: fracturedatlas.org | F77: Theresa Hubbard | G77: Chief Executive Officer | H77: primary | I77: https://www.linkedin.com/in/theresa-hubbard-7068447a/ | J77: theresa@fracturedatlas.org | K77: inferred | L77: (212) 277-8020 | M77: (212) 277-8020 | N77: New York NY | O77: 113451703 | P77: $31M | Q77: 453 | R77: 313 | S77: 84 | T77: Since 2011; fiscal sponsorship expert | U77: batch2_2025-12-18
B78: 7 | C78: Fractured Atlas | D78: Fiscal Sponsor Arts | E78: fracturedatlas.org | F78: Sophia Park | G78: Director of External Relations | H78: secondary | J78: sophia@fracturedatlas.org | K78: inferred | L78: (212) 277-8020 | M78: (212) 277-8020 | N78: New York NY | O78: 113451703 | P78: $31M | Q78: 453 | R78: 313 | S78: 84 | T78: NYU instructor | U78: batch2_2025-12-18
B79: 7 | C79: National Philanthropic Trust | D79: DAF/Fiscal Sponsor | E79: nptrust.org | F79: Holly Welch Stubbing | G79: President and CEO | H79: primary | J79: hstubbing@nptrust.org | K79: inferred | L79: (215) 277-3010 | M79: (215) 277-3010 | N79: Jenkintown PA | O79: 237825575 | P79: $28.2B | Q79: 11 | R79: 5 | S79: 2 | T79: Since July 2024; former E4E Relief CEO | U79: batch2_2025-12-18
B80: 7 | C80: National Philanthropic Trust | D80: DAF/Fiscal Sponsor | E80: nptrust.org | F80: Jeff Gerold CFP CEPA | G80: SVP Enterprise Development | H80: secondary | J80: jgerold@nptrust.org | K80: inferred | L80: (215) 277-3010 | M80: (215) 277-3010 | N80: Jenkintown PA | O80: 237825575 | P80: $28.2B | Q80: 11 | R80: 5 | S80: 2 | T80: Leads Regional Directors and Advisor Services | U80: batch2_2025-12-18
B81: 7 | C81: New Venture Fund | D81: Fiscal Sponsor | E81: newventurefund.org | F81: Lee Bodner | G81: President | H81: primary | J81: lbodner@newventurefund.org | K81: inferred | L81: (202) 595-1061 | M81: (202) 595-1061 | N81: Washington DC | O81: 205806345 | P81: $768M | Q81: 1071 | R81: 262 | S81: 111 | T81: 20+ years; former Arabella Managing Director | U81: batch2_2025-12-18
B82: 7 | C82: New Venture Fund | D82: Fiscal Sponsor | E82: newventurefund.org | F82: Lessie Askew | G82: Chief People Officer | H82: secondary | J82: laskew@newventurefund.org | K82: inferred | L82: (202) 595-1061 | M82: (202) 595-1061 | N82: Washington DC | O82: 205806345 | P82: $768M | Q82: 1071 | R82: 262 | S82: 111 | U82: batch2_2025-12-18
B83: 7 | C83: Tides Foundation | D83: Fiscal Sponsor | E83: tides.org | F83: Janiece Evans-Page | G83: Chief Executive Officer | H83: primary | J83: jevanspage@tides.org | K83: inferred | L83: (415) 561-6400 | M83: (415) 561-6400 | N83: San Francisco CA | O83: 510198509 | P83: $646M | Q83: 567 | R83: 242 | S83: 96 | U83: batch2_2025-12-18
B84: 7 | C84: Tides Foundation | D84: Fiscal Sponsor | E84: tides.org | F84: Greg Taylor | G84: Executive Director Tides Foundation | H84: secondary | J84: gtaylor@tides.org | K84: inferred | L84: (415) 561-6400 | M84: (415) 561-6400 | N84: San Francisco CA | O84: 510198509 | P84: $646M | Q84: 567 | R84: 242 | S84: 96 | T84: Leads 30 staff | U84: batch2_2025-12-18
B85: 7 | C85: Tides Foundation | D85: Fiscal Sponsor | E85: tides.org | F85: Dan Shannon | G85: Chief Partnerships Officer | H85: secondary | J85: dshannon@tides.org | K85: inferred | L85: (415) 561-6400 | M85: (415) 561-6400 | N85: San Francisco CA | O85: 510198509 | P85: $646M | Q85: 567 | R85: 242 | S85: 96 | U85: batch2_2025-12-18
C86: Arden Trust Company | D86: Trust Company | F86: Theresa de Leon | G86: National Director of Sales | H86: Primary | K86: Inferred | N86: Wilmington DE | T86: JD, MBA Accounting, BA Yale. 20+ years trust experience. Joined 2022. | U86: batch1_2025-12-17
C87: Arden Trust Company | D87: Trust Company | F87: Adam Davis | G87: Chief Fiduciary Officer | H87: Secondary | N87: JD SMU. Oversees fiduciary, compliance. | U87: batch1_2025-12-17
C88: Arden Trust Company | D88: Trust Company | F88: Maria Sturges | G88: Chief Operating Officer | H88: Secondary | N88: Wilmington DE | T88: 30+ years financial services | U88: batch1_2025-12-17
C89: Bessemer Trust | D89: Multi-Family Office | F89: Jim Kronenberg | G89: Managing Director Chief Fiduciary Counsel | H89: Secondary | I89: linkedin.com/in/jim-kronenberg-b852435/ | T89: Oversees philanthropic advisory. Management Committee member. | U89: batch1_2025-12-17
C90: Bessemer Trust | D90: Multi-Family Office | F90: Alyson Wise | G90: Senior Philanthropy and Family Governance Advisor | H90: Secondary | N90: New York NY | T90: Featured in Crain Currency | U90: batch1_2025-12-17
C91: BlueStone Services | D91: Outsourced Administration | F91: Karen Warthen SPHR SHRM-SCP | G91: HR Leadership | H91: Secondary | N91: Timonium MD | T91: 2024 honoree | U91: batch1_2025-12-17
C92: Crewe Foundation Services | D92: Dedicated Manager | F92: Ryan Halliday | G92: Managing Partner Crewe Advisors | H92: Secondary | N92: Salt Lake City UT | T92: Related company - Crewe Family of Companies | U92: batch1_2025-12-17
C93: Fiduciary Trust Company | D93: Trust Company | F93: Aimee Fukuchi Bryant JD | G93: Vice President and Trust Counsel | H93: Primary | K93: Inferred | L93: (617) 574-3460 | N93: Boston MA | T93: Estate planning, charitable giving. Former Chair Advisors in Philanthropy Boston. | U93: batch1_2025-12-17
C94: Fiduciary Trust Company | D94: Trust Company | F94: Suma V. Nair | G94: Chief Fiduciary Officer | H94: Secondary | N94: Boston MA | T94: Boston Bar Association President 2025-26 | U94: batch1_2025-12-17
C95: Foundation Source | D95: Dedicated Manager | F95: Joseph Mrak | G95: Chief Executive Officer | H95: Primary | J95: firstname.lastname@foundationsource.com | K95: Inferred pattern | L95: 800-839-0054 | N95: Fairfield CT | T95: CEO since Sept 2023. Former CEO of FolioDynamix. | U95: batch1_2025-12-17
C96: Foundation Source | D96: Dedicated Manager | F96: Robyn Hullihan | G96: Senior Philanthropic Director | H96: Secondary | I96: linkedin.com/in/robyn-hullihan-7864b6b/ | N96: New York | T96: Manages foundation relationships | U96: batch1_2025-12-17
C97: Foundation Source | D97: Dedicated Manager | F97: Anne Hennessy CAP | G97: Director Philanthropic Advisor and Relationship Manager | H97: Secondary | I97: linkedin.com/in/anne-hennessy-cap-5a202b59/ | T97: Manages nonprofit client relationships, Philanthropic Solutions division | U97: batch1_2025-12-17
C98: Foundation Source | D98: Dedicated Manager | F98: Jessica Donahue | G98: Senior Managing Director | H98: Secondary | I98: linkedin.com/in/jessica-donahue-06262811b/ | U98: batch1_2025-12-17
C99: Foundation Source | D99: Dedicated Manager | F99: John Johnson CAP | G99: Managing Director | H99: Secondary | I99: linkedin.com/in/john-johnson-cap-6b6ba713/ | T99: Expertise in philanthropy, HNW individuals | U99: batch1_2025-12-17
C100: Glenmede Trust | D100: Trust Company | F100: Kenneth E. Spruill | G100: Managing Director Center for Family Philanthropy and Wealth Education | H100: Primary | J100: k***@glenmede.com | K100: ZoomInfo partial | N100: Pittsburgh PA | T100: Former Grantmakers of Western PA president, former PNC | U100: batch1_2025-12-17
C101: Glenmede Trust | D101: Trust Company | F101: Thom Melcher | G101: Director of Family Wealth and New York Metro Region | H101: Secondary | N101: Leads Private Wealth Group since Jan 2023 | U101: batch1_2025-12-17
...

Sheet Prospects V2
B2: ein | C2: org name | D2: contact name | E2: contact title | F2: phone | G2: website | H2: mission statement | I2: state | J2: city | K2: zip | L2: ntee code | M2: sector | N2: form type | O2: tax year | P2: total revenue | Q2: total expenses | R2: total assets | S2: contributions grants | T2: program service revenue | U2: grant dependency pct | V2: employee count | W2: volunteer count | X2: num foundation grants | Y2: num unique funders | Z2: total foundation grant amount | AA2: most recent grant year | AB2: revenue band | AC2: grant dep band | AD2: yoy revenue growth | AE2: icp score | AF2: priority tier | AG2: reach employees 1 10 | AH2: reach revenue 1m 2m | AI2: reach form 990 | AJ2: reach sector e p | AK2: reach grant dep 75 | AL2: reach more employees than volunteers | AM2: reach all flags | AN2: capacity grant date | AO2: capacity grant amount | AP2: capacity grant funder ein | AQ2: capacity grant funder name | AR2: capacity grant pct of revenue | AS2: received capacity grant | AT2: has concrete mission | AU2: fundraising likelihood score | AV2: likely active fundraiser | AW2: fiscal year end soon | AX2: has biz dev staff | AY2: new to foundations | AZ2: shares funder with beta | BA2: current fundraising
B3: 920000000 | C3: Alaska Family Child Care Association | D3: Raquel Hanni | E3: Executive Director | F3: 9072724432 | H3: ALASKA FAMILY CHILD CARE ASSOCIATION PROMOTES AND DEVELOPS QUALITY PROFESSIONAL HOME BASED CHILD CARE. | I3: AK | J3: Anchorage | K3: 99518 | L3: P20 | M3: P | N3: 990 | O3: 2023 | P3: 1758060 | Q3: 1752986 | R3: 170520 | S3: 1758060 | T3: 0 | U3: 100 | V3: 3 | X3: 0 | Y3: 0 | Z3: 0 | AB3: $1M-$2M | AC3: 90-100% | AD3: -7 | AE3: 10 | AF3: 1 | AG3: 1 | AH3: 1 | AI3: 1 | AJ3: 1 | AK3: 1 | AL3: 1 | AM3: 1 | AS3: 0 | AT3: 0 | AU3: 0 | AV3: 0 | AW3: 0 | AX3: no | AY3: 1 | AZ3: 0
B4: 203000000 | C4: CENTRAL PENINSULA HEALTH FOUNDATION | D4: Sheryl Cook | E4: Vice President | F4: 9077144626 | G4: www.givingheals.org/giving-heals/ | H4: To support Central Peninsula Residents by seeking innovative partnerships, and creating resources for the health and wellness of our communities. | I4: AK | J4: Soldotna | K4: 99669 | L4: E112 | M4: E | N4: 990 | O4: 2022 | P4: 1566489 | Q4: 431820 | R4: 2502596 | S4: 1494987 | T4: 0 | U4: 95.44 | V4: 0 | W4: 0 | X4: 0 | Y4: 0 | Z4: 0 | AB4: $1M-$2M | AC4: 90-100% | AD4: 434.3 | AE4: 10 | AF4: 1 | AG4: 0 | AH4: 1 | AI4: 1 | AJ4: 1 | AK4: 1 | AL4: 0 | AM4: 0 | AS4: 0 | AT4: 0 | AU4: 0 | AV4: 0 | AW4: 0 | AX4: no | AY4: 1 | AZ4: 0
B5: 162000000 | C5: MALAWI CHILDREN'S VILLAGE | D5: JAMES MILLER | E5: PRESIDENT | F5: 9073375036 | G5: MALAWICHILDRENSVILLAGE.ORG | H5: ENHANCING THE LIVES OF ORPHANS BY PROVIDING HEALTH, SOCIAL, AND EDUCATIONAL RESOURCES IN MALAWI. | I5: AK | J5: ANCHORAGE | K5: 99524 | L5: P70 | M5: P | N5: 990 | O5: 2023 | P5: 1316094 | Q5: 430847 | R5: 1196573 | S5: 1316094 | T5: 0 | U5: 100 | V5: 0 | W5: 10 | X5: 0 | Y5: 0 | Z5: 0 | AB5: $1M-$2M | AC5: 90-100% | AD5: 229.4 | AE5: 10 | AF5: 1 | AG5: 0 | AH5: 1 | AI5: 1 | AJ5: 1 | AK5: 1 | AL5: 0 | AM5: 0 | AS5: 0 | AT5: 1 | AU5: 0 | AV5: 0 | AW5: 0 | AX5: no | AY5: 1 | AZ5: 0
B6: 863000000 | C6: BIRMINGHAM HOST COMMITTEE 2025 WORLD POL | D6: DJ MACKOVETS | E6: CEO | F6: 2052972230 | G6: BHM2025.COM | H6: THE BIRMINGHAM HOST COMMITTEE 2025 WORLD POLICE & FIRE GAMES (BHM2025) IS A NONPROFIT 501(C)(3) CORPORATION ESTABLISHED TO ORGANIZE, MANAGE AND OPERATE ALL ACTIVITIES RELATED TO THE 2025 WORLD POLICE & FIRE GAMES. OUR PRIMARY OBJECTIVE IS TO HONOR AND CELEBRATE OUR COMMUNITY HEROES & PUBLIC SAFETY OFFICERS FROM AROUND THE WORLD BY DELIVERING AN AMAZING ATHLETE EXPERIENCE AND FULLY ENGAGING THE COMMUNITY TO PRODUCE THE BEST GAMES POSSIBLE WHILE SHOWCASING BIRMINGHAM, ALABAMA. | I6: AL | J6: BIRMINGHAM | K6: 35203 | L6: P20 | M6: P | N6: 990 | O6: 2024 | P6: 1841832 | Q6: 2290177 | R6: 392691 | S6: 1840500 | T6: 0 | U6: 99.93 | V6: 0 | W6: 13 | X6: 0 | Y6: 0 | Z6: 0 | AB6: $1M-$2M | AC6: 90-100% | AD6: 54.4 | AE6: 10 | AF6: 1 | AG6: 0 | AH6: 1 | AI6: 1 | AJ6: 1 | AK6: 1 | AL6: 0 | AM6: 0 | AS6: 0 | AT6: 0 | AU6: 0 | AV6: 0 | AW6: 1 | AX6: no | AY6: 1 | AZ6: 0
B7: 275000000 | C7: CLERESTORY INC | D7: GREG MIXON | E7: CHAIRMAN/PRESIDENT | F7: 2052596636 | G7: WWW.CLERESTORYINC.ORG | H7: TO PROVIDE A VEHICLE THROUGH WHICH ECONOMIC DEVELOPEMENT AND RELATED INITIATIVES FOR THE BENEFIT OF THE POOR AND AT RISK CAN BE IMPLEMENTED. | I7: AL | J7: BIRMINGHAM | K7: 35242 | L7: P20 | M7: P | N7: 990 | O7: 2023 | P7: 1071834 | Q7: 382353 | R7: 1033320 | S7: 1122853 | T7: 0 | U7: 104.76 | V7: 0 | W7: 4 | X7: 2 | Y7: 2 | Z7: 6000 | AA7: 2024 | AB7: $1M-$2M | AC7: 90-100% | AE7: 10 | AF7: 1 | AG7: 0 | AH7: 1 | AI7: 1 | AJ7: 1 | AK7: 1 | AL7: 0 | AM7: 0 | AS7: 0 | AT7: 0 | AU7: 0 | AV7: 0 | AW7: 1 | AX7: no | AY7: 0 | AZ7: 0
B8: 631000000 | C8: EMPOWERMENT INCORPORATED | D8: CEDRIC ALLEN | E8: PRESIDENT | F8: 2059016263 | H8: To provide additional support services for homeless and low income children and sponsor after school programs and computer workshops. To identify unmet community needs of area youths and to determine if the activity required to meet these needs are within the nonprofit purpose | I8: AL | J8: BIRMINGHAM | K8: 35242 | L8: P30 | M8: P | N8: 990 | O8: 2023 | P8: 1511094 | Q8: 1499725 | R8: 77188 | S8: 1511094 | T8: 0 | U8: 100 | V8: 0 | W8: 170 | X8: 0 | Y8: 0 | Z8: 0 | AB8: $1M-$2M | AC8: 90-100% | AD8: -7.7 | AE8: 10 | AF8: 1 | AG8: 0 | AH8: 1 | AI8: 1 | AJ8: 1 | AK8: 1 | AL8: 0 | AM8: 0 | AS8: 0 | AT8: 0 | AU8: 0 | AV8: 0 | AW8: 1 | AX8: no | AY8: 1 | AZ8: 0
B9: 630000000 | C9: FREE WILL BAPTIST CHILDRENS HO | F9: 2059249751 | H9: MISSION IS TO PROVIDE A LOVING CHRISTIAN HOME TO CHILDREN WHO ARE IN NEED OF CARE AND MAY BE HURTING BECAUSE OF THE CIRCUMSTANCES OF LIFE INSTRUCTION | I9: AL | J9: ELDRIDGE | K9: 35554 | L9: P76 | M9: P | N9: 990 | O9: 2023 | P9: 1501288 | Q9: 1532986 | R9: 3900732 | S9: 1429870 | T9: 0 | U9: 95.24 | V9: 0 | X9: 0 | Y9: 0 | Z9: 0 | AB9: $1M-$2M | AC9: 90-100% | AD9: 3.1 | AE9: 10 | AF9: 1 | AG9: 0 | AH9: 1 | AI9: 1 | AJ9: 1 | AK9: 1 | AL9: 0 | AM9: 0 | AS9: 0 | AT9: 1 | AU9: 0 | AV9: 0 | AW9: 0 | AX9: uncertain | AY9: 1 | AZ9: 0
B10: 631000000 | C10: MOWA BAND OF CHOCTAW INDIAN COMMISSION | D10: LEBARON BYRD | E10: CEO | F10: 2518295500 | G10: N/A | H10: PUBLIC CHARITY | I10: AL | J10: MOUNT VERNON | K10: 36560 | L10: P20 | M10: P | N10: 990 | O10: 2023 | P10: 1146712 | Q10: 1757835 | R10: 2560740 | S10: 1146712 | T10: 0 | U10: 100 | V10: 0 | W10: 12 | X10: 1 | Y10: 1 | Z10: 15000 | AA10: 2022 | AB10: $1M-$2M | AC10: 90-100% | AD10: -44.1 | AE10: 10 | AF10: 1 | AG10: 0 | AH10: 1 | AI10: 1 | AJ10: 1 | AK10: 1 | AL10: 0 | AM10: 0 | AS10: 0 | AT10: 0 | AU10: 0 | AV10: 0 | AW10: 1 | AX10: no | AY10: 0 | AZ10: 0
B11: 209000000 | C11: THE SOUTHEAST ALABAMA MEDICAL | D11: AMY BUNTING | E11: DIRECTOR | F11: 2298837878 | G11: WWW.SEHEALTHFOUNDATION.ORG | H11: OUR MISSION IS TO SUPPORT HEALTHCARE IN SOUTHEAST ALABAMA AND SURROUNDING AREAS. THE FOUNDATION PROVIDES FINANCIAL SUPPORT TO THE HOUSTON COUNTY HEALTH CARE AUTHORITY DBA SOUTHEAST HEALTH MEDICAL CENTER (SOUTHEAST HEALTH) AND ITS AFFILIATES BY ESTABLISHING PARTNERSHIPS IN ORDER TO ENHANCE HEALTH AND WELLNESS IN SOUTHEAST ALABAMA, NORTHWEST FLORIDA AND SOUTHWEST GEORGIA. THE FOUNDATION WORKS TO STRENGTHEN RELATIONSHIPS BETWEEN SOUTHEAST HEALTH, ITS AFFILIATES AND THE COMMUNITY WHILE HELPING FUND BOTH PRESENT AND FUTURE EQUIPMENT, TECHNOLOGY, FACILITY EXPANSION AND CLINICAL PROGRAM NEEDS. THE FOUNDATION SEEKS TO SUPPORT THE FEASIBILITY, DESIGN, AND CONSTRUCTION OF PHYSICAL STRUCTURES OUTLINED IN THE LONG-RANGE FACILITY IMPROVEMENT PLAN FOR SOUTHEAST HEALTH AND ITS AFFILIATES; ASSIST IN UNDERWRITING NEW TECHNOLOGY AND LIFESAVING MEDICAL EQUIPMENT; PREVENT OR LESSEN THE IMPACT DETECTION PROGRAMS AND INTERVENTION; FACILITATE INITIATIVES THAT ENCOURAGE A HEALTHY COMMUNITY; AND IDENTIFY AND C | I11: AL | J11: DOTHAN | K11: 36301 | L11: E11 | M11: E | N11: 990 | O11: 2023 | P11: 1153126 | Q11: 932051 | R11: 4601419 | S11: 901738 | T11: 0 | U11: 78.2 | V11: 0 | X11: 3 | Y11: 2 | Z11: 215100 | AA11: 2023 | AB11: $1M-$2M | AC11: 75-90% | AD11: 15.4 | AE11: 10 | AF11: 1 | AG11: 0 | AH11: 1 | AI11: 1 | AJ11: 1 | AK11: 1 | AL11: 0 | AM11: 0 | AN11: 45291 | AO11: 100 | AP11: 201000000 | AQ11: THE BANK OF AMERICA CHARITABLE | AR11: 0 | AS11: 1 | AT11: 0 | AU11: 0 | AV11: 0 | AW11: 0 | AX11: no | AY11: 0 | AZ11: 0
B12: 631000000 | C12: THOMAS HOSPITAL FOUNDATION INC | D12: DEANNA AUNER | E12: DIRECTOR | F12: 2514353030 | G12: INFIRMARYHEALTH.ORG/THOMASHOSPITAL/FND | H12: THE ORGANIZATION WAS FOUNDED TO FOSTER AND SUPPORT THE ACTIVITIES OF THOMAS HOSPITAL, TO ENCOURAGE PUBLIC SUPPORT OF THE HOSPITAL AND TO ADVANCE ITS CHARITABLE, EDUCATIONAL AND SCIENTIFIC PURPOSES. | I12: AL | J12: FAIRHOPE | K12: 36532 | L12: E11 | M12: E | N12: 990 | O12: 2023 | P12: 1538161 | Q12: 498770 | R12: 14492647 | S12: 1307847 | T12: 0 | U12: 85.03 | V12: 0 | W12: 27 | X12: 3 | Y12: 3 | Z12: 507359 | AA12: 2023 | AB12: $1M-$2M | AC12: 75-90% | AD12: 126.2 | AE12: 10 | AF12: 1 | AG12: 0 | AH12: 1 | AI12: 1 | AJ12: 1 | AK12: 1 | AL12: 0 | AM12: 0 | AN12: 45291 | AO12: 1250 | AP12: 201000000 | AQ12: THE BANK OF AMERICA CHARITABLE | AR12: 0.1 | AS12: 1 | AT12: 0 | AU12: 0 | AV12: 0 | AW12: 0 | AX12: yes | AY12: 0 | AZ12: 1
B13: 631000000 | C13: TUM TUM TREE FOUNDATION | D13: LIBBY SIBLEY | E13: EXECUTIVE DIRECTOR (END. DEC. 2018) | F13: 2054018231 | G13: WWW.TUMTUMTREEFOUNDATION.ORG | H13: TO PROVIDE SUPPORT TO ALABAMA CHILDREN WITH CHRONIC LIFE-THREATENING OR CERTAIN LIFE-ALTERING CONDITIONS BY RAISING AND PROVIDING FUNDS TO OTHER NONPROFIT ORGANIZATIONS. | I13: AL | J13: BIRMINGHAM | K13: 35243 | L13: E118 | M13: E | N13: 990 | O13: 2023 | P13: 1229295 | Q13: 1119045 | R13: 256869 | S13: 1637325 | T13: 0 | U13: 133.19 | V13: 2 | W13: 20 | X13: 3 | Y13: 2 | Z13: 152500 | AA13: 2023 | AB13: $1M-$2M | AC13: 90-100% | AD13: 36 | AE13: 10 | AF13: 1 | AG13: 1 | AH13: 1 | AI13: 1 | AJ13: 1 | AK13: 1 | AL13: 0 | AM13: 0 | AN13: 43465 | AO13: 12400 | AP13: 686000000 | AQ13: MARMONTOR FOUNDATION | AR13: 1 | AS13: 1 | AT13: 0 | AU13: 0 | AV13: 0 | AW13: 1 | AX13: no | AY13: 0 | AZ13: 0
B14: 275000000 | C14: Antioch Consolidated Association for | D14: Heather Sanders | E14: President | F14: 4794590669 | G14: https://antiochyouthfamily.org/ | H14: Food distributions to those in need, adequate food maintenance to those in need, and youth development. | I14: AR | J14: Fort Smith | K14: 72902 | L14: P20 | M14: P | N14: 990 | O14: 2024 | P14: 1098387 | Q14: 1251852 | R14: 1074348 | S14: 1098387 | T14: 0 | U14: 100 | V14: 0 | W14: 265 | X14: 1 | Y14: 1 | Z14: 10000 | AA14: 2024 | AB14: $1M-$2M | AC14: 90-100% | AE14: 10 | AF14: 1 | AG14: 0 | AH14: 1 | AI14: 1 | AJ14: 1 | AK14: 1 | AL14: 0 | AM14: 0 | AS14: 0 | AT14: 0 | AU14: 0 | AV14: 0 | AW14: 1 | AX14: no | AY14: 0 | AZ14: 0
B15: 871000000 | C15: Mision Para Cristo Inc | D15: Donna L Baker | E15: Vice-President | F15: 3185602868 | G15: www.misionparacristo.com | H15: See Schedule O | I15: AR | J15: Judsonia | K15: 72081 | L15: P20 | M15: P | N15: 990 | O15: 2024 | P15: 1282473 | Q15: 1259747 | R15: 215549 | S15: 1282473 | T15: 0 | U15: 100 | V15: 0 | W15: 11 | X15: 2 | Y15: 1 | Z15: 5000 | AA15: 2023 | AB15: $1M-$2M | AC15: 90-100% | AD15: 0.1 | AE15: 10 | AF15: 1 | AG15: 0 | AH15: 1 | AI15: 1 | AJ15: 1 | AK15: 1 | AL15: 0 | AM15: 0 | AS15: 0 | AT15: 0 | AU15: 0 | AV15: 0 | AW15: 1 | AX15: uncertain | AY15: 0 | AZ15: 0
B16: 912000000 | C16: OUTCOMES INC | D16: TONY POSEY | E16: EXECUTIVE DIRECTOR | F16: 4792361254 | H16: PROVIDE COMMUNITY BASED SUPPORT SERVICES FOR CUSTOMERS WITH INTELLECTUAL AND DEVELOPMENTAL DISABILITIES | I16: AR | J16: SPRINGDALE | K16: 72764 | L16: P82 | M16: P | N16: 990 | O16: 2023 | P16: 1946757 | Q16: 1892271 | R16: 957995 | S16: 1946757 | T16: 0 | U16: 100 | V16: 0 | X16: 0 | Y16: 0 | Z16: 0 | AB16: $1M-$2M | AC16: 90-100% | AD16: -7.3 | AE16: 10 | AF16: 1 | AG16: 0 | AH16: 1 | AI16: 1 | AJ16: 1 | AK16: 1 | AL16: 0 | AM16: 0 | AS16: 0 | AT16: 0 | AU16: 0 | AV16: 0 | AW16: 1 | AX16: no | AY16: 1 | AZ16: 0
B17: 273000000 | C17: PROGRESSIVE ELDERCARE SERVICES INC | D17: W JARRED FRANKLIN ESQ | E17: PRESIDENT | F17: 9054275007 | G17: N/A | H17: THE ORGANIZATION PROVIDES AFFORDABLE SKILLED NURSING AND REHABILITATIVE CARE TO ILL, INFIRM, MEDICALLY DISABLED AND ELDERLY INDIVIDUALS IN A NON-TRADITIONAL LONG-TERM CARE ENVIRONMENT UTILIZING THE "CULTURE CHANGE OR "PERSON-CENTERED" CARE MODEL. | I17: AR | J17: MAGNOLIA | K17: 71753 | L17: E12 | M17: E | N17: 990 | O17: 2023 | P17: 1101740 | Q17: 1633003 | R17: -26339 | S17: 1091467 | T17: 0 | U17: 99.07 | V17: 0 | W17: 5 | X17: 0 | Y17: 0 | Z17: 0 | AB17: $1M-$2M | AC17: 90-100% | AE17: 10 | AF17: 1 | AG17: 0 | AH17: 1 | AI17: 1 | AJ17: 1 | AK17: 1 | AL17: 0 | AM17: 0 | AS17: 0 | AT17: 0 | AU17: 0 | AV17: 0 | AW17: 1 | AX17: no | AY17: 1 | AZ17: 0
B18: 711000000 | C18: RIVER CITY MINISTRY OF PULASKI COUNTY | D18: PAUL WILKERSON | E18: EXECUTIVE DIRECTOR | F18: 5013766694 | G18: N/A | H18: SERVING THE UNDER PRIVILEDGED AMD UNDER SERVED OF THE INNER CITY PROVIDING MEALS, MEDICAL AND DENTAL CARE, AND SOCIAL SERVICES. PROVIDING SOCIAL, ECONOMIC, AND EMOTIONAL SUPPORT TO LOW INCOME AND HOMELESS. | I18: AR | J18: NORTH LITTLE ROCK | K18: 721000000 | L18: P60 | M18: P | N18: 990 | O18: 2023 | P18: 1142020 | Q18: 891521 | R18: 1534665 | S18: 923596 | T18: 168554 | U18: 80.87 | V18: 2 | W18: 120 | X18: 2 | Y18: 2 | Z18: 25300 | AA18: 2023 | AB18: $1M-$2M | AC18: 75-90% | AD18: 44.6 | AE18: 10 | AF18: 1 | AG18: 1 | AH18: 1 | AI18: 1 | AJ18: 1 | AK18: 1 | AL18: 0 | AM18: 0 | AN18: 44196 | AO18: 300 | AP18: 201000000 | AQ18: THE BANK OF AMERICA CHARITABLE | AR18: 0 | AS18: 1 | AT18: 0 | AU18: 0 | AV18: 0 | AW18: 1 | AX18: no | AY18: 0 | AZ18: 0
B19: 823000000 | C19: Somerset Senior Living at Harrison | D19: Lillie Dean | E19: Former Director | F19: 8707413438 | G19: N/A | H19: THE ORGANIZATION PROVIDES AFFORDABLE SKILLED NURSING AND REHABILATIVE CARE TO ILL, INFIRM, MEDICALLY DISABLED AND ELDERLY INDIVIDUALS IN A LONG-TERM CARE ENVIRONMENT FOCUSED ON PERSON CENTERED CARE. | I19: AR | J19: Benton | K19: 72018 | L19: E91 | M19: E | N19: 990 | O19: 2023 | P19: 1187982 | Q19: 541834 | R19: 2090675 | S19: 1031359 | T19: 0 | U19: 86.82 | V19: 0 | W19: 2 | X19: 0 | Y19: 0 | Z19: 0 | AB19: $1M-$2M | AC19: 75-90% | AE19: 10 | AF19: 1 | AG19: 0 | AH19: 1 | AI19: 1 | AJ19: 1 | AK19: 1 | AL19: 0 | AM19: 0 | AS19: 0 | AT19: 1 | AU19: 0 | AV19: 0 | AW19: 1 | AX19: no | AY19: 1 | AZ19: 0
B20: 814000000 | C20: Arizona Community Health Workers | D20: Floribella Redondo | E20: Executive Director | F20: 9283663016 | G20: www.AZCHOW.org | H20: The Mission of the Arizona Community Health Outreach Workers Network AzCHOW is to provide a forum for community health workers to inform and unite culturally diverse community health workers of all disciplines, and to strengthen the professional development of the field through resource sharing and collaborative opportunities with community, government, health and educational institutions | I20: AZ | J20: Douglas | K20: 85608 | L20: E11 | M20: E | N20: 990 | O20: 2023 | P20: 1912524 | Q20: 1455435 | R20: 773127 | S20: 1640169 | T20: 272355 | U20: 85.76 | V20: 2 | X20: 0 | Y20: 0 | Z20: 0 | AB20: $1M-$2M | AC20: 75-90% | AE20: 10 | AF20: 1 | AG20: 1 | AH20: 1 | AI20: 1 | AJ20: 1 | AK20: 1 | AL20: 1 | AM20: 1 | AS20: 0 | AT20: 0 | AU20: 0 | AV20: 0 | AW20: 1 | AX20: no | AY20: 1 | AZ20: 0 | BA20: 0
B21: 866000000 | C21: ASSISTANCE LEAGUE OF TUCSON INC | D21: KIMBERLY SPARLING | E21: PRESIDENT/CEO | F21: 5203268452 | G21: ALTUCSON.ORG | H21: VOLUNTEERS WORKING IN THE TUCSON COMMUNITY TO HELP THOSE IN NEED. | I21: AZ | J21: TUCSON | K21: 85712 | L21: P44Z | M21: P | N21: 990 | O21: 2023 | P21: 1428549 | Q21: 1224005 | R21: 3221482 | S21: 1384841 | T21: 0 | U21: 96.94 | V21: 3 | W21: 375 | X21: 0 | Y21: 0 | Z21: 0 | AB21: $1M-$2M | AC21: 90-100% | AD21: 10.1 | AE21: 10 | AF21: 1 | AG21: 1 | AH21: 1 | AI21: 1 | AJ21: 1 | AK21: 1 | AL21: 0 | AM21: 0 | AS21: 0 | AT21: 0 | AU21: 0 | AV21: 0 | AW21: 0 | AX21: yes | AY21: 1 | AZ21: 0
B22: 861000000 | C22: CHRISTIAN CARE HOLDING COMPANY INC | D22: ALAN HIEB | E22: CEO | F22: 6023851592 | G22: FELLOWSHIPSQUARESENIORLIVING.ORG | H22: THROUGH CHRISTIAN LOVE AND EXCELLENCE, WE ARE DEDICATED TO PROVIDING A FULFILLING LIFESTYLE AND PROMOTING INDEPENDENCE TO THOSE WE SERVE. | I22: AZ | J22: PHOENIX | K22: 85021 | L22: P81Z | M22: P | N22: 990 | O22: 2023 | P22: 1337745 | Q22: 13200 | R22: 11022866 | S22: 1100000 | T22: 236901 | U22: 82.23 | V22: 0 | W22: 10 | X22: 0 | Y22: 0 | Z22: 0 | AB22: $1M-$2M | AC22: 75-90% | AD22: 3.2 | AE22: 10 | AF22: 1 | AG22: 0 | AH22: 1 | AI22: 1 | AJ22: 1 | AK22: 1 | AL22: 0 | AM22: 0 | AS22: 0 | AT22: 0 | AU22: 0 | AV22: 0 | AW22: 1 | AX22: no | AY22: 1 | AZ22: 0
B23: 205000000 | C23: Community Network and Fellowship | F23: 5205002992 | H23: Outpatient services | I23: AZ | J23: Phoenix | K23: 85027 | L23: P20 | M23: P | N23: 990 | O23: 2023 | P23: 1176220 | Q23: 897787 | R23: 1056110 | S23: 1176124 | T23: 0 | U23: 99.99 | V23: 0 | X23: 0 | Y23: 0 | Z23: 0 | AB23: $1M-$2M | AC23: 90-100% | AE23: 10 | AF23: 1 | AG23: 0 | AH23: 1 | AI23: 1 | AJ23: 1 | AK23: 1 | AL23: 0 | AM23: 0 | AS23: 0 | AT23: 0 | AU23: 0 | AV23: 0 | AW23: 1 | AX23: uncertain | AY23: 1 | AZ23: 0
B24: 472000000 | C24: HELPING WITH ALL MY HEART INC | D24: CRISTOBAL PEREZ | E24: PRESIDENT | F24: 6027630918 | H24: HELP MIGRANTS TO OBTAIN POLITICA ASILE | I24: AZ | J24: PHOENIX | K24: 85040 | L24: P60 | M24: P | N24: 990 | O24: 2023 | P24: 1461124 | Q24: 1278412 | R24: 422500 | S24: 1461124 | T24: 0 | U24: 100 | V24: 2 | X24: 0 | Y24: 0 | Z24: 0 | AB24: $1M-$2M | AC24: 90-100% | AE24: 10 | AF24: 1 | AG24: 1 | AH24: 1 | AI24: 1 | AJ24: 1 | AK24: 1 | AL24: 1 | AM24: 1 | AS24: 0 | AT24: 0 | AU24: 0 | AV24: 0 | AW24: 1 | AX24: no | AY24: 1 | AZ24: 0
B25: 934000000 | C25: Heros Foundation Inc | D25: James Linse | E25: Director | F25: 4143011687 | G25: herosfoundation.org | H25: Provide Rapid ReHousing and Emergency Housing Solutions to men women single parents and families in or near homelessness. Additionally we refer these same individuals to other organizations for supportive services. | I25: AZ | J25: Wickenburg | K25: 85390 | L25: P60 | M25: P | N25: 990 | O25: 2024 | P25: 1277750 | Q25: 1276325 | R25: 1425 | S25: 1277750 | T25: 0 | U25: 100 | V25: 0 | W25: 0 | X25: 0 | Y25: 0 | Z25: 0 | AB25: $1M-$2M | AC25: 90-100% | AD25: 314.6 | AE25: 10 | AF25: 1 | AG25: 0 | AH25: 1 | AI25: 1 | AJ25: 1 | AK25: 1 | AL25: 0 | AM25: 0 | AS25: 0 | AT25: 0 | AU25: 0 | AV25: 0 | AW25: 1 | AX25: uncertain | AY25: 1 | AZ25: 0
B26: 842000000 | C26: INSIDE AND OUT PROJECT | D26: Daya Wright | E26: President | F26: 8887134267 | H26: The primary mission is Youth Outreach and Family Unification services. The organization provides camps activities and events that promote mental physical behavioral emotional and overall health and wellness for youth and their families. Also to provide Fiscal Sponsorship for organizations that align with our charitable mission. | I26: AZ | J26: Casa Grande | K26: 85130 | L26: P20 | M26: P | N26: 990 | O26: 2022 | P26: 1002043 | Q26: 989941 | R26: 1002043 | S26: 967043 | T26: 35000 | U26: 96.51 | V26: 0 | W26: 0 | X26: 0 | Y26: 0 | Z26: 0 | AB26: $1M-$2M | AC26: 90-100% | AE26: 10 | AF26: 1 | AG26: 0 | AH26: 1 | AI26: 1 | AJ26: 1 | AK26: 1 | AL26: 0 | AM26: 0 | AS26: 0 | AT26: 0 | AU26: 0 | AV26: 0 | AW26: 0 | AX26: uncertain | AY26: 1 | AZ26: 0
B27: 861000000 | C27: Saddlebrooke Community Outreach Inc | D27: Denise Anthony | E27: President | F27: 5208253302 | G27: www.community-outreach.org | H27: To make a positive impact on the lives of underprivileged schoolchildren in neighboring communities by improving self-esteem, school attendance and scholastic achievement. | I27: AZ | J27: Tucson | K27: 85739 | L27: P20 | M27: P | N27: 990 | O27: 2023 | P27: 1240546 | Q27: 1038524 | R27: 4166720 | S27: 1153093 | T27: 0 | U27: 92.95 | V27: 0 | W27: 400 | X27: 3 | Y27: 2 | Z27: 2750 | AA27: 2023 | AB27: $1M-$2M | AC27: 90-100% | AD27: 20.2 | AE27: 10 | AF27: 1 | AG27: 0 | AH27: 1 | AI27: 1 | AJ27: 1 | AK27: 1 | AL27: 0 | AM27: 0 | AS27: 0 | AT27: 0 | AU27: 0 | AV27: 0 | AW27: 0 | AX27: no | AY27: 0 | AZ27: 1
B28: 861000000 | C28: Southeastern Arizona Community Unique | D28: ROYCE HUNT | E28: EXECUTIVE DIRECTOR | F28: 9289653226 | G28: SEACUS.ORG | H28: To provide services to the elderly and disabled in the form of congregate and home delivered meals, housekeeping services, in-home nursing care, home health aides, and other services. | I28: AZ | J28: Safford | K28: 85546 | L28: E92 | M28: E | N28: 990 | O28: 2023 | P28: 1028121 | Q28: 940555 | R28: 879533 | S28: 984952 | T28: 43169 | U28: 95.8 | V28: 0 | X28: 0 | Y28: 0 | Z28: 0 | AB28: $1M-$2M | AC28: 90-100% | AD28: 7.2 | AE28: 10 | AF28: 1 | AG28: 0 | AH28: 1 | AI28: 1 | AJ28: 1 | AK28: 1 | AL28: 0 | AM28: 0 | AS28: 0 | AT28: 0 | AU28: 0 | AV28: 0 | AW28: 0 | AX28: no | AY28: 1 | AZ28: 0
B29: 861000000 | C29: THE BEATITUDES CAMPUS FOUNDATION | D29: MICHELLE JUST | E29: PRESIDENT & CEO, SECRETARY | F29: 6029952611 | G29: HTTPS://BEATITUDESCAMPUS.ORG/ABOUT-US/FOUNDATION/ | H29: THE BEATITUDES CAMPUS FOUNDATION PROVIDES FUNDING TO ENHANCE THE RESIDENT LIFE AT THE BEATITUDES CAMPUS. THE FOUNDATION CONNECTS PEOPLE, COMMUNITY PROGRAMS, AND FUNDS WITHIN THE WORK OF THE BEATITUDES CAMPUS MAKING IT A POSITIVE EXPERIENCE FOR THE RESIDENTS. | I29: AZ | J29: PHOENIX | K29: 85021 | L29: P75I | M29: P | N29: 990 | O29: 2023 | P29: 1367141 | Q29: 1652914 | R29: 1662244 | S29: 1032052 | T29: 0 | U29: 75.49 | V29: 0 | W29: 2 | X29: 3 | Y29: 2 | Z29: 10150 | AA29: 2023 | AB29: $1M-$2M | AC29: 75-90% | AD29: 26.1 | AE29: 10 | AF29: 1 | AG29: 0 | AH29: 1 | AI29: 1 | AJ29: 1 | AK29: 1 | AL29: 0 | AM29: 0 | AN29: 45291 | AO29: 4850 | AP29: 201000000 | AQ29: THE BANK OF AMERICA CHARITABLE | AR29: 0.4 | AS29: 1 | AT29: 0 | AU29: 0 | AV29: 0 | AW29: 0 | AX29: no | AY29: 0 | AZ29: 0
B30: 262000000 | C30: VIT-BUCKLE SOCIETY INC | D30: R ROSS LAKHANPAL MD | E30: DIRECTOR/PAST PRESIDENT | F30: 6027891425 | G30: VITBUCKLESOCIETY.ORG | H30: THE VIT-BUCKLE SOCIETY PROVIDES AN OPEN FORUM THAT MENTORS DEVELOPING VITREORETINAL SURGEONS, NURTURES INNOVATIVE SURGICAL TECHNOLOGIES AND THERAPEUTIC APPROACHES FOR RETINAL DISEASES, AND FOSTERS BEST PRACTICES. | I30: AZ | J30: PHOENIX | K30: 85014 | L30: E03 | M30: E | N30: 990 | O30: 2023 | P30: 1505368 | Q30: 1221156 | R30: 1269224 | S30: 1277193 | T30: 208275 | U30: 84.84 | V30: 0 | W30: 0 | X30: 0 | Y30: 0 | Z30: 0 | AB30: $1M-$2M | AC30: 75-90% | AE30: 10 | AF30: 1 | AG30: 0 | AH30: 1 | AI30: 1 | AJ30: 1 | AK30: 1 | AL30: 0 | AM30: 0 | AS30: 0 | AT30: 0 | AU30: 0 | AV30: 0 | AW30: 1 | AX30: no | AY30: 1 | AZ30: 0
B31: 331000000 | C31: 4 CHRIST MISSION | D31: PAUL SUH | E31: PRESIDENT | F31: 8587487001 | G31: WWW.4CHRISTMISSION.ORG | H31: TO ENGAGE IN RELIGIOUS ACTIVITIES AND ADMINISTER AND EVANGELISM | I31: CA | J31: SAN DIEGO | K31: 92128 | L31: P20 | M31: P | N31: 990 | O31: 2023 | P31: 1015387 | Q31: 1179663 | R31: 956744 | S31: 907870 | T31: 106816 | U31: 89.41 | V31: 3 | X31: 0 | Y31: 0 | Z31: 0 | AB31: $1M-$2M | AC31: 75-90% | AD31: -18 | AE31: 11 | AF31: 1 | AG31: 1 | AH31: 1 | AI31: 1 | AJ31: 1 | AK31: 1 | AL31: 1 | AM31: 1 | AS31: 0 | AT31: 0 | AU31: 0 | AV31: 0 | AW31: 1 | AX31: no | AY31: 1 | AZ31: 1 | BA31: 0
B32: 274000000 | C32: 4 KIDS 2 KIDS | D32: LORIE VOS | E32: BOARD MEMBER/CEO | F32: 8055730752 | G32: 4K2KONLINE.ORG | H32: RESIDENTIAL CARE AND TREATMENT OF EMOTIONALLY AND PHYSICALLY NEGLECTED CHILDREN. | I32: CA | J32: OAK VIEW | K32: 930000000 | L32: P20 | M32: P | N32: 990 | O32: 2023 | P32: 1705963 | Q32: 1751557 | R32: 225930 | S32: 1692675 | T32: 0 | U32: 99.22 | V32: 0 | X32: 3 | Y32: 3 | Z32: 20000 | AA32: 2023 | AB32: $1M-$2M | AC32: 90-100% | AE32: 11 | AF32: 1 | AG32: 0 | AH32: 1 | AI32: 1 | AJ32: 1 | AK32: 1 | AL32: 0 | AM32: 0 | AN32: 45291 | AO32: 5000 | AP32: 776000000 | AQ32: LATKIN CHARITABLE FOUNDATION | AR32: 0.3 | AS32: 1 | AT32: 0 | AU32: 0 | AV32: 0 | AW32: 1 | AX32: no | AY32: 0 | AZ32: 1 | BA32: 1
B33: 874000000 | C33: A2SV FOUNDATION | D33: BRIAN BELL | E33: CEO/DIRECTOR | F33: 4708469962 | G33: HTTPS://A2SV.ORG/ | H33: A2SV IS A SOCIAL ENTERPRISE THAT ENABLES HIGH-POTENTIAL UNIVERSITY STUDENTS TO CREATE DIGITAL SOLUTIONS TO AFRICAS MOST PRESSING PROBLEMS. WE UPSKILL HIGH-POTENTIAL UNIVERSITY STUDENTS, CONNECT THEM WITH INTERNSHIP INTERVIEWS AT THE WORLDS TOP TECH COMPANIES, AND CREATE DIGITAL SOLUTIONS TO URGENT PROBLEMS IN THEIR HOME COUTRIES TOGETHER. THE PROGRAM IS FREE FOR STUDENTS, MAKING THE OPPORTUNIT AVAILABLE FOR YOUTH WHO HAVE TALENT BUT LACK THE MEANS TO USE IT. A2SVS ROGOROUS THREE-MONTH TRAINING PROGRAM PREPARES STUDENTS FOR INTERNSHIPS WITH COMPANIES LIKE GOOGLE, PALANTIR, AND LINKEDIN. THE INTERNSHIPS GIVE STUDENTS THE EXPERIENCE THEY NEED TO DESIGN AND BUILD PRODUCTS THAT IMPROVE THE QUALITY OF LIFE IN AFRICA. WE ARE UNLIKE ANY OTHER PROGRAMMING ACADEMY BECAUSE WE PERMANENTLY INCORPORATE STUDENTS VENTURES UNDER THE UMBRELLA OF THE ORGANIZATION, GOING BEYOND TRAINING TO DELIVER CONCRETE IMPACT. OFFERING STUDENTS AN ECOSYSTEM TO ACTUALIZE THEIR IDEAS MEANS THAT UP-AND-COMING DEVELOPERS | I33: CA | J33: PALO ALTO | K33: 94301 | L33: P20 | M33: P | N33: 990 | O33: 2023 | P33: 1249363 | Q33: 1506740 | R33: 1605714 | S33: 1220372 | T33: 0 | U33: 97.68 | V33: 1 | W33: 12 | X33: 1 | Y33: 1 | Z33: 101353 | AA33: 2023 | AB33: $1M-$2M | AC33: 90-100% | AD33: 24.9 | AE33: 11 | AF33: 1 | AG33: 1 | AH33: 1 | AI33: 1 | AJ33: 1 | AK33: 1 | AL33: 0 | AM33: 0 | AS33: 0 | AT33: 0 | AU33: 0 | AV33: 0 | AW33: 1 | AX33: uncertain | AY33: 0 | AZ33: 1 | BA33: 0
B34: 800000000 | C34: AFRICAN AMERICAN CULTURAL CENTER | D34: JOANNA FARRIS | E34: PRESIDENT | F34: 4089106958 | G34: SVAFRICANAMERICANCULTURALCENTER.ORG | H34: CREATING, DEVELOPING AND BUILDING THE NEW AFRICAN-AMERICAN COMMUNITY SERVICE AGENCY PROJECT - AN AFFORDABLE HOUSING MIXED USE DEVELOPMENT WHICH WILL INCLUDE A COMMUNITY SERVICE AGENCY, COMMUNITY HEALTH CLINICS, ADULT AND FAMILY SERVICES, AND OTHER RELATED PROGRAMS. | I34: CA | J34: SAN JOSE | K34: 95126 | L34: P29 | M34: P | N34: 990 | O34: 2022 | P34: 1084290 | Q34: 50851 | R34: 1629599 | S34: 1081100 | T34: 0 | U34: 99.71 | V34: 0 | X34: 3 | Y34: 2 | Z34: 101107 | AA34: 2023 | AB34: $1M-$2M | AC34: 90-100% | AE34: 11 | AF34: 1 | AG34: 0 | AH34: 1 | AI34: 1 | AJ34: 1 | AK34: 1 | AL34: 0 | AM34: 0 | AN34: 45291 | AO34: 100000 | AP34: 261000000 | AQ34: THE HEISING-SIMONS FOUNDATION | AR34: 9.2 | AS34: 1 | AT34: 0 | AU34: 0 | AV34: 0 | AW34: 0 | AX34: uncertain | AY34: 0 | AZ34: 1 | BA34: 0
B35: 301000000 | C35: ANTARA INTERNATIONAL INC | D35: MADHURA V NIRKHE | E35: Former CEO | F35: 4152542927 | G35: www.antarainternational.org | H35: Antara International Inc. is operating as a non-profit organization working in the public health space supporting Programs providing quality public health delivery solutions to the people. Antara International Inc. focuses primarily on preventive healthcare for maternal and child beneficiaries, including nutrition. | I35: CA | J35: SANTA CLARA | K35: 95054 | L35: E70 | M35: E | N35: 990 | O35: 2023 | P35: 1088537 | Q35: 2338199 | R35: 5230348 | S35: 876218 | T35: 0 | U35: 80.5 | V35: 1 | X35: 0 | Y35: 0 | Z35: 0 | AB35: $1M-$2M | AC35: 75-90% | AD35: 9.2 | AE35: 11 | AF35: 1 | AG35: 1 | AH35: 1 | AI35: 1 | AJ35: 1 | AK35: 1 | AL35: 1 | AM35: 1 | AS35: 0 | AT35: 0 | AU35: 0 | AV35: 0 | AW35: 1 | AX35: no | AY35: 1 | AZ35: 1 | BA35: 0
B36: 203000000 | C36: ARROYO GRANDE COMMUNITY HOSPITAL | D36: CHARLES COVA | E36: FORMER OFFICER (DIV SVP OPERATIONS & CEO) | F36: 8057393686 | G36: WWW.DIGNITYHEALTH.ORG | H36: ARROYO GRANDE COMMUNITY HOSPITAL FOUNDATION RELIES ON THE GENEROSITY OF THE COMMUNITY TO HELP SUPPORT DIGNITY HEALTH DBA ARROYO GRANDE COMMUNITY HOSPITAL'S EFFORTS OF PROVIDING QUALITY AFFORDABLE HEALTHCARE TO THE COMMUNITIES IT SERVES. FOUNDATION SUPPORT ALSO ALLOWS THE HOSPITAL TO FURTHER ITS MISSION BY MAKING THE HEALING PRESENCE OF GOD KNOWN IN OUR WORLD BY IMPROVING THE HEALTH OF THE PEOPLE WE SERVE, ESPECIALLY THOSE WHO ARE VULNERABLE, WHILE WE ADVANCE SOCIAL JUSTICE FOR ALL. | I36: CA | J36: ARROYO GRANDE | K36: 93420 | L36: E11 | M36: E | N36: 990 | O36: 2022 | P36: 1305855 | Q36: 2013562 | R36: 1855086 | S36: 1314875 | T36: 0 | U36: 100.69 | V36: 0 | W36: 15 | X36: 1 | Y36: 1 | Z36: 100 | AA36: 2022 | AB36: $1M-$2M | AC36: 90-100% | AD36: -9.3 | AE36: 11 | AF36: 1 | AG36: 0 | AH36: 1 | AI36: 1 | AJ36: 1 | AK36: 1 | AL36: 0 | AM36: 0 | AS36: 0 | AT36: 0 | AU36: 0 | AV36: 0 | AW36: 0 | AX36: yes | AY36: 0 | AZ36: 1 | BA36: 0
B37: 455000000 | C37: ARYANA HEALTH CARE FOUNDATION | D37: BOBBY SARNEVESHT | E37: President | F37: 4086667335 | G37: N/A | H37: TO PROVIDE NECESSARY HEALTH CARE FOR UNINSURED INDIVIDUALS | I37: CA | J37: BURLINGAME | K37: 94010 | L37: E70 | M37: E | N37: 990 | O37: 2023 | P37: 1358317 | Q37: 629721 | R37: 15998387 | S37: 1296130 | T37: 0 | U37: 95.42 | V37: 0 | W37: 15 | X37: 2 | Y37: 1 | Z37: 123000 | AA37: 2023 | AB37: $1M-$2M | AC37: 90-100% | AD37: 747.8 | AE37: 11 | AF37: 1 | AG37: 0 | AH37: 1 | AI37: 1 | AJ37: 1 | AK37: 1 | AL37: 0 | AM37: 0 | AS37: 0 | AT37: 0 | AU37: 0 | AV37: 0 | AW37: 1 | AX37: no | AY37: 0 | AZ37: 1
B38: 952000000 | C38: ASSISTANCE LEAGUE OF SANTA BARBARA | D38: Chris Nelson | E38: President Elect | F38: 8058981967 | G38: ASSISTANCELEAGUESB.ORG | H38: THIS COMMUNITY SERVICE ORGANIZATION'S VOLUNTEER MEMBERS IDENTIFY, DEVELOP, IMPLEMENT, AND FUND ONGOING PHILANTHROPIC PROGRAMS TO SERVE THE SPECIFIC NEEDS OF CHILDREN AND ADULTS IN SANTA BARBARA COUNTY, CALIFORNIA. | I38: CA | J38: SANTA BARBARA | K38: 93105 | L38: P20Z | M38: P | N38: 990 | O38: 2023 | P38: 1007875 | Q38: 937581 | R38: 4993525 | S38: 907576 | T38: 0 | U38: 90.05 | V38: 0 | W38: 397 | X38: 0 | Y38: 0 | Z38: 0 | AB38: $1M-$2M | AC38: 90-100% | AD38: 9.3 | AE38: 11 | AF38: 1 | AG38: 0 | AH38: 1 | AI38: 1 | AJ38: 1 | AK38: 1 | AL38: 0 | AM38: 0 | AS38: 0 | AT38: 0 | AU38: 0 | AV38: 0 | AW38: 0 | AX38: yes | AY38: 1 | AZ38: 1 | BA38: 0
B39: 812000000 | C39: Bloom Workforce Development Inc | D39: Michelle Darne | E39: CEO/President | F39: 9176275877 | G39: www.bloomworkforce.org | H39: Workforce development for the Bay Areas most disenfranchised communities: addicts in recovery, youth timing out of foster care, veterans, seniors, and LGBTQI+. | I39: CA | J39: Concord | K39: 94518 | L39: P20 | M39: P | N39: 990 | O39: 2022 | P39: 1189847 | Q39: 241678 | R39: 1587220 | S39: 1189553 | T39: 0 | U39: 99.98 | V39: 0 | W39: 33 | X39: 0 | Y39: 0 | Z39: 0 | AB39: $1M-$2M | AC39: 90-100% | AE39: 11 | AF39: 1 | AG39: 0 | AH39: 1 | AI39: 1 | AJ39: 1 | AK39: 1 | AL39: 0 | AM39: 0 | AS39: 0 | AT39: 0 | AU39: 0 | AV39: 0 | AW39: 1 | AX39: uncertain | AY39: 1 | AZ39: 1 | BA39: 0
B40: 954000000 | C40: Camp Laurel Foundation | D40: Margot Anderson | E40: FounderCEO | F40: 6266830800 | G40: www.Laurel-Foundation.org | H40: The mission of The Laurel Foundation is to empower children, youth and families affected by HIV/AIDS and transgender/gender non-conforming youth through educational and support programs in a safe and trusting environment. | I40: CA | J40: Pasadena | K40: 91105 | L40: P82Z | M40: P | N40: 990 | O40: 2023 | P40: 1078571 | Q40: 1100361 | R40: 181499 | S40: 868892 | T40: 0 | U40: 80.56 | V40: 3 | W40: 200 | X40: 2 | Y40: 2 | Z40: 28000 | AA40: 2023 | AB40: $1M-$2M | AC40: 75-90% | AD40: 0.2 | AE40: 11 | AF40: 1 | AG40: 1 | AH40: 1 | AI40: 1 | AJ40: 1 | AK40: 1 | AL40: 0 | AM40: 0 | AN40: 45291 | AO40: 10000 | AP40: 461000000 | AQ40: GSF FOUNDATION | AR40: 0.9 | AS40: 1 | AT40: 0 | AU40: 0 | AV40: 0 | AW40: 1 | AX40: no | AY40: 0 | AZ40: 1 | BA40: 1
B41: 451000000 | C41: Casa de los Pobres USA | D41: PATRICIA ERZINGER | E41: President | F41: 8587617744 | G41: casadelospobresusa.com | H41: We support Casa de los Pobres in Tijuana, Mexico; a nonprofit charity that serves the poor by providing food, water, clothing, medical and dental care, shelter, social services, and childrens' education. | I41: CA | J41: San Diego | K41: 92169 | L41: P122 | M41: P | N41: 990 | O41: 2024 | P41: 1067553 | Q41: 1187905 | R41: 660615 | S41: 1046027 | T41: 0 | U41: 97.98 | V41: 0 | W41: 40 | X41: 2 | Y41: 1 | Z41: 1200 | AA41: 2023 | AB41: $1M-$2M | AC41: 90-100% | AD41: 22.4 | AE41: 11 | AF41: 1 | AG41: 0 | AH41: 1 | AI41: 1 | AJ41: 1 | AK41: 1 | AL41: 0 | AM41: 0 | AN41: 45291 | AO41: 1000 | AP41: 237000000 | AQ41: JPMORGAN CHASE FOUNDATION | AR41: 0.1 | AS41: 1 | AT41: 0 | AU41: 0 | AV41: 0 | AW41: 1 | AX41: no | AY41: 0 | AZ41: 1 | BA41: 0
B42: 954000000 | C42: CATHEDRAL CENTER | D42: GEOFF CORBIN | E42: EXECUTIVE DIRECTOR | F42: 7603211548 | G42: WWW.THECATHEDRALCENTER.ORG | H42: CATHEDRAL CENTER IS DEDICATED TO HELPING SENIORS LIVE MEANINGFUL LIVES WITH DIGNITY FROM THE ACTIVE TO THE HOMEBOUND, IMPROVING THEIR QUALITY OF LIFE BY ASSISTING ALL SENIORS. | I42: CA | J42: CATHEDRAL CITY | K42: 92234 | L42: P81 | M42: P | N42: 990 | O42: 2023 | P42: 1149902 | Q42: 1226683 | R42: 387091 | S42: 1092628 | T42: 22400 | U42: 95.02 | V42: 0 | W42: 0 | X42: 2 | Y42: 1 | Z42: 10000 | AA42: 2023 | AB42: $1M-$2M | AC42: 90-100% | AD42: 76.2 | AE42: 11 | AF42: 1 | AG42: 0 | AH42: 1 | AI42: 1 | AJ42: 1 | AK42: 1 | AL42: 0 | AM42: 0 | AN42: 44926 | AO42: 5000 | AP42: 397000000 | AQ42: BERT L AND PATRICIA S STEIGLEDER CHARITABLE | AR42: 0.4 | AS42: 1 | AT42: 0 | AU42: 0 | AV42: 0 | AW42: 1 | AX42: no | AY42: 0 | AZ42: 1 | BA42: 0
B43: 770000000 | C43: CBCC FOUNDATION FOR COMMUNITY WELLNESS | D43: KAREN LEVINE | E43: PRESIDENT | F43: 6613222206 | G43: N/A | H43: SERVING THE EDUCATIONAL, FINANCIAL, AND EMOTIONAL NEEDS OF KERN COUNTY CANCER PATIENTS AND THEIR FAMILIES. | I43: CA | J43: BAKERSFIELD | K43: 93309 | L43: E70 | M43: E | N43: 990 | O43: 2023 | P43: 1023585 | Q43: 98475 | R43: 437624 | S43: 916681 | T43: 0 | U43: 89.56 | V43: 2 | W43: 1 | X43: 0 | Y43: 0 | Z43: 0 | AB43: $1M-$2M | AC43: 75-90% | AD43: 349.1 | AE43: 11 | AF43: 1 | AG43: 1 | AH43: 1 | AI43: 1 | AJ43: 1 | AK43: 1 | AL43: 1 | AM43: 1 | AS43: 0 | AT43: 0 | AU43: 0 | AV43: 0 | AW43: 1 | AX43: no | AY43: 1 | AZ43: 1
B44: 955000000 | C44: CENTER ON DEAFNESS-INLAND EMPIRE | D44: PATRICIA HUGHES | E44: CEO | F44: 3238922205 | G44: WWW.GLADINC.ORG | H44: SOCIAL SERVICES FOR THE DEAF & HARD OF HEARING | I44: CA | J44: LOS ANGELES | K44: 90041 | L44: P87 | M44: P | N44: 990 | O44: 2023 | P44: 1319689 | Q44: 1296767 | R44: 197784 | S44: 1199512 | T44: 120177 | U44: 90.89 | V44: 0 | W44: 5 | X44: 0 | Y44: 0 | Z44: 0 | AB44: $1M-$2M | AC44: 90-100% | AD44: 3.7 | AE44: 11 | AF44: 1 | AG44: 0 | AH44: 1 | AI44: 1 | AJ44: 1 | AK44: 1 | AL44: 0 | AM44: 0 | AS44: 0 | AT44: 0 | AU44: 0 | AV44: 0 | AW44: 0 | AX44: no | AY44: 1 | AZ44: 1 | BA44: 0
B45: 883000000 | C45: CHILDRENS ONCOLOGY SUPPORT FUND | D45: THOMAS PIERCE | E45: PRESIDENT | F45: 9177150316 | G45: WWW.COSFFOUNDATION.ORG | H45: MISSION IS TO PROVIDE LESS TOXIC TREATMENTS AND ALTERNATIVE THERAPIES FOR CHILDREN BATTLING CANCER THOUGH FUNDING GROUNDBREAKING RESEARCH AND THERAPEUTIC PROGRAMS. COSF WILL ACCOMPLISH ITS MISSION THROUGH INNOVATIVE EVENTS AND ACTIVITIES. THUS, CHILDRENS ONCOLOGY SUPPORT FUND IS KEEN ON FOSTERING NEW IDEAS, INFLUENCING GIVING TO SUPPORT THE WELLBEING AND HEALTH OF PEDIATRIC CANCER PATIENTS, AND AFFECTING CHANGE THROUGH INNOVATIVE PROCESSES AND SERVICES. | I45: CA | J45: W HOLLYWOOD | K45: 90046 | L45: P12 | M45: P | N45: 990 | O45: 2023 | P45: 1793400 | Q45: 1673210 | R45: 268570 | S45: 1793400 | T45: 0 | U45: 100 | V45: 0 | X45: 2 | Y45: 2 | Z45: 18000 | AA45: 2023 | AB45: $1M-$2M | AC45: 90-100% | AD45: 265.5 | AE45: 11 | AF45: 1 | AG45: 0 | AH45: 1 | AI45: 1 | AJ45: 1 | AK45: 1 | AL45: 0 | AM45: 0 | AN45: 45291 | AO45: 15000 | AP45: 943000000 | AQ45: CONRAD N HILTON FOUNDATION | AR45: 0.8 | AS45: 1 | AT45: 1 | AU45: 6 | AV45: 1 | AW45: 1 | AX45: uncertain | AY45: 0 | AZ45: 1 | BA45: 1
B46: 943000000 | C46: CHILDRENS SERVICES FOUNDATION | D46: CHRIS STONER-MERTZ | E46: CEO | F46: 9164492273 | G46: https://www.catalyst-center.org | H46: PROMOTING THE HEALTH, WELL-BEING AND SAFETY OF CHILDREN, YOUTH AND FAMILIES IN CALIFORNIA AS A COLLECTIVE VOICE IMPACTING POLICY AND BEST PRACTICES TO STRENGTHEN THE SYSTEMS THAT SERVE THEM. | I46: CA | J46: SACRAMENTO | K46: 95816 | L46: P30 | M46: P | N46: 990 | O46: 2023 | P46: 1315181 | Q46: 1567537 | R46: 1536558 | S46: 1281544 | T46: 3672 | U46: 97.44 | V46: 0 | X46: 2 | Y46: 1 | Z46: 590000 | AA46: 2023 | AB46: $1M-$2M | AC46: 90-100% | AD46: -44 | AE46: 11 | AF46: 1 | AG46: 0 | AH46: 1 | AI46: 1 | AJ46: 1 | AK46: 1 | AL46: 0 | AM46: 0 | AS46: 0 | AT46: 0 | AU46: 0 | AV46: 0 | AW46: 0 | AX46: no | AY46: 0 | AZ46: 1 | BA46: 0
B47: 474000000 | C47: COMMUNITY & EMPLOYMENT LINKS | D47: SUSAN MOODY | E47: PRESIDENT | F47: 5309570338 | G47: N/A | H47: AT COMMUNITY & EMPLOYMENT LINKS OUR MISSION IS TO PROVIDE OPPORTUNITIES FOR PEOPLE WITH DEVELOPMENTAL DISABILITIES TO PARTICIPATE IN ACTIVITIES THAT WILL ENCOURAGE AND FACILITATE SKILL BUILDING IN SUCH AREAS AS COMMUNITY INVOLVEMENT AND EMPLOYMENT. | I47: CA | J47: SHINGLE SPRINGS | K47: 95682 | L47: P80 | M47: P | N47: 990 | O47: 2023 | P47: 1256606 | Q47: 1461183 | R47: 293096 | S47: 1256326 | T47: 0 | U47: 99.98 | V47: 0 | X47: 0 | Y47: 0 | Z47: 0 | AB47: $1M-$2M | AC47: 90-100% | AE47: 11 | AF47: 1 | AG47: 0 | AH47: 1 | AI47: 1 | AJ47: 1 | AK47: 1 | AL47: 0 | AM47: 0 | AS47: 0 | AT47: 0 | AU47: 0 | AV47: 0 | AW47: 0 | AX47: no | AY47: 1 | AZ47: 1
B48: 951000000 | C48: COMMUNITY SETTLEMENT ASSOCIATION | D48: LISA WRIGHT | E48: CEO | F48: 9516866266 | G48: WWW.CSARIVERSIDE.ORG | H48: TO MAINTAIN A SOCIAL SETTLEMENT IN WHICH THE RESIDENTS AND OTHER WORKERS SHALL SEEK TO PERFORM THE SERVICES OF A GOOD NEIGHBOR TO THE PEOPLE OF THE DISTRICT AND ESPECIALLY TO PROMOTE THE WELFARE OF ALL IN EDUCATIONAL GUIDANCE, MEDICAL ASSISTANCE AND DIRECTED RECREATION. TO UNDERSTAND ALL GROUPS, TO INTERPRET THEIR NEEDS TO THE COMMUNITY, TO CONTRIBUTE TO AN APPRECIATION OF THEIR CULTURE TO DEVELOP INDEPENDENCE AND LEADERSHIP AND TO ASSIST IN DEVELOPING GOOD CITIZENS FOR THE COMMUNITY. | I48: CA | J48: RIVERSIDE | K48: 925000000 | L48: P300 | M48: P | N48: 990 | O48: 2023 | P48: 1144796 | Q48: 1178613 | R48: 1042092 | S48: 1048885 | T48: 102178 | U48: 91.62 | V48: 0 | W48: 5 | X48: 0 | Y48: 0 | Z48: 0 | AB48: $1M-$2M | AC48: 90-100% | AD48: 42.9 | AE48: 11 | AF48: 1 | AG48: 0 | AH48: 1 | AI48: 1 | AJ48: 1 | AK48: 1 | AL48: 0 | AM48: 0 | AS48: 0 | AT48: 0 | AU48: 0 | AV48: 0 | AW48: 1 | AX48: no | AY48: 1 | AZ48: 1 | BA48: 0
B49: 455000000 | C49: CORRECTIVE CARE MINISTRY | D49: UDOH OBIOHA | E49: President | F49: 5098338330 | G49: N/A | H49: TO PROVIDE FREE MEDICAL, HUMANITARIAN AND CHRISTIAN RESOURCES FOR THE IMPROVEMENT OF THE LIVES OF THE NEEDY AND SICK POPULATION OF THE USA. | I49: CA | J49: CLAREMONT | K49: 91711 | L49: P20 | M49: P | N49: 990 | O49: 2023 | P49: 1460127 | Q49: 1462688 | R49: 3455 | S49: 1460127 | T49: 0 | U49: 100 | V49: 0 | W49: 13 | X49: 0 | Y49: 0 | Z49: 0 | AB49: $1M-$2M | AC49: 90-100% | AD49: 284.8 | AE49: 11 | AF49: 1 | AG49: 0 | AH49: 1 | AI49: 1 | AJ49: 1 | AK49: 1 | AL49: 0 | AM49: 0 | AS49: 0 | AT49: 0 | AU49: 0 | AV49: 0 | AW49: 1 | AX49: no | AY49: 1 | AZ49: 1
B50: 455000000 | C50: CULTURAL BROKERS INCORPORATED | D50: MARGARET JACKSON | E50: EXECUTIVE DIRECTOR | F50: 5598244724 | G50: N/A | H50: SUPPORTING THE POWER OF FAMILIES TO STRENGTHEN COMMUNITES | I50: CA | J50: FRESNO | K50: 93721 | L50: P40 | M50: P | N50: 990 | O50: 2023 | P50: 1169182 | Q50: 1089699 | R50: 387858 | S50: 1169176 | T50: 0 | U50: 100 | V50: 0 | X50: 0 | Y50: 0 | Z50: 0 | AB50: $1M-$2M | AC50: 90-100% | AD50: 21.8 | AE50: 11 | AF50: 1 | AG50: 0 | AH50: 1 | AI50: 1 | AJ50: 1 | AK50: 1 | AL50: 0 | AM50: 0 | AN50: 43465 | AO50: 60000 | AP50: 824000000 | AQ50: Living Legacy Foundation | AR50: 5.1 | AS50: 1 | AT50: 0 | AU50: 0 | AV50: 0 | AW50: 1 | AX50: no | AY50: 1 | AZ50: 1
B51: 814000000 | C51: DMT Quest | D51: John Chavez | E51: President | F51: 4158103549 | G51: N/A | H51: The specific purpose of the corporation is to raise awareness in the medical community and general public about the health and societal benefits of meditation, sleep, and mindbody feedback practices. | I51: CA | J51: Burlingame | K51: 94010 | L51: P20 | M51: P | N51: 990 | O51: 2024 | P51: 1075335 | Q51: 790584 | R51: 287921 | S51: 1075335 | T51: 0 | U51: 100 | V51: 0 | X51: 0 | Y51: 0 | Z51: 0 | AB51: $1M-$2M | AC51: 90-100% | AE51: 11 | AF51: 1 | AG51: 0 | AH51: 1 | AI51: 1 | AJ51: 1 | AK51: 1 | AL51: 0 | AM51: 0 | AN51: 44196 | AO51: 100 | AP51: 372000000 | AQ51: FOUNDERS PLEDGE INC | AR51: 0 | AS51: 1 | AT51: 0 | AU51: 0 | AV51: 0 | AW51: 1 | AX51: no | AY51: 1 | AZ51: 1
B52: 202000000 | C52: Donate Life California | D52: Jim Martin | E52: CEO | F52: 9166786044 | G52: donatelifecalifornia.org | H52: Donate Life Californa is a nonprofit organ and tissue donor registry dedicated to saving the lives of thousands of Californians awaiting life-saving transplants. The registry is used by the states organ and tissue recovery organizations. | I52: CA | J52: West Sacramento | K52: 95691 | L52: E65 | M52: E | N52: 990 | O52: 2023 | P52: 1571214 | Q52: 793774 | R52: 3839984 | S52: 1525325 | T52: 0 | U52: 97.08 | V52: 3 | W52: 6 | X52: 1 | Y52: 1 | Z52: 5000 | AA52: 2024 | AB52: $1M-$2M | AC52: 90-100% | AD52: 52.6 | AE52: 11 | AF52: 1 | AG52: 1 | AH52: 1 | AI52: 1 | AJ52: 1 | AK52: 1 | AL52: 0 | AM52: 0 | AS52: 0 | AT52: 0 | AU52: 0 | AV52: 0 | AW52: 1 | AX52: no | AY52: 0 | AZ52: 1 | BA52: 1
B53: 471000000 | C53: EDUCHRIST | D53: ELAINE REMY | E53: PRESIDENT & SECRETARY | F53: 8056742902 | G53: WWW.ZOZUPROJECT.ORG | H53: THE ORGANIZATION'S MISSION IS TO LIFT COMMUNITIES OUT OF EXTREME PROVERTY BY PARTNERING WITH LOCAL AFRICAN LEADERS TO PROVIDE FAMILY-FOCUSED HOPE, EDUCATION, AND ECONOMIC OPPORTUNITY. | I53: CA | J53: TEMPLETON | K53: 93465 | L53: P12 | M53: P | N53: 990 | O53: 2023 | P53: 1955698 | Q53: 1839480 | R53: 856920 | S53: 1931921 | T53: 0 | U53: 98.78 | V53: 1 | W53: 0 | X53: 0 | Y53: 0 | Z53: 0 | AB53: $1M-$2M | AC53: 90-100% | AE53: 11 | AF53: 1 | AG53: 1 | AH53: 1 | AI53: 1 | AJ53: 1 | AK53: 1 | AL53: 1 | AM53: 1 | AS53: 0 | AT53: 0 | AU53: 0 | AV53: 0 | AW53: 1 | AX53: no | AY53: 1 | AZ53: 1 | BA53: 0
B54: 262000000 | C54: F C Cancer Foundation A California | D54: John McGuinness | E54: Founder | F54: 8555283336 | G54: www.fccancerfoundation.org | H54: Education and awareness of cancer patients' challenges | I54: CA | J54: Costa Mesa | K54: 92627 | L54: E86 | M54: E | N54: 990 | O54: 2023 | P54: 1058801 | Q54: 903179 | R54: 749177 | S54: 870689 | T54: 0 | U54: 82.23 | V54: 3 | X54: 3 | Y54: 2 | Z54: 1025 | AA54: 2023 | AB54: $1M-$2M | AC54: 75-90% | AE54: 11 | AF54: 1 | AG54: 1 | AH54: 1 | AI54: 1 | AJ54: 1 | AK54: 1 | AL54: 1 | AM54: 1 | AN54: 43830 | AO54: 250 | AP54: 472000000 | AQ54: DM3 FUND | AR54: 0 | AS54: 1 | AT54: 0 | AU54: 0 | AV54: 0 | AW54: 1 | AX54: no | AY54: 0 | AZ54: 1 | BA54: 1
B55: 204000000 | C55: FIREFIGHTER CANCER SUPPORT NETWORK INC | D55: Lisa Marie Raggio | E55: Executive Director | F55: 8184645740 | G55: FIREFIGHTERCANCERSUPPORT.ORG | H55: NONE | I55: CA | J55: BURBANK | K55: 91505 | L55: P20 | M55: P | N55: 990 | O55: 2023 | P55: 1306429 | Q55: 1260444 | R55: 514644 | S55: 1255883 | T55: 0 | U55: 96.13 | V55: 0 | W55: 0 | X55: 2 | Y55: 2 | Z55: 20500 | AA55: 2023 | AB55: $1M-$2M | AC55: 90-100% | AD55: 41.1 | AE55: 11 | AF55: 1 | AG55: 0 | AH55: 1 | AI55: 1 | AJ55: 1 | AK55: 1 | AL55: 0 | AM55: 0 | AN55: 45291 | AO55: 20000 | AP55: 956000000 | AQ55: THE MORRIS A HAZAN FAMILY FOUNDATION | AR55: 1.5 | AS55: 1 | AT55: 1 | AU55: 6 | AV55: 1 | AW55: 1 | AX55: yes | AY55: 0 | AZ55: 1 | BA55: 1
B56: 771000000 | C56: First 5 Association of California Inc | D56: Kim Goll | E56: Past President | F56: 5109023937 | G56: First5Association.org | H56: THE ASSOCIATION'S MISSION IS TO IMPROVE THE LIVES OF CALIFORNIA'S YOUNGEST CHILDREN AND THEIR FAMILIES THROUGH AN EFFECTIVE, COORDINATED AND INCLUSIVE IMPLEMENTATION OF THE CALIFORNIA CHILDREN AND FAMILIES ACT AT THE STATE AND LOCAL LEVEL. | I56: CA | J56: Alameda | K56: 94501 | L56: P02 | M56: P | N56: 990 | O56: 2022 | P56: 1632624 | Q56: 1868916 | R56: 2116806 | S56: 1423896 | T56: 208362 | U56: 87.22 | V56: 0 | X56: 0 | Y56: 0 | Z56: 0 | AB56: $1M-$2M | AC56: 75-90% | AD56: 6.2 | AE56: 11 | AF56: 1 | AG56: 0 | AH56: 1 | AI56: 1 | AJ56: 1 | AK56: 1 | AL56: 0 | AM56: 0 | AS56: 0 | AT56: 0 | AU56: 0 | AV56: 0 | AW56: 0 | AX56: no | AY56: 1 | AZ56: 1 | BA56: 0
B57: 813000000 | C57: Friends of India Network | D57: Jack Klassen | E57: President | F57: 5304040717 | G57: www.foinetwork.net | H57: Friends of India Network establishes partnerships and empowers indigenous workers to spread the Gospel across Northern India through financial and prayerful support and vital practical relief. | I57: CA | J57: Sacramento | K57: 95825 | L57: P73 | M57: P | N57: 990 | O57: 2023 | P57: 1744820 | Q57: 1903922 | R57: 176231 | S57: 1744747 | T57: 0 | U57: 100 | V57: 0 | W57: 3 | X57: 0 | Y57: 0 | Z57: 0 | AB57: $1M-$2M | AC57: 90-100% | AE57: 11 | AF57: 1 | AG57: 0 | AH57: 1 | AI57: 1 | AJ57: 1 | AK57: 1 | AL57: 0 | AM57: 0 | AS57: 0 | AT57: 0 | AU57: 0 | AV57: 0 | AW57: 1 | AX57: no | AY57: 1 | AZ57: 1 | BA57: 0
B58: 993000000 | C58: FRIENDS OF THE CHILDREN - COACHELLA VALL | D58: KARRIE SCHAAF | E58: EXECUTIVE DIRECTOR | F58: 5032816633 | G58: FRIENDSOFTHECHILDREN.ORG | H58: FRIENDS OF THE CHILDREN - COACHELLA VALLEY HAS A MISSION OF IMPACTING GENERATIONAL CHANGE BY EMPOWERING YOUTH WHO ARE FACING THE GREATEST OBSTACLES THROUGH RELATIONSHIPS WITH PROFESSIONAL MENTORS - 12+ YEARS, NO MATTER WHAT. 83% OF OUR YOUTH RECEIVE A HIGH SCHOOL DIPLOMA OR GED, 98% WAIT TO BECOME PARENTS UNTIL AFTER THEIR TEENS, 93% REMAIN FREE FROM JUVENILE JUSTICE SYSTEM INVOLVEMENT, AND 92% GO ON TO ENROLL IN POST-SECONDARY EDUCATION, SERVE OUR COUNTRY, OR ENTER THE WORKFORCE. | I58: CA | J58: RANCHO MIRAGE | K58: 92270 | L58: P20 | M58: P | N58: 990 | O58: 2023 | P58: 1368652 | Q58: 13484 | R58: 1355168 | S58: 1368652 | T58: 0 | U58: 100 | V58: 0 | W58: 0 | X58: 0 | Y58: 0 | Z58: 0 | AB58: $1M-$2M | AC58: 90-100% | AE58: 11 | AF58: 1 | AG58: 0 | AH58: 1 | AI58: 1 | AJ58: 1 | AK58: 1 | AL58: 0 | AM58: 0 | AS58: 0 | AT58: 1 | AU58: 0 | AV58: 0 | AW58: 0 | AX58: uncertain | AY58: 1 | AZ58: 1 | BA58: 1
B59: 811000000 | C59: FRIENDSHIPS FOR HOPE INC | D59: WILL JAMES | E59: PRESIDENT | F59: 6193955087 | H59: TO AID IN THE ASSIMILATION OF IMMIGRANTS AND REFUGEES INTO THE COMMUNITY | I59: CA | J59: NATIONAL CITY | K59: 91950 | L59: P84 | M59: P | N59: 990 | O59: 2023 | P59: 1549299 | Q59: 294867 | R59: 160384 | S59: 1549299 | T59: 0 | U59: 100 | V59: 3 | X59: 2 | Y59: 1 | Z59: 50000 | AA59: 2023 | AB59: $1M-$2M | AC59: 90-100% | AE59: 11 | AF59: 1 | AG59: 1 | AH59: 1 | AI59: 1 | AJ59: 1 | AK59: 1 | AL59: 1 | AM59: 1 | AS59: 0 | AT59: 0 | AU59: 0 | AV59: 0 | AW59: 1 | AX59: no | AY59: 0 | AZ59: 1
B60: 471000000 | C60: GLOBAL COMMUNITIES OF HOPE | D60: GUY EAST | E60: President | F60: 6194007254 | G60: www.globalcommunitiesofhope.org | H60: Global Communities of Hope partners with and provides support to entities that work in impoverished communities around the world. The Organization's mission is in seven key areas of need; food, water, shelter, health care, clothing, education and entrepreneurship. | I60: CA | J60: CHULA VISTA | K60: 91911 | L60: P60 | M60: P | N60: 990 | O60: 2023 | P60: 1883939 | Q60: 101180 | R60: 2948840 | S60: 1829342 | T60: 44697 | U60: 97.1 | V60: 0 | W60: 38 | X60: 0 | Y60: 0 | Z60: 0 | AB60: $1M-$2M | AC60: 90-100% | AE60: 11 | AF60: 1 | AG60: 0 | AH60: 1 | AI60: 1 | AJ60: 1 | AK60: 1 | AL60: 0 | AM60: 0 | AS60: 0 | AT60: 0 | AU60: 0 | AV60: 0 | AW60: 1 | AX60: no | AY60: 1 | AZ60: 1 | BA60: 0
B61: 845000000 | C61: HEALING GROVE HEALTH CENTER FOUNDATION INC | D61: BRETT BYMASTER | E61: EXECUTIVE DIRECTOR | F61: 4086487865 | H61: THE ORGANIZATIONS MISSION IS TO SHARE THE LOVE OF JESUS THROUGH HEALTH CARE, SOUL CARE, AND CULTURE CARE TO BRING THE HEALING OF NATIONS TO OUR COMMUNITY. | I61: CA | J61: SAN JOSE | K61: 95110 | L61: E80 | M61: E | N61: 990 | O61: 2023 | P61: 1902669 | Q61: 1648158 | R61: 2207525 | S61: 1593704 | T61: 308965 | U61: 83.76 | V61: 0 | X61: 0 | Y61: 0 | Z61: 0 | AB61: $1M-$2M | AC61: 75-90% | AD61: -4.9 | AE61: 11 | AF61: 1 | AG61: 0 | AH61: 1 | AI61: 1 | AJ61: 1 | AK61: 1 | AL61: 0 | AM61: 0 | AN61: 44196 | AO61: 25500 | AP61: 844000000 | AQ61: ANALOG DEVICES FOUNDATION | AR61: 1.3 | AS61: 1 | AT61: 0 | AU61: 0 | AV61: 0 | AW61: 0 | AX61: no | AY61: 1 | AZ61: 1
B62: 264000000 | C62: HMONG YOUTH AND PARENTS UNITED | D62: MAI YANG THOR | E62: EXECUTIVE DIRECTOR | F62: 9164184016 | G62: N/A | H62: HYPU MISSION IS TO EMPOWER UNDERSERVED COMMUNITIES BY OFFERING CULTURALLY SENSITIVE EDUCATIONAL, SOCIAL, AND ECONOMIC SERVICES AND RESOURCES TO YOUTH, ADULTS, AND PARENTS. | I62: CA | J62: SACRAMENTO | K62: 95815 | L62: P50 | M62: P | N62: 990 | O62: 2023 | P62: 1023111 | Q62: 1158505 | R62: 0 | S62: 1023111 | T62: 0 | U62: 100 | V62: 0 | W62: 50 | X62: 1 | Y62: 1 | Z62: 250 | AA62: 2022 | AB62: $1M-$2M | AC62: 90-100% | AE62: 11 | AF62: 1 | AG62: 0 | AH62: 1 | AI62: 1 | AJ62: 1 | AK62: 1 | AL62: 0 | AM62: 0 | AS62: 0 | AT62: 1 | AU62: 0 | AV62: 0 | AW62: 1 | AX62: no | AY62: 0 | AZ62: 1
B63: 801000000 | C63: Home Preservation & Prevention Inc | D63: KATHERINE PEOPLES MC GILL | E63: President & CEO | F63: 5622818861 | G63: HPPCARES.ORG | H63: HUD APPROVED HOUSING COUNSELING AGENCY PROVIDING FINANCIAL EDUCATION FOCUSED ON EFFECTIVE DEBT MANAGEMENT PROVIDNG CONSUMERS WITH TOOLS AND RESOURCES AND CREATING AFFORDABLE HOUSING OPPORTUNITIES TO BECOME POTENTIAL HOME BUYERS | I63: CA | J63: Long Beach | K63: 90808 | L63: P51 | M63: P | N63: 990 | O63: 2023 | P63: 1472787 | Q63: 1412782 | R63: 16634 | S63: 1436788 | T63: 35983 | U63: 97.56 | V63: 0 | W63: 24 | X63: 0 | Y63: 0 | Z63: 0 | AB63: $1M-$2M | AC63: 90-100% | AE63: 11 | AF63: 1 | AG63: 0 | AH63: 1 | AI63: 1 | AJ63: 1 | AK63: 1 | AL63: 0 | AM63: 0 | AS63: 0 | AT63: 0 | AU63: 0 | AV63: 0 | AW63: 1 | AX63: uncertain | AY63: 1 | AZ63: 1 | BA63: 1
B64: 861000000 | C64: HOMEBOY ART ACADEMY INC | D64: THOMAS VOZZO | E64: CEO | F64: 3235261254 | G64: N/A | H64: TO RELIEVE POVERTY AND DISTRESS OF THE UNDERPRIVILEGED, LESSEN NEIGHBOR TENSIONS, ELIMINATE PREJUDICE AND DISCRIMINATION, AND COMBAT COMMUNITY DETERIORATION IN LOW-INCOME AND UNDERSERVED COMMUNITIES THROUGH THE USE OF ART AND OTHER CREATIVE MEANS. THE ACTIVITIES ARE CONDUCTED BY THE EXECUTIVE DIRECTOR AT THE ART STUDIO, PROBATION CAMPS, AND CITY PARKS. HE SPENDS 100% OF THE TIME ON THESE ACTIVITIES. THE ACTIVITIES ARE FUNDED BY DONATION AND GRANTS AND 100% OF THE OVERALL EXPENSES ARE ALLOCATED TO THESE ACTIVITIES. THESE ACTIVITIES KEEP FORMERLY INCARCERATED GANG MEMBERS ACTIVE AND PRODUCTIVE MEMBERS OF THE COMMUNITY. | I64: CA | J64: LOS ANGELES | K64: 90012 | L64: P20 | M64: P | N64: 990 | O64: 2023 | P64: 1736497 | Q64: 925053 | R64: 1533915 | S64: 1710647 | T64: 0 | U64: 98.51 | V64: 0 | W64: 0 | X64: 3 | Y64: 2 | Z64: 100350 | AA64: 2023 | AB64: $1M-$2M | AC64: 90-100% | AD64: 297.4 | AE64: 11 | AF64: 1 | AG64: 0 | AH64: 1 | AI64: 1 | AJ64: 1 | AK64: 1 | AL64: 0 | AM64: 0 | AN64: 45291 | AO64: 100000 | AP64: 612000000 | AQ64: Snap Foundation | AR64: 5.8 | AS64: 1 | AT64: 0 | AU64: 0 | AV64: 0 | AW64: 1 | AX64: no | AY64: 0 | AZ64: 1
B65: 884000000 | C65: HOPE CENTER OF ORANGE COUNTY | F65: 6572537053 | G65: HTTPS://OCHOPECENTER.ORG/ | H65: TO BRING RELIABLE RELIEF AND CONSISTENT SUPPORT TO INDIVIDUALS EXPERIENCING HOMELESSNESS IN THE NORTH ORANGE COUNTY SERVICE PLANNING AREA (SPA). | I65: CA | J65: FULLERTON | K65: 92835 | L65: P85 | M65: P | N65: 990 | O65: 2022 | P65: 1274907 | Q65: 1196015 | R65: 78892 | S65: 1274907 | T65: 0 | U65: 100 | V65: 2 | W65: 0 | X65: 0 | Y65: 0 | Z65: 0 | AB65: $1M-$2M | AC65: 90-100% | AE65: 11 | AF65: 1 | AG65: 1 | AH65: 1 | AI65: 1 | AJ65: 1 | AK65: 1 | AL65: 1 | AM65: 1 | AS65: 0 | AT65: 0 | AU65: 0 | AV65: 0 | AW65: 0 | AX65: uncertain | AY65: 1 | AZ65: 1 | BA65: 0
B66: 844000000 | C66: INSTITUTE FOR ADVANCED CONSCIOUSNESS | D66: ALEXANDER SASHA BYSTRITSKY | E66: PRESIDENT | F66: 3109079216 | G66: WWW.ADVANCEDCONSCIOUSNESS.ORG | H66: THE INSTITUTE FOR ADVANCED CONSCIOUSNESS ("IACS OR ORGANIZATION") IS DEDICATED TO FURTHERING THE SCIENTIFIC UNDERSTANDING OF CONSCIOUSNESS. | I66: CA | J66: SANTA MONICA | K66: 90403 | L66: E05 | M66: E | N66: 990 | O66: 2023 | P66: 1252687 | Q66: 1319103 | R66: 641574 | S66: 1252687 | T66: 0 | U66: 100 | V66: 0 | W66: 18 | X66: 3 | Y66: 2 | Z66: 1592786 | AA66: 2023 | AB66: $1M-$2M | AC66: 90-100% | AD66: 77.5 | AE66: 11 | AF66: 1 | AG66: 0 | AH66: 1 | AI66: 1 | AJ66: 1 | AK66: 1 | AL66: 0 | AM66: 0 | AN66: 45291 | AO66: 304000 | AP66: 372000000 | AQ66: FOUNDERS PLEDGE INC | AR66: 24.3 | AS66: 1 | AT66: 0 | AU66: 0 | AV66: 0 | AW66: 1 | AX66: no | AY66: 0 | AZ66: 1 | BA66: 0
B67: 954000000 | C67: IRANIAN JEWISH FEDERATION | D67: ELHAM YAGOUBZADEH | E67: Vice President | F67: 3236544700 | G67: N/A | H67: PROVIDING CHARITABLE, FINANCIAL AND MEDICAL ASSISTANCE AND SERVICES TO OTHER CHARITABLE ORGANIZATIONS AND TO THE COMMUNITY MEMBERS WHO ARE IN CRITICAL NEED. | I67: CA | J67: LOS ANGELES | K67: 90046 | L67: P840 | M67: P | N67: 990 | O67: 2023 | P67: 1215911 | Q67: 809078 | R67: 2030339 | S67: 953944 | T67: 0 | U67: 78.46 | V67: 0 | X67: 1 | Y67: 1 | Z67: 5100 | AA67: 2023 | AB67: $1M-$2M | AC67: 75-90% | AD67: 136.5 | AE67: 11 | AF67: 1 | AG67: 0 | AH67: 1 | AI67: 1 | AJ67: 1 | AK67: 1 | AL67: 0 | AM67: 0 | AS67: 0 | AT67: 0 | AU67: 0 | AV67: 0 | AW67: 1 | AX67: no | AY67: 0 | AZ67: 1
B68: 822000000 | C68: JOSEPH MINISTRY INTERNATIONAL | D68: IVAN VENIKOV | E68: CEO / PRESIDENT | F68: 9166004454 | H68: TO PROVIDE ESSENTIAL HUMANITARIAN AID, INCLUDING FOOD, CLOTHING, MEDICAL SUPPLIES, AND TOYS, TO SUPPORT AND ASSIST MISSIONS IN THE FORMER SOVIET UNION, FOCUSING ON AIDING NEEDY CHILDREN AND INDIVIDUALS. | I68: CA | J68: ORANGEVALE | K68: 95662 | L68: P20 | M68: P | N68: 990 | O68: 2024 | P68: 1593741 | Q68: 1630165 | R68: 15234 | S68: 1593741 | T68: 0 | U68: 100 | V68: 0 | W68: 214 | X68: 0 | Y68: 0 | Z68: 0 | AB68: $1M-$2M | AC68: 90-100% | AE68: 11 | AF68: 1 | AG68: 0 | AH68: 1 | AI68: 1 | AJ68: 1 | AK68: 1 | AL68: 0 | AM68: 0 | AS68: 0 | AT68: 0 | AU68: 0 | AV68: 0 | AW68: 1 | AX68: uncertain | AY68: 1 | AZ68: 1
B69: 320000000 | C69: KARIMU INTERNATIONAL HELP FOUNDATION | D69: MARIANNE KENT-STOLL | E69: President | F69: 9516592171 | G69: KARIMUFOUNDATION.ORG | H69: The organization aims to provide funds for, and help execute, completion of schools and other community projects enhancing the well-being of rural villages in the developing world. | I69: CA | J69: PALM DESERT | K69: 92211 | L69: P80 | M69: P | N69: 990 | O69: 2022 | P69: 1286390 | Q69: 1976320 | R69: 275701 | S69: 1286390 | T69: 0 | U69: 100 | V69: 0 | W69: 56 | X69: 1 | Y69: 1 | Z69: 5650 | AA69: 2023 | AB69: $1M-$2M | AC69: 90-100% | AD69: 15.1 | AE69: 11 | AF69: 1 | AG69: 0 | AH69: 1 | AI69: 1 | AJ69: 1 | AK69: 1 | AL69: 0 | AM69: 0 | AS69: 0 | AT69: 0 | AU69: 0 | AV69: 0 | AW69: 1 | AX69: no | AY69: 0 | AZ69: 1 | BA69: 1
B70: 365000000 | C70: Kern Medical Center Foundation | F70: 6618683817 | G70: kernmedicalfoundation.com | H70: KERN MEDICAL CENTER FOUNDATION IS DEDICATED TO PROMOTE EDUCATION AND PROGRAMS THAT SUPPORT THE MISSION OF KERN MEDICAL CENTER | I70: CA | J70: Bakersfield | K70: 93306 | L70: E112 | M70: E | N70: 990 | O70: 2023 | P70: 1643341 | Q70: 592407 | R70: 5121264 | S70: 1569449 | T70: 0 | U70: 95.5 | V70: 0 | X70: 0 | Y70: 0 | Z70: 0 | AB70: $1M-$2M | AC70: 90-100% | AD70: -1.3 | AE70: 11 | AF70: 1 | AG70: 0 | AH70: 1 | AI70: 1 | AJ70: 1 | AK70: 1 | AL70: 0 | AM70: 0 | AN70: 43830 | AO70: 7500 | AP70: 201000000 | AQ70: THE BANK OF AMERICA CHARITABLE | AR70: 0.5 | AS70: 1 | AT70: 0 | AU70: 0 | AV70: 0 | AW70: 1 | AX70: no | AY70: 1 | AZ70: 1 | BA70: 1
B71: 955000000 | C71: Kkottongnae Inc | D71: Woong Jin Oh | E71: CEO | F71: 3107645331 | G71: N/A | H71: Charitable Purpose: To provide Joy, Peace and Hope to the Helpless who have no strength to beg, and who suffer from Hunger for Love rather than for Bread. | I71: CA | J71: Lynwood | K71: 90262 | L71: P20 | M71: P | N71: 990 | O71: 2024 | P71: 1215063 | Q71: 804452 | R71: 10348025 | S71: 1138356 | T71: 0 | U71: 93.69 | V71: 0 | W71: 20 | X71: 3 | Y71: 2 | Z71: 140000 | AA71: 2022 | AB71: $1M-$2M | AC71: 90-100% | AD71: -39.7 | AE71: 11 | AF71: 1 | AG71: 0 | AH71: 1 | AI71: 1 | AJ71: 1 | AK71: 1 | AL71: 0 | AM71: 0 | AS71: 0 | AT71: 0 | AU71: 0 | AV71: 0 | AW71: 1 | AX71: no | AY71: 0 | AZ71: 1
B72: 465000000 | C72: Korean American Community Foundation | D72: So Yong Park | E72: Director | F72: 6506565705 | G72: www.kacfsf.org | H72: The Korean American Community Foundation of San Francisco uplifts and connects the Korean-American community through philanthropy. | I72: CA | J72: San Jose | K72: 95128 | L72: P80 | M72: P | N72: 990 | O72: 2023 | P72: 1144451 | Q72: 915496 | R72: 2913898 | S72: 1365999 | T72: 0 | U72: 119.36 | V72: 3 | W72: 60 | X72: 1 | Y72: 1 | Z72: 2500 | AA72: 2023 | AB72: $1M-$2M | AC72: 90-100% | AE72: 11 | AF72: 1 | AG72: 1 | AH72: 1 | AI72: 1 | AJ72: 1 | AK72: 1 | AL72: 0 | AM72: 0 | AN72: 45291 | AO72: 2500 | AP72: 881000000 | AQ72: MAKAHAKAMA FOUNDATION | AR72: 0.2 | AS72: 1 | AT72: 0 | AU72: 0 | AV72: 0 | AW72: 1 | AX72: no | AY72: 0 | AZ72: 1 | BA72: 1
B73: 842000000 | C73: LADMC FOUNDATION | D73: William Nelson | E73: Board Member President | F73: 6263310781 | G73: N/A | H73: LADMC FOUNDATIONS GOAL IS TO TRAIN LOS ANGELES COUNTY NURSES IN LEADERSHIP AND HEALTH CARE, AND TO PROMOTE HEALTH AND WELLNESS EDUCATION TO COMMUNITIES AND NEIGHBORHOODS THROUGHOUT THE LOS ANGELES REGION. | I73: CA | J73: LOS ANGELES | K73: 90026 | L73: E70 | M73: E | N73: 990 | O73: 2024 | P73: 1460775 | Q73: 784802 | R73: 3963066 | S73: 1460775 | T73: 0 | U73: 100 | V73: 3 | W73: 1 | X73: 1 | Y73: 1 | Z73: 2500 | AA73: 2023 | AB73: $1M-$2M | AC73: 90-100% | AD73: 5.1 | AE73: 11 | AF73: 1 | AG73: 1 | AH73: 1 | AI73: 1 | AJ73: 1 | AK73: 1 | AL73: 1 | AM73: 1 | AS73: 0 | AT73: 0 | AU73: 0 | AV73: 0 | AW73: 1 | AX73: no | AY73: 0 | AZ73: 1
B74: 832000000 | C74: LEADING WOMEN DEFINED FOUNDATION | D74: GABRIELLE GLORE | E74: EXECUTIVE DIRECTOR | F74: 3104784148 | G74: N/A | H74: THE LEADING WOMEN DEFINED FOUNDATION IS AN ORGANIZATION DEDICATED TO THE EMPOWERMENT OF BLACK AND BROWN WOMEN THROUGH CONTINUING EDUCATION, THOUGHT LEADERSHIP, AND SISTERHOOD. ESTABLISHED TO ADDRESS A RANGE OF ISSUES CENTRAL TO THIS AUDIENCE, LWD FOCUSES ON PROFESSIONAL ADVANCEMENT, PERSONAL HEALTH AND WELLNESS, AND COLLECTIVE COMMUNITY IMPACT. | I74: CA | J74: LOS ANGELES | K74: 90025 | L74: P80 | M74: P | N74: 990 | O74: 2023 | P74: 1846931 | Q74: 1630570 | R74: 1562018 | S74: 1585938 | T74: 254500 | U74: 85.87 | V74: 2 | W74: 3 | X74: 0 | Y74: 0 | Z74: 0 | AB74: $1M-$2M | AC74: 75-90% | AD74: 12.7 | AE74: 11 | AF74: 1 | AG74: 1 | AH74: 1 | AI74: 1 | AJ74: 1 | AK74: 1 | AL74: 0 | AM74: 0 | AS74: 0 | AT74: 0 | AU74: 0 | AV74: 0 | AW74: 1 | AX74: no | AY74: 1 | AZ74: 1
B75: 873000000 | C75: LIFELINE INSTITUTE INC | D75: Rick Martinez | E75: President | F75: 7607264900 | G75: N/A | H75: THE ORGANIZATION IS A COMMUNITY-BASED ORGANIZATION DEDICATED TO CHARITABLE PURPOSES. THE ORGANIZATION PROVIDES REAL AND PERSONAL PROPERTIES FOR THE USE AND ENJOYMENT OF OTHER NONPROFIT PUBLIC BENEFIT ORGANIZATIONS AND IS DEDICATED TO REDUCING THE BURDENS OF GOVERNMENT AND SERVING THE POOR, DISTRESSED AND UNDERPRIVILEGED POPULATIONS IN SAN DIEGO COUNTY. | I75: CA | J75: VISTA | K75: 92084 | L75: P11 | M75: P | N75: 990 | O75: 2022 | P75: 1588411 | Q75: 29293 | R75: 1569021 | S75: 1567469 | T75: 0 | U75: 98.68 | V75: 0 | X75: 0 | Y75: 0 | Z75: 0 | AB75: $1M-$2M | AC75: 90-100% | AE75: 11 | AF75: 1 | AG75: 0 | AH75: 1 | AI75: 1 | AJ75: 1 | AK75: 1 | AL75: 0 | AM75: 0 | AS75: 0 | AT75: 0 | AU75: 0 | AV75: 0 | AW75: 0 | AX75: uncertain | AY75: 1 | AZ75: 1
B76: 312000000 | C76: LOS ANGELES COMMUNITY GARDEN COUNCIL | D76: DIANA CAMPOS JIMENEZ | E76: INTERIM EXECUTIVE DIRECTOR | F76: 3239027167 | G76: WWW.LAGARDENCOUNCIL.ORG | H76: TO STRENGTHEN COMMUNITIES BY BUILDING AND SUPPORTING COMMUNITY GARDENS WHERE PEOPLE CAN GROW HEALTHY FOOD IN THEIR NEIGHBORHOOD. | I76: CA | J76: LOS ANGELES | K76: 90029 | L76: P80 | M76: P | N76: 990 | O76: 2023 | P76: 1009457 | Q76: 680185 | R76: 1749411 | S76: 1009457 | T76: 0 | U76: 100 | V76: 1 | W76: 0 | X76: 3 | Y76: 3 | Z76: 65150 | AA76: 2023 | AB76: $1M-$2M | AC76: 90-100% | AD76: 131.7 | AE76: 11 | AF76: 1 | AG76: 1 | AH76: 1 | AI76: 1 | AJ76: 1 | AK76: 1 | AL76: 1 | AM76: 1 | AN76: 45291 | AO76: 50000 | AP76: 236000000 | AQ76: THE ANNENBERG FOUNDATION | AR76: 5 | AS76: 1 | AT76: 0 | AU76: 0 | AV76: 0 | AW76: 1 | AX76: no | AY76: 0 | AZ76: 1 | BA76: 0
B77: 845000000 | C77: MARTA ELIZA MILLERFOUNDATION | D77: MARTA MILLER | E77: President | F77: 8189806888 | H77: To create support and education for scoliosis awareness, especially when it affects young athletes with a desire to be strong, stand tall and not be affected mentally by the physical challenges scoliosis can sometimes create. | I77: CA | J77: Studio City | K77: 91604 | L77: P99 | M77: P | N77: 990 | O77: 2024 | P77: 1003049 | Q77: 93158 | R77: 918109 | S77: 1002987 | T77: 0 | U77: 99.99 | V77: 0 | W77: 2 | X77: 0 | Y77: 0 | Z77: 0 | AB77: $1M-$2M | AC77: 90-100% | AE77: 11 | AF77: 1 | AG77: 0 | AH77: 1 | AI77: 1 | AJ77: 1 | AK77: 1 | AL77: 0 | AM77: 0 | AS77: 0 | AT77: 0 | AU77: 0 | AV77: 0 | AW77: 1 | AX77: no | AY77: 1 | AZ77: 1
B78: 832000000 | C78: Meaning Foundation | D78: TAYLOR P ADAMS | E78: CHIEF EXECUTIVE OFFICER | F78: 5622858303 | H78: The Meaning Foundation the Organization or TMF is a non-profit organization committed to eliminating barriers to meaningful employment for the formerly incarcerated. We believe that adaptive combination of foundation healing workforce development and meaningful employment is the most powerful mechanism for enabling long-term human transformation and multi-generational socioeconomic impact. | I78: CA | J78: Los Angeles | K78: 90017 | L78: P99 | M78: P | N78: 990 | O78: 2023 | P78: 1652418 | Q78: 671648 | R78: 1089120 | S78: 1651756 | T78: 0 | U78: 99.96 | V78: 0 | W78: 1 | X78: 1 | Y78: 1 | Z78: 150000 | AA78: 2023 | AB78: $1M-$2M | AC78: 90-100% | AD78: 1520 | AE78: 11 | AF78: 1 | AG78: 0 | AH78: 1 | AI78: 1 | AJ78: 1 | AK78: 1 | AL78: 0 | AM78: 0 | AS78: 0 | AT78: 0 | AU78: 0 | AV78: 0 | AW78: 1 | AX78: yes | AY78: 0 | AZ78: 1
B79: 770000000 | C79: MEDICAL MINISTRIES INTERNATIONAL | D79: RALPH HANDLY OD | E79: President | F79: 5593241255 | G79: https://www.medministries.org/ | H79: TO PROVIDE A CHRISTIAN OUTREACH MINISTRY BY PROVIDING MEDIAL CARE NOT OBTAINABLE IN CERTAIN REGIONS OF THE WORLD. TO PROVIDE MEDICAL EQUIPMENT AND SUPPLIES TO CLINICS AND HOSPITALS WHERE THE NEED HAS BEEN IDENTIFIED. TO COORDINATE AND SEND CONSTRUCTION TEAMS TO WORK ON CILNICS AND HOSPITALS. | I79: CA | J79: FRESNO | K79: 93721 | L79: P20 | M79: P | N79: 990 | O79: 2023 | P79: 1909020 | Q79: 1991563 | R79: 1643605 | S79: 1872282 | T79: 0 | U79: 98.08 | V79: 3 | X79: 1 | Y79: 1 | Z79: 50000 | AA79: 2023 | AB79: $1M-$2M | AC79: 90-100% | AD79: -3.9 | AE79: 11 | AF79: 1 | AG79: 1 | AH79: 1 | AI79: 1 | AJ79: 1 | AK79: 1 | AL79: 1 | AM79: 1 | AS79: 0 | AT79: 0 | AU79: 0 | AV79: 0 | AW79: 1 | AX79: no | AY79: 0 | AZ79: 1 | BA79: 1
B80: 814000000 | C80: MERCY COALITION OF WEST SACRAMENTO | F80: 9165093566 | G80: https://wsmercycoalition.org/ | H80: The Mercy Coalition exiss as an expression of tangible and intangible embrace to those impacted by homelessness and poverty in West Scaramento. We are a diverse and inclusive interfaith collaborative, mobilized for works of compassion and empowerment, holding reverence and worth for each individual and the story they're in. | I80: CA | J80: WEST SACRAMENTO | K80: 95691 | L80: P85 | M80: P | N80: 990 | O80: 2024 | P80: 1135529 | Q80: 1029597 | R80: 318286 | S80: 1093728 | T80: 0 | U80: 96.32 | V80: 0 | X80: 0 | Y80: 0 | Z80: 0 | AB80: $1M-$2M | AC80: 90-100% | AE80: 11 | AF80: 1 | AG80: 0 | AH80: 1 | AI80: 1 | AJ80: 1 | AK80: 1 | AL80: 0 | AM80: 0 | AS80: 0 | AT80: 0 | AU80: 0 | AV80: 0 | AW80: 0 | AX80: uncertain | AY80: 1 | AZ80: 1 | BA80: 1
B81: 770000000 | C81: MERCY MEDICAL CENTER MERCED FOUNDATION | D81: Jacob McDougal | E81: Executive Director | F81: 2093846734 | G81: WWW.SUPPORTMERCYMERCED.ORG | H81: TO PROVIDE FINANCIAL ASSISTANCE AND SUPPORTING SERVICES FOR DIGNITY HEALTH (DBA: MERCY MEDICAL CENTER MERCED). THE FINANCIAL SUPPORT PROVIDED BY THE FOUNDATION CONTRIBUTES TO THE HOSPITAL'S MISSION BY MAKING THE HEALING PRESENCE OF GOD KNOWN IN OUR WORLD BY IMPROVING THE HEALTH OF THE PEOPLE WE SERVE, ESPECIALLY THOSE WHO ARE VULNERABLE, WHILE WE ADVANCE SOCIAL JUSTICE FOR ALL. | I81: CA | J81: MERCED | K81: 95340 | L81: E11 | M81: E | N81: 990 | O81: 2022 | P81: 1425915 | Q81: 1751064 | R81: 2971106 | S81: 1384796 | T81: 0 | U81: 97.12 | V81: 0 | W81: 75 | X81: 1 | Y81: 1 | Z81: 10000 | AA81: 2022 | AB81: $1M-$2M | AC81: 90-100% | AD81: -38.2 | AE81: 11 | AF81: 1 | AG81: 0 | AH81: 1 | AI81: 1 | AJ81: 1 | AK81: 1 | AL81: 0 | AM81: 0 | AS81: 0 | AT81: 0 | AU81: 0 | AV81: 0 | AW81: 0 | AX81: yes | AY81: 0 | AZ81: 1 | BA81: 1
B82: 873000000 | C82: MILLION DOLLAR VEGAN INC | D82: NAOMI HALLUM | E82: CEO | F82: 7578372276 | G82: HTTPS://GENV.ORG | H82: TO EDUCATE ABOUT THE ENVIRONMENTAL, ETHICAL, PERSONAL, AND PUBLIC HEALTH BENEFITS OF A PLANT-BASED LIFESTYLE AND TO PROVIDE GUIDANCE, SUPPORT, AND FREE PLANT-BASED MEALS TO ESSENTIAL WORKERS AND UNDERSERVED COMMUNITIES. | I82: CA | J82: SANTA BARBARA | K82: 931000000 | L82: P20 | M82: P | N82: 990 | O82: 2023 | P82: 1784563 | Q82: 1858932 | R82: 184192 | S82: 1784563 | T82: 0 | U82: 100 | V82: 2 | W82: 0 | X82: 0 | Y82: 0 | Z82: 0 | AB82: $1M-$2M | AC82: 90-100% | AE82: 11 | AF82: 1 | AG82: 1 | AH82: 1 | AI82: 1 | AJ82: 1 | AK82: 1 | AL82: 1 | AM82: 1 | AS82: 0 | AT82: 0 | AU82: 0 | AV82: 0 | AW82: 1 | AX82: uncertain | AY82: 1 | AZ82: 1 | BA82: 0
B83: 452000000 | C83: MIRAGLO FOUNDATION | D83: CATHERINE WENUK | E83: BOARD DIRECTOR | F83: 8584596919 | G83: WWW.MIRAGLOFOUNDATION.ORG | H83: MIRAGLO FOUNDATION HAS SEVEN SPECIFIC PURPOSES: (1) TO CONDUCT RESEARCH AND/OR SUPPORT RESEARCH ABOUT ALTERNATIVE HEALING TECHNIQUES AND GLOBAL HEALING TRADITIONS;(2) TO PROVIDE EDUCATION ABOUT AND INCREASE AWARENESS OF ALTERNATIVE HEALING TECHNIQUES AND GLOBAL HEALING TRADITIONS; (3) TO MAKE GRANTS TO MEDICAL PERSONNEL(INCLUDING BOTH CONVENTIONAL AND ALTERNATIVE PRACTICES) TO ASSIST IN SERVING UNDER-SERVED COMMUNITIES, BOTH NATIONALLY AND INTERNATIONALLY; (4) TO MAKE GRANTS IN SUPPORT OF MEDICAL SERVICES AND FACILITIES (INCLUDING BOTH CONVENTIONAL AND ALTERNATIVE PRACTICES) IN UNDER-SERVED COMMUNITIES, BOTH NATIONALLY AND INTERNATIONALLY; (5) TO AWARD SCHOLARSHIPS AND GRANTS TO AND/OR FOR EDUCATIONAL PROGRAMS, SCHOOLS AND INDIVIDUALS IN UNDER-SERVED COMMUNITIES, BOTH NATIONALLY AND INTERNATIONALLY; (6) TO MAKE QUALIFYING DISTRIBUTIONS AND EXPENDITURES DIRECTLY FOR THE ACTIVE CONDUCT OF AND/OR FOR THE SUPPORT OF ACTIVIES CONSTITUTING THE PURPOSES FOR WHICH THIS CORPORATION IS ORGANIZED | I83: CA | J83: LA JOLLA | K83: 92038 | L83: E60 | M83: E | N83: 990 | O83: 2023 | P83: 1056886 | Q83: 753085 | R83: 806731 | S83: 1033762 | T83: 20048 | U83: 97.81 | V83: 0 | W83: 2 | X83: 2 | Y83: 2 | Z83: 60000 | AA83: 2022 | AB83: $1M-$2M | AC83: 90-100% | AD83: 78.7 | AE83: 11 | AF83: 1 | AG83: 0 | AH83: 1 | AI83: 1 | AJ83: 1 | AK83: 1 | AL83: 0 | AM83: 0 | AN83: 44926 | AO83: 10000 | AP83: 364000000 | AQ83: MARGOT & THOMAS PRITZKER FAMILY | AR83: 0.9 | AS83: 1 | AT83: 0 | AU83: 0 | AV83: 0 | AW83: 1 | AX83: no | AY83: 0 | AZ83: 1 | BA83: 0
