Workbook

Sheet Calls
B2: Org | C2: Priority | D2: Date Contacted | E2: Phone | F2: Contact | G2: Title | H2: Email | I2: State | J2: Timezone | K2: Dependents | L2: EIN | M2: Rating | N2: Website | O2: About | P2: Sunsetting | Q2: Segment | R2: Org Type | S2: Outcome | T2: Call Notes
B3: ERB FAMILY FOUNDATION | C3: 200 | D3: 46029 | E3: 248-498-2503 | F3: Tara Tuomaala | G3: Vice President of Programs | H3: ttuomaala@erbff.org | I3: MI | J3: #N/A | K3: 0 | L3: 205966333 | M3: 1.5 Sunsetting | O3: SE Michigan/Detroit focus. Funds arts/culture, democracy, sustainable business. Full staff with direct emails. Spending down by 2034 - grantees need help. | P3: 2034 | R3: Foundation | S3: 5. Interested | T3: 1/7 - VM 1/9 - Tara tuomaala at Erb Family Foundation called back – she said they do give out capacity building grant service things and that I can send info and she’d have people take a look at it. Then I asked if I could share what we do. She asked some great questions like: What size nonprofit 500K-2M (or bigger if they have regional offices) - What type of nonprofito Education, health, art- Geographically specific? o Yes, lots of smaller nonprofits who could benefit from local partnerships - How is it different from Candid(I think that’s what it’s called) where someone does research o Predictive modeling and time saved doing research...I also told her about the pilot idea and sending a list of who we recommend they offer it to as well as the price point (she seemed completely unquestionably unphased)..She said to send the stuff and I said I’d send the one pager, the example report, and the list of nonprofits we recommend should use our service 2/9 - called, left VM. Sent follow up email
B4: VetsBoats | C4: =_xlfn.XLOOKUP(Table1[[#This Row],[EIN]],Sheet5!#REF!,Sheet5!#REF!) -> #REF! | D4: 46029 | E4: 720.473.3844 | F4: Matt Goettelman | H4: matt.goettelman@vetsboats.org | I4: CA | J4: Pacific | R4: Nonprofit | S4: 5. Interested | T4: 1/7 - Alec requested Matt complete a questionnaire and submit payment to receive a first report by January 1st. Matt confirmed he would complete the questionnaire and submit payment information later that night. Alec confirmed receiving the survey but noted payment had not processed, then Matt requested a sample report before committing to annual billing.
B5: Aspiriant | D5: 46027 | E5: 650 305 3481 | F5: Talia Pierluissi | G5: Director - Wealth Management | I5: CA | J5: Pacific | M5: 1. Excellent | O5: Ex-Stanford dev | Q5: Foundation Management | R5: MFO | S5: 4. Reached Decision Maker | T5: 1/5 - Connected to her VM, she called back and gave her email. I sent her an email about what we do asking to meet. tpierluissi@aspiriant.com 1/7 - Called, left voicemail -- Need to send list of foundation recommendatins like i did with Jesse 2/9 - Called, left VM, sent follow up text - she responded and said that she's not involved in this type of work
B6: Mt Sinai Health Care Foundation | D6: 46027 | E6: (216) 421-5500 | F6: Mitch Balk | G6: President | I6: OH | J6: 0 | O6: Improving health and well being of Jewish and general communities in Cleveland. | Q6: Nonprofit | R6: Foundation | S6: 4. Reached Decision Maker | T6: 1/5 - Told me their actually a foundation and that they do capacity building 1/7 - Called, was in meeting. Do some research on them and then call back. 1/9 - Called, didn't give me the option to leave a VM
B7: THE COLLINS FOUNDATION | D7: 46029 | E7: 503-227-7171 | F7: Kymberli Contreras | G7: Executive Administrator | H7: kcontreras@collinsfoundation.org | J7: Pacific | K7: 200 | L7: 936021893 | M7: 1.Excellent | O7: 50 Oregon community nonprofits. $10M/year grantmaking. $310M+ awarded since 1947. Professional staff with direct contact. | R7: Foundation | S7: 4. Reached Decision Maker | T7: 1/7 - She thought I wanted to be their data guy, then she thought I was tech, then she understood what I was saying and said send a one pager (though they just did the budget and she wasn't sure how much they have ) she gets back into town next week (is gone the rest of this week) 1/9 - left VM (her extension is 1014), Sent email
B8: THE DYSON FOUNDATION | C8: =_xlfn.XLOOKUP(Table1[[#This Row],[EIN]],Sheet5!#REF!,Sheet5!#REF!) -> #REF! | D8: 46029 | E8: 845-790-6321 | F8: Andrea L. Reynolds | G8: Director of Programs | H8: cstancell@dyson.org | I8: NY | J8: Eastern | K8: 36 | L8: 136084888 | M8: 1.Excellent | O8: CEO: Andrea L. Reynolds areynolds@dyson.org 845-790-6321. Program Officers: Jennifer Drake jdrake@dyson.org, Jennifer Killian jkillian@dyson.org. 25 Halcyon Road, Millbrook, NY 12545. General: 845-677-0644. | R8: Foundation | S8: 4. Reached Decision Maker | T8: 1/7 - Left VM 1/8 - Andrea called back. She said she wasn't sure this would be something they would do for their grantees but if their grantees approached them asking for it then they'd consider it that way. I asked if she would mind looking through a list of grantees they have who might benefit and share her thoughts on if it would actually be helpful or not (pushed that the feedback itself is super helpful) she said sure. She also mentioned that a problem they have is that they get applications from people that are totally unqualified and it wastes their time. I askwed if I could share what we do and she said no just send it in the email. I said I'd put it in the email and call back in a week. 1/9 - Left VM
B9: The William & Flora Hewlett Foundation | D9: 46027 | E9: (650) 234-4500 ext 4769 | F9: Jennifer Wei | G9: Director, Effective Philanthropy Group | I9: CA | J9: Pacific | L9: 941655673 | M9: 2. Good | N9: https://hewlett.org/about-us/people/ | O9: Portland, OR; Oregon-focused grantmaking | Q9: Foundation | R9: Foundation | S9: 4. Reached Decision Maker | T9: 1/5 - She thought I was calling to tell her that her raising Cane's order was ready. she said she want sure because they don't have open applications. I told her it was actually so that their nonprofits could find other foundations and become less dependent just in them. she gave me her email and said to shoot over the info 1/7 - Called, no answer and no option for VM 1/8 - Hi Alec, Thank you for the follow-up information – it’s helpful to see the summary info as well as the sample report. I appreciate what you’re doing to help the nonprofit sector especially during a time of significant government funding cuts! We are not in a position to make any new investments at this time as our funds are already allocated for the year, but I’ve shared this with some colleagues to put on their radars. I’d be interested to hear how you’re doing later this year – perhaps check back in the summer or fall. Thanks again for reaching out! Best, Jennifer
B10: Whittier Trust | D10: 46027 | E10: 626-441-5111 | F10: Jesse Ostroff | G10: VP - Philanthropic Services | I10: CA | J10: #N/A | M10: 1.Excellent | O10: YOUR CONTACT | Q10: Foundation Management | R10: MFO | S10: 4. Reached Decision Maker | T10: 12/23 - He said it sounded interesting and liked that it would encourage nonprofits to reach out to more applicable foundations (sounds like they get a lot of random applicants who don't qualify. Sent one pager and sample report 1/7 - Called left VM 1/9 - Called left VM
C11: =_xlfn.XLOOKUP(Table1[[#This Row],[EIN]],Sheet5!#REF!,Sheet5!#REF!) -> #REF! | D11: 46027 | F11: Bri | G11: Owner | S11: 4. Reached Decision Maker
B12: BBR Partners | D12: 46027 | E12: 212-313-9870 | F12: Stephanie Diamond | G12: Director of Strategic Philanthropy | I12: NY | J12: 0 | O12: Ex-Schwab Charitable | Q12: Foundation Management | R12: MFO | S12: 3. Talked to Someone | T12: She said she'd let Stephanie know I called
B13: Chilton Trust | D13: 46027 | E13: 212-843-6882 | F13: David Hamar (Hey mar) | G13: Philanthropy Advisory | I13: NY | J13: 0 | O13: 96% capacity grants! | Q13: Foundation Management | R13: MFO | S13: 3. Talked to Someone | T13: She said if I don't have a name she won't connect me with someone but she took a message
B14: El Pomar Foundation | D14: 46027 | E14: (719) 633-7733 | F14: Matt Carpenter | G14: EVP & COO | I14: CO | J14: #N/A | L14: 846002373 | M14: 2. Good | N14: https://elpomar.org/about-us/leadership/ | O14: President: Tonya Allen; ~70 staff; Stephanie Duffy (Dir. Grants & Program Ops) | Q14: Foundation | R14: Foundation | S14: 3. Talked to Someone | T14: Reached Ellen P. who may be the secretary for Matt Carpenter. she gave me an email so I can send her our blurb and then she'd see if Matt's the right guy to talk to Ellenp20@elpomar.org
B15: HEADWATERS HEALTH FOUNDATION | C15: =_xlfn.XLOOKUP(Table1[[#This Row],[EIN]],Sheet5!#REF!,Sheet5!#REF!) -> #REF! | D15: 46031 | E15: (406) 926-6526 | F15: Erin Switalski | G15: Staff (Program Leadership) | I15: MT | J15: Mountain | K15: 29 | L15: 811099715 | M15: 1.Excellent | O15: 20+ years nonprofit experience. Montana/human rights/housing/environmental health. Founding CEO Brenda Solorzano left to lead CA Endowment. 725 W Central Ave Ste 210, Missoula MT 59801. | R15: Foundation | S15: 3. Talked to Someone
B16: Kashif Incubator | D16: 46027 | E16: (917) 282-1903 | F16: Chanelle Elaine | G16: President | I16: NY | J16: 0 | O16: Original pathways into filmmaking through equity-access practices. | Q16: Nonprofit | R16: Nonprofit | S16: 3. Talked to Someone | T16: Veronicas personal cell. call her next week(they're off this week) she didn't seem to mind that I accidentally called her cell
B17: O.L. Halsell Foundation | D17: 46027 | F17: W. David Stauffer Jr. | G17: President | H17: mroach@ncousa.com | I17: CA | J17: #N/A | L17: 956027266 | M17: 2. Good | R17: Foundation | S17: 3. Talked to Someone | T17: Email is from their CPA and is for Morgan Roach
B18: Oxford Financial | D18: 46027 | E18: 317-843-5678 | F18: Michele Hargis CAP | G18: Managing Director | I18: IN | J18: 0 | O18: CAP designation | Q18: Foundation Management | R18: MFO | S18: 3. Talked to Someone | T18: She's not involved in that and said to call back after 3:30 and she can find out who the right person is to talk to.
B19: PRICE PHILANTHROPIES FOUNDATION | C19: =_xlfn.XLOOKUP(Table1[[#This Row],[EIN]],Sheet5!#REF!,Sheet5!#REF!) -> #REF! | D19: 46031 | E19: (619) 795-2000 | F19: Sakara Tear | G19: Senior Director of Community Initiatives | H19: stear@pricephilanthropies.org | I19: CA | J19: Pacific | K19: 36 | L19: 465129465 | M19: 1.Excellent | O19: 93% capacity; grantees are small City Heights nonprofits who need funding diversification | R19: Foundation | S19: 3. Talked to Someone | T19: ckam@pricephilanthropies.org - talked to Christina and she took a message for Sakara and gave me her email so I can forward a little shpeal about us.
B20: Seven Acres Foundation | D20: 46027 | E20: (509) 670-9058 | F20: Maribel Cruz | G20: Executive Director | I20: WA | J20: #N/A | O20: Fund and construct the Community Center at Lake Chelan. | Q20: Nonprofit | R20: Nonproft | S20: 3. Talked to Someone | T20: Shoot her an email at maribel@chelancommunity.org-Ben 1/9 - called, apparently the number goes to Bens personal cell. He told me to email Maribel
B21: THE RALPH C WILSON JR FOUNDATION | C21: =_xlfn.XLOOKUP(Table1[[#This Row],[EIN]],Sheet5!#REF!,Sheet5!#REF!) -> #REF! | E21: 313-885-1895 | F21: Amber Slichta | G21: Vice President of Programs | H21: info@rcwjrf.org | I21: MI | J21: #N/A | K21: 63 | L21: 450921232 | M21: 1.Excellent | O21: Also: David Egner (President/CEO), Maura Dewan (VP Programs & Corporate Affairs), Jim Boyle (VP Programs & Strategy). 27 full-time staff. $1.2B over 20 years expiring Jan 2035. Focus: SE Michigan and Western NY. | P21: Sunsetting | R21: Foundation | S21: 3. Talked to Someone | T21: Taked to Maria (Suchyta?) She said they're a spend down foundation ending at the end of 2038. I mentioned it could be helpful for their grantees so they can get funding after their gone. She got my info and said to send more info
B22: THE ROUNDHOUSE FOUNDATION | D22: 46029 | E22: 541-904-0700 | F22: Erin Borla | G22: Executive Director & Trustee | H22: emily@roundhousefoundation.org | J22: Pacific | K22: 91 | L22: 226930631 | M22: 1.Excellent | O22: 91 dependent grantees (rural Oregon nonprofits). 6 CB service grants including strategic planning and technical assistance. Professional staff with direct emails on website. | R22: Foundation | S22: 3. Talked to Someone | T22: Talked to Emily, she said I put it simply and had me send an email.
B23: Acton School of Business | D23: 46027 | E23: (512) 695-2954 | F23: Chris Coggin | G23: President/CEO | I23: TX | J23: #N/A | K23: 0 | O23: Preparing entrepreneurs and world changers ages 6-66 using learner-driven approach. | Q23: Nonprofit | R23: Education | S23: 2. VM
B24: AlTi Tiedemann | D24: 46027 | E24: 212-396-5900 | F24: Jill Shipley | G24: Managing Director | I24: NY | J24: #N/A | K24: 0 | O24: Philanthropy curriculum | Q24: Foundation Management | R24: MFO | S24: 2. VM
B25: Ann Jackson Family Foundation | D25: 46027 | E25: (805) 969-2258 | F25: Palmer Jackson Jr. | G25: Managing Trustee | H25: palmer.jackson@gmail.com | I25: CA | J25: #N/A | L25: 953367511 | M25: 1. Excellent | O25: Santa Barbara based | S25: 2. VM
B26: Aspen Art Museum Foundation | D26: 46027 | E26: (970) 925-8050 | F26: Nicola Lees | G26: Artistic Director and CEO | I26: CO | J26: 0 | O26: Endowment fund for Aspen Art Museum. | Q26: Nonprofit | R26: Arts & Culture | S26: 2. VM
B27: Bay Education Fund | D27: 46027 | E27: (650) 204-0575 | F27: Tammy Crown | G27: President | I27: CA | J27: 0 | O27: Community investment fund transforming district capacity with families and teachers. | Q27: Nonprofit | R27: Education | S27: 2. VM
B28: Better Angels United | D28: 46027 | E28: (213) 293-6950 | F28: Adam Miller | G28: Director/President | I28: CA | J28: 0 | O28: Holistic approach to tackling homelessness in Los Angeles. | Q28: Nonprofit | R28: Human Services | S28: 2. VM
B29: Brown Brothers Harriman | D29: 46027 | E29: 212-483-1818 | F29: Drew Rabe | G29: MD - Head of Philanthropy | I29: NY | J29: 0 | O29: Ex-Arabella; Columbia Law | Q29: Foundation Management | R29: MFO | S29: 2. VM
B30: C K BLANDIN FOUNDATION | C30: =_xlfn.XLOOKUP(Table1[[#This Row],[EIN]],Sheet5!#REF!,Sheet5!#REF!) -> #REF! | D30: 46031 | E30: 218-326-0523 | F30: Kyle Erickson | G30: Director of Rural Grantmaking | H30: info@blandinfoundation.org | I30: MN | J30: #N/A | K30: 67 | L30: 416038619 | M30: 1.Excellent | O30: CEO: Tuleah Palmer. Also: Linda Gibeau (Grants Program Officer - Small Communities), Mary Magnuson (Grants Program Officer - Rural Placemaking). Toll-free: 877-882-2257. 100 North Pokegama Avenue, Grand Rapids, MN 55744. | S30: 2. VM
B31: CH ROBINSON WORLDWIDE FOUNDATION | C31: =_xlfn.XLOOKUP(Table1[[#This Row],[EIN]],Sheet5!#REF!,Sheet5!#REF!) -> #REF! | D31: 46031 | E31: 952-937-8500 | F31: Rachel Schwalbach | G31: VP, ESG & President of C.H. Robinson Foundation | H31: communityrelations@chrobinson.com | I31: SD | J31: #N/A | K31: 133 | L31: 680599299 | M31: 1.Excellent | O31: Rachel leads Foundation budget and strategy. Focus: Minneapolis-St. Paul metro. Since 2005, donated $29M to nonprofits. | S31: 2. VM | T31: 1/9 - Voicemail for evelyn
B32: CLAUDE WORTHINGTON BENEDUM FOUNDATION | C32: =_xlfn.XLOOKUP(Table1[[#This Row],[EIN]],Sheet5!#REF!,Sheet5!#REF!) -> #REF! | D32: 46031 | E32: 412-246-3634 | F32: Kim Tieman | G32: Vice President and Program Director | H32: info@benedum.org | I32: PA | J32: #N/A | K32: 42 | L32: 251086799 | M32: 1.Excellent | O32: President: Jen Giovannitti 412-246-3642. Sr Program Officers: Melanie Claxton 412-246-3624, Bill Woodrum 412-246-3644 (community/econ dev lead). Dir Strategic Initiatives: Rochelle Goodwin. 223 Fourth Ave, 1400 Benedum-Trees Bldg, Pittsburgh, PA 15222. | S32: 2. VM | T32: left a message for Jen (Kim's mailbox was full)
B33: Conrad & Virginia Klee Foundation | D33: 46031 | E33: 607-722-2266 | F33: Amanda McIntyre | G33: Executive Director | H33: amanda@kleefoundation.org | I33: NY | J33: Eastern | K33: 28 | L33: 156019821 | M33: 1.Excellent | N33: kleefoundation.org | O33: 14 CB grants. Office hours 9am-1pm M-F. Admin: Michele Duquella. 84 Court St, Suite 510, Binghamton, NY 13901. | R33: Foundation | S33: 2. VM
B34: Conrad N. Hilton Foundation | C34: =_xlfn.XLOOKUP(Table1[[#This Row],[EIN]],Sheet5!#REF!,Sheet5!#REF!) -> #REF! | D34: 46027 | E34: (818) 851-3700 | F34: Christie Cardenas ext 410 | G34: Program Officer, Opportunity Youth | I34: CA | J34: Pacific | K34: 170 | L34: 943100217 | M34: 1. Excellent | N34: https://www.hiltonfoundation.org/about/people/ | O34: Colorado Springs-based; statewide focus | Q34: Foundation | S34: 2. VM | T34: 1/5 - VM
B35: Cook Family Foundation | D35: 46031 | E35: 989-725-1621 | F35: Tom Cook | G35: Executive Director | I35: MI | J35: Eastern | K35: 7 | L35: 382283809 | M35: 1.Excellent | N35: cookfamilyfoundation.org | O35: Small foundation (7 grantees). 15 CB grants. Backup: Kelleigh Tanton kelleigh@cookfamilyfoundation.org. 120 W. Exchange St, Suite 202, Owosso, MI 48867. | R35: Foundation | S35: 2. VM
B36: CTrees | D36: 46027 | E36: (818) 354-1666 | F36: Sasan Saatchi | G36: CEO | I36: CA | J36: 0 | O36: Track carbon in every tree on the planet for natural climate solutions. | Q36: Nonprofit | R36: Environment | S36: 2. VM
B37: Elevate Charter Schools | D37: 46027 | E37: (203) 843-4890 | F37: Jeffrey Cirillo | G37: President | I37: CT | J37: 0 | O37: Developing high-performing charter schools with rigorous personalized education. | Q37: Nonprofit | R37: Education | S37: 2. VM
B38: EWING MARION KAUFFMAN FOUNDATION | C38: =_xlfn.XLOOKUP(Table1[[#This Row],[EIN]],Sheet5!#REF!,Sheet5!#REF!) -> #REF! | D38: 46031 | E38: (816) 932-1000 | F38: Allison Greenwood Bajracharya | G38: Chief Impact and Strategy Officer | I38: MO | J38: #N/A | K38: 103 | L38: 436064859 | M38: 1.Excellent | O38: New role 2024. KC native, formerly America Achieves. CEO: DeAngela Burns-Wallace. VP Programs: not listed. LinkedIn outreach recommended. 263 employees. | S38: 2. VM
B39: FAUQUIER HEALTH FOUNDATION | C39: =_xlfn.XLOOKUP(Table1[[#This Row],[EIN]],Sheet5!#REF!,Sheet5!#REF!) -> #REF! | D39: 46031 | E39: 540-680-4100 | F39: Beth Foddrell | G39: Program Officer | H39: bfoddrell@pathforyou.org | I39: VA | J39: #N/A | K39: 63 | L39: 300219424 | M39: 1.Excellent | O39: NOW CALLED PATH FOUNDATION (pathforyou.org). TA Grant explicitly funds "software for donor management". Also: Andy Johnston (Dir Programs). Fauquier/Rappahannock/Culpeper VA. | S39: 2. VM | T39: 1/7 - VM for margi 1/9- another VM for margi (not sure how to spell her name - she's a grants manager)
B40: First Interstate BancSystem Foundation | C40: =_xlfn.XLOOKUP(Table1[[#This Row],[EIN]],Sheet5!#REF!,Sheet5!#REF!) -> #REF! | D40: 46031 | E40: 406-255-5393 | F40: James Reuter | G40: Chair, Foundation Board of Directors | H40: firstinterstatefoundation@fib.com | I40: MT | J40: Mountain | K40: 538 | L40: 810465899 | M40: 1.Excellent | O40: Chair leads 5-member board. PO Box 7113, Billings MT 59103. LOI via nearest bank branch first. Focus: community development, leadership. | S40: 2. VM
B41: GERALDINE R DODGE FOUNDATION INC | C41: =_xlfn.XLOOKUP(Table1[[#This Row],[EIN]],Sheet5!#REF!,Sheet5!#REF!) -> #REF! | D41: 46029 | E41: 973-540-8442 | F41: Samra Haider | G41: President & CEO | H41: shaider@grdodge.org | I41: NJ | J41: #N/A | K41: 37 | L41: 237406010 | M41: 1.Excellent | O41: 61% capacity; 335 NJ grantees; racial wealth gap focus; new CEO June 2025; RECOMMENDED | S41: 2. VM
B42: Grace S & W Linton Nelson Foundation | D42: 46031 | E42: 610-977-2488 | F42: Jenny Snyder | G42: Director of Grantmaking | H42: info@nelsonfoundationpa.org | I42: PA | J42: Eastern | K42: 66 | L42: 222583922 | M42: 1.Excellent | N42: nelsonfoundationpa.org | O42: 24 CB grants ($1.09M). Jenny manages grant programs - best for CB discussions. 150 N. Radnor Chester Rd, F200, Radnor, PA 19087. | R42: Foundation | S42: 2. VM
B43: HELLMAN FOUNDATION | C43: 50 | D43: 46029 | E43: 415-837-5408 | F43: Dorian Luey | G43: Director, Capacity Building | H43: dorian.luey@thirdplateau.com | I43: CA | J43: Pacific | K43: 0 | L43: 611583546 | M43: 1.5 Sunsetting | O43: SF Bay Area community focus. Funds health equity, education, youth development, food access. Has capacity building director. Sunsetting by 2034 - grantees need help finding other funders. | P43: 2034 | R43: Foundation | S43: 2. VM
B44: HILLMAN FAMILY FOUNDATIONS | C44: =_xlfn.XLOOKUP(Table1[[#This Row],[EIN]],Sheet5!#REF!,Sheet5!#REF!) -> #REF! | D44: 46029 | E44: 412-338-3466 | F44: Hilary A. Brown | G44: Program Director of Family Foundations | H44: hbrown@hillmanfo.com | I44: PA | J44: #N/A | K44: 79 | L44: 256065959 | M44: 1.Excellent | O44: Email pattern from RocketReach (h******@hillmanfo.com). Also: Meredith Mavero (Program Officer). 310 Grant St Ste 2000, Pittsburgh PA 15219. 12 staff, 18 foundations. $70M/yr grants. | S44: 2. VM
B45: Human Cell Atlas | D45: 46027 | E45: (617) 714-7093 | F45: Aviv Regev | G45: Director, Co-Chair | I45: MA | J45: 0 | O45: Mapping every cell type in the human body. | Q45: Nonprofit | R45: Science & Tech | S45: 2. VM
B46: Joseph and Vera Zilber Family Foundation Inc | C46: =_xlfn.XLOOKUP(Table1[[#This Row],[EIN]],Sheet5!#REF!,Sheet5!#REF!) -> #REF! | D46: 46029 | E46: (414) 274-2447 | F46: Erin Frederick | G46: Sector Supports Director (leads capacity building) | H46: erin.frederick@zilberfamilyfoundation.org | I46: WI | J46: #N/A | K46: 41 | L46: 392076346 | M46: 1.Excellent | O46: ED: Lianna Bishop lianna.bishop@zilberfamilyfoundation.org. Program Dir: Demetria Smith demetria.smith@. Program Officers: Yalanda Ludtke yalanda.ludtke@, Meredith Trockman meredith.trockman@. Grants Mgr: Danielle Johnson danielle.johnson@zilberfamilyfoundation.org | S46: 2. VM
B47: LNW (Laird Norton) | D47: 46027 | E47: 206-464-5100 | F47: John Goodwin | G47: Director & Chief Legacy Strategist | I47: WA | J47: #N/A | O47: Pacific NW | Q47: Foundation Management | R47: MFO | S47: 2. VM
B48: M J MURDOCK CHARITABLE TRUST | C48: =_xlfn.XLOOKUP(Table1[[#This Row],[EIN]],Sheet5!#REF!,Sheet5!#REF!) -> #REF! | D48: 46029 | E48: (360) 694-8415 | F48: Kimberly Thornbury, Ph.D. | G48: Vice President, Programs & Partnerships | H48: info@murdocktrust.org | I48: WA | J48: Pacific | K48: 134 | L48: 237456468 | M48: 1.Excellent | O48: Also: Jill Lemke (VP Grants Mgmt), Pauline Fong (Chief Program Officer). Focus: AK, ID, MT, OR, WA. Free nonprofit resources. | S48: 2. VM
B49: MARGUERITE CASEY FOUNDATION | C49: =_xlfn.XLOOKUP(Table1[[#This Row],[EIN]],Sheet5!#REF!,Sheet5!#REF!) -> #REF! | D49: 46029 | E49: 510-295-8484 | F49: Dr. Carmen Rojas | G49: President & CEO | H49: crojas@caseygrants.org | I49: WA | J49: Pacific | K49: 35 | L49: 912062197 | M49: 1.Excellent | O49: 68% capacity; 509 movement-building orgs; Highlander $1.5M; preselected OK for B2B; RECOMMENDED | S49: 2. VM
B50: Marici | D50: 46027 | E50: (415) 745-3300 | F50: Divya Joshi | G50: President | I50: CA | J50: 0 | O50: Increasing resources and building capacity for grassroots organizations. | Q50: Nonprofit | R50: Human Services | S50: 2. VM | T50: Left message for Al Weedman
B51: MARIE LAMFROM CHARITABLE FOUNDATION | C51: =_xlfn.XLOOKUP(Table1[[#This Row],[EIN]],Sheet5!#REF!,Sheet5!#REF!) -> #REF! | D51: 46029 | E51: 5038773943 | F51: Tyler Hobbs | G51: President | H51: tyler@marielamfrom.org | I51: OR | J51: Pacific | K51: 149 | L51: 931254171 | M51: 1.Excellent | O51: 57% capacity; 958 grantees; expanded GOS & multi-year; BIPOC/LGBTQ+ focus; Oregon's #2 capacity builder | S51: 2. VM
B52: MARSHALL L AND PERRINE D MCCUNE | C52: =_xlfn.XLOOKUP(Table1[[#This Row],[EIN]],Sheet5!#REF!,Sheet5!#REF!) -> #REF! | D52: 46031 | E52: 505-983-8300 | F52: Carla Romero | G52: Executive Director | H52: mccune@nmmccune.org | I52: NM | J52: Mountain | K52: 43 | L52: 850429439 | M52: 1.Excellent | O52: Also: Ernesto Torres (Dir Grantmaking & Community Inclusion), Henry Rael (Dir Strategy), Allison Hagerman (Dir Learning & Ops). 345 E Alameda St, Santa Fe NM 87501. grants@nmmccune.org for grantmaking. | S52: 2. VM | T52: 1/7 - not contacted 1/9 - Vm for Ernesto
B53: MEDINA FOUNDATION | C53: 54 | D53: 46029 | E53: 206-652-8783 | F53: Jennifer Teunon | G53: Executive Director | I53: WA | J53: Pacific | K53: 0 | L53: 910745225 | M53: 1.5 Sunsetting | O53: Puget Sound human services focus. 4 CB service grants. Funds racial equity, general operating. SUNSETTING 3-5 years - grantees urgently need other funders. | P53: 2028 | R53: Foundation | S53: 2. VM
B54: Meyer Memorial Trust | C54: =_xlfn.XLOOKUP(Table1[[#This Row],[EIN]],Sheet5!#REF!,Sheet5!#REF!) -> #REF! | D54: 46027 | E54: (503) 228-5512 | F54: Nancy Haque | H54: questions@mmt.org | I54: OR | J54: Pacific | K54: 107 | L54: 930806316 | M54: 1. Excellent | N54: https://mmt.org/about/our-team | O54: President: Aileen Lee; Chair: Ken Moore; $8.7B assets | Q54: Foundation | S54: 2. VM
B55: PALLOTTINE FOUNDATION OF HUNTINGTON | C55: =_xlfn.XLOOKUP(Table1[[#This Row],[EIN]],Sheet5!#REF!,Sheet5!#REF!) -> #REF! | D55: 46029 | E55: 304-397-5955 | F55: Jana Stoner | G55: Senior Program Officer for Mission and Strategy | H55: jkstoner@pallottinehuntington.org | I55: WV | J55: #N/A | K55: 52 | L55: 815135504 | M55: 1.Excellent | O55: CEO: Laura Boone (lkboone@pallottinehuntington.org). Also: Claire Snyder, Senior Program Officer for Learning and Impact (cesnyder@pallottinehuntington.org). Strong capacity building focus with examples like board development, strategic planning, and fundraising strategy development. | S55: 2. VM
B56: Pathstone | D56: 46027 | E56: 888-750-7284 | F56: Hannah Kanstroom | G56: Director - Family Advisory (Philanthropy) | I56: NJ | J56: 0 | O56: Ex-BofA; CAP | Q56: Foundation Management | R56: MFO | S56: 2. VM
B57: Peter Kiewit Foundation | C57: 206 | D57: 46029 | E57: (402) 575-5786 | F57: Wendy Boyer | G57: Executive Director | H57: wwb@pkfdn.org | I57: NE | J57: #N/A | K57: 0 | L57: 476098282 | M57: 1.5 Sunsetting | O57: Nebraska/W Iowa focus. 6 CB service grants. Funds education, youth, affordable housing, community foundation capacity. SUNSETTING 2030 - grantees urgently need other funders. | P57: 2030 | R57: Foundation | S57: 2. VM
B58: POHLAD FAMILY FOUNDATION | C58: =_xlfn.XLOOKUP(Table1[[#This Row],[EIN]],Sheet5!#REF!,Sheet5!#REF!) -> #REF! | D58: 46031 | E58: 612-661-3859 | F58: Susan Bass Roberts | G58: President | I58: MN | J58: #N/A | K58: 41 | L58: 411768558 | M58: 1.Excellent | O58: VP: Brian Paulson. Program Officers: Lea Blackwell Favor (Racial Justice), Sommer Green (Housing Stability). 250 Nicollet Mall Ste 600, Minneapolis MN 55401. | S58: 2. VM
B59: PowerCA Action | D59: 46027 | E59: (510) 698-3828 | F59: Luis Sanchez | G59: Executive Director | I59: CA | J59: 0 | O59: Engaging young voters of color and families to advance progressive agenda. | Q59: Nonprofit | R59: Civil Rights | S59: 2. VM
B60: RAIKES FOUNDATION | D60: 46029 | E60: (206) 801-9500 | F60: Dr. Zoe Stemm-Calderon | G60: Executive Director (starting Jan 2026) | H60: info@raikesfoundation.org | J60: Pacific | K60: 0 | L60: 912173492 | M60: 1.Excellent | O60: Seattle-based, national reach. 7 CB service grants. Funds education, youth homelessness, democracy/equity. Top grantees include Seattle Foundation, National Equity Project. | S60: 2. VM
B61: RASMUSON FOUNDATION | C61: =_xlfn.XLOOKUP(Table1[[#This Row],[EIN]],Sheet5!#REF!,Sheet5!#REF!) -> #REF! | D61: 46031 | E61: 907-297-2700 | F61: Gretchen Guess | G61: President & CEO | H61: grants@rasmuson.org | I61: AK | J61: #N/A | K61: 213 | L61: 916340739 | M61: 1.Excellent | O61: NEW CEO Feb 2024; Alaska's largest grantmaker; partners with Foraker Group for capacity building | S61: 2. VM
B62: SEMPRA FOUNDATION | D62: 46029 | E62: 619-696-2467 | F62: Christy Ihrig | G62: Director | J62: Pacific | K62: 688 | L62: 261325469 | M62: 1.Excellent | O62: 688 dependent grantees - massive reach. 2,382 grants last year. Corporate foundation of Sempra Energy in San Diego. Focus: education, environment, emergency preparedness. High-volume grantor with broad community impact. | S62: 2. VM
B63: SIERRA HEALTH FOUNDATION | D63: 46031 | E63: 916-922-4755 | F63: Chet P. Hewitt | G63: President and CEO | H63: info@sierrahealth.org | J63: Pacific | K63: 45 | L63: 680050036 | M63: 1.Excellent | O63: 45 dependent grantees focused on health equity and vulnerable youth. Professional leadership team with 17+ year CEO tenure. Strong focus on community health disparities in Sacramento/Northern CA region. | S63: 2. VM
B64: Stewart W & Willma C Hoyt Foundation | D64: 46031 | E64: 607-772-0780 | F64: Catherine Schwoeffermann | G64: Executive Director | I64: NY | J64: Eastern | K64: 25 | L64: 223209342 | M64: 1.Excellent | N64: hoytfoundation.org | O64: 7 CB grants. Key Staff: Amy Pepe. 70 Front St, Suite 1, Binghamton, NY 13905. | R64: Foundation | S64: 2. VM
B65: STUPSKI FOUNDATION | C65: 210 | D65: 46029 | E65: 415.655.4405 | F65: Glen Galaich, Ph.D. | G65: CEO | H65: glen@stupski.org | I65: CA | J65: Pacific | K65: 31 | L65: 680397103 | M65: 1.5 Sunsetting | O65: SUNSETTING BY 2029 - grantees urgently need other funders. 10 CB service grants (BIPOC-led CBO capacity building, leadership development, technical assistance). Professional staff with direct contact. Grantees include West Hawaii Community Health Center, Hawaii Good Food Alliance, Kokua Kalihi Valley. | P65: 2029 | R65: Foundation | S65: 2. VM
B66: SWIFT FOUNDATION | C66: 0 | D66: 46029 | F66: Suzanne Benally | G66: ED | I66: CA | J66: Pacific | K66: 0 | L66: 770559600 | M66: 1.5 Sunsetting | O66: SUNSETTING 2028 - 190+ Native-led grantees urgently need other funders. Supports Indigenous Environmental Network, Indigenous Climate Action, Gaia Amazonas. Under-resourced grassroots orgs that would benefit from grant research. | P66: 2028 | R66: Foundation | S66: 2. VM | T66: no number, emailed their contact page
B67: Tauck Family Foundation | D67: 46031 | E67: 203-899-6525 | F67: Kim Hein | G67: Executive Director | H67: kim@tauckfoundation.org | I67: CT | J67: Eastern | K67: 55 | L67: 270729341 | M67: 1.Excellent | N67: tauckfamilyfoundation.org | O67: 45 CB grants ($1.45M). Strong CB background - joined as PO 2017, became ED 2022. Backup: Patricia Nunez patricia@tauckfoundation.org. PO Box 650, Wilton, CT 06897. | R67: Foundation | S67: 2. VM
B68: Temple Hoyne Buell Foundation | D68: 46027 | E68: (303) 744-1688 | F68: Laura Carlson | G68: Vice President of Programs | I68: CO | J68: 0 | N68: https://buellfoundation.org/about/team/ | O68: Asheville, NC; Western NC health focus; $1.9B assets | Q68: Foundation | S68: 2. VM
B69: The California Wellness Foundation | C69: =_xlfn.XLOOKUP(Table1[[#This Row],[EIN]],Sheet5!#REF!,Sheet5!#REF!) -> #REF! | D69: 46027 | E69: (818) 702-1900 | F69: Monica Gomez | G69: Program Officer, Equity in Access & Economic Security | I69: CA | J69: Pacific | K69: 126 | L69: 954292101 | M69: 1. Excellent | N69: https://calwellness.org/about-us/our-team/ | O69: Online portal for applications; Maine-focused | Q69: Foundation | S69: 2. VM
B70: THE CALIFORNIA WELLNESS FOUNDATION | C70: =_xlfn.XLOOKUP(Table1[[#This Row],[EIN]],Sheet5!#REF!,Sheet5!#REF!) -> #REF! | D70: 46029 | E70: 818-702-1900 | F70: Monica Gomez | G70: Program Officer - Equity in Access & Economic Security | H70: info@calwellness.org | I70: CA | J70: Pacific | K70: 126 | L70: 954292101 | M70: 1.Excellent | O70: 20+ years nonprofit experience. Focuses on capacity-building for social change orgs. LA: 818-702-1900, Oakland: 415-908-3000. No direct emails published. | S70: 2. VM
B71: THE COLORADO HEALTH FOUNDATION | D71: 46031 | E71: 303-953-3628 | F71: Karen McNeil-Miller | G71: President and CEO | J71: Mountain | L71: 742568941 | M71: 1.Excellent | O71: $2.8 BILLION assets - largest foundation in batch by far. 238 dependent Colorado grantees. Professional staff with CEO, Chief Impact Officer, VP Philanthropy - all with direct phone numbers. Major health equity funder. | S71: 2. VM
B72: THE FB HERON FOUNDATION | C72: =_xlfn.XLOOKUP(Table1[[#This Row],[EIN]],Sheet5!#REF!,Sheet5!#REF!) -> #REF! | D72: 46031 | E72: 475-250-1020 | F72: Felecia Lucky | G72: President & CEO | H72: info@heron.org | I72: CT | J72: #N/A | K72: 26 | L72: 133647019 | M72: 1.Excellent | O72: 86% capacity; 289 grantees inc CDFIs (Black Belt CF $3.6M); new CEO Oct 2025 from BBCF; RECOMMENDED | S72: 2. VM
B73: The Ford Family Foundation | C73: =_xlfn.XLOOKUP(Table1[[#This Row],[EIN]],Sheet5!#REF!,Sheet5!#REF!) -> #REF! | D73: 46029 | E73: (541) 957-5574 | F73: Keavy Cook | G73: Vice President of Programs | H73: keavy@tfff.org | I73: OR | J73: Pacific | K73: 171 | L73: 936026156 | M73: 1.Excellent | O73: Promoted Dec 2024. Also: Kasi Allen (VP Learning & Impact). HQ: Roseburg OR. | S73: 2. VM
B74: The George Gund Foundation | C74: =_xlfn.XLOOKUP(Table1[[#This Row],[EIN]],Sheet5!#REF!,Sheet5!#REF!) -> #REF! | D74: 46029 | E74: 216-241-3114 | F74: Tony Richardson | G74: President | H74: trichardson@gundfdn.org | I74: OH | J74: #N/A | K74: 41 | L74: 346519769 | M74: 1.Excellent | O74: 42% capacity; 391 Cleveland grantees; Cleveland Foundation $18M; equity-focused; RECOMMENDED | S74: 2. VM
B75: THE HEINZ ENDOWMENTS | C75: =_xlfn.XLOOKUP(Table1[[#This Row],[EIN]],Sheet5!#REF!,Sheet5!#REF!) -> #REF! | D75: 46029 | E75: 412-281-5777 | F75: Carmen Anderson | G75: Vice President, Community & Economic Development | H75: canderson@heinz.org | I75: PA | J75: #N/A | K75: 85 | L75: 251721100 | M75: 1.Excellent | O75: Also: Josie Innamorato (Dir Eval & Learning) jinnamorato@heinz.org, Rob Stephany (Sr Dir) rstephany@heinz.org. $90M/yr grants. | S75: 2. VM
B76: The James Irvine Foundation | C76: =_xlfn.XLOOKUP(Table1[[#This Row],[EIN]],Sheet5!#REF!,Sheet5!#REF!) -> #REF! | D76: 46029 | E76: (415) 777-2244 | F76: Don Howard | G76: President & CEO | H76: dhoward@irvine.org | I76: CA | J76: Pacific | K76: 109 | L76: 941236937 | M76: 1.Excellent | O76: Direct CEO email confirmed. Also: Cindy Downing (Program Officer, manages Leadership Awards). 1 Bush St Ste 800, San Francisco CA 94104. ~80 employees. $158.7M grants in 2024. | S76: 2. VM
B77: The McKnight Foundation | C77: =_xlfn.XLOOKUP(Table1[[#This Row],[EIN]],Sheet5!#REF!,Sheet5!#REF!) -> #REF! | D77: 46031 | E77: (612) 333-4220 | F77: Neeraj Mehta | G77: Vice President of Programs | I77: MN | J77: #N/A | K77: 111 | L77: 410754835 | M77: 1.Excellent | O77: President: Tonya Allen. Chief of Staff: Erin Imon Gavin. Dir Grants & Program Ops: Stephanie Duffy. All-women majority POC leadership. ~50 staff. No emails on website. | S77: 2. VM
B78: THE NORD FAMILY FOUNDATION | C78: =_xlfn.XLOOKUP(Table1[[#This Row],[EIN]],Sheet5!#REF!,Sheet5!#REF!) -> #REF! | D78: 46031 | E78: 440-984-3939 | F78: Sharon Bennett | G78: Grants Administrator | H78: sharonbennett@nordff.org | I78: OH | J78: #N/A | K78: 41 | L78: 341595929 | M78: 1.Excellent | O78: 58 underfunded grantees; Lorain County OH community focus; funds small local orgs that urgently need diversification; RECOMMENDED | S78: 2. VM
B79: THE PATRICIA KIND FAMILY FOUNDATION | C79: =_xlfn.XLOOKUP(Table1[[#This Row],[EIN]],Sheet5!#REF!,Sheet5!#REF!) -> #REF! | D79: 46029 | E79: 215-836-9536 | F79: Lauren Stebbins | G79: Executive Director | H79: lstebbins@pkindfamilyfoundation.org | I79: PA | J79: #N/A | K79: 24 | L79: 237839035 | M79: 1.Excellent | O79: Also: Jordan Muse (Philanthropic Partnerships Coordinator) jordan@pkindfamilyfoundation.org, Regina Bosca (Grants Manager, 25+ years), Valerie Kind-Rubin (Managing Trustee) valeriekr@pkindfamilyfoundation.org. 714 N Bethlehem Pike, Suite 304, Lower Gwynedd, PA 19002. | S79: 2. VM
B80: The Satterberg Foundation | C80: =_xlfn.XLOOKUP(Table1[[#This Row],[EIN]],Sheet5!#REF!,Sheet5!#REF!) -> #REF! | D80: 46027 | E80: (206) 441-3045 | F80: Sarah Walczyk | G80: Executive Director | H80: swalczyk@satterberg.org | I80: WA | J80: Pacific | K80: 32 | L80: 911501066 | M80: 1. Excellent | O80: Washington; TOP 5 PRIORITY | S80: 2. VM
B81: The Triangle Fund | D81: 46031 | E81: 607-346-4453 | F81: Pam Noviello | G81: Executive Director | H81: director@trianglefund.org | I81: NY | J81: Eastern | K81: 18 | L81: 311591261 | M81: 1.Excellent | N81: trianglefund.org | O81: Very small (18 grantees). 21 CB grants. ED handles all program decisions. 80 E Market St, Suite 202, Corning, NY 14830. | R81: Foundation | S81: 2. VM
B82: THE WILLIAM PENN FOUNDATION | C82: =_xlfn.XLOOKUP(Table1[[#This Row],[EIN]],Sheet5!#REF!,Sheet5!#REF!) -> #REF! | D82: 46031 | E82: 215-988-1830 | F82: Shawn McCaney | G82: Executive Director | H82: grants@williampennfoundation.org | I82: PA | J82: #N/A | K82: 127 | L82: 231503488 | M82: 1.Excellent | O82: 15 program officers, 460+ active grantees. Two Logan Square 11th Fl, 100 N 18th St, Philadelphia PA 19103. 50 employees. Founded 1945 by Otto & Phoebe Haas. | S82: 2. VM
B83: Topos Institute | D83: 46027 | E83: (949) 529-1429 | F83: Brendan Fong | G83: CEO | I83: CA | J83: #N/A | O83: Shaping technology for public benefit through sciences of connection. | Q83: Nonprofit | R83: Education | S83: 2. VM
B84: Walton Family Foundation | D84: 46027 | E84: (479) 464-1500 | F84: Sara Guillaume | G84: Executive Director | I84: AR | J84: 0 | Q84: Foundation | R84: Education | S84: 2. VM | T84: Walton enterprises
B85: Weingart Foundation | C85: =_xlfn.XLOOKUP(Table1[[#This Row],[EIN]],Sheet5!#REF!,Sheet5!#REF!) -> #REF! | D85: 46027 | E85: (213) 688-7799 | F85: Crystal Crawford | G85: Sr. Dir Strategic Partnerships | H85: jjackson@weingartfnd.org | I85: CA | J85: Pacific | K85: 61 | L85: 956054814 | M85: 1. Excellent | N85: https://www.weingartfnd.org/about/ | Q85: Foundation | S85: 2. VM
B86: Weldon F Osborne Foundation | D86: 46031 | E86: 423-267-0931 | F86: Barbara Marter | G86: Executive Director | I86: TN | J86: Eastern | K86: 87 | L86: 626026442 | M86: 1.Excellent | N86: wfosbornefoundation.org | O86: 31 CB grants ($744K). Chattanooga community focus. 100 W ML King Blvd, Suite 210, Chattanooga, TN 37402. | R86: Foundation | S86: 2. VM
B87: Bessemer Trust | D87: 46027 | E87: 212-708-9100 | F87: Caroline Hodkinson | G87: MD - Head of Philanthropy | I87: NY | J87: #N/A | K87: 0 | O87: MS Philanthropy NYU | Q87: Foundation Management | R87: MFO | S87: 1. Not Contacted | T87: Couldn't connect
B88: Civilization Research Initiative | D88: 46027 | E88: (858) 367-0629 | F88: Daniel Schmachtenberger | G88: President & CEO | I88: NC | J88: #N/A | K88: 0 | O88: Think tank focused on reducing systemic fragility and advancing governance. | Q88: Nonprofit | R88: Environment | S88: 1. Not Contacted | T88: voicemail tone didn't ring
B89: Corient | D89: 46027 | E89: 305-351-6650 | F89: Laura (Boston) | G89: Regional Head of Wealth Planning | I89: FL | J89: #N/A | K89: 0 | O89: Ex-Boston Foundation; CAP | Q89: Foundation Management | R89: MFO | S89: 1. Not Contacted | T89: Bad number
B90: Cresset | D90: 46027 | E90: 312-429-2400 | F90: Laura Neal | G90: Director - Family Office Services | I90: IL | J90: #N/A | K90: 0 | O90: Ex-ICONIQ; philanthropy structuring | Q90: Foundation Management | R90: MFO | S90: 1. Not Contacted
B91: Destiny Community Services | D91: 46027 | E91: (916) 780-1873 | F91: Greg Fairrington | G91: CEO | I91: CA | J91: 0 | K91: 0 | O91: Health and wellness services for individuals and families. | Q91: Nonprofit | R91: Community Improvement | S91: 1. Not Contacted
B92: DOGWOOD HEALTH TRUST | C92: =_xlfn.XLOOKUP(Table1[[#This Row],[EIN]],Sheet5!#REF!,Sheet5!#REF!) -> #REF! | D92: 46029 | E92: (828) 771-6710 | F92: Jehan Benton-Clark | G92: Vice President of Grantmaking & Strategy | H92: jbentonclark@dhtrust.org | I92: NC | J92: #N/A | K92: 140 | L92: 830590696 | M92: 1.Excellent | O92: Also: Dominica Bockes (Dir Grantmaking Ops) dbockes@dhtrust.org, Mark Constantine (SVP Community Investment). Asheville NC focus. | S92: 1. Not Contacted | T92: no voicemail tone
B93: Elmina B Sewall Foundation | C93: =_xlfn.XLOOKUP(Table1[[#This Row],[EIN]],Sheet5!#REF!,Sheet5!#REF!) -> #REF! | E93: 207-865-3810 | F93: M. Gabriela Alcalde, MPH, DrPH | G93: Executive Director | H93: info@sewallfoundation.org | I93: ME | J93: #N/A | K93: 58 | L93: 10387404 | M93: 1.Excellent | O93: Program emails: foodsystems@, ruralpartnerships@, keystone@sewallfoundation.org. Also: Thomas Mitchell (Finance), Amie Hutchison (Animal Welfare), Sonya LaCoute-Dana (Wabanaki). PO Box 1319, Portland, ME 04104. | S93: 1. Not Contacted | T93: 1/9 - rang then dropped
B94: Fiduciary Trust | D94: 46027 | E94: 617-482-5270 | F94: Todd Eckler | G94: President - FT Charitable | I94: MA | J94: #N/A | K94: 0 | O94: DAF innovation | Q94: Foundation Management | R94: MFO | S94: 1. Not Contacted
B95: Focus Partners | D95: 46027 | E95: 617-236-0800 | F95: Adrienne Penta | G95: National Head of Wealth Management | I95: MA | J95: #N/A | K95: 0 | O95: Colony Group merger | Q95: Foundation Management | R95: MFO | S95: 1. Not Contacted
B96: Glenmede Trust | D96: 46027 | E96: 215-419-6000 | F96: Nina Cohen | G96: Director - Endowment & Foundation | I96: PA | J96: #N/A | K96: 0 | O96: CAP; 10+ yrs | Q96: Foundation Management | R96: MFO | S96: 1. Not Contacted
B97: ICONIQ Capital | D97: 46027 | E97: 415-967-7763 | F97: Katie Hunt-Morr | G97: COO & VP - ICONIQ Impact | I97: CA | J97: 0 | K97: 0 | O97: $519M+ grants advised | Q97: Foundation Management | R97: MFO | S97: 1. Not Contacted
B98: Limitless Space Institute | E98: (281) 339-7800 | F98: Harold White | G98: Director of Advanced Research | I98: TX | J98: #N/A | K98: 0 | O98: Inspire next generation to travel beyond our solar system. | Q98: Nonprofit | R98: Education | S98: 1. Not Contacted | T98: Call didn't go through
B99: Northern Trust | D99: 46027 | E99: 312-630-6000 | F99: Marguerite Griffin | G99: SVP - Director Philanthropic Advisory | I99: IL | J99: #N/A | K99: 0 | O99: Leads philanthropy advisory | Q99: Foundation Management | R99: MFO | S99: 1. Not Contacted
B100: Price Philanthropies Foundation | C100: =_xlfn.XLOOKUP(Table1[[#This Row],[EIN]],Sheet5!#REF!,Sheet5!#REF!) -> #REF! | D100: 46027 | E100: 858-300-1390 | F100: Sakara Tear | G100: Senior Director of Community Initiatives | H100: stear@pricephilanthropies.org | I100: CA | J100: Pacific | K100: 36 | L100: 465129465 | M100: 1. Excellent | O100: San Diego; large grantee network | S100: 1. Not Contacted
B101: SAMUELI FOUNDATION | D101: 46031 | E101: 949-760-4400 | F101: Annette Fritzsche | G101: Director of Grants Management | H101: info@samueli.org | J101: Pacific | K101: 45 | L101: 330758237 | M101: 1.Excellent | O101: 45 Orange County nonprofits. Major programs: Breakaway Fund ($11M), Build OC Fund (up to $1M capital grants). Very active. | S101: 1. Not Contacted | T101: 1/9 - all representatives were busy
...

Sheet Sheet1
B2: 1. Not Contacted
B3: 2. VM
B4: 3. Talked to Someone
B5: 4. Reached Decision Maker
B6: 5. Interested

Sheet Sheet2
B2: Org | C2: Researched | D2: Date_Contacted | E2: Rating | F2: Why_Rating | G2: Pitch_Angle | H2: State | I2: EIN | J2: Assets | K2: Grantees | L2: Capacity_Pct | M2: Accepts_Apps | N2: Recommended_Contact | O2: Contact_Title | P2: Contact_Email | Q2: Phone | R2: Website | S2: About
B3: Ann Jackson Family Foundation | C3: 1 | E3: Excellent | F3: 98% capacity grants, small family foundation, 90% grants local to Santa Barbara | G3: Your 98% GOS rate shows commitment to nonprofit flexibility. TheGrantScout helps your Santa Barbara grantees find additional local funders. | H3: CA | I3: 953367511 | J3: 88737372 | K3: 152 | L3: 0.98 | M3: Yes | N3: Palmer Jackson Jr. | O3: Managing Trustee | P3: palmer.jackson@gmail.com | Q3: (805) 969-2258 | R3: ajff.org | S3: 98% capacity grants, small family foundation, 90% grants local to Santa Barbara
B4: California Wellness Foundation | C4: 1 | E4: Excellent | F4: 52% capacity grants, 1,326 grantees, known leader in core operating support, community nonprofits | G4: Your 52% GOS rate shows commitment to nonprofit sustainability. TheGrantScout helps your grantees discover other foundations aligned with their missions. | H4: CA | I4: 954292101 | J4: 1042135742 | K4: 1326 | L4: 0.52 | M4: Yes | N4: Monica Gomez | O4: Program Officer - Equity in Access | R4: calwellness.org | S4: 52% capacity grants, 1,326 grantees, known leader in core operating support, community nonprofits
B5: Conrad N. Hilton Foundation | C5: 1 | E5: Excellent | F5: 43% capacity grants, 1,637 grantees, funds intermediaries for capacity building, explicit capacity building focus | G5: You fund intermediaries for capacity building. TheGrantScout helps your 1,637 grantees find additional funders to diversify their revenue streams. | H5: CA | I5: 943100217 | J5: 7099706570 | K5: 1637 | L5: 0.43 | M5: Yes | N5: Christie Cardenas | O5: Program Officer - Opportunity Youth | R5: hiltonfoundation.org | S5: 43% capacity grants, 1,637 grantees, funds intermediaries for capacity building, explicit capacity building focus
B6: El Pomar Foundation | C6: 1 | E6: Good | F6: 31% capacity grants, 1,021 grantees, strong leadership programs, Colorado focus | G6: Your leadership programs build nonprofit capacity. TheGrantScout extends that support by helping grantees find additional Colorado funders. | H6: CO | I6: 846002373 | J6: 446140929 | K6: 1021 | L6: 0.31 | M6: Yes | N6: Matt Carpenter | O6: EVP & COO | P6: grants@elpomar.org | Q6: 719-633-7733 | R6: elpomar.org | S6: 31% capacity grants, 1,021 grantees, strong leadership programs, Colorado focus
B7: Fred Maytag Family Foundation | C7: 1 | E7: Good | F7: 76% capacity grants but only 81 grantees. Small grantee pool limits B2B scale. | G7: Your 76% GOS rate is strong but grantee pool (81) limits B2B scale. Could pilot with your Iowa/California grantees. | H7: CA | I7: 421444870 | J7: 67782266 | K7: 81 | L7: 0.76 | M7: Yes | N7: Frederick L. Maytag III | O7: CEO/Vice President | R7: N/A - mail only | S7: 76% capacity grants but only 81 grantees. Small grantee pool limits B2B scale. HQ: 3701 Sacramento St Suite 369, SF CA 94118
B8: Joseph Drown Foundation | C8: 1 | E8: Good | F8: 51% capacity grants, 193 grantees, LA County education focus, 70-yr history, professional staff | G8: Your 51% GOS focus on LA County education is solid. TheGrantScout helps your grantees discover additional Southern California education funders. | H8: CA | I8: 956093178 | J8: 104011094 | K8: 193 | L8: 0.51 | M8: Yes | N8: Alyssa Santino | O8: President of Programs & Operations | P8: alyssa@jdrown.org | Q8: (310) 277-4488 | R8: jdrown.org | S8: 51% capacity grants, 193 grantees, LA County education focus, 70-yr history, professional staff
B9: Lisa & Douglas Goldman Fund | C9: 1 | E9: Excellent | F9: 53% capacity grants, 328 grantees, Levi Strauss family, democracy/climate/education focus | G9: Your 53% capacity focus and democratic values align well. TheGrantScout helps your grantees build sustainable funding portfolios. | H9: CA | I9: 943167546 | J9: 270254108 | K9: 328 | L9: 0.53 | M9: Yes | N9: Nancy Kami | O9: Executive Director | P9: NKami@ldgfund.org (inferred) | Q9: 415-771-1717 | R9: ldgfund.org | S9: 53% capacity grants, 328 grantees, Levi Strauss family, democracy/climate/education focus
B10: Marie Lamfrom Charitable Foundation | C10: 1 | E10: Excellent | F10: 57% capacity grants, 958 grantees, expanded GOS & multi-year, BIPOC/LGBTQ+ focus, Oregon's #2 capacity builder | G10: You've expanded GOS & multi-year funding for sustainability. TheGrantScout helps your 958 Oregon grantees find additional funders to reduce single-funder dependence. | H10: OR | I10: 931254171 | J10: 388446637 | K10: 958 | L10: 0.57 | M10: Yes | N10: Tyler Hobbs | O10: President | P10: tyler@marielamfrom.org | R10: marielamfrom.org | S10: 57% capacity grants, 958 grantees, expanded GOS & multi-year, BIPOC/LGBTQ+ focus, Oregon's #2 capacity builder
B11: Meyer Memorial Trust | C11: 1 | E11: Excellent | F11: 37% capacity grants, 880 grantees, already partners with Resilia, Oregon's top capacity builder | G11: You already partner with Resilia for capacity building. TheGrantScout complements that - helping your 880 Oregon grantees find additional foundation funding. | H11: OR | I11: 930806316 | J11: 885167113 | K11: 880 | L11: 0.37 | M11: Yes | N11: Nancy Haque | O11: Director of Policy and Programs | P11: questions@mmt.org | Q11: 503-228-5512 | R11: mmt.org | S11: 37% capacity grants, 880 grantees, already partners with Resilia, Oregon's top capacity builder
B12: O.L. Halsell Foundation | C12: 1 | E12: Good | F12: 68% capacity grants, 118 grantees, Orange County youth focus, small OC nonprofits | G12: Your 68% capacity focus on Orange County youth orgs is strong. TheGrantScout helps these grantees discover additional Southern California funders. | H12: CA | I12: 956027266 | J12: 46370868 | K12: 118 | L12: 0.68 | M12: Yes | N12: W. David Stauffer Jr. | O12: President | Q12: (714) 546-0755 | S12: 68% capacity grants, 118 grantees, Orange County youth focus. No website. Mail: PO Box 6300, Santa Ana CA 92706
B13: Price Philanthropies Foundation | C13: 1 | E13: Excellent | F13: 93% capacity grants, 387 grantees, small City Heights nonprofits who need funding diversification | G13: Your 93% capacity focus on City Heights nonprofits is remarkable. TheGrantScout helps these small orgs find additional funders to reduce dependence on any single source. | H13: CA | I13: 465129465 | J13: 470624292 | K13: 387 | L13: 0.93 | M13: Invitation Only | N13: Sakara Tear | O13: Senior Director of Community Initiatives | P13: stear@pricephilanthropies.org | Q13: (619) 795-2000 | R13: pricephilanthropies.org | S13: 93% capacity grants, 387 grantees, small City Heights nonprofits who need funding diversification
B14: Ronald W. Naito MD Foundation | C14: 1 | E14: Good | F14: 64% capacity grants, 211 grantees, Oregon focus, pausing new apps = grantees need other funding | G14: You're pausing new applications - your existing grantees need other funding sources! TheGrantScout helps them find additional Oregon funders. | H14: OR | I14: 836622391 | J14: 38830815 | K14: 211 | L14: 0.64 | M14: Yes | N14: Kris Anderson | O14: Executive Director | P14: info@rwnfoundation.org | R14: rwnfoundation.org | S14: 64% capacity grants, 211 grantees, Oregon focus, pausing new apps = grantees need other funding
B15: The Crail-Johnson Foundation | C15: 1 | E15: Excellent | F15: 58% capacity grants, 199 grantees, San Pedro/South LA children focus, provides TA to grantees | G15: You already provide TA to grantees! TheGrantScout complements that - helping your San Pedro/South LA grantees find additional foundation funding. | H15: CA | I15: 330247161 | J15: 19589623 | K15: 199 | L15: 0.58 | M15: Yes | N15: Rachel Roth | O15: Executive Director | P15: rroth@crail-johnson.org | Q15: (310) 519-7413 | R15: crail-johnson.org | S15: 58% capacity grants, 199 grantees, San Pedro/South LA children focus, provides TA to grantees
B16: The Kresge Foundation | C16: 1 | E16: Good | F16: 29% capacity grants, 1,264 grantees, LIFT team with $2M/yr capacity building budget | G16: Your LIFT team has a $2M/yr capacity building budget. TheGrantScout could be part of your grantee support toolkit. | H16: MI | I16: 381359217 | J16: 4073115789 | K16: 1264 | L16: 0.29 | M16: Yes | N16: Neesha Modi | O16: Director, Program & Social Investment Operations | Q16: 248-643-9630 | R16: kresge.org | S16: 29% capacity grants, 1,264 grantees, LIFT team with $2M/yr capacity building budget
B17: The Satterberg Foundation | C17: 1 | E17: Excellent | F17: 82% capacity grants, 292 grantees, 300+ BIPOC-led partners, shifting to retention mode = grantees need other funding | G17: You're shifting to RETENTION mode - perfect timing! TheGrantScout helps your 300+ BIPOC-led partners find additional funders as you step back. | H17: WA | I17: 911501066 | J17: 443335399 | K17: 292 | L17: 0.82 | M17: Invitation Only | N17: Sarah Walczyk | O17: Executive Director | P17: swalczyk@satterberg.org | Q17: (206) 441-3045 | R17: sfrfoundation.org | S17: 82% capacity grants, 292 grantees, 300+ BIPOC-led partners, shifting to retention mode = grantees need other funding
B18: The William & Flora Hewlett Foundation | C18: 1 | E18: Good | F18: 32% capacity grants, 1,796 grantees, Effective Philanthropy Group, strong OE grants program | G18: Your Effective Philanthropy Group funds organizational effectiveness. TheGrantScout helps grantees become more sustainable through funding diversification. | H18: CA | I18: 941655673 | J18: 13332174215 | K18: 1796 | L18: 0.32 | M18: Yes | N18: Jehan Velji | O18: Director - Effective Philanthropy Group | P18: jvelji@hewlett.org | Q18: (650) 234-4500 | R18: hewlett.org | S18: 32% capacity grants, 1,796 grantees, Effective Philanthropy Group, strong OE grants program
B19: Weingart Foundation | C19: 1 | E19: Excellent | F19: 64% capacity grants, 872 grantees, unrestricted core support leader, LA-area community nonprofits | G19: Your 64% unrestricted funding shows deep commitment to nonprofit sustainability. TheGrantScout helps your 872 LA-area grantees find additional funders. | H19: CA | I19: 956054814 | J19: 866296097 | K19: 872 | L19: 0.64 | M19: Yes | N19: Joanna Jackson | O19: President & CEO | P19: jjackson@weingartfnd.org | Q19: (213) 688-7799 | R19: weingartfnd.org | S19: 64% capacity grants, 872 grantees, unrestricted core support leader, LA-area community nonprofits

Sheet Sheet3
B2: foundation name | C2: recommended contact | D2: why recommended | E2: contact name | F2: contact title | G2: contact email | H2: contact phone | I2: contact linkedin | J2: ein
B3: Conrad N. Hilton Foundation | C3: YES | D3: Primary contact with direct email/LinkedIn; most relevant for B2B pitch | E3: Christie Cardenas | F3: Program Officer - Opportunity Youth | I3: https://www.linkedin.com/in/christie-cardenas/ | J3: 943100217 | K3: 15+ years equity-focused grantmaking; manages capacity building grants
B4: Conrad N. Hilton Foundation | E4: Elizabeth Cheung | F4: Sr. Program Officer - Opportunity Youth | I4: https://www.linkedin.com/in/elizabeth-cheung-58a8544/ | J4: 943100217 | K4: Leads New Orleans portfolio including capacity building
B5: Conrad N. Hilton Foundation | E5: Angelina McCormick Soll LCSW | F5: Program Officer - Foster Youth | I5: https://www.linkedin.com/in/angelinasoll/ | J5: 943100217 | K5: Manages grants to Greater Horizons (capacity building intermediary)
B6: Conrad N. Hilton Foundation | E6: Caitlyn Pecoraro | F6: Sr. Advocacy Officer - Older Youth | I6: https://www.linkedin.com/in/caitlyn-pecoraro-9819a876/ | J6: 943100217 | K6: Bridges Foster Youth + Opportunity Youth programs
B7: California Wellness Foundation | C7: YES | D7: Primary contact with direct email/LinkedIn; most relevant for B2B pitch | E7: Monica Gomez | F7: Program Officer - Equity in Access | I7: https://www.linkedin.com/in/gomezmonica22/ | J7: 954292101 | K7: 20+ years capacity-building experience
B8: California Wellness Foundation | E8: Jennifer Wright | F8: Senior Program Officer | I8: https://www.linkedin.com/in/jennifer-wright-calwellness/ | J8: 954292101 | K8: Leads grantmaking initiatives; supports nonprofit organizations
B9: El Pomar Foundation | C9: YES | D9: Primary contact with direct email/LinkedIn; most relevant for B2B pitch | E9: Matt Carpenter | F9: EVP & COO | H9: 719-633-7733 | J9: 846002373 | K9: Oversees grants & programs; Fellowship alum
B10: El Pomar Foundation | E10: Grants Office | G10: grants@elpomar.org | H10: 719-633-7733 | J10: 846002373 | K10: General grants inquiries
B11: El Pomar Foundation | E11: Erin Hannan | F11: SVP Communications | H11: 719-577-5750 | J11: 846002373 | K11: Communications lead
B12: Meyer Memorial Trust | C12: YES | D12: Primary contact with direct email/LinkedIn; most relevant for B2B pitch | E12: Nancy Haque | F12: Director of Policy and Programs | I12: https://www.linkedin.com/in/nancy-haque-8470305/ | J12: 930806316 | K12: Decision-maker for programs
B13: Meyer Memorial Trust | E13: Huy Ong | F13: Senior Program Officer - Our Resilient Places | I13: https://www.linkedin.com/in/huy-ong-a73bb23/ | J13: 930806316 | K13: Climate and resilience portfolio
B14: Meyer Memorial Trust | E14: Allister Byrd | F14: Senior Program Officer - Justice Oregon | I14: https://www.linkedin.com/in/allister-byrd-03b27382/ | J14: 930806316 | K14: $25M Black-led orgs initiative
B15: Meyer Memorial Trust | E15: Sally Yee | F15: Program Officer | I15: https://www.linkedin.com/in/sally-yee-11398853/ | J15: 930806316
B16: Meyer Memorial Trust | E16: General Contact | G16: questions@mmt.org | H16: 503-228-5512 | J16: 930806316 | K16: General inquiries
B17: The California Endowment | C17: YES | D17: Primary contact with direct email/LinkedIn; most relevant for B2B pitch | J17: 954523232 | K17: Large funder but preselected only - not accepting applications
B18: Gordon E. and Betty I. Moore Foundation | C18: YES | D18: Primary contact with direct email/LinkedIn; most relevant for B2B pitch | E18: Aileen Lee | F18: President (Chief of Programs) | H18: 650-213-3000 | I18: https://www.linkedin.com/in/aileen-lee-a404baa2/ | J18: 943397785 | K18: Oversees all programs; no capacity building focus
B19: Gordon E. and Betty I. Moore Foundation | E19: Ignacio Estrada | F19: Director, Grants Administration | G19: i***@moore.org | H19: 650-213-3000 | J19: 943397785 | K19: 12+ years grants admin experience
B20: Gordon E. and Betty I. Moore Foundation | E20: Jennifer Rea Sandin | F20: Director, Program Operations | H20: 650-213-3000 | I20: https://www.moore.org/people-detail?personUrl=jenniferr | J20: 943397785 | K20: Program operations lead
B21: Gordon E. and Betty I. Moore Foundation | E21: General Contact | G21: communications@moore.org | H21: 650-213-3000 | J21: 943397785 | K21: HQ: 1661 Page Mill Road, Palo Alto CA
B22: The William & Flora Hewlett Foundation | C22: YES | D22: Primary contact with direct email/LinkedIn; most relevant for B2B pitch | E22: Jehan Velji | F22: Director - Effective Philanthropy Group | G22: jvelji@hewlett.org | H22: (650) 234-4500 | I22: https://www.linkedin.com/in/jehan-velji/ | J22: 941655673 | K22: 30+ yrs capacity building; leads OE program; former Blue Meridian; Harvard MBA
B23: The William & Flora Hewlett Foundation | E23: Jennifer Wei | F23: Organizational Effectiveness Officer | G23: jwei@hewlett.org | I23: https://www.linkedin.com/in/jennifer-wei-23477/ | J23: 941655673 | K23: Oversees capacity grants across all programs; Stanford MBA
B24: The William & Flora Hewlett Foundation | E24: Amber D. Miller | F24: President | G24: amiller@hewlett.org | H24: (650) 234-4500 | J24: 941655673 | K24: New president Sept 2024; sets foundation direction
B25: Weingart Foundation | C25: YES | D25: Primary contact with direct email/LinkedIn; most relevant for B2B pitch | E25: Joanna Jackson | F25: President & CEO | G25: jjackson@weingartfnd.org | H25: (213) 688-7799 | I25: https://www.linkedin.com/in/joanna-jackson-91484027 | J25: 956054814 | K25: New CEO June 2024; 15 yrs at Weingart; board of GEO & SoCal Grantmakers
B26: Weingart Foundation | E26: Crystal Crawford | F26: Sr. Director of Strategic Partnerships | G26: ccrawford@weingartfnd.org | H26: (213) 688-7799 | J26: 956054814 | K26: NEW ROLE 2024 - manages key stakeholder relationships; former ED Western Center on Law & Poverty
B27: Weingart Foundation | E27: Joyce Ybarra | F27: Vice President of Programs | G27: jybarra@weingartfnd.org | H27: (213) 688-7799 | J27: 956054814 | K27: Oversees grantmaking & learning programs; 15+ yrs at foundation; MPH UCLA
B28: Weingart Foundation | E28: Eric Medina | F28: Senior Program Officer | H28: (213) 688-7799 | J28: 956054814 | K28: 12+ yrs at Weingart; promoted May 2024
B29: Weingart Foundation | E29: Rosa Benitez | F29: Director of Program Investments | H29: (213) 688-7799 | J29: 956054814 | K29: Oversees grant investments
B30: Temple Hoyne Buell Foundation | C30: YES | D30: Primary contact with direct email/LinkedIn; most relevant for B2B pitch | E30: Laura Carlson | F30: Vice President of Programs | H30: 303-744-1688 | I30: https://www.linkedin.com/in/laura-carlson-4425513/ | J30: 846037604 | K30: 15 yrs at Buell; chairs CO Early Childhood Funders Network; decision-maker for grants
B31: Temple Hoyne Buell Foundation | E31: Steve ErkenBrack | F31: President & CEO | G31: s***@buellfoundation.org | H31: 303-744-1688 | J31: 846037604 | K31: Started Jan 2023; former DA & Chief Deputy AG Colorado; 10 yrs on board before CEO
B32: Temple Hoyne Buell Foundation | E32: Jason Callegari | F32: Director of Initiatives | H32: 303-744-1688 | J32: 846037604 | K32: Leads local financing initiatives; background in early childhood policy
B33: Temple Hoyne Buell Foundation | E33: Lesa Nesbit | F33: Senior Program Officer Supervisor | H33: 303-744-1688 | J33: 846037604 | K33: Manages grant review process; relationships with nonprofits
B34: Temple Hoyne Buell Foundation | E34: General Contact | G34: info@buellfoundation.org | H34: 303-744-1688 | J34: 846037604 | K34: HQ: 1873 S Bellaire St Suite 600 Denver CO 80222
B35: The Kresge Foundation | C35: YES | D35: Primary contact with direct email/LinkedIn; most relevant for B2B pitch | E35: Neesha Modi | F35: Director, Program & Social Investment Operations | H35: 248-643-9630 | I35: https://www.linkedin.com/in/neeshamodi/ | J35: 381359217 | K35: LEADS LIFT team; $2M/yr capacity building budget; ex-Deloitte talent strategy
B36: The Kresge Foundation | E36: Caroline Altman Smith | F36: Deputy Director, Education | H36: 248-643-9630 | I36: https://www.linkedin.com/in/cbasmith | J36: 381359217 | K36: LIFT founder; created FUEL program; on Council of Michigan Foundations board
B37: The Kresge Foundation | E37: Shamar A. Bibbins | F37: Managing Director, Environment | H37: 248-643-9630 | I37: https://www.linkedin.com/in/shamarbibbins/ | J37: 381359217 | K37: $23M Climate Change Health Equity initiative; promoted 2024
B38: Arnold and Mabel Beckman Foundation | C38: YES | D38: Primary contact with direct email/LinkedIn; most relevant for B2B pitch | E38: Dr. Anne Hultgren | F38: Executive Director & CEO | H38: 949-721-2222 | J38: 953169713 | K38: *100% is misleading - all grants use generic purpose text; grantees are research universities not nonprofits
B39: Arnold and Mabel Beckman Foundation | E39: Catrina Bryant | F39: Deputy Director | H39: 949-721-2222 | J39: 953169713 | K39: Oversees programs team; CPA; MBA Pepperdine
B40: Arnold and Mabel Beckman Foundation | E40: Nicole Patras | F40: Sr. Program Officer | H40: 949-721-2222 | I40: https://www.linkedin.com/in/nicole-patras-9a823a8b/ | J40: 953169713 | K40: Leads Beckman Young Investigator Program; heads JEDI committee
B41: Arnold and Mabel Beckman Foundation | E41: General Contact | G41: info@beckman-foundation.org | H41: 949-721-2222 | J41: 953169713 | K41: HQ: Irvine CA; focus on scientific research at elite universities
B42: Ann Jackson Family Foundation | C42: YES | D42: Primary contact with direct email/LinkedIn; most relevant for B2B pitch | E42: Palmer Jackson Jr. | F42: Managing Trustee | G42: palmer.jackson@gmail.com | H42: (805) 969-2258 | I42: https://www.linkedin.com/in/palmerjackson/ | J42: 953367511 | K42: Family foundation; 4th gen Santa Barbara native; 90% grants local; Yale/Haas MBA
B43: Price Philanthropies Foundation | C43: YES | D43: Primary contact with direct email/LinkedIn; most relevant for B2B pitch | E43: Sakara Tear | F43: Senior Director of Community Initiatives | G43: stear@pricephilanthropies.org | H43: (619) 795-2000 | I43: https://www.linkedin.com/in/sakara-tear-35853924b/ | J43: 465129465 | K43: 93% capacity; grantees are small City Heights nonprofits who need funding diversification
B44: Price Philanthropies Foundation | E44: Rosario Iannacone | F44: Human Rights Initiative Contact | G44: riannacone@pricephilanthropies.org | H44: (619) 795-2000 | J44: 465129465 | K44: Human Rights/immigrants rights portfolio
B45: Leo Adler Trust | C45: YES | D45: Primary contact with direct email/LinkedIn; most relevant for B2B pitch | E45: Carrie Folkman | F45: Committee Chair (Volunteer) | G45: leo.adler@jpmorgan.com | J45: 936289087 | K45: Bank-managed (JPMorgan trustee); hyper-local Baker County pop 18K; volunteer committee; 100% GOS; NOT GOOD B2B - too small/local
B46: Leo Adler Trust | E46: General Contact | G46: leo.adler@jpmorgan.com | J46: 936289087 | K46: Mailing: 805 SW Broadway Suite 1000 Portland OR 97205
B47: O.L. Halsell Foundation | C47: YES | D47: Primary contact with direct email/LinkedIn; most relevant for B2B pitch | E47: W. David Stauffer Jr. | F47: President | H47: (714) 546-0755 | J47: 956027266 | K47: Morgan Stanley advisor; Boys & Girls Club of Central OC board; 68% capacity grants
B48: O.L. Halsell Foundation | E48: Morgan Roach | F48: Secretary | H48: (714) 546-0755 | J48: 956027266 | K48: Trustee; single father of four
B49: O.L. Halsell Foundation | E49: James W. Schramm | F49: Treasurer | H49: (714) 546-0755 | J49: 956027266 | K49: CPA 40+ yrs; ex-Price Waterhouse; Cal State Fullerton
B50: O.L. Halsell Foundation | E50: General Contact | H50: 714-546-0755 | J50: 956027266 | K50: PO Box 6300 Santa Ana CA 92706; Orange County youth focus; grantees are small OC nonprofits
B51: The Satterberg Foundation | C51: YES | D51: Primary contact with direct email/LinkedIn; most relevant for B2B pitch | E51: Sarah Walczyk | F51: Executive Director | G51: swalczyk@satterberg.org | H51: (206) 441-3045 | I51: https://www.linkedin.com/in/sarah-walczyk-a010456/ | J51: 911501066 | K51: 82% capacity; 300+ BIPOC-led grantee partners; shifting to RETENTION mode - grantees need other funding; Trust-Based Philanthropy leader
B52: The Satterberg Foundation | E52: Rosa Peralta | F52: Senior Program Officer - Equity Impact | G52: rperalta@satterberg.org | H52: (206) 441-3045 | I52: https://www.linkedin.com/in/rosaperalta/ | J52: 911501066 | K52: Seattle College Board President; 'philanthropic infiltrator'; ex-Marguerite Casey Foundation
B53: The Satterberg Foundation | E53: Monserrat Padilla | F53: Program Officer | H53: (206) 441-3045 | I53: https://www.linkedin.com/in/monserrat-padilla/ | J53: 911501066 | K53: 12+ yrs capacity building for LGBTQ+ and immigrant orgs; ex-WA Immigrant Solidarity Network
B54: W.M. Keck Foundation | C54: YES | D54: Primary contact with direct email/LinkedIn; most relevant for B2B pitch | E54: Allison M. Keller | F54: President & CFO | G54: info@wmkeck.org | H54: (213) 612-2000 | J54: 956092354 | K54: *75% misleading - grantees are research universities (USC UCLA Caltech Stanford); project grants not capacity
B55: W.M. Keck Foundation | E55: Anneli Stone | F55: Program Director | G55: socal@wmkeck.org | H55: (213) 612-2000 | J55: 956092354 | K55: SoCal Program contact; $100K-$500K project grants to LA nonprofits
B56: W.M. Keck Foundation | E56: Saskia Pallais | F56: Program Officer | H56: (213) 612-2000 | J56: 956092354 | K56: Program officer
B57: W.M. Keck Foundation | E57: General Contact | G57: info@wmkeck.org | H57: (213) 612-2000 | J57: 956092354 | K57: 515 S Flower St Suite 800 LA CA 90071; Research = universities; SoCal = project grants not capacity
B58: Fred Maytag Family Foundation | C58: YES | D58: Primary contact with direct email/LinkedIn; most relevant for B2B pitch | E58: Frederick L. Maytag III | F58: CEO/Vice President | J58: 421444870 | K58: Family foundation; Newton Iowa roots (Maytag appliance); 76% GOS; small grantee pool (81) limits B2B scale
B59: Fred Maytag Family Foundation | E59: Kenneth P. Maytag | F59: CFO/President | J59: 421444870 | K59: President/Trustee
B60: Fred Maytag Family Foundation | E60: Julia Damir | F60: Foundation Administrator | J60: 421444870 | K60: Secretary; manages day-to-day operations
B61: Fred Maytag Family Foundation | E61: General Contact | J61: 421444870 | K61: 3701 Sacramento St Suite 369 San Francisco CA 94118; Iowa focus; avg grant $153K
B62: The Crail-Johnson Foundation | C62: YES | D62: Primary contact with direct email/LinkedIn; most relevant for B2B pitch | E62: Rachel Roth | F62: Executive Director | G62: rroth@crail-johnson.org | H62: (310) 519-7413 | I62: https://www.linkedin.com/in/raeroth/ | J62: 330247161 | K62: 58% GOS; San Pedro/South LA children focus; provides TA to grantees; STRONG B2B prospect
B63: The Crail-Johnson Foundation | E63: General Contact | G63: info@crail-johnson.org | H63: (310) 519-7413 | J63: 330247161 | K63: 461 W 6th St Suite 300 San Pedro CA 90731; 3 grant cycles (Education/Human Services/Health)
B64: Ronald W. Naito MD Foundation | C64: YES | D64: Primary contact with direct email/LinkedIn; most relevant for B2B pitch | E64: Kris Anderson | F64: Executive Director | G64: info@rwnfoundation.org | I64: https://www.linkedin.com/in/krisandersonpdx/ | J64: 836622391 | K64: 64% capacity; Climate/Health Equity/Oregon Arts focus; PAUSING new apps = grantees need other funding; consultant-run
B65: Ronald W. Naito MD Foundation | E65: Elizabeth Anderson | F65: Board President | G65: info@rwnfoundation.org | J65: 836622391 | K65: Board President
B66: Ronald W. Naito MD Foundation | E66: General Contact | G66: info@rwnfoundation.org | J66: 836622391 | K66: 25 NW 23rd Pl Suite 6-152 Portland OR 97210; founded 2019; $2.8M granted 2023
B67: Medina Foundation | C67: YES | D67: Primary contact with direct email/LinkedIn; most relevant for B2B pitch | E67: Jennifer Teunon | F67: Executive Director | H67: (206) 652-8783 | I67: https://www.linkedin.com/in/jennifer-teunon-a5927024 | J67: 910745225 | K67: SUNSETTING 2025-2028; no new LOIs after July 2025; 30 yrs nonprofit exp; ED since 2013
B68: Medina Foundation | E68: Aana Lauckhart | F68: Senior Program Officer | H68: (206) 652-8783 | J68: 910745225 | K68: King County grantmaking since 2012
B69: Medina Foundation | E69: Jessica Case | F69: Senior Program Officer | H69: (206) 652-8783 | J69: 910745225 | K69: Rural counties focus
B70: Medina Foundation | E70: General Contact | G70: (206) 652-8783 | H70: 206-652-8783 | J70: 910745225 | K70: 801 2nd Ave Suite 1108 Seattle WA 98104; 55% capacity but WINDING DOWN - not a B2B target
B71: Marie Lamfrom Charitable Foundation | C71: YES | D71: Primary contact with direct email/LinkedIn; most relevant for B2B pitch | E71: Tyler Hobbs | F71: President | G71: tyler@marielamfrom.org | I71: https://www.linkedin.com/in/johntylerhobbs/ | J71: 931254171 | K71: 57% capacity; 958 grantees; expanded GOS & multi-year; BIPOC/LGBTQ+ focus; Oregon's #2 capacity builder
B72: Marie Lamfrom Charitable Foundation | E72: Keisha Olsen | F72: Director of Grant Programs | G72: keisha@marielamfrom.org | I72: https://www.linkedin.com/in/keisha-olsen-590484ab/ | J72: 931254171 | K72: Oversees Zinnia Grant (transformative awards); manages Program Officer team
B73: Marie Lamfrom Charitable Foundation | E73: Brittany Leland | F73: Sr. Director of Operations | G73: brittany@marielamfrom.org | J73: 931254171 | K73: Operations lead; could discuss infrastructure tools
B74: Marie Lamfrom Charitable Foundation | E74: Marina Bhargava | F74: Program Officer | G74: marina@marielamfrom.org | J74: 931254171 | K74: Evaluates applicants; direct grantee relationships
B75: Marie Lamfrom Charitable Foundation | E75: General Contact | G75: info@marielamfrom.org | J75: 931254171 | K75: 29030 SW Town Center Loop E Ste 202 Wilsonville OR 97070; Rose/Daffodil = capacity grants
B76: The Marisla Foundation | C76: YES | D76: Primary contact with direct email/LinkedIn; most relevant for B2B pitch | E76: Sara Lowell | F76: Marine Program Director | G76: sara@marisla.org | H76: 949-494-0365 | J76: 330200133 | K76: *57% capacity misleading - grantees are large env orgs (Oceana TNC NRDC) & intermediaries; not small nonprofits needing funding help
B77: The Marisla Foundation | E77: Peggy Lauer | F77: Human Services Program Director / Administrator | G77: peggy@marisla.org | H77: 949-494-0365 | J77: 330200133 | K77: Human Services via OC Community Foundation; funding few new grantees; 3 staff
B78: Lisa & Douglas Goldman Fund | C78: YES | D78: Primary contact with direct email/LinkedIn; most relevant for B2B pitch | E78: Nancy Kami | F78: Executive Director | G78: NKami@ldgfund.org (inferred) | H78: 415-771-1717 | I78: https://www.linkedin.com/in/nancy-kami-0014a95/ | J78: 943167546 | K78: 53% capacity; 27 yrs at fund; Levi Strauss heir family; $14.3M granted 2024; democracy/climate/education focus
B79: Lisa & Douglas Goldman Fund | E79: Pamela Allen | F79: Senior Program Officer | G79: PAllen@ldgfund.org (inferred) | H79: 415-771-1717 | J79: 943167546 | K79: Program officer; manages grantmaking; SF Bay Area based
B80: Lisa & Douglas Goldman Fund | E80: Debbie Findling Ed.D | F80: Strategic Philanthropy Advisor | H80: 415-771-1717 | J80: 943167546 | K80: Strategic role; Ed.D suggests capacity/education background
B81: Lisa & Douglas Goldman Fund | E81: General Contact | G81: [email protected] | H81: 415-771-1717 | J81: 943167546 | K81: 1 Montgomery St Suite 3440 SF CA 94104; email format: FLast@ldgfund.org
B82: Joseph Drown Foundation | C82: YES | D82: Primary contact with direct email/LinkedIn; most relevant for B2B pitch | E82: Alyssa Santino | F82: President of Programs & Operations | G82: alyssa@jdrown.org | H82: (310) 277-4488 | I82: https://www.linkedin.com/in/alyssa-santino-67a90397/ | J82: 956093178 | K82: 51% GOS; LA County education focus; 70-yr history; professional staff; grants $100K-500K
B83: Joseph Drown Foundation | E83: Ann Miller | F83: President of Finance & Investments | G83: ann@jdrown.org | H83: (310) 277-4488 | J83: 956093178 | K83: Finance lead
B84: Joseph Drown Foundation | E84: Anamaria Alarcón | F84: Program Associate | G84: anamaria@jdrown.org | H84: (310) 277-4488 | J84: 956093178 | K84: Program associate; grantee relationships
B85: Joseph Drown Foundation | E85: Wendy Wachtell | F85: Board Chair | H85: (310) 277-4488 | J85: 956093178 | K85: Board Chair; key decision-maker
B86: Joseph Drown Foundation | E86: General Contact | G86: info@jdrown.org | H86: (310) 277-4488 | J86: 956093178 | K86: LA County; deadlines Jan/Apr/Jul/Oct 15; max 4 consecutive yrs funding

Sheet Sheet4
C2: 1875 Finance | E2: +41-22-310-1875 | F2: TBD | G2: Philanthropy Advisory | I2: CH | M2: Swiss | N2: Foundation Management | O2: MFO
C3: Alliance for Innovative Regulation | E3: (917) 446-5425 | F3: David Ehrich | G3: Executive Director | I3: DC | M3: Promoting responsible innovation to solve financial services challenges. | N3: Nonprofit | O3: Education
C4: Arnold and Mabel Beckman Foundation | F4: Bad | I4: CA | K4: 953169713 | M4: Science focus; very high capacity %
C5: Atkinson Foundation | E5: 650-876-0222 | I5: CA | K5: 946075613 | M5: Bay Area
C6: Austin Justice Coalition | E6: (512) 576-8152 | F6: Chas Moore | G6: Executive Director | I6: TX | M6: Improving quality of life for people of color in Austin. | N6: Nonprofit | O6: Human Services
C7: Ballentine Partners | E7: 781-314-1300 | F7: TBD | G7: Philanthropy Advisory | I7: MA | M7: Fee-only | N7: Foundation Management | O7: MFO
C8: Bangor Savings Bank Foundation | E8: (877) 226-4671 | F8: Foundation Team | G8: Foundation Staff | I8: ME | L8: https://www.bangor.com/the-bangor-savings-bank-foundation | M8: Battle Creek, MI; use Concierge Desk for inquiries | N8: Foundation
C9: Bess J. Hodges Foundation | I9: CA | K9: 330046140 | M9: Very high capacity %
C10: Blue Shield of California Foundation | E10: 415-901-3200 | I10: CA | K10: 942822302 | M10: Healthcare focus; good network
C11: Brittingham Family Foundation | I11: CA | K11: 262992045 | M11: San Diego
C12: Caprock | E12: 208-368-9600 | F12: Sophie Kelly | G12: Director of Impact Investments | I12: PA | M12: Impact investing | N12: Foundation Management | O12: MFO
C13: Charlotte Y. Martin Foundation | I13: WA | K13: 472057123 | M13: Washington; high capacity %
C14: Coda Media | E14: (650) 208-6846 | F14: Natalia Antelava | G14: CEO & Editor-in-Chief | I14: NY | M14: Publishing news articles on global crises - making complex issues accessible. | N14: Nonprofit | O14: Media
C15: Competency-Based Education Network | E15: (615) 517-1256 | F15: Charla Sheid Long | G15: President | I15: TN | M15: Catalyzing competency and skills-first society for all individuals. | N15: Nonprofit | O15: Education
C16: Conrad Prebys Foundation | E16: 858-565-6480 | I16: CA | K16: 203216993 | M16: $1.1B assets; San Diego
C17: Crescent Grove | E17: 847-752-9479 | F17: TBD | G17: Philanthropy Advisory | I17: WI | M17: Midwest | N17: Foundation Management | O17: MFO
C18: Crestview Academy | E18: (715) 835-2275 | F18: Margaret Waldhart-Larsen | G18: President | I18: WI | M18: Helping students reach potential academically and morally. | N18: Nonprofit | O18: Education
C19: CS Fund | I19: CA | K19: 953607882
C20: Descendants Truth and Reconciliation | E20: (225) 297-1120 | F20: La June Montgomery Tabron | G20: President & CEO | I20: LA | M20: Supporting truth-seeking, racial healing and transformation programs. | N20: Nonprofit | O20: Civil Rights
C21: Dogwood Health Trust | E21: (828) 771-6710 | F21: Grants Help Desk | G21: Via Grants Help Desk | I21: NC | L21: https://dogwoodhealthtrust.org/about/meet-the-team/ | M21: Los Angeles-based; Southern California focus | N21: Foundation
C22: Educopia Institute | E22: (404) 532-9766 | F22: Jessica Meyerson | G22: Co-Executive Director | I22: GA | M22: Connecting diverse knowledge communities with resources and power. | N22: Nonprofit | O22: Arts & Culture
C23: Elmina B. Sewall Foundation | E23: (207) 373-9206 | F23: Laura Dover | G23: Grants Contact | I23: ME | L23: https://sewallfoundation.org/staff-board | M23: ~130 employees; ~$631M annual grantmaking; ~3,000 active grants | N23: Foundation
C24: Firedoll Foundation | I24: CA | K24: 943301999
C25: Fleishhacker Foundation | E25: 415-561-5350 | I25: CA | K25: 946051048 | M25: SF Bay Area
C26: Foundation Source | E26: 800-839-0054 | F26: Elizabeth Wong | G26: Head of Philanthropic Advisory | I26: CT | M26: TOP TARGET | N26: Foundation Management | O26: MFO
C27: Fred Maytag Family Foundation | F27: Frederick L. Maytag III | G27: CEO/Vice President | I27: CA | J27: 2. Good | K27: 421444870
C28: Frontlines International | E28: (813) 293-6206 | F28: Charles White | G28: President | I28: FL | M28: Supporting persecuted Christians worldwide. | N28: Nonprofit | O28: Human Services
C29: FThree Foundation | I29: CA | K29: 943376857
C30: Fusion Global | E30: (856) 341-0396 | F30: Jason Sobel | G30: President | I30: NJ | M30: Connecting old and new to bring faith alive in new ways. | N30: Nonprofit | O30: Religion
C31: Gaia Fund | I31: CA | K31: 943215541 | M31: Environment focus
C32: Gaylord and Dorothy Donnelley Foundation | E32: (312) 977-2700 | F32: Foundation Staff | G32: Program Officer | I32: IL | L32: https://gddf.org/about/staff/ | M32: Board Chair: Linda Hilton; $7B+ in assets | N32: Foundation
C33: Global 70 MFO | D33: 46027 | E33: TBD | F33: TBD | G33: Philanthropy Advisory | I33: HK | M33: Network of 70 families | N33: Foundation Management | O33: MFO
C34: Global Food Partners | E34: (727) 237-6223 | F34: Elissa Lane | G34: President & CEO | I34: DC | M34: Improving conditions for animals in food supply chain - cage-free eggs focus. | N34: Nonprofit | O34: Food & Nutrition
C35: Gresham Partners | E35: 312-327-5020 | F35: TBD | G35: Philanthropy Advisory | I35: IL | M35: Pritzker connections | N35: Foundation Management | O35: MFO
C36: Growth Opportunity Partners | E36: (216) 462-0600 | F36: Michael Jeans | G36: President | I36: OH | M36: Advisory services for under-resourced communities to improve quality of life. | N36: Nonprofit | O36: Community Improvement
C37: Hatch Inc | E37: (317) 331-3364 | F37: Daniel Leckie | G37: Executive Director | I37: IN | M37: Hatch for Hunger connects egg producers with food banks - 11M eggs in 36 states. | N37: Nonprofit | O37: Food & Nutrition
C38: Hero's Journey Foundation | E38: (412) 363-1530 | F38: Michael Mervosh | G38: Executive Director | I38: PA | M38: Adventures and experiences for individuals seeking spirit and aliveness. | N38: Nonprofit | O38: Mental Health
C39: Hottinger Group | E39: +44-20-7399-0000 | F39: TBD | G39: Philanthropy Advisory | I39: UK | M39: Rothschild 2025 | N39: Foundation Management | O39: MFO
C40: Houston Endowment | E40: (713) 238-8100 | F40: Communications Team | G40: Via Invited Process | I40: TX | L40: https://houstonendowment.org/about/people | N40: Foundation
C41: Hutton Foundation | I41: CA | K41: 330779894
C42: Intrepid Philanthropy Foundation | I42: CA | K42: 300527867
C43: James F. & Marion L. Miller Foundation | E43: 503-228-0492 | I43: OR | K43: 30373895 | M43: Oregon arts/education
C44: John D. and Catherine T. MacArthur Foundation | E44: (312) 726-8000 | F44: Grants Team | G44: Info for Grantseekers | I44: IL | L44: https://www.macfound.org/about/contact-us | M44: President: Brenda Solórzano; oversees grant programs and health justice funding | N44: Foundation
C45: Joseph Drown Foundation | E45: 310-277-4488 | F45: Alyssa Santino | G45: President of Programs & Operations | H45: alyssa@jdrown.org | I45: CA | J45: 2. Good | K45: 956093178 | M45: LA area
C46: Kankouran West African Dance | E46: (202) 518-1213 | F46: Assane Konte | G46: President | I46: DC | M46: Preserving and promoting traditional West African performing arts. | N46: Nonprofit | O46: Arts & Culture
C47: Kennedy Wilson Charitable Foundation | I47: CA | K47: 954682181 | M47: High capacity %
C48: Koret Foundation | E48: 415-882-7740 | I48: CA | K48: 941624987 | M48: SF Bay Area; large grantee network
C49: Leo Adler Trust | F49: Bad | I49: OR | K49: 936289087 | M49: Oregon regional
C50: Lisa & Douglas Goldman Fund | E50: 415-771-1717 | F50: Nancy Kami | G50: Executive Director | H50: NKami@ldgfund.org (inferred) | I50: CA | J50: 1. Excellent | K50: 943167546 | M50: SF Bay Area
C51: Marie Lamfrom Charitable Foundation | F51: Tyler Hobbs | G51: President | H51: tyler@marielamfrom.org | I51: OR | J51: 1. Excellent | K51: 931254171 | M51: TOP 5 PRIORITY - 958 grantees Oregon
C52: McCune Charitable Foundation | E52: (505) 983-8300 | F52: Ernesto Torres | G52: Grants Contact | I52: NM | L52: https://www.nmmccune.org/about/ | M52: Directors: Lauren Bon, Gregory Annenberg Weingarten, Charles Annenberg Weingarten | N52: Foundation
C53: Medina Foundation | E53: 206-652-8783 | F53: Jennifer Teunon | G53: Executive Director | I53: WA | K53: 910745225 | M53: They are winding down and their grantees need new funders.
C54: Meeschaert | E54: +33-1-53-40-20-20 | F54: TBD | G54: Philanthropy Advisory | I54: FR | M54: French | N54: Foundation Management | O54: MFO
C55: Mid-Hudson Energy Transition | E55: (845) 383-1050 | F55: Susan Gillespie | G55: President | I55: NY | M55: Empowering municipalities to own renewable energy and build community wealth. | N55: Nonprofit | O55: Environment
C56: Mitchell Kapor Foundation | I56: CA | K56: 943330604 | M56: Tech/social justice
C57: Munzer Foundation | I57: CA | K57: 330686779 | M57: LA area
C58: National Assoc for Family School & Community | E58: (703) 518-5546 | F58: Vito Borrello | G58: Executive Director | I58: VA | M58: Advancing family engagement practices to improve children's learning. | N58: Nonprofit | O58: Education
C59: Organizing Institute South and West | E59: (512) 459-6551 | F59: Joe Rubio | G59: Executive Director | I59: TX | M59: Strengthening organizing and developing organizers for Industrial Areas Foundation. | N59: Nonprofit | O59: Community Improvement
C60: Otto Bremer Trust | E60: (651) 227-8036 | F60: Danielle Cheslog | G60: Director of Grant Operations | I60: MN | L60: https://ottobremer.org/about-us/staff-trustees/ | M60: Chicago-based; arts, land conservation, and regional programs | N60: Foundation
C61: Oyate Group | E61: (718) 344-2930 | F61: Tomas Ramos | G61: President/CEO | I61: NY | M61: Alleviating poverty through sustainable solutions for NYC communities. | N61: Nonprofit | O61: Youth Development
C62: Pinpoint Foundation | I62: CA | K62: 352559691
C63: Pipeline Inc | E63: (913) 307-0004 | F63: Melissa Vincent | G63: Executive Director | I63: KS | M63: Entrepreneurial program for high-growth companies in the Midwest. | N63: Nonprofit | O63: Community Improvement
C64: Pittsburgh Christian Academy | E64: (412) 235-9757 | F64: John Isett | G64: President | I64: PA | M64: Christian school offering Christian-based curriculum. | N64: Nonprofit | O64: Education
C65: Pohlad Family Foundation | E65: (612) 661-3801 | F65: Brian Paulson | G65: Contact from 990 | I65: MN | L65: https://pohladfoundation.org/our-team/ | M65: New Mexico focus; Santa Fe-based | N65: Foundation
C66: Ralph Wilson Park Conservancy | E66: (716) 479-4124 | F66: Katie Campos | G66: Executive Director | I66: NY | M66: Operating and maintaining parks and public spaces in Buffalo, NY. | N66: Nonprofit | O66: Recreation
C67: Richter Family Office | E67: +1-514-934-3400 | F67: TBD | G67: Philanthropy Advisory | I67: QC | M67: Canadian | N67: Foundation Management | O67: MFO
C68: Rockefeller Capital | E68: 212-549-5100 | F68: Timothy O'Hara | G68: President - Multi-Family Office | I68: NY | M68: Philanthropy solutions team | N68: Foundation Management | O68: MFO
C69: Ronald W. Naito MD Foundation | F69: Kris Anderson | G69: Executive Director | H69: info@rwnfoundation.org | I69: OR | J69: 2. Good | K69: 836622391 | M69: Oregon; healthcare focus
C70: S. Mark Taper Foundation | E70: 213-229-0134 | I70: CA | K70: 320516588 | M70: LA area
C71: Safe City Commission | E71: (817) 885-7774 | F71: Ken Shetter | G71: President | I71: TX | M71: Supporting law enforcement and crime prevention in Fort Worth. | N71: Nonprofit | O71: Public Safety
C72: Sand Hill Foundation | I72: CA | K72: 943219107 | M72: Silicon Valley
C73: Sierra Health Foundation | E73: 916-922-4755 | I73: CA | K73: 680050036 | M73: Sacramento; health focus
C74: Silvercrest | E74: 212-649-0600 | F74: TBD | G74: Director - Foundation Services | I74: NY | M74: OCIO focus | N74: Foundation Management | O74: MFO
C75: Stanhope Capital | E75: +44-20-7822-0900 | F75: TBD | G75: Philanthropy Advisory | I75: UK | M75: UK-based | N75: Foundation Management | O75: MFO
C76: State Power Caucus | E76: (703) 912-1264 | F76: Margie Del Castillo | G76: Executive Director | I76: VA | M76: Building multiracial alignment for economic, racial, environmental justice. | N76: Nonprofit | O76: Civil Rights
C77: Stonehage Fleming | E77: +44-1534-500-400 | F77: TBD | G77: Philanthropy Advisory | I77: UK | M77: Global; need UK research | N77: Foundation Management | O77: MFO
C78: T. Gary & Kathleen Rogers Foundation | I78: CA | K78: 651202020 | M78: 100% capacity grants
C79: TAG Associates | E79: 212-274-0200 | F79: TBD | G79: Philanthropy Advisory | I79: NY | M79: Need research | N79: Foundation Management | O79: MFO
C80: The Annenberg Foundation | E80: (610) 341-9268 | F80: Leadership Team | G80: Directors | I80: PA | L80: https://annenberg.org/about/contact-us/ | M80: Chattanooga, TN-based; faith-based grantmaking | N80: Foundation
C81: The Autzen Foundation | I81: OR | K81: 936021333 | M81: Oregon; 652 grantees - large network
C82: The Bamford Foundation | I82: WA | K82: 911504193 | M82: Washington
C83: The California Endowment | E83: (213) 928-8800 | F83: Carolyn Wang Kong | G83: Chief Strategy Officer | I83: CA | L83: https://www.calendow.org/about/leadership/ | M83: Health-focused foundation in Los Angeles area | N83: Foundation
C84: The Crail-Johnson Foundation | E84: (310) 519-7413 | F84: Rachel Roth | G84: Executive Director | H84: rroth@crail-johnson.org | I84: CA | J84: 1. Excellent | K84: 330247161 | M84: LA area children/youth
C85: The Fletcher Jones Foundation | E85: 213-943-4646 | I85: CA | K85: 237030155 | M85: Higher education focus
C86: The Howard Gilman Foundation | E86: (212) 408-0400 | F86: Foundation Team | G86: Via Contact Page | I86: NY | L86: https://howardgilmanfoundation.org/our-team/ | M86: Troy, MI; $4B+ assets; arts, education, environment, health | N86: Foundation
C87: The Kresge Foundation | E87: (248) 643-9630 | F87: Neesha Modi | G87: Director of Program & Social Investment Operations | I87: MI | L87: https://www.kresge.org/about/ | M87: Houston area focus; invited applicants only; $2.4B assets | N87: Foundation
C88: The MacLellan Foundation | E88: (423) 755-1051 | F88: David G. Denmark | G88: Contact from 990 | I88: TN | L88: https://www.maclellan.net/about/ | M88: Denver-based; children and families in Colorado focus | N88: Foundation
C89: The Marisla Foundation | I89: CA | K89: 330200133 | M89: Environment focus
C90: The McKnight Foundation | E90: (612) 333-4220 | F90: Neeraj Mehta | G90: Vice President of Programs | I90: MN | L90: https://www.mcknight.org/about/staff-board/ | M90: Exec Dir: Stephanie Cornell; $5.7B assets; education, environment, home region | N90: Foundation
C91: The Ralph M. Parsons Foundation | E91: 213-362-7600 | I91: CA | K91: 956085895 | M91: TOP 5 PRIORITY - 729 grantees
C92: The Renaissance Foundation | I92: OR | K92: 931306116 | M92: Oregon
C93: The Roddenberry Foundation | I93: CA | K93: 954755672 | M93: Star Trek legacy; social justice
C94: The Russell Family Foundation | E94: 253-858-5050 | I94: WA | K94: 911663336 | M94: Washington; environment
C95: The Skoll Foundation | E95: 650-331-1031 | I95: CA | K95: 113659133 | M95: Social entrepreneurship
C96: The Sobrato Family Foundation | E96: 650-917-2464 | I96: CA | K96: 770348912 | M96: $877M assets; Silicon Valley
C97: The Zellerbach Family Foundation | E97: 415-421-2629 | I97: CA | K97: 946069482 | M97: SF Bay Area; immigrant focus
C98: Thelma Gibson Health Initiative | E98: (305) 446-1543 | F98: Merline Barton | G98: Executive Director | I98: FL | M98: Quality social services for underserved groups in Coconut Grove and South Miami. | N98: Nonprofit | O98: Health
C99: Tolleson Wealth | E99: 214-252-3250 | F99: TBD | G99: Philanthropy Advisory | I99: TX | M99: Texas-based | N99: Foundation Management | O99: MFO
C100: Tony Blair Foundation | E100: (760) 586-4242 | F100: Paolo Pellegrini | G100: President | I100: NY | M100: Supporting governance initiatives across Africa. | N100: Nonprofit | O100: International
C101: Upturn Inc | E101: (202) 677-2359 | F101: Harlan Yu | G101: President & Executive Director | I101: DC | M101: Advancing equity and justice in technology design and governance. | N101: Nonprofit | O101: Civil Rights
...

Sheet Sheet5
B3: Rating | C3: Foundation Name | D3: State | E3: Time Zone | F3: Assets | G3: Grantees | H3: Contact Name | I3: Contact Title | J3: Email | K3: Phone | L3: LinkedIn | M3: Website | N3: Why This Rating | O3: Notes | P3: EIN
A4: =_xlfn.XLOOKUP(P4,Calls!L:L,Calls!B:B) -> MEDINA FOUNDATION | B4: Excellent | C4: MEDINA FOUNDATION | D4: WA | E4: Pacific | F4: 103615717 | H4: Jennifer Teunon | I4: Executive Director | K4: 206-652-8783 | N4: Puget Sound human services focus. 4 CB service grants. Funds racial equity, general operating. SUNSETTING 3-5 years - grantees urgently need other funders. | O4: $104M assets. Top grantees: YMCA Seattle, Plymouth Housing, DESC, Housing Hope - all community nonprofits. Staff: Jessica Case & Aana Lauckhart (Senior Program Officers), Alexia Casiano (Grants Manager). No longer accepting new LOIs as of July 2025. Address: 801 2nd Ave #1108, Seattle WA 98104. | P4: 910745225
A5: =_xlfn.XLOOKUP(P5,Calls!L:L,Calls!B:B) -> HELLMAN FOUNDATION | B5: Excellent | C5: HELLMAN FOUNDATION | D5: CA | E5: Pacific | F5: 635837954 | H5: Dorian Luey | I5: Director, Capacity Building | K5: 415-837-5408 | N5: SF Bay Area community focus. Funds health equity, education, youth development, food access. Has capacity building director. Sunsetting by 2034 - grantees need help finding other funders. | O5: $636M assets. Managed by Third Plateau. ED: Annie Ulevitch. Collaborative Change Initiative. $310M granted to date. Accelerating giving before 2034 sunset. Media: media@thirdplateau.com. Address: 595 Market St #820, SF CA 94105. | P5: 611583546
A6: =_xlfn.XLOOKUP(P6,Calls!L:L,Calls!B:B) -> RAIKES FOUNDATION | B6: Excellent | C6: RAIKES FOUNDATION | D6: WA | E6: Pacific | F6: 90404225 | H6: Dr. Zoe Stemm-Calderon | I6: Executive Director (starting Jan 2026) | J6: info@raikesfoundation.org | K6: (206) 801-9500 | N6: Seattle-based, national reach. 7 CB service grants. Funds education, youth homelessness, democracy/equity. Top grantees include Seattle Foundation, National Equity Project. | O6: $90M assets. Founded by Jeff & Tricia Raikes (Microsoft). Chief of Staff: Fatima Gulamali. ~24 employees. Focus: K-12 education, youth housing stability, impact philanthropy, community organizing. Address: 2157 N Northlake Way #220, Seattle WA 98103. | P6: 912173492
A7: =_xlfn.XLOOKUP(P7,Calls!L:L,Calls!B:B) -> SEMPRA FOUNDATION | B7: Excellent | C7: SEMPRA FOUNDATION | D7: CA | E7: Pacific | F7: 14132710 | G7: 688 | H7: Christy Ihrig | I7: Director | K7: 619-696-2467 | M7: WWW.SEMPRAFOUNDATION.ORG | N7: 688 dependent grantees - massive reach. 2,382 grants last year. Corporate foundation of Sempra Energy in San Diego. Focus: education, environment, emergency preparedness. High-volume grantor with broad community impact. | O7: Address: 488 8th Avenue, HQ08S3, San Diego CA 92101. Also: Andy Carrasco (Director). Recent grantees: Monarch School (homeless youth), MAAC (anti-poverty), Voices for Children (CASAs). Online application portal available. Founded 2007, invested $50M+. | P7: 261325469
A8: =_xlfn.XLOOKUP(P8,Calls!L:L,Calls!B:B) -> First Interstate BancSystem Foundation | B8: Excellent | C8: First Interstate BancSystem Foundation | D8: MT | E8: Mountain | F8: 20270202 | G8: 538 | H8: Mr. Reuter | I8: Chair, Foundation Board of Directors | J8: firstinterstatefoundation@fib.com | K8: 406-255-5393 | M8: firstinterstatebank.com | O8: Chair leads 5-member board. PO Box 7113, Billings MT 59103. LOI via nearest bank branch first. Focus: community development, leadership. | P8: 810465899
A9: =_xlfn.XLOOKUP(P9,Calls!L:L,Calls!B:B) -> THE COLORADO HEALTH FOUNDATION | B9: Excellent | C9: THE COLORADO HEALTH FOUNDATION | D9: CO | E9: Mountain | F9: 2822619846 | G9: 238 | H9: Karen McNeil-Miller | I9: President and CEO | K9: 303-953-3628 | M9: WWW.COLORADOHEALTH.ORG | N9: $2.8 BILLION assets - largest foundation in batch by far. 238 dependent Colorado grantees. Professional staff with CEO, Chief Impact Officer, VP Philanthropy - all with direct phone numbers. Major health equity funder. | O9: Chief Impact Officer: Bruce Byington (303.953.3689). VP Philanthropy: Amy Latham (303.953.3670). Main: 303-953-3600. Address: 1780 Pennsylvania St, Denver CO 80203. Focus: health equity in Colorado. Top grantees: Trailhead Institute, Latino Community Foundation, Ute tribes, Denver Foundation. | P9: 742568941
A10: =_xlfn.XLOOKUP(P10,Calls!L:L,Calls!B:B) -> The Ford Family Foundation | B10: Excellent | C10: The Ford Family Foundation | D10: OR | E10: Pacific | F10: 1125032912 | G10: 171 | H10: Keavy Cook | I10: Vice President of Programs | J10: keavy@tfff.org | K10: (541) 957-5574 | L10: https://www.linkedin.com/in/keavy-cook-ab758110/ | M10: www.tfff.org | N10: 171 dependent rural Oregon grantees. 64 CB grants for strategic planning. VP of Programs (Keavy Cook) newly promoted Dec 2024 with direct email. | O10: Promoted Dec 2024. Also: Kasi Allen (VP Learning & Impact). HQ: Roseburg OR. | P10: 936026156
A11: =_xlfn.XLOOKUP(P11,Calls!L:L,Calls!B:B) -> Conrad N. Hilton Foundation | B11: Excellent | C11: CONRAD N HILTON FOUNDATION | D11: CA | E11: Pacific | F11: 7099706570 | G11: 170 | H11: Christie Cardenas | I11: Program Officer - Opportunity Youth | J11: ccardenas@hiltonfoundation.org | L11: https://www.linkedin.com/in/christie-cardenas/ | M11: WWW.HILTONFOUNDATION.ORG | O11: 15+ years equity-focused grantmaking. Email pattern based on CEO Peter Laugharn (plaugharn@hiltonfoundation.org). LinkedIn: linkedin.com/in/christie-cardenas/ | P11: 943100217
A12: =_xlfn.XLOOKUP(P12,Calls!L:L,Calls!B:B) -> MARIE LAMFROM CHARITABLE FOUNDATION | B12: Excellent | C12: MARIE LAMFROM CHARITABLE FOUNDATION | D12: OR | E12: Pacific | F12: 374872001 | G12: 149 | H12: Tyler Hobbs | I12: President | J12: tyler@marielamfrom.org | L12: https://www.linkedin.com/in/johntylerhobbs/ | M12: WWW.MARIELAMFROM.ORG | O12: 57% capacity; 958 grantees; expanded GOS & multi-year; BIPOC/LGBTQ+ focus; Oregon's #2 capacity builder | P12: 931254171
A13: =_xlfn.XLOOKUP(P13,Calls!L:L,Calls!B:B) -> M J MURDOCK CHARITABLE TRUST | B13: Excellent | C13: M J MURDOCK CHARITABLE TRUST | D13: WA | E13: Pacific | F13: 1892899273 | G13: 134 | H13: Kimberly Thornbury, Ph.D. | I13: Vice President, Programs & Partnerships | J13: info@murdocktrust.org | K13: (360) 694-8415 | L13: https://www.linkedin.com/in/kimberly-thornbury-12451b28/ | M13: WWW.MURDOCKTRUST.ORG | N13: 134 dependent grantees in Pacific NW, 59 CB grants. VP Programs focuses on board governance, exec leadership, fundraising capacity. | O13: Also: Jill Lemke (VP Grants Mgmt), Pauline Fong (Chief Program Officer). Focus: AK, ID, MT, OR, WA. Free nonprofit resources. | P13: 237456468
A14: =_xlfn.XLOOKUP(P14,Calls!L:L,Calls!B:B) -> The California Wellness Foundation | B14: Excellent | C14: THE CALIFORNIA WELLNESS FOUNDATION | D14: CA | E14: Pacific | F14: 1042135742 | G14: 126 | H14: Monica Gomez | I14: Program Officer - Equity in Access & Economic Security | J14: info@calwellness.org | K14: 818-702-1900 | L14: https://www.linkedin.com/in/gomezmonica22/ | M14: WWW.CALWELLNESS.ORG | O14: 20+ years nonprofit experience. Focuses on capacity-building for social change orgs. LA: 818-702-1900, Oakland: 415-908-3000. No direct emails published. | P14: 954292101
A15: =_xlfn.XLOOKUP(P15,Calls!L:L,Calls!B:B) -> The James Irvine Foundation | B15: Excellent | C15: The James Irvine Foundation | D15: CA | E15: Pacific | F15: 3300619484 | G15: 109 | H15: Don Howard | I15: President & CEO | J15: dhoward@irvine.org | L15: www.irvine.org | M15: www.Irvine.org | O15: Direct CEO email confirmed. Also: Cindy Downing (Program Officer, manages Leadership Awards). 1 Bush St Ste 800, San Francisco CA 94104. ~80 employees. $158.7M grants in 2024. | P15: 941236937
A16: =_xlfn.XLOOKUP(P16,Calls!L:L,Calls!B:B) -> Meyer Memorial Trust | B16: Excellent | C16: MEYER MEMORIAL TRUST | D16: OR | E16: Pacific | F16: 885167113 | G16: 107 | H16: Nancy Haque | I16: Director of Policy and Programs | J16: questions@mmt.org | K16: 503-228-5512 | L16: https://www.linkedin.com/in/nancy-haque-8470305/ | M16: WWW.MMT.ORG | O16: Decision-maker for programs | P16: 930806316
A17: =_xlfn.XLOOKUP(P17,Calls!L:L,Calls!B:B) -> THE ROUNDHOUSE FOUNDATION | B17: Excellent | C17: THE ROUNDHOUSE FOUNDATION | D17: OR | E17: Pacific | F17: 358883108 | G17: 91 | H17: Erin Borla | I17: Executive Director & Trustee | J17: erin@roundhousefoundation.org | K17: 541-904-0700 | M17: https://roundhousefoundation.org | N17: 91 dependent grantees (rural Oregon nonprofits). 6 CB service grants including strategic planning and technical assistance. Professional staff with direct emails on website. | O17: Key staff: Rebeckah Berry (Grants Program Director) rebeckah@roundhousefoundation.org, Chaney Coman (Grants Manager) chaney@roundhousefoundation.org. Focus: rural Oregon and tribal communities. Grants $500-$30K. Small Grants open Jan-Nov. Open Calls: Spring (Jan-Mar) and Fall (Jun-Aug). | P17: 226930631
A18: =_xlfn.XLOOKUP(P18,Calls!L:L,Calls!B:B) -> Weingart Foundation | B18: Excellent | C18: WEINGART FOUNDATION | D18: CA | E18: Pacific | F18: 866296097 | G18: 61 | H18: Joanna Jackson | I18: President & CEO | J18: jjackson@weingartfnd.org | K18: (213) 688-7799 | L18: https://www.linkedin.com/in/joanna-jackson-91484027 | M18: WWW.WEINGARTFND.ORG | O18: New CEO June 2024; 15 yrs at Weingart; board of GEO & SoCal Grantmakers | P18: 956054814
A19: =_xlfn.XLOOKUP(P19,Calls!L:L,Calls!B:B) -> THE COLLINS FOUNDATION | B19: Excellent | C19: THE COLLINS FOUNDATION | D19: OR | E19: Pacific | F19: 227675139 | G19: 50 | H19: Sara Yada | I19: Program Officer | J19: information@collinsfoundation.org | K19: 503-227-7171 | M19: https://www.collinsfoundation.org | N19: 50 Oregon community nonprofits. $10M/year grantmaking. $310M+ awarded since 1947. Professional staff with direct contact. | O19: Founded 1947. 1618 SW First Ave Suite 505, Portland OR. Focus: arts, education, health equity, environment. Note: Responsive grants paused until late Spring 2025 for program redesign. | P19: 936021893
A20: =_xlfn.XLOOKUP(P20,Calls!L:L,Calls!B:B) -> SIERRA HEALTH FOUNDATION | B20: Excellent | C20: SIERRA HEALTH FOUNDATION | D20: CA | E20: Pacific | F20: 57860059 | G20: 45 | H20: Chet P. Hewitt | I20: President and CEO | J20: info@sierrahealth.org | K20: 916-922-4755 | L20: https://www.linkedin.com/in/chet-hewitt-5a1988277/ | M20: WWW.SIERRAHEALTH.ORG | N20: 45 dependent grantees focused on health equity and vulnerable youth. Professional leadership team with 17+ year CEO tenure. Strong focus on community health disparities in Sacramento/Northern CA region. | O20: SVP Programs: Kaying Hang. COO/CFO: Edward Harris. Multiple program officers. 1321 Garden Hwy, Sacramento CA 95833. Founded 1984. Also operates The Center at Sierra Health Foundation (nonprofit intermediary). | P20: 680050036
A21: =_xlfn.XLOOKUP(P21,Calls!L:L,Calls!B:B) -> SAMUELI FOUNDATION | B21: Excellent | C21: SAMUELI FOUNDATION | D21: CA | E21: Pacific | F21: 45536119 | G21: 45 | H21: Annette Fritzsche | I21: Director of Grants Management | J21: info@samueli.org | K21: 949-760-4400 | M21: https://www.samueli.org | N21: 45 Orange County nonprofits. Major programs: Breakaway Fund ($11M), Build OC Fund (up to $1M capital grants). Very active. | O21: Founded 1998 by Henry & Susan Samueli (Giving Pledge). Corona Del Mar CA. Breakaway Fund: $50-100K grants. Build OC Fund: up to $1M capital. 2026 funding cycles confirmed. Also: Dr. Shauntina Sorrells (Chief Program Officer background). | P21: 330758237
A22: =_xlfn.XLOOKUP(P22,Calls!L:L,Calls!B:B) -> SUNLIGHT GIVING | B22: Excellent | C22: SUNLIGHT GIVING | D22: CA | E22: Pacific | F22: 471220977 | G22: 44 | H22: Cedrick Andrews | I22: Program Director | L22: https://www.linkedin.com/in/cedrickandrews/ | M22: HTTP://WWW.SUNLIGHTGIVING.ORG/ | N22: 44 dependent Silicon Valley grantees - all community nonprofits serving low-income families (LifeMoves, Second Harvest Food Banks, Abode Services). 9 CB service grants including organizational development and strategic planning. Professional program team with dedicated grants manager. | O22: Brian Acton (WhatsApp founder) family foundation. Part of Wildcard Giving. Program Officers: Sepi Aghdaee, Jessica Avendano, Erika Matadamas. Grants Manager: Kelsey Leuchars. Focus: young children and families in poverty in Silicon Valley. No direct contact info on website - use LinkedIn. Address: 855 El Camino Real Bldg 4 Ste 200, Palo Alto CA 94301. | P22: 471820379
A23: =_xlfn.XLOOKUP(P23,Calls!L:L,Calls!B:B) -> MARSHALL L AND PERRINE D MCCUNE | B23: Excellent | C23: MARSHALL L AND PERRINE D MCCUNE | D23: NM | E23: Mountain | F23: 91819670 | G23: 43 | H23: Carla Romero | I23: Executive Director | J23: mccune@nmmccune.org | K23: 505-983-8300 | L23: www.nmmccune.org | M23: WWW.NMMCCUNE.ORG | O23: Also: Ernesto Torres (Dir Grantmaking & Community Inclusion), Henry Rael (Dir Strategy), Allison Hagerman (Dir Learning & Ops). 345 E Alameda St, Santa Fe NM 87501. grants@nmmccune.org for grantmaking. | P23: 850429439
A24: =_xlfn.XLOOKUP(P24,Calls!L:L,Calls!B:B) -> The McConnell Foundation | B24: Excellent | C24: The McConnell Foundation | D24: CA | E24: Pacific | F24: 420547459 | G24: 39 | H24: John A. Mancasola | I24: President & CEO | K24: 530-226-6200 | M24: HTTP://WWW.MCCONNELLFOUNDATION.ORG | N24: $420M assets, 39 dependent grantees in Shasta County/Redding CA. Full professional staff with direct phone lines. Major regional funder supporting local community foundations, education, and environment. | O24: COO: Shannon Phillips (530-226-6231). Dir Children/Youth/Ed: Kelly Salter (530-226-6232). Dir College Success: David Tanner (530-226-6233). Dir Ecosystem Resilience: Alex Carter (530-226-6249). Executive Asst: Marie Welch (530-226-6217). Mancasola has been director since 1991. | P24: 946102700
A25: =_xlfn.XLOOKUP(P25,Calls!L:L,Calls!B:B) -> PRICE PHILANTHROPIES FOUNDATION | B25: Excellent | C25: PRICE PHILANTHROPIES FOUNDATION | D25: CA | E25: Pacific | F25: 470624292 | G25: 36 | H25: Sakara Tear | I25: Senior Director of Community Initiatives | J25: stear@pricephilanthropies.org | K25: (619) 795-2000 | L25: https://www.linkedin.com/in/sakara-tear-35853924b/ | M25: WWW.PRICEPHILANTHROPIES.ORG | O25: 93% capacity; grantees are small City Heights nonprofits who need funding diversification | P25: 465129465
A26: =_xlfn.XLOOKUP(P26,Calls!L:L,Calls!B:B) -> MARGUERITE CASEY FOUNDATION | B26: Excellent | C26: MARGUERITE CASEY FOUNDATION | D26: WA | E26: Pacific | F26: 856573767 | G26: 35 | H26: Dr. Carmen Rojas | I26: President & CEO | J26: crojas@caseygrants.org | K26: 510-295-8484 | L26: https://www.linkedin.com/in/carmen-rojas-phd-she-her-1b521316/ | M26: WWW.CASEYGRANTS.ORG | O26: 68% capacity; 509 movement-building orgs; Highlander $1.5M; preselected OK for B2B; RECOMMENDED | P26: 912062197
A27: =_xlfn.XLOOKUP(P27,Calls!L:L,Calls!B:B) -> The Satterberg Foundation | B27: Excellent | C27: THE SATTERBERG FOUNDATION INC | D27: WA | E27: Pacific | F27: 443335399 | G27: 32 | H27: Sarah Walczyk | I27: Executive Director | J27: swalczyk@satterberg.org | K27: (206) 441-3045 | L27: https://www.linkedin.com/in/sarah-walczyk-a010456/ | M27: WWW.SATTERBERG.ORG | O27: 82% capacity; 300+ BIPOC-led grantee partners; shifting to RETENTION mode - grantees need other funding; Trust-Based Philanthropy leader | P27: 911501066
A28: =_xlfn.XLOOKUP(P28,Calls!L:L,Calls!B:B) -> Hughes Charitable Foundation | B28: Excellent | C28: Hughes Charitable Foundation | D28: WY | E28: Mountain | F28: 6285282 | G28: 32 | H28: Molly Hughes | I28: Executive Director/President | L28: https://www.linkedin.com/in/molly-hughes-6863a73a | M28: https://hughescf.org/ | N28: 32 dependent Wyoming community nonprofits. 4 CB service grants including strategic planning. Supported 300+ WY organizations since 2020. Focus on vulnerable populations: poor, hungry, housing insecure, veterans, women/children, Indigenous. | O28: Also: Hunter Christensen (Senior VP), Brenna Jenkins (EA). Family foundation led by B. Wayne Hughes Jr. and wife Molly. Reestablished in Wyoming in 2020. Based in Jackson Hole. | P28: 853683086
A29: =_xlfn.XLOOKUP(P29,Calls!L:L,Calls!B:B) -> CLIF FAMILY FOUNDATION | B29: Excellent | C29: CLIF FAMILY FOUNDATION | D29: CA | E29: Pacific | F29: 563707533 | G29: 31 | J29: info@cliffamilyfoundation.org | K29: 510-596-6383 | M29: https://cliffamilyfoundation.org | N29: $564M assets, OPEN applications (March 1 & Aug 1 deadlines). Founded by Clif Bar founders. Professional process, email contact, clear focus areas. | O29: Founded 2006 by Kit Crawford & Gary Erickson. Became independent 2022 when Clif Bar sold to Mondelez. Focus: sustainable agriculture, food systems, environment, climate justice. Grants $5K-$50K. Next deadline March 1, 2026. Alt email: familyfoundation@clifbar.com. Address: 1334 B Vidovich Ave, St Helena CA 94574. | P29: 204345935
A30: =_xlfn.XLOOKUP(P30,Calls!L:L,Calls!B:B) -> STUPSKI FOUNDATION | B30: Excellent | C30: STUPSKI FOUNDATION | D30: CA | E30: Pacific | F30: 223687249 | G30: 31 | H30: Claire Callahan | I30: Communications Director | J30: claire@stupski.org | K30: 415.655.4405 | M30: HTTP://WWW.STUPSKI.ORG | N30: SUNSETTING BY 2029 - grantees urgently need other funders. 10 CB service grants (BIPOC-led CBO capacity building, leadership development, technical assistance). Professional staff with direct contact. Grantees include West Hawaii Community Health Center, Hawaii Good Food Alliance, Kokua Kalihi Valley. | O30: CEO: Glen Galaich Ph.D. Directors: Jennifer Nguyen (Postsecondary), Dan Tuttle (Health), Aileen Suzara (Food Justice). Focuses on CA and Hawaii. General: info@stupski.org, 415.655.4400. Spend-down foundation closing 2029. | P30: 680397103
A31: =_xlfn.XLOOKUP(P31,Calls!L:L,Calls!B:B) -> HEADWATERS HEALTH FOUNDATION | B31: Excellent | C31: HEADWATERS HEALTH FOUNDATION | D31: MT | E31: Mountain | F31: 123719137 | G31: 29 | H31: Erin Switalski | I31: Staff (Program Leadership) | M31: WWW.HEADWATERSMT.ORG | O31: 20+ years nonprofit experience. Montana/human rights/housing/environmental health. Founding CEO Brenda Solorzano left to lead CA Endowment. 725 W Central Ave Ste 210, Missoula MT 59801. | P31: 811099715
A32: =_xlfn.XLOOKUP(P32,Calls!L:L,Calls!B:B) -> WALTER AND ELISE HAAS FUND | B32: Excellent | C32: WALTER AND ELISE HAAS FUND | D32: CA | E32: Pacific | F32: 252512662 | G32: 28 | H32: Jamie Allison | I32: Executive Director | K32: 415-398-4474 | L32: https://www.linkedin.com/in/jamieallisonhope/ | M32: https://haassr.org | N32: 28 dependent grantees all community nonprofits (La Cocina, Oakland Promise, Young Womens Freedom Center). 4 CB grants including strategic planning and technical assistance. Professional staff with relationship managers. | O32: Key staff: Marcel Marania (Grants Manager), Pui Ling Tam (Economic Well-being), Natalia Vigil (Social Well-being). Focus on SF/Alameda County especially Oakland/Berkeley. Grants $25-125K. LOI accepted ongoing, 6-week response. Address: 1 Lombard St Ste 305, SF 94111. | P32: 946068564
A33: =_xlfn.XLOOKUP(P33,Calls!L:L,Calls!B:B) -> KEN BIRDWELL FOUNDATION | B33: Excellent | C33: KEN BIRDWELL FOUNDATION | D33: WA | E33: Pacific | F33: 100008103 | G33: 20 | H33: Tiffany Johnson | I33: Chief Strategy Officer | J33: hello@magiccabinet.org | L33: https://www.linkedin.com/company/ken-birdwell-foundation | M33: WWW.MAGICCABINET.ORG | N33: 213 CB service grants (highest in dataset). DBA Magic Cabinet - explicitly focuses on capacity building and trust-based philanthropy. Grantees are community nonprofits (First Graduate, Somali Health Board, Southeast Seattle Education Coalition). 31 professional staff. | O33: General: hello@magiccabinet.org, Partnerships: partnerships@magiccabinet.org. Also consider: Molly Judge (Director of Philanthropic Solutions), Myeshia Grice-Robinson (Co-Program Director). No individual staff emails on website. Preselected-only does NOT matter for B2B sales. | P33: 825328231
A34: =_xlfn.XLOOKUP(P34,Calls!L:L,Calls!B:B) -> SWIFT FOUNDATION | B34: Good | C34: SWIFT FOUNDATION | D34: CA | E34: Pacific | F34: 51631550 | N34: SUNSETTING 2028 - 190+ Native-led grantees urgently need other funders. Supports Indigenous Environmental Network, Indigenous Climate Action, Gaia Amazonas. Under-resourced grassroots orgs that would benefit from grant research. | O34: No direct contact - very private. Try: swiftfoundation.org. Moving $67M to grantee-led orgs by sunset. Focus: Indigenous rights, food sovereignty, biocultural diversity (Pacific NW, Amazon, Andes). | P34: 770559600
A35: =_xlfn.XLOOKUP(P35,Calls!L:L,Calls!B:B) -> THE GAP FOUNDATION | B35: Good | C35: THE GAP FOUNDATION | D35: CA | E35: Pacific | F35: 4777763 | G35: 250 | H35: Mame Annan-Brown | I35: Chief Communications Officer (oversees Gap Foundation) | K35: 415-427-7473 | M35: https://www.bewhatspossible.com | N35: 250 dependent grantees including GLIDE and OpportunityWork (community nonprofits focused on youth job readiness). Corporate foundation with employee engagement focus. | O35: Focus: underserved youth job readiness & women in developing world. Field Team Grants: $250 per 25 volunteer hours. Money for Time: $150 per 15 volunteer hours. Donation match up to $15K. Located: 2 Folsom St Fl 15, SF CA 94105. | P35: 942474426
A36: =_xlfn.XLOOKUP(P36,Calls!L:L,Calls!B:B) -> LAMB WESTON CHARITABLE FOUNDATION | B36: Good | C36: LAMB WESTON CHARITABLE FOUNDATION | D36: ID | E36: Mountain | F36: 13539943 | G36: 161 | H36: Carrie Cereghino | I36: Foundation Coordinator | K36: 208-869-8548 | N36: 161 dependent grantees including food banks (Second Harvest, Idaho Foodbank, Oregon Food Bank). Named Foundation Coordinator with direct phone. Corporate foundation with community focus. | O36: President: Shelby Stoolman. Address: 599 S Rivershore Lane, Eagle ID 83616. Est 2019. Also has scholarship program through Scholarship America and Team Member Relief Fund for employees. | P36: 830562671
A37: =_xlfn.XLOOKUP(P37,Calls!L:L,Calls!B:B) -> The William & Flora Hewlett Foundation | B37: Good | C37: THE WILLIAM & FLORA HEWLETT FOUNDATION | D37: CA | E37: Pacific | F37: 13332174215 | G37: 139 | H37: Jehan Velji | I37: Director - Effective Philanthropy Group | J37: jvelji@hewlett.org | K37: (650) 234-4500 | L37: https://www.linkedin.com/in/jehan-velji/ | M37: WWW.HEWLETT.ORG | O37: 30+ yrs capacity building; leads OE program; former Blue Meridian; Harvard MBA | P37: 941655673
A38: =_xlfn.XLOOKUP(P38,Calls!L:L,Calls!B:B) -> The Yelp Foundation | B38: Good | C38: The Yelp Foundation | D38: CA | E38: Pacific | F38: 8560195 | G38: 83 | H38: Marla Landa | I38: Yelp Foundation Ambassador | J38: marla@yelp.com | M38: https://www.yelpfoundation.org | N38: 83 dependent grantees including Hot Bread Kitchen, Fresh Start Womens Foundation, 826NYC - community nonprofits serving local communities. Focus on education and local economic development. | O38: General: info@yelpfoundation.org. No unsolicited applications - uses grant contests. Founded 2011 with 1% of Yelp equity. Typical awards $4-50K. 678 awards in 2023. Offices: SF, NYC, Chicago, Phoenix. $1K employee donation match. | P38: 454001403
A39: =_xlfn.XLOOKUP(P39,Calls!L:L,Calls!B:B) -> Umpqua Bank Charitable Foundation | B39: Good | C39: Umpqua Bank Charitable Foundation | D39: OR | E39: Pacific | F39: 16830197 | G39: 56 | H39: Randy Choy | I39: VP of Philanthropy Programs and Managing Director | J39: Community@UmpquaBank.com | K39: 503-727-4100 | M39: www.umpquabank.com/community | N39: 56 dependent grantees. 12 CB grants for BIPOC entrepreneur TA, business capacity. Grantees are CDFIs/intermediaries (LISC, Seattle EDF, Centro Community Partners) who serve community nonprofits. Corporate foundation but economic development focused. | O39: Subsidiary of Columbia Banking System. Nicole Stein also listed as contact. 1 SW Columbia Street, Suite 1200, Portland, OR 97258. Uses GrantsConnect platform for applications. | P39: 471247608
A40: =_xlfn.XLOOKUP(P40,Calls!L:L,Calls!B:B) -> NV Energy Charitable Foundation | B40: Good | C40: NV Energy Charitable Foundation | D40: NV | E40: Pacific | F40: 33071128 | G40: 40 | H40: L. Harris | I40: Staff Contact | J40: lharris@nvenergy.com | K40: 775-834-5642 | N40: 40 dependent grantees in Nevada including United Way, Three Square Food Bank, Public Education Foundation. Explicitly funds nonprofit capacity building. Berkshire Hathaway subsidiary with open grant process. | O40: Corporate foundation. Grants $5K-$25K. Moved to open LOI process March 2025. Focuses on Nevada: Las Vegas, Reno-Sparks, Henderson, Elko. General phone: 775-834-3067. PO Box 10100, Reno NV 89520-0024. | P40: 880244735
A41: =_xlfn.XLOOKUP(P41,Calls!L:L,Calls!B:B) -> NAMES FAMILY FOUNDATION | B41: Good | C41: NAMES FAMILY FOUNDATION | D41: WA | E41: Pacific | F41: 159866686 | G41: 36 | H41: Patricia Shults | I41: Executive Director | K41: 253-236-7333 | L41: https://www.linkedin.com/in/patricia-shults-23417719/ | M41: WWW.NAMESFOUNDATION.ORG | N41: $160M assets, 36 dependent grantees in Pierce County WA. Professional Executive Director (first outside-the-family hire). Niche focus on sports, physical education, health/wellness. Partner on Aspen Institute State of Play report. | O41: Grants Manager: Linsey Sauer. President: Kim Hegardt. VP: Rick Names. 1019 Regents Blvd Ste 201, Fircrest WA 98466. Founded 1996 by Scott and Evelyn Names. Focus: youth sports, recreation, wellness in Puget Sound/Pierce County. | P41: 943250195
A42: =_xlfn.XLOOKUP(P42,Calls!L:L,Calls!B:B) -> CRANKSTART FOUNDATION | B42: Good | C42: CRANKSTART FOUNDATION | D42: CA | E42: Pacific | F42: 3909004192 | G42: 34 | H42: Missy Narula | I42: Chief Executive Officer | J42: communications@crankstart.org | L42: https://www.linkedin.com/in/missy-narula/ | M42: https://crankstart.org | N42: $3.9B foundation funding intermediaries (SF Foundation, Tipping Point) that serve community nonprofits. 60% Bay Area focus. Professional CEO. However, does not accept unsolicited inquiries. | O42: Founded by Harriet Heyman and Michael Moritz (Sequoia Capital). 15 employees. c/o Pacific Foundation Services, 1660 Bush St Suite 300, SF CA. Focus: education, housing, democracy, climate. Median grant $250K. Does NOT accept unsolicited requests but has contact form for those who reviewed their programs. | P42: 943377099
A43: =_xlfn.XLOOKUP(P43,Calls!L:L,Calls!B:B) -> Vincent C and Pamela A Immordino | B43: Good | C43: Vincent C and Pamela A Immordino | D43: NV | E43: Pacific | F43: 20753871 | G43: 31 | H43: Vincent C. Immordino | I43: Founder | N43: 31 Las Vegas community nonprofits (Catholic Charities, ThreeSquare, Forgotten Dogs Rescue). $20.8M assets, 58 awards in 2024. No direct contact available. | O43: No website. Founder former C.H. Robinson VP (25 yrs). Based Henderson NV. Preselected only. Recent: $100K to Lions Club Foundation (2025). Growth: 34→44→58 awards over 3 yrs. | P43: 812727904
A44: =_xlfn.XLOOKUP(P44,Calls!L:L,Calls!B:B) -> THE STEVE MIHAYLO AND LOIS MIHAYLO | B44: Good | C44: THE STEVE MIHAYLO AND LOIS MIHAYLO | D44: AZ | E44: Mountain | F44: 8207067 | G44: 31 | H44: Sarah Mihaylo | I44: Madam Chairman | K44: 602-732-7990 | M44: https://mihaylofoundation.org | N44: 31 Arizona community nonprofits (Junior Achievement, Tempe Community Action, HonorHealth). Named board members found. Preselected only but B2B still viable. | O44: Board: Steve Mihaylo (Director/CEO), Doug Gaylor, Jeff Korn, Matthew Mihaylo, Elijah Mihaylo, Ron Vincent, Michael Gray. Contact form at mihaylofoundation.org/contact/. Focus: youth education, after school programs. 94 awards in 2023 ($362K). | P44: 880457469
A45: =_xlfn.XLOOKUP(P45,Calls!L:L,Calls!B:B) -> THE SOBRATO FAMILY FOUNDATION | B45: Good | C45: THE SOBRATO FAMILY FOUNDATION | D45: CA | E45: Pacific | F45: 876730998 | G45: 30 | H45: Alexa Cortés Culwell | I45: President, Sobrato Philanthropies | K45: 650-876-7010 | M45: WWW.SOBRATO.ORG | N45: Grants to intermediaries serving community nonprofits (Silicon Valley Community Foundation, Foundation for Hispanic Education, Californians Together). 17 CB grants for technical assistance and capacity building. Large professional staff. | O45: Also key: Camille Llanes-Fontanilla (VP Community Impact), Zelica Rodriguez-Deams (Director Thriving Communities). Does not accept unsolicited grants but welcomes introductions. Focus areas: Silicon Valley community + English Learners statewide. Real estate focus with Social Purpose Real Estate program. | P45: 770348912
A46: =_xlfn.XLOOKUP(P46,Calls!L:L,Calls!B:B) -> EDWARDS LIFESCIENCES FOUNDATION | B46: Good | C46: EDWARDS LIFESCIENCES FOUNDATION | D46: CA | E46: Pacific | F46: 56296533 | G46: 28 | H46: Tiffany Simmons | I46: Senior Manager, Edwards Lifesciences Foundation | K46: 949-250-5184 | M46: HTTP://WWW.EDWARDS.COM/ABOUTUS/CORPORATEGIVING | N46: 28 dependent grantees but mixed profile (includes Stanford Medicine, CAF America for matching gifts). 3 CB service grants. Corporate foundation with health/medical focus. Good community involvement but grantee profile is mixed. | O46: Corporate foundation. Address: One Edwards Way, Irvine, CA 92614. Focus: health-related and community causes in Orange County. Partners with charities to improve quality of life for patients. Website: edwards.com/about-us/global-corporate-giving | P46: 461702755
A47: =_xlfn.XLOOKUP(P47,Calls!L:L,Calls!B:B) -> CASEY FAMILY PROGRAMS | B47: Good | C47: CASEY FAMILY PROGRAMS | D47: WA | E47: Pacific | F47: 2637089778 | G47: 27 | H47: William C. Bell PhD | I47: President & CEO | K47: 206-282-7300 | L47: https://www.linkedin.com/in/david-sanders-70947113/ | M47: WWW.CASEY.ORG | O47: $2.6B; 48% capacity; 411 child welfare grantees across 50 states; foster care focus; RECOMMENDED | P47: 910793881
A48: =_xlfn.XLOOKUP(P48,Calls!L:L,Calls!B:B) -> KENNETH RAININ FOUNDATION | B48: Good | C48: KENNETH RAININ FOUNDATION | D48: CA | E48: Pacific | F48: 614668063 | G48: 27 | H48: Ted Russell | I48: Director of Arts Strategy & Ventures | K48: 510-625-5200 | M48: https://krfoundation.org | N48: 27 dependent grantees focused on Oakland (SF Film Society, Oakland USD, Community Arts Stabilization). 2 CB grants for strategic planning. Strong focus on early childhood literacy in Oakland. | O48: Key staff: Dana Cilono (Dir Education), Sarah Williams (Arts PO), Nicole Kendrick (Education PO). Focus: Arts, early childhood literacy (Oakland), IBD research. Education grants by invitation. Address: 155 Grand Ave Ste 1000, Oakland 94612. | P48: 943289283
A49: =_xlfn.XLOOKUP(P49,Calls!L:L,Calls!B:B) -> THE ZELLERBACH FAMILY FOUNDATION | B49: Good | C49: THE ZELLERBACH FAMILY FOUNDATION | D49: CA | E49: Pacific | F49: 160251196 | G49: 24 | H49: Grants Manager | I49: Grants Manager | J49: grantsmanager@zff.org | K49: 415-421-2629 | M49: ZFF.ORG | N49: $160M assets, 24 grantees. Professional staff with Grants Manager email. 65+ years of grantmaking. BUT very narrow geographic focus: Alameda, Contra Costa, SF counties only. | O49: Focus: Safety & Belonging, Arts & Culture. Community Arts program accepts applications (quarterly cycles). Address: 455 Market Street, Suite 2200, SF CA 94105. | P49: 946069482
A50: =_xlfn.XLOOKUP(P50,Calls!L:L,Calls!B:B) -> HN and Frances C Berger Foundation | B50: Good | C50: HN and Frances C Berger Foundation | D50: CA | E50: Pacific | F50: 489101990 | G50: 23 | H50: Catharine N. Reed | I50: Vice President - Charitable Programs | M50: hnberger.org | N50: $489M assets, 23 grantees. Professional staff (President, VP Charitable Programs). Palm Desert based. Focus on education, health, social services. Limited to Coachella Valley area. | O50: President: Christopher M. McGuire. VP General Counsel: Michael B. Rover. VP Finance: Joseph K. Glassett. Focus: helping people help themselves. Based in Palm Desert CA. Contact via website: hnberger.org/contact-us | P50: 521757452
A51: =_xlfn.XLOOKUP(P51,Calls!L:L,Calls!B:B) -> ANDERSON CHILDRENS FOUNDATION | B51: Good | C51: ANDERSON CHILDRENS FOUNDATION | D51: CA | E51: Pacific | F51: 25287510 | G51: 23 | H51: Brianna Uhlhorn | I51: Director of Grants & Media | J51: brianna@andersonchildrensfoundation.org | K51: 760-778-1777 | M51: https://www.andersonchildrensfoundation.org | N51: 23 grantees focused on Coachella Valley youth. Direct contact with Grants Director email. Small but focused foundation with clear application process. | O51: Trustee: Diane Schlesinger (diane@andersonchildrensfoundation.org). Address: 1111 E Tahquitz Canyon Way Suite 109, Palm Springs CA. Applications Feb 1 - Apr 30. Coachella Valley/Riverside County only. Youth under 18. | P51: 237089096
A52: =_xlfn.XLOOKUP(P52,Calls!L:L,Calls!B:B) -> MAPS COMMUNITY FOUNDATION | B52: Good | C52: MAPS COMMUNITY FOUNDATION | D52: OR | E52: Pacific | F52: 4307884 | G52: 21 | H52: Avery Ackerman | I52: Foundation Contact | J52: aackerman@mapscu.com | K52: 503-375-2449 | M52: MAPSCU.COM/COMMUNITYFOUNDATION | N52: Credit union foundation serving Marion/Polk counties Oregon. Named contact (Avery Ackerman). $4.3M assets, 21 grantees. Focus: financial education, capital projects, scholarships. Local but professional. | O52: MAPS Credit Union foundation. Address: PO Box 12398, Salem OR 97309. Impact Partnership Grants: $25K-$50K for capital projects. Serves Marion and Polk counties. Also: idamanagers@mapscu.com, 503-588-0181. | P52: 450705509

Sheet Sheet6
B3: 562618866 | C3: 1
B4: 383237572 | C4: 2
B5: 611583546 | C5: 3
B6: 470805015 | C6: 4
B7: 680283878 | C7: 5
B8: N/A | C8: 6
B9: 880389016 | C9: 7
B10: 910745225 | C10: 8
B11: 476017619 | C11: 9
B12: 912173492 | C12: 10
B13: 383521608 | C13: 11
B14: 943224234 | C14: 12
B15: 943085652 | C15: 13
B16: 476032365 | C16: 14
B17: 770559600 | C17: 15
B18: 134146467 | C18: 16
B19: 134146467 | C19: 17
